Workbook

Sheet KPI Dashboard
A1: Healthy4U
A2: KPI DASHBOARD
A3: Ключевые показатели эффективности
A5: 📊 REVENUE METRICS
A6: MRR (Monthly Recurring Revenue) | B6: =SUM('Monthly forecast'!$D$4:$CW$4) | C6: Ежемесячная регулярная выручка
A7: ARR (Annual Recurring Revenue) | B7: =B6*12 | C7: Годовая регулярная выручка
A8: Revenue Growth Rate (MoM) | B8: =(B6-B6)/B6 | C8: Рост выручки месяц к месяцу
A9: Cumulative Revenue | B9: =SUM('Monthly forecast'!$D$4:$CW$4) | C9: Суммарная выручка за все время
A11: 👥 CUSTOMER METRICS
A12: Total Customers | B12: =COUNTA('Unit economics'!$D$6:$CW$6) | C12: Всего активных клиентов
A13: New Customers (Last Month) | B13: =B12 | C13: Новых клиентов за последний месяц
A14: Monthly Churn Rate | B14: =15% | C14: Процент ушедших клиентов в месяц
A15: Customer Lifetime (months) | B15: =1/B14 | C15: Средняя продолжительность подписки
A16: ARPPU (Avg Revenue Per User) | B16: =$100 | C16: Средний доход на пользователя
A18: 💰 UNIT ECONOMICS
A19: LTV (Lifetime Value) | B19: ='Unit economics'!D54 | C19: Пожизненная ценность клиента
A20: CAC (Customer Acquisition Cost) | B20: ='Unit economics'!D59 | C20: Стоимость привлечения клиента
A21: LTV:CAC Ratio | B21: =B19/B20 | C21: Соотношение LTV к CAC (цель: 3-5)
A22: CAC Payback Period (months) | B22: =B20/B16 | C22: Срок окупаемости затрат на привлечение
A23: LTV 12 month | B23: ='Unit economics'!D57 | C23: LTV за 12 месяцев
A25: 💵 FINANCIAL HEALTH
A26: Monthly Burn Rate | B26: =SUM('P&L | Cash Flow | Balance'!D20:D60) | C26: Ежемесячный расход денег
A27: Cash Balance | B27: ='P&L | Cash Flow | Balance'!D70 | C27: Текущий остаток денег
A28: Runway (months) | B28: =B27/B26 | C28: Сколько месяцев работы до конца денег
A29: Gross Margin % | B29: =80% | C29: Валовая маржа (типично для SaaS)
A31: 🎯 BENCHMARKS (B2B SaaS)
A32: LTV:CAC Target (B2B SaaS) | B32: 4:1 | C32: Здоровое соотношение для роста
A33: CAC Payback Target | B33: < 12 months | C33: Рекомендуемый срок окупаемости
A34: Monthly Churn Target (B2B) | B34: < 1% | C34: Целевой показатель оттока
A35: MRR Growth Target | B35: > 10% MoM | C35: Целевой рост для раннего этапа
A37: ⚠️ ВАЖНЫЕ ЗАМЕЧАНИЯ
A38: • Churn 15% в месяц слишком высок для B2B (норма <1%)
A39: • Проверьте: это месячный или годовой churn?
A40: • При корректном churn (1%) LTV вырастет в 15 раз!
A41: • Уточните pricing: $100 за сотрудника или за компанию?

Sheet Scenarios
A1: Healthy4U
A2: СЦЕНАРНОЕ ПЛАНИРОВАНИЕ
A3: Прогнозы развития бизнеса на 24 месяца
A5: ОПИСАНИЕ СЦЕНАРИЕВ
A6: Base Case (Базовый) | B6: Наиболее вероятный сценарий развития
A7: Best Case (Оптимистичный) | B7: Благоприятное развитие событий, быстрый рост
A8: Worst Case (Пессимистичный) | B8: Неблагоприятные условия, медленный рост
A10: КЛЮЧЕВЫЕ ПАРАМЕТРЫ СЦЕНАРИЕВ
A11: Параметр | B11: Base Case | C11: Best Case | D11: Worst Case
A12: 📈 Customer Growth
A13: Monthly New Customers (Month 1-6) | B13: 50 | C13: 80 | D13: 30
A14: Monthly New Customers (Month 7-12) | B14: 100 | C14: 150 | D14: 60
A15: Monthly New Customers (Month 13-24) | B15: 150 | C15: 250 | D15: 80
A17: 💸 Churn Rate
A18: Monthly Churn % | B18: 1.0% | C18: 0.5% | D18: 2.0%
A19: Annual Churn % | B19: 12% | C19: 6% | D19: 24%
A21: 💰 Unit Economics
A22: ARPPU ($/month) | B22: $100 | C22: $120 | D22: $80
A23: CAC ($) | B23: $150 | C23: $120 | D23: $180
A24: LTV:CAC Ratio | B24: 4.0x | C24: 6.0x | D24: 2.7x
A26: 🎯 Market & Growth
A27: Market Penetration (Year 2) | B27: 5% | C27: 10% | D27: 2%
A28: Revenue Growth (MoM avg) | B28: 15% | C28: 25% | D28: 8%
A29: Team Growth (by Month 24) | B29: +30 people | C29: +50 people | D29: +15 people
A31: 💵 Financial
A32: Gross Margin | B32: 80% | C32: 85% | D32: 75%
A33: Operating Expenses Growth | B33: Умеренный | C33: Агрессивный | D33: Консервативный
A34: Break-even Month | B34: Month 18 | C34: Month 12 | D34: Month 24+
A36: ПРОГНОЗНЫЕ МЕТРИКИ НА 24 МЕСЯЦА
A37: Метрика | B37: Base Case | C37: Best Case | D37: Worst Case
A38: После 12 месяцев:
A39: Total Customers | B39: 600 | C39: 960 | D39: 360
A40: MRR | B40: $60,000 | C40: $115,200 | D40: $28,800
A41: ARR | B41: $720,000 | C41: $1,382,400 | D41: $345,600
A42: Cumulative Revenue | B42: $420,000 | C42: $720,000 | D42: $210,000
A44: После 24 месяцев:
A45: Total Customers | B45: 2,100 | C45: 4,200 | D45: 1,200
A46: MRR | B46: $210,000 | C46: $504,000 | D46: $96,000
A47: ARR | B47: $2,520,000 | C47: $6,048,000 | D47: $1,152,000
A48: Cumulative Revenue | B48: $1,890,000 | C48: $3,780,000 | D48: $756,000
A50: Ключевые вехи:
A51: Break-even (месяц) | B51: 18 | C51: 12 | D51: 24+
A52: Profitability ARR | B52: $2.5M | C52: $1.5M | D52: $3.5M+
A53: Funding needed | B53: $1.5M | C53: $2.5M | D53: $800k
A56: 💡 РЕКОМЕНДАЦИИ ПО ИСПОЛЬЗОВАНИЮ
A57: ✓ Base Case - используйте для внутреннего планирования и бюджетирования
A58: ✓ Best Case - покажите инвесторам потенциал при благоприятных условиях
A59: ✓ Worst Case - используйте для стресс-тестирования и планирования рисков
A60: ✓ Регулярно пересматривайте сценарии на основе актуальных данных
A61: ✓ Фокусируйтесь на Base Case, но готовьтесь к Worst Case

Sheet Assumptions
A1: Healthy4U
A2: KEY ASSUMPTIONS
A3: Обоснование всех предположений финансовой модели
A5: ⚠️ ВАЖНО: Мы pre-revenue стартап. Все финансовые прогнозы основаны на предположениях ниже.
A7: Параметр | B7: Значение/Диапазон | C7: Источник обоснования | D7: Confidence | E7: Как валидируем
A8: PRICING & REVENUE
A9: ARPPU (Average Revenue Per User) | B9: $100/month | C9: Опрос 15 клиник: 80% готовы платить $80-120. Аналоги: $70-150. Экономия для клиники: $500/мес → наша цена = 20% от экономии (типично для B2B SaaS) | D9: Medium | E9: A/B тест pricing в первых 10 продажах. Интервью после каждой продажи
A10: Tier Adoption | B10: Basic: 70%, Premium: 30% | C10: Assumption на основе B2B SaaS benchmarks. В пилоте все используют "базовый" функционал | D10: Low | E10: Отслеживание feature usage. Предложение premium после 3 месяцев использования
A11: Upsell Growth | B11: $100 → $120 → $150 (over 24 months) | C11: Запланированные premium features. Benchmark: SaaS ARPPU растёт 15-25% годовых при successful upsell | D11: Low | E11: Quarterly upsell campaigns. Tracking conversion to premium tier
A13: CUSTOMER ACQUISITION
A14: Sales Cycle Length | B14: 45 days (1.5 months) | C14: Healthcare procurement research + опыт пилота (2 месяца, но это было без urgency). B2B healthcare: 30-90 дней | D14: Medium | E14: Tracking каждой сделки: первый контакт → close. Цель: сократить до 30 дней
A15: Lead → Demo Conversion | B15: 20% | C15: Industry benchmark для outbound B2B SaaS: 15-25%. Пилот показал высокий интерес, используем mid-point | D15: Medium | E15: Weekly tracking conversion rates по каналам. Оптимизация worst performers
A16: Demo → Customer Conversion | B16: 20% | C16: B2B SaaS benchmark: 15-30%. У нас strong product (пилот NPS 8/10) → используем 20% | D16: Medium | E16: Анализ каждой lost deal. Improve sales materials. Target: 25% к M6
A17: Sales Rep Capacity | B17: 2-3 customers/month | C17: Расчёт: 30 calls/day × 20 days = 600 calls/month → 120 connects → 24 meetings → 5 demos → 1-2 closes. First rep: консервативно 2/month, scaling to 3 | D17: Medium | E17: Weekly sales metrics. После 3 месяцев: adjust targets на основе actual data
A18: CAC Target | B18: $150 (long-term) | C18: Расчёт от LTV:CAC = 4:1. LTV ~$10k (при 1% churn) → CAC = $2.5k / 4 = $625. Но мы aggressive target $150 через product-led growth + content | D18: Low | E18: Monthly CAC tracking. В первые 6 месяцев ожидаем $500-1000. Оптимизация каналов
A20: RETENTION & CHURN
A21: Monthly Churn Rate | B21: 1% (12% annual) | C21: B2B healthcare SaaS benchmark: 0.4-0.8% monthly. Используем 1% консервативно. НЕТ ДАННЫХ - пилот бесплатный | D21: Low | E21: Cohort analysis с первого paying customer. Surveys при cancellation. Target: <0.7% к M12
A22: Customer Lifetime | B22: 100 months (~8 years) | C22: Расчёт: 1 / 0.01 churn = 100 месяцев. Для B2B с годовыми контрактами - realistic | D22: Low | E22: Tracking retention by cohort. Contract renewal rates. Churn reasons analysis
A23: Contract Type | B23: Annual (80%), Monthly (20%) | C23: Healthcare предпочитает предсказуемость → годовые контракты. Но даём опцию monthly для малых клиник | D23: Medium | E23: First 20 sales: предлагаем оба варианта, смотрим preference
A25: MARKET & GROWTH
A26: Total Addressable Market | B26: 50,000 клиник в target regions | C26: Market research: [конкретный источник]. Фокус на клиники 20-200 сотрудников | D26: High | E26: Уже validated через desk research. Ongoing: сегментация рынка
A27: Serviceable Market (5 years) | B27: 5,000 клиник (10% TAM) | C27: Realistic penetration для B2B SaaS в niche. Top competitors имеют 2-5% market share | D27: Medium | E27: Track market share quarterly. Competitive analysis
A28: Year 1 Target | B28: 100 клиник (2% of SAM) | C28: Conservative first year target. Proof of GTM motion before aggressive scaling | D28: Medium | E28: Monthly tracking vs. target. Quarterly plan adjustments
A29: Adoption Rate within Clinic | B29: 70% of staff | C29: Пилот показал 75% adoption (15/20). Используем 70% для paying customers (может быть ниже сопротивление) | D29: High | E29: Track actual adoption in first 10 clinics. Improve onboarding based on data
A31: OPERATIONAL
A32: Onboarding Time | B32: 2 weeks | C32: Пилот: 2 недели от договора до first value. Includes training, integration, setup | D32: High | E32: Already validated. Track time-to-value for each customer. Target: 1 week
A33: Support Load | B33: 2-3 tickets/month/customer | C33: Пилот: 2-3 support requests в месяц. Low-touch product → low support needs | D33: High | E33: Track support metrics. Build knowledge base to reduce tickets
A34: Gross Margin | B34: 80% | C34: Typical SaaS gross margin: 70-85%. Costs: servers, support. High margin business | D34: High | E34: Track actual costs. Should improve to 85%+ at scale
A36: TEAM & SCALING
A37: Sales Hire Timeline | B37: 1 rep at M0, +1 at M6, +1 at M12 | C37: Start with 1 rep to validate sales process. Scale when proven (>10 customers) | D37: High | E37: Hire when: previous rep consistently hits 3 customers/month for 2 months
A38: Payback Period | B38: < 12 months | C38: Target: CAC payback in <12 months. At $150 CAC and $100 MRR = 1.5 months. Comfortable! | D38: Low | E38: Monthly calculation. Adjust marketing if payback > 12 months
A41: CONFIDENCE LEVELS
A42: High | B42: Данные из пилота или подтверждённые исследования
A43: Medium | B43: Индустриальные бенчмарки или обоснованные estimates
A44: Low | B44: Educated guesses - будут validated в первые 6-12 месяцев
A47: 📅 ПЛАН ОБНОВЛЕНИЯ ASSUMPTIONS
A48: Месяц 1-3: Validate pricing, sales cycle, conversion rates с первыми 5 клиентами
A49: Месяц 3-6: Update CAC на основе actual marketing spend и conversions
A50: Месяц 6-12: Начинаем видеть early churn data, корректируем LTV assumptions
A51: Месяц 12+: Mature data, можем строить predictive models
A53: ⚡ Обновление модели: ежемесячно на основе actual vs. assumed metrics
A54: ⚡ Presentation для investors: ежеквартально с updated assumptions
A57: PRICING (Updated 2026-01-27)
A58: Parameter | B58: Old Value | C58: New Value | D58: Notes
A59: Doctor Professional Base | B59: $100 | C59: $249 | D59: Market-validated pricing
A60: Early Adopter Tier 1 (30% off) | B60: $70 | C60: $174 | D60: Founder's Circle
A61: Early Adopter Tier 2 (20% off) | B61: $80 | C61: $199 | D61: Early Adopter
A62: Early Adopter Tier 3 (10% off) | B62: $90 | C62: $224 | D62: Launch Partner
A63: Patient Premium (NEW) | B63: - | C63: $9.99 | D63: B2C monetization
A64: Revenue Share to Doctors (NEW) | B64: - | C64: 25% | D64: $2.50 per Premium patient
A66: DOCTOR COGS (per month, 340 visits)
A67: Component | B67: Per Visit | C67: Monthly | D67: Notes
A68: Whisper Transcription | B68: $0.09 | C68: $30.60 | D68: 15-min avg visit
A69: GPT-4o SOAP Notes | B69: $0.0155 | C69: $5.27 | D69: AI-generated
A70: AI Clinical Consultant | B70: $0.0023 | C70: $0.77 | D70: 30% of visits
A71: Infrastructure | B71: - | C71: $0.50 | D71: Fixed cost
A72: Analytics & Reports | B72: - | C72: $0.05 | D72: Batch processing
A73: TOTAL DOCTOR COGS | B73: $0.1055 | C73: $37.19 | D73: 85% gross margin
A75: PATIENT COGS (optimized)
A76: User Type | B76: Monthly COGS | C76: Notes
A77: Free User | B77: $0.77 | C77: 50 msg, 10 photos, 5 labs
A78: Premium Typical | B78: $2.80 | C78: 200 msg, 60 photos
A79: Premium Weighted Avg | B79: $2.83 | C79: 72% margin before rev share
A81: CONVERSION & LIMITS
A82: Metric | B82: Value | C82: Notes
A83: Free to Premium Conversion | B83: 10-15% | C83: Target: 12%
A84: Patients per Doctor | B84: 100 | C84: Conservative
A85: Doctor Visits Included | B85: 600/month | C85: 30 per day
A86: Patient Messages (Premium) | B86: 500/month | C86: 16 per day
A87: Patient Photos (Premium) | B87: 150/month | C87: 5 per day
A88: Patient Labs (Premium) | B88: 20/month

Sheet Description
B1: Сайт: | C1: https://anastasianikolaeva.com/ | D1: Телеграм: | E1: https://t.me/anikolayeva
C2: Материалы этого файла могут быть использованы только лицом, купившим данный материал на сайте https://anastasianikolaeva.com/, в целях индивидуального обучения и развития своих бизнес-проектов. Массовое распространение данного материала, продажа и передача 3м лицам являются нарушением авторского права. Если вы хотите порекомендовать материалы своим коллегам, партнерам и друзьям, поделитесь ссылкой на сайт: https://anastasianikolaeva.com/
B3: Если вы хотите получить консультацию или заказать разработку финансовой модели для вашей компании, запишитесь на пробную бесплатную консультацию здесь: https://anastasianikolaeva.com/#expressform
B4: Финансовая модель
B6: Данный шаблон разработан для прогнозирования доходов и расходов компании, продающей цифровые решения по модели "Подписка". Мы рассматриваем 3 потока дохода, которые основаны на способе привлечения клиентов: наиболее популярных способа монетизации для такого продукта: "Самостоятельное приобретение подписки", "Входящие продажи" и "Исходящие продажи". Эта финансовая модель позволяет спрогнозировать точку безубыточности и оценить сумму необходимых инвестиций. Модель автоматически рассчитывает прогноз для вашего бизнеса во вкладках "Monthly forecast", "P&L | Cash Flow | Balance", "Unit Economics" и визуализирует их в "Charts" "For Pitchdeck" на основании данных, введенных на вкладках "Settings", "Roadmap", "Payroll", "Projections".
B9: Инструкции
B11: 1000 | D11: Синим шрифтом выделены поля, куда вносятся данные.
B12: 2000 | D12: Черным шрифтом выделены поля, в которых вычисления производятся по формулам.
B13: Incorporation | D13: В выпадающих списках заданы списки параметров, выбор которых влияет на расчеты в модели.
B14: Вкладка "Setting" | D14: В этой вкладке задаются общие параметры бизнеса. На основании указанных здесь налоговых ставок рассчитывается налог на прибыль во вкладке "P&L and Cash Flow" и налог на заработную плату во вкладке "Payroll".
B15: Вкладка "Roadmap" | D15: В этой вкладке перечисляются события дорожной карты бизнеса, которые будут влиять на динамику доходов и расходов компании. Здесь нужно перечислить такие события и указать их плановые даты. Даты можно задать, указав, через сколько месяцев после привлечения инвестиций произойдет событие. Перечисленные в этой вкладке события попадают в выпадающие списки на вкладках "Payroll" и "Projections". Благодаря этому вы можете привязывать появление новых затрат или доходов и найм определенных сотрудников к событиям в вашей дорожной карте. В зависимости от выбранного события во вкладках "Payroll" и "Projections" автоматически проставляются даты, начиная с которых возникают отдельные доходы и расходы, а во вкладке "Monthly Forecast" начинают учитываться эти данные с нужного месяца.
B16: Вкладка "Payroll" | D16: В этой вкладке вносятся все позиции наемных сотрудников, которые неоходимы вашему бизнесу, их зарплаты, события, при которых они нанимаются, и динамика увеличения зарплат. Здесь нужно внести названия должностей, размер зарплат, выбрать событие из дорожной карты, при котором происходит найм, указать планируемый процент ежегодного увеличения зарплат. Общие затраты на сотрудника с учетом налогов рассчитаются на основании ставки, указанной в "Settings", даты найма проставятся из "Roadmap" на основании выбранного события.
B17: Вкладка "Projections" | D17: В этой вкладке вносятся вводные данные для формирования всех потоков доходов и расходов. Здесь перечисляются все статьи доходов и расходов, задаются их значения, стартовые даты, периодичность и методы расчета динамики. При этом начало возникновения различных статей доходов и расходов связано с событиями дорожной карты, а генерация доходов зависит от прямых расходов, приводящих к продажам. На основании внесенных здесь значений формируется прогноз во вкладке "Monthly forecast".
B18: Вкладка "Monthly Forecast" | D18: В этой вкладке формируется подробный финансовый прогноз бизнеса по месяцам. Все расчеты производятся на основании данных, внесенных во вкладки "Settings", "Roadmap", "Payroll", "Projections" по заданным формулам. В этой вкладке ничего вносить не нужно.
B19: Вкладка "Unit Economics" | D19: В этой вкладке формируется расчет юнит экономики отдельно для каждого варианта монетизации. Расчитывается LTV продукта, CAC (стоимость привлечения клиента), отношение LTV к CAC.
B20: Вкладка "P&L and Cash Flow" | D20: В этой вкладке формируются финансовые отчеты P&L (Прибыли и убытки) и Cash Flow (Денежный поток) по месяцам. Все расчеты производятся на основании данных вкладки "Monthly forecast" по заданным формулам. В этой вкладке ничего вносить не нужно.
B21: Вкладка "For Pitchdeck" | D21: В этой вкладке формируется таблица с динамикой выручки, операционной прибыли (EBITDA) и чистой прибыли по годам и строятся графики для лаконичной визуализации. Таблицу и график из этой вкладки можно скопировать на слайд с финансовой информацией питчдека вашего проекта для презентации инвесторам и партнерам.
B22: Вкладка "Cap Table" | D22: В этой вкладке вносится информация о всех держателях акций компании, привлеченных инвестициях по раундам, планируемой оценке стоимости компании и рассчитываются доли всех участников в динамике по раундам.
B23: Вкладка "Dividends" | D23: В этой вкладке рассчитываются начисленные дивиденды по годам для всех держателей акций компании исходя из прогнозируемой чистой прибыли в соответствии с долями, указанными на вкладке "Cap Table".
B24: Вкладка "Exit scenarios" | D24: В этой вкладке описывается предполагаемый сценарий выхода из компании (как пример приводится продажа компании в виде стратегического поглощения), задается планируемая стоимость продажи компании и предполагаемый год сделки. Рассчитывается доход каждого владельца акций компании при условии продажи всех акции, сумма вложенных инвестиций и ROI при выходе.
... B26: Вкладка "Data for Charts" | D26: Вспомогательная вкладка для упрощения создания графиков для вкладки "Charts". Вынесение данных, для которых необходима визуализация, на отдельную вкладку, помогает избежать ошибок и сделать модель понятнее как для команды проекта, так и для внешних партнеров (например, инвесторов). Все данные расчитываются по формулам на основании остальных вкладок. При необходимости, вы можете вынести сюда и другие метрики, по которым хотите постоить дополнительные графики для вашего бизнеса.

Sheet Settings
A2: GENERAL SETTINGS
A4: Company name | B4: Healthy4U
A5: Currency | B5: USD
A6: Country of incorporation | B6: Israel
A7: Income tax rate | B7: 0.23
A8: Payroll tax rate | B8: 0.35
A9: Tax Payment Month | B9: 3
A10: Cash in bank at start | B10: 0

Sheet Roadmap
A1: =Settings!$B$4
A2: ROADMAP
A4: Growth driving events
B6: Type | C6: Date | D6: Months after seed round
A7: Incorporation | B7: incorporation | C7: 45139 | D7: 0
A8: B2B solution: MVP release | B8: new product | C8: 45884 | D8: 0
A9: B2B solution: 5 clients | B9: monetization | C9: 45899 | D9: 0
A10: Pre-seed round money transfer | B10: fundraising | C10: 45901 | D10: 0
A11: B2B solution: v.1 release | B11: new feature | C11: =if(D11>0,EDATE($C$10,D11),"not set") | D11: 2
A12: Android App for B2B | B12: new feature | C12: =if(D12>0,EDATE($C$11,D12),"not set") | D12: 4
A13: B2B solution: 50 clients | B13: monetization | C13: =if(D13>0,EDATE($C$11,D13),"not set") | D13: 6
A14: B2B solution: 100 clients | B14: fundraising | C14: =if(D14>0,EDATE($C$11,D14),"not set") | D14: 9
A15: Seed round money transfer | B15: fundraising | C15: =if(D15>0,EDATE($C$11,D15),"not set") | D15: 10
A16: EU expansion | B16: new region | C16: =if(D16>0,EDATE($C$11,D16),"not set") | D16: 12

Sheet Payroll
A1: =Settings!$B$4
A2: PAYROLL
D4: Monthly salary | E4: Payroll taxes | F4: Monthly cost to company | G4: Annaul salary | H4: Start event in the roadmap | I4: Hire date | J4: Annual salary increase
A5: Administrative
A6: CEO | D6: 5000 | E6: =Settings!$B$8 | F6: =D6/(1-E6) | G6: =D6*12 | H6: Pre-seed round money transfer | I6: =IFERROR(VLOOKUP(H6,Roadmap!$A$7:$D$110,3,0),"not set, choose the event") | J6: 0.02 | K6: 12
A7: CFO | D7: 0 | E7: =Settings!$B$8 | F7: =D7/(1-E7) | G7: =D7*12 | H7: B2B solution: 5 clients | I7: =IFERROR(VLOOKUP(H7,Roadmap!$A$7:$D$110,3,0),"not set, choose the event") | J7: 0 | K7: 12
A8: COO | D8: 0 | E8: =Settings!$B$8 | F8: =D8/(1-E8) | G8: =D8*12 | H8: B2B solution: 100 clients | I8: =IFERROR(VLOOKUP(H8,Roadmap!$A$7:$D$110,3,0),"not set, choose the event") | J8: 0 | K8: 12
A9: HRD | D9: 0 | E9: =Settings!$B$8 | F9: =D9/(1-E9) | G9: =D9*12 | I9: =IFERROR(VLOOKUP(H9,Roadmap!$A$7:$D$110,3,0),"not set, choose the event") | J9: 0 | K9: 12
A10: Operations Coordinator / Office Manager | D10: 0 | E10: =Settings!$B$8 | F10: =D10/(1-E10) | G10: =D10*12 | I10: =IFERROR(VLOOKUP(H10,Roadmap!$A$7:$D$110,3,0),"not set, choose the event") | J10: 0 | K10: 12
A11: Employee 1 | D11: 0 | E11: =Settings!$B$8 | F11: =D11/(1-E11) | G11: =D11*12 | I11: =IFERROR(VLOOKUP(H11,Roadmap!$A$7:$D$110,3,0),"not set, choose the event") | J11: 0 | K11: 12
A12: Employee 2 | D12: 0 | E12: =Settings!$B$8 | F12: =D12/(1-E12) | G12: =D12*12 | I12: =IFERROR(VLOOKUP(H12,Roadmap!$A$7:$D$110,3,0),"not set, choose the event") | J12: 0 | K12: 12
A13: Employee 3 | D13: 0 | E13: =Settings!$B$8 | F13: =D13/(1-E13) | G13: =D13*12 | I13: =IFERROR(VLOOKUP(H13,Roadmap!$A$7:$D$110,3,0),"not set, choose the event") | J13: 0 | K13: 12
A14: Employee 4 | D14: 0 | E14: =Settings!$B$8 | F14: =D14/(1-E14) | G14: =D14*12 | I14: =IFERROR(VLOOKUP(H14,Roadmap!$A$7:$D$110,3,0),"not set, choose the event") | J14: 0 | K14: 12
A16: IT
A17: CTO | D17: 10000 | E17: =Settings!$B$8 | F17: =D17/(1-E17) | G17: =D17*12 | H17: Seed round money transfer | I17: =IFERROR(VLOOKUP(H17,Roadmap!$A$7:$D$110,3,0),"not set, choose the event") | J17: 0 | K17: 12
A18: Developer frontend | D18: 4000 | E18: =Settings!$B$8 | F18: =D18/(1-E18) | G18: =D18*12 | H18: Seed round money transfer | I18: =IFERROR(VLOOKUP(H18,Roadmap!$A$7:$D$110,3,0),"not set, choose the event") | J18: 0.04 | K18: 12
A19: Developer backend | D19: 0 | E19: =Settings!$B$8 | F19: =D19/(1-E19) | G19: =D19*12 | I19: =IFERROR(VLOOKUP(H19,Roadmap!$A$7:$D$110,3,0),"not set, choose the event") | J19: 0 | K19: 12
A20: Developer fullstack | D20: 0 | E20: =Settings!$B$8 | F20: =D20/(1-E20) | G20: =D20*12 | I20: =IFERROR(VLOOKUP(H20,Roadmap!$A$7:$D$110,3,0),"not set, choose the event") | J20: 0 | K20: 12
A21: UX designer | D21: 3500 | E21: =Settings!$B$8 | F21: =D21/(1-E21) | G21: =D21*12 | I21: =IFERROR(VLOOKUP(H21,Roadmap!$A$7:$D$110,3,0),"not set, choose the event") | J21: 0 | K21: 12
A22: Product manager | D22: 0 | E22: =Settings!$B$8 | F22: =D22/(1-E22) | G22: =D22*12 | I22: =IFERROR(VLOOKUP(H22,Roadmap!$A$7:$D$110,3,0),"not set, choose the event") | J22: 0 | K22: 12
A23: DevOps | D23: 0 | E23: =Settings!$B$8 | F23: =D23/(1-E23) | G23: =D23*12 | I23: =IFERROR(VLOOKUP(H23,Roadmap!$A$7:$D$110,3,0),"not set, choose the event") | J23: 0 | K23: 12
A24: Project Manager | D24: 0 | E24: =Settings!$B$8 | F24: =D24/(1-E24) | G24: =D24*12 | I24: =IFERROR(VLOOKUP(H24,Roadmap!$A$7:$D$110,3,0),"not set, choose the event") | J24: 0 | K24: 12
A25: Developer cross-platform | D25: 0 | E25: =Settings!$B$8 | F25: =D25/(1-E25) | G25: =D25*12 | I25: =IFERROR(VLOOKUP(H25,Roadmap!$A$7:$D$110,3,0),"not set, choose the event") | J25: 0 | K25: 12
A26: QA | D26: 0 | E26: =Settings!$B$8 | F26: =D26/(1-E26) | G26: =D26*12 | I26: =IFERROR(VLOOKUP(H26,Roadmap!$A$7:$D$110,3,0),"not set, choose the event") | J26: 0 | K26: 12
A27: Security engineer | D27: 0 | E27: =Settings!$B$8 | F27: =D27/(1-E27) | G27: =D27*12 | I27: =IFERROR(VLOOKUP(H27,Roadmap!$A$7:$D$110,3,0),"not set, choose the event") | J27: 0 | K27: 12
A28: Employee 4 | D28: 0 | E28: =Settings!$B$8 | F28: =D28/(1-E28) | G28: =D28*12 | I28: =IFERROR(VLOOKUP(H28,Roadmap!$A$7:$D$110,3,0),"not set, choose the event") | J28: 0 | K28: 12
A30: Marketing
A31: Head of Marketing | D31: 3000 | E31: =Settings!$B$8 | F31: =D31/(1-E31) | G31: =D31*12 | H31: Seed round money transfer | I31: =IFERROR(VLOOKUP(H31,Roadmap!$A$7:$D$110,3,0),"not set, choose the event") | J31: 0.04 | K31: 12
A32: Content Marketing Manager | D32: 0 | E32: =Settings!$B$8 | F32: =D32/(1-E32) | G32: =D32*12 | I32: =IFERROR(VLOOKUP(H32,Roadmap!$A$7:$D$110,3,0),"not set, choose the event") | J32: 0 | K32: 12
A33: Performance Marketing Manager | D33: 0 | E33: =Settings!$B$8 | F33: =D33/(1-E33) | G33: =D33*12 | I33: =IFERROR(VLOOKUP(H33,Roadmap!$A$7:$D$110,3,0),"not set, choose the event") | J33: 0 | K33: 12
A34: Community Manager / SMM | D34: 0 | E34: =Settings!$B$8 | F34: =D34/(1-E34) | G34: =D34*12 | I34: =IFERROR(VLOOKUP(H34,Roadmap!$A$7:$D$110,3,0),"not set, choose the event") | J34: 0 | K34: 12
A35: PR / Comms Manager | D35: 0 | E35: =Settings!$B$8 | F35: =D35/(1-E35) | G35: =D35*12 | I35: =IFERROR(VLOOKUP(H35,Roadmap!$A$7:$D$110,3,0),"not set, choose the event") | J35: 0 | K35: 12
A36: Marketing Designer | D36: 0 | E36: =Settings!$B$8 | F36: =D36/(1-E36) | G36: =D36*12 | I36: =IFERROR(VLOOKUP(H36,Roadmap!$A$7:$D$110,3,0),"not set, choose the event") | J36: 0 | K36: 12
A37: Employee 3 | D37: 0 | E37: =Settings!$B$8 | F37: =D37/(1-E37) | G37: =D37*12 | I37: =IFERROR(VLOOKUP(H37,Roadmap!$A$7:$D$110,3,0),"not set, choose the event") | J37: 0 | K37: 12
A38: Employee 4 | D38: 0 | E38: =Settings!$B$8 | F38: =D38/(1-E38) | G38: =D38*12 | I38: =IFERROR(VLOOKUP(H38,Roadmap!$A$7:$D$110,3,0),"not set, choose the event") | J38: 0 | K38: 12
A40: Sales
A41: Head of Sales | D41: 5000 | E41: =Settings!$B$8 | F41: =D41/(1-E41) | G41: =D41*12 | H41: Incorporation | I41: =IFERROR(VLOOKUP(H41,Roadmap!$A$7:$D$110,3,0),"not set, choose the event") | J41: 0.02 | K41: 12
A42: BDM | D42: 5000 | E42: =Settings!$B$8 | F42: =D42/(1-E42) | G42: =D42*12 | H42: Incorporation | I42: =IFERROR(VLOOKUP(H42,Roadmap!$A$7:$D$110,3,0),"not set, choose the event") | J42: 0.02 | K42: 12
A43: Partnerships Manager | D43: 1000 | E43: =Settings!$B$8 | F43: =D43/(1-E43) | G43: =D43*12 | H43: Incorporation | I43: =IFERROR(VLOOKUP(H43,Roadmap!$A$7:$D$110,3,0),"not set, choose the event") | J43: 0.02 | K43: 12
A44: Inbound Sales Manager | D44: 1000 | E44: =Settings!$B$8 | F44: =D44/(1-E44) | G44: =D44*12 | H44: Incorporation | I44: =IFERROR(VLOOKUP(H44,Roadmap!$A$7:$D$110,3,0),"not set, choose the event") | J44: 0.02 | K44: 12
A45: SDR | D45: 1000 | E45: =Settings!$B$8 | F45: =D45/(1-E45) | G45: =D45*12 | H45: Incorporation | I45: =IFERROR(VLOOKUP(H45,Roadmap!$A$7:$D$110,3,0),"not set, choose the event") | J45: 0.02 | K45: 12
A46: Employee | D46: 0 | E46: =Settings!$B$8 | F46: =D46/(1-E46) | G46: =D46*12 | H46: Incorporation | I46: =IFERROR(VLOOKUP(H46,Roadmap!$A$7:$D$110,3,0),"not set, choose the event") | J46: 0.02 | K46: 12
A48: Customer Success & Support
A49: Head of Customer Success | D49: 1000 | E49: =Settings!$B$8 | F49: =D49/(1-E49) | G49: =D49*12 | H49: Seed round money transfer | I49: =IFERROR(VLOOKUP(H49,Roadmap!$A$7:$D$110,3,0),"not set, choose the event") | J49: 0 | K49: 12
A50: Customer Success / Account Manager | D50: 1000 | E50: =Settings!$B$8 | F50: =D50/(1-E50) | G50: =D50*12 | H50: Seed round money transfer | I50: =IFERROR(VLOOKUP(H50,Roadmap!$A$7:$D$110,3,0),"not set, choose the event") | J50: 0 | K50: 12
A51: Onboarding manager | D51: 0 | E51: =Settings!$B$8 | F51: =D51/(1-E51) | G51: =D51*12 | I51: =IFERROR(VLOOKUP(H51,Roadmap!$A$7:$D$110,3,0),"not set, choose the event") | J51: 0 | K51: 12
A52: Technical Support Specialist 1 | D52: 0 | E52: =Settings!$B$8 | F52: =D52/(1-E52) | G52: =D52*12 | I52: =IFERROR(VLOOKUP(H52,Roadmap!$A$7:$D$110,3,0),"not set, choose the event") | J52: 0 | K52: 12
A53: Technical Support Specialist 2 | D53: 0 | E53: =Settings!$B$8 | F53: =D53/(1-E53) | G53: =D53*12 | I53: =IFERROR(VLOOKUP(H53,Roadmap!$A$7:$D$110,3,0),"not set, choose the event") | J53: 0 | K53: 12
A54: Project manager CS | D54: 0 | E54: =Settings!$B$8 | F54: =D54/(1-E54) | G54: =D54*12 | I54: =IFERROR(VLOOKUP(H54,Roadmap!$A$7:$D$110,3,0),"not set, choose the event") | J54: 0 | K54: 12
A55: Account Manager | D55: 8000 | E55: =Settings!$B$8 | F55: =D55/(1-E55) | G55: =D55*12 | H55: B2B solution: 50 clients | I55: =IFERROR(VLOOKUP(H55,Roadmap!$A$7:$D$110,3,0),"not set, choose the event") | J55: 0 | K55: 12
A56: Employee 4 | D56: 0 | E56: =Settings!$B$8 | F56: =D56/(1-E56) | G56: =D56*12 | I56: =IFERROR(VLOOKUP(H56,Roadmap!$A$7:$D$110,3,0),"not set, choose the event") | J56: 0 | K56: 12

Sheet Projections
A1: Healthy4U Revenue Projections | K1: Updated: 2026-01-27
A3: CONSERVATIVE SCENARIO (3 doctors by Month 3)
A4: Month | B4: Doctors | C4: Doctor MRR | D4: Patients | E4: Patient MRR | F4: Rev Share | G4: Net Patient | H4: Total MRR | I4: Total COGS | J4: Profit | K4: Margin %
A5: 1 | B5: 1 | C5: $174 | D5: 15 | E5: $150 | F5: -$38 | G5: $112 | H5: $286 | I5: $80 | J5: $206 | K5: 72%
A6: 2 | B6: 2 | C6: $348 | D6: 30 | E6: $300 | F6: -$75 | G6: $225 | H6: $573 | I6: $159 | J6: $414 | K6: 72%
A7: 3 | B7: 3 | C7: $547 | D7: 45 | E7: $450 | F7: -$113 | G7: $337 | H7: $884 | I7: $239 | J7: $645 | K7: 73%
A9: Q1 Total Revenue | H9: $1,743
A10: Month 3 ARR | H10: $10,608
A12: TARGET SCENARIO (5 doctors by Month 3)
A13: Month | B13: Doctors | C13: Doctor MRR | D13: Patients | E13: Patient MRR | F13: Rev Share | G13: Net Patient | H13: Total MRR | I13: Total COGS | J13: Profit | K13: Margin %
A14: 1 | B14: 2 | C14: $348 | D14: 30 | E14: $300 | F14: -$75 | G14: $225 | H14: $573 | I14: $159 | J14: $414 | K14: 72%
A15: 2 | B15: 4 | C15: $721 | D15: 60 | E15: $599 | F15: -$150 | G15: $449 | H15: $1,170 | I15: $319 | J15: $852 | K15: 73%
A16: 3 | B16: 5 | C16: $920 | D16: 75 | E16: $749 | F16: -$188 | G16: $562 | H16: $1,482 | I16: $398 | J16: $1,084 | K16: 73%
A18: Q1 Total Revenue | H18: $3,225
A19: Month 3 ARR | H19: $17,781
A21: AGGRESSIVE SCENARIO (8 doctors by Month 6)
A22: Month | B22: Doctors | C22: Doctor MRR | D22: Patients | E22: Patient MRR | F22: Rev Share | G22: Net Patient | H22: Total MRR | I22: Total COGS | J22: Profit | K22: Margin %
A23: 6 | B23: 8 | C23: $1,880 | D23: 120 | E23: $1,199 | F23: -$300 | G23: $899 | H23: $2,779 | I23: $637 | J23: $2,142 | K23: 77%
A25: Month 6 ARR | H25: $33,345

Sheet Charts
B1: =Settings!$B$4
B2: KEY INDICATORS
B20: CAPITAL
C22: Months to reach break even | D22: =COUNTIF('P&L | Cash Flow | Balance'!28:28,"<=0")
C24: Capital required | D24: =iferror(-MIN('P&L | Cash Flow | Balance'!39:39),"-")
B26: REVENUE

Sheet For Pitchdeck
C2: =YEAR('Monthly forecast'!E2) | D2: =C2+1 | E2: =D2+1 | F2: =E2+1 | G2: =F2+1 | I2: * Для слайда питчдека "Финансовый прогноз" ("Financial Forecast") скопируйте таблицу и графики на этом листе, которые показывают динамику выручки и прибыли по годам.
B3: ='P&L | Cash Flow | Balance'!A6 | C3: =SUM(C4:C6) | D3: =SUM(D4:D6) | E3: =SUM(E4:E6) | F3: =SUM(F4:F6) | G3: =SUM(G4:G6)
B4: ='P&L | Cash Flow | Balance'!A7 | C4: =SUMIFS('P&L | Cash Flow | Balance'!D7:CW7,'P&L | Cash Flow | Balance'!D2:CW2,">="&DATE(C2,1,1),'P&L | Cash Flow | Balance'!D2:CW2,"<="&DATE(C2,12,31)) | D4: =SUMIFS('P&L | Cash Flow | Balance'!E7:CX7,'P&L | Cash Flow | Balance'!E2:CX2,">="&DATE(D2,1,1),'P&L | Cash Flow | Balance'!E2:CX2,"<="&DATE(D2,12,31)) | E4: =SUMIFS('P&L | Cash Flow | Balance'!F7:CY7,'P&L | Cash Flow | Balance'!F2:CY2,">="&DATE(E2,1,1),'P&L | Cash Flow | Balance'!F2:CY2,"<="&DATE(E2,12,31)) | F4: =SUMIFS('P&L | Cash Flow | Balance'!G7:CZ7,'P&L | Cash Flow | Balance'!G2:CZ2,">="&DATE(F2,1,1),'P&L | Cash Flow | Balance'!G2:CZ2,"<="&DATE(F2,12,31)) | G4: =SUMIFS('P&L | Cash Flow | Balance'!H7:DA7,'P&L | Cash Flow | Balance'!H2:DA2,">="&DATE(G2,1,1),'P&L | Cash Flow | Balance'!H2:DA2,"<="&DATE(G2,12,31))
B5: ='P&L | Cash Flow | Balance'!A8 | C5: =SUMIFS('P&L | Cash Flow | Balance'!D8:CW8,'P&L | Cash Flow | Balance'!D2:CW2,">="&DATE(C2,1,1),'P&L | Cash Flow | Balance'!D2:CW2,"<="&DATE(C2,12,31)) | D5: =SUMIFS('P&L | Cash Flow | Balance'!E8:CX8,'P&L | Cash Flow | Balance'!E2:CX2,">="&DATE(D2,1,1),'P&L | Cash Flow | Balance'!E2:CX2,"<="&DATE(D2,12,31)) | E5: =SUMIFS('P&L | Cash Flow | Balance'!F8:CY8,'P&L | Cash Flow | Balance'!F2:CY2,">="&DATE(E2,1,1),'P&L | Cash Flow | Balance'!F2:CY2,"<="&DATE(E2,12,31)) | F5: =SUMIFS('P&L | Cash Flow | Balance'!G8:CZ8,'P&L | Cash Flow | Balance'!G2:CZ2,">="&DATE(F2,1,1),'P&L | Cash Flow | Balance'!G2:CZ2,"<="&DATE(F2,12,31)) | G5: =SUMIFS('P&L | Cash Flow | Balance'!H8:DA8,'P&L | Cash Flow | Balance'!H2:DA2,">="&DATE(G2,1,1),'P&L | Cash Flow | Balance'!H2:DA2,"<="&DATE(G2,12,31))
B6: ='P&L | Cash Flow | Balance'!A9 | C6: =SUMIFS('P&L | Cash Flow | Balance'!D9:CW9,'P&L | Cash Flow | Balance'!D2:CW2,">="&DATE(C2,1,1),'P&L | Cash Flow | Balance'!D2:CW2,"<="&DATE(C2,12,31)) | D6: =SUMIFS('P&L | Cash Flow | Balance'!E9:CX9,'P&L | Cash Flow | Balance'!E2:CX2,">="&DATE(D2,1,1),'P&L | Cash Flow | Balance'!E2:CX2,"<="&DATE(D2,12,31)) | E6: =SUMIFS('P&L | Cash Flow | Balance'!F9:CY9,'P&L | Cash Flow | Balance'!F2:CY2,">="&DATE(E2,1,1),'P&L | Cash Flow | Balance'!F2:CY2,"<="&DATE(E2,12,31)) | F6: =SUMIFS('P&L | Cash Flow | Balance'!G9:CZ9,'P&L | Cash Flow | Balance'!G2:CZ2,">="&DATE(F2,1,1),'P&L | Cash Flow | Balance'!G2:CZ2,"<="&DATE(F2,12,31)) | G6: =SUMIFS('P&L | Cash Flow | Balance'!H9:DA9,'P&L | Cash Flow | Balance'!H2:DA2,">="&DATE(G2,1,1),'P&L | Cash Flow | Balance'!H2:DA2,"<="&DATE(G2,12,31))
B7: ='P&L | Cash Flow | Balance'!A17 | C7: =SUMIFS('P&L | Cash Flow | Balance'!D17:CW17,'P&L | Cash Flow | Balance'!D2:CW2,">="&DATE(C2,1,1),'P&L | Cash Flow | Balance'!D2:CW2,"<="&DATE(C2,12,31)) | D7: =SUMIFS('P&L | Cash Flow | Balance'!E17:CX17,'P&L | Cash Flow | Balance'!E2:CX2,">="&DATE(D2,1,1),'P&L | Cash Flow | Balance'!E2:CX2,"<="&DATE(D2,12,31)) | E7: =SUMIFS('P&L | Cash Flow | Balance'!F17:CY17,'P&L | Cash Flow | Balance'!F2:CY2,">="&DATE(E2,1,1),'P&L | Cash Flow | Balance'!F2:CY2,"<="&DATE(E2,12,31)) | F7: =SUMIFS('P&L | Cash Flow | Balance'!G17:CZ17,'P&L | Cash Flow | Balance'!G2:CZ2,">="&DATE(F2,1,1),'P&L | Cash Flow | Balance'!G2:CZ2,"<="&DATE(F2,12,31)) | G7: =SUMIFS('P&L | Cash Flow | Balance'!H17:DA17,'P&L | Cash Flow | Balance'!H2:DA2,">="&DATE(G2,1,1),'P&L | Cash Flow | Balance'!H2:DA2,"<="&DATE(G2,12,31))
B8: ='P&L | Cash Flow | Balance'!A28 | C8: =SUMIFS('P&L | Cash Flow | Balance'!D28:CW28,'P&L | Cash Flow | Balance'!D2:CW2,">="&DATE(C2,1,1),'P&L | Cash Flow | Balance'!D2:CW2,"<="&DATE(C2,12,31)) | D8: =SUMIFS('P&L | Cash Flow | Balance'!E28:CX28,'P&L | Cash Flow | Balance'!E2:CX2,">="&DATE(D2,1,1),'P&L | Cash Flow | Balance'!E2:CX2,"<="&DATE(D2,12,31)) | E8: =SUMIFS('P&L | Cash Flow | Balance'!F28:CY28,'P&L | Cash Flow | Balance'!F2:CY2,">="&DATE(E2,1,1),'P&L | Cash Flow | Balance'!F2:CY2,"<="&DATE(E2,12,31)) | F8: =SUMIFS('P&L | Cash Flow | Balance'!G28:CZ28,'P&L | Cash Flow | Balance'!G2:CZ2,">="&DATE(F2,1,1),'P&L | Cash Flow | Balance'!G2:CZ2,"<="&DATE(F2,12,31)) | G8: =SUMIFS('P&L | Cash Flow | Balance'!H28:DA28,'P&L | Cash Flow | Balance'!H2:DA2,">="&DATE(G2,1,1),'P&L | Cash Flow | Balance'!H2:DA2,"<="&DATE(G2,12,31))

Sheet Monthly forecast
A1: =Settings!B4
A2: Month | B2: Expense category | D2: =EDATE(E2,-1) | E2: =Projections!$B$4 | F2: =EDATE(E2,1) | G2: =EDATE(F2,1) | H2: =EDATE(G2,1) | I2: =EDATE(H2,1) | J2: =EDATE(I2,1) | K2: =EDATE(J2,1) | L2: =EDATE(K2,1) | M2: =EDATE(L2,1) | ... CX2: =EDATE(CW2,1)
A4: REVENUE
A6: KEY INDICATORS
A8: Traffic | Z8: =N8*(1+Projections!$B$14)
A9: Organic traffic | E9: =IF(E2=Projections!$D$13,Projections!$B$13,IF(E2>Projections!$D$13,MIN(D9*(1+Projections!$B$14),Projections!$B$15),0)) | F9: =IF(F2=Projections!$D$13,Projections!$B$13,IF(F2>Projections!$D$13,MIN(E9*(1+Projections!$B$14),Projections!$B$15),0)) | G9: =IF(G2=Projections!$D$13,Projections!$B$13,IF(G2>Projections!$D$13,MIN(F9*(1+Projections!$B$14),Projections!$B$15),0)) | H9: =IF(H2=Projections!$D$13,Projections!$B$13,IF(H2>Projections!$D$13,MIN(G9*(1+Projections!$B$14),Projections!$B$15),0)) | I9: =IF(I2=Projections!$D$13,Projections!$B$13,IF(I2>Projections!$D$13,MIN(H9*(1+Projections!$B$14),Projections!$B$15),0)) | J9: =IF(J2=Projections!$D$13,Projections!$B$13,IF(J2>Projections!$D$13,MIN(I9*(1+Projections!$B$14),Projections!$B$15),0)) | K9: =IF(K2=Projections!$D$13,Projections!$B$13,IF(K2>Projections!$D$13,MIN(J9*(1+Projections!$B$14),Projections!$B$15),0)) | L9: =IF(L2=Projections!$D$13,Projections!$B$13,IF(L2>Projections!$D$13,MIN(K9*(1+Projections!$B$14),Projections!$B$15),0)) | ... CX9: =IF(CX2=Projections!$D$13,Projections!$B$13,IF(CX2>Projections!$D$13,MIN(CW9*(1+Projections!$B$14),Projections!$B$15),0))
A10: CPC | E10: =IF(E2=Projections!$D$19,Projections!$B$21,IF(E2>Projections!$D$19,MAX(Projections!$B$23,D10*(1-Projections!$B$22)),0)) | F10: =IF(F2=Projections!$D$19,Projections!$B$21,IF(F2>Projections!$D$19,MAX(Projections!$B$23,E10*(1-Projections!$B$22)),0)) | G10: =IF(G2=Projections!$D$19,Projections!$B$21,IF(G2>Projections!$D$19,MAX(Projections!$B$23,F10*(1-Projections!$B$22)),0)) | H10: =IF(H2=Projections!$D$19,Projections!$B$21,IF(H2>Projections!$D$19,MAX(Projections!$B$23,G10*(1-Projections!$B$22)),0)) | I10: =IF(I2=Projections!$D$19,Projections!$B$21,IF(I2>Projections!$D$19,MAX(Projections!$B$23,H10*(1-Projections!$B$22)),0)) | J10: =IF(J2=Projections!$D$19,Projections!$B$21,IF(J2>Projections!$D$19,MAX(Projections!$B$23,I10*(1-Projections!$B$22)),0)) | K10: =IF(K2=Projections!$D$19,Projections!$B$21,IF(K2>Projections!$D$19,MAX(Projections!$B$23,J10*(1-Projections!$B$22)),0)) | L10: =IF(L2=Projections!$D$19,Projections!$B$21,IF(L2>Projections!$D$19,MAX(Projections!$B$23,K10*(1-Projections!$B$22)),0)) | ... CX10: =IF(CX2=Projections!$D$19,Projections!$B$21,IF(CX2>Projections!$D$19,MAX(Projections!$B$23,CW10*(1-Projections!$B$22)),0))
A11: Paid traffic | E11: =IFERROR(E65/E10,0) | F11: =IFERROR(F65/F10,0) | G11: =IFERROR(G65/G10,0) | H11: =IFERROR(H65/H10,0) | I11: =IFERROR(I65/I10,0) | J11: =IFERROR(J65/J10,0) | K11: =IFERROR(K65/K10,0) | L11: =IFERROR(L65/L10,0) | ... CX11: =IFERROR(CX65/CX10,0)
A12: Total traffic | E12: =SUM(E9:E11) | F12: =SUM(F9:F11) | G12: =SUM(G9:G11) | H12: =SUM(H9:H11) | I12: =SUM(I9:I11) | J12: =SUM(J9:J11) | K12: =SUM(K9:K11) | L12: =SUM(L9:L11) | ... CX12: =SUM(CX9:CX11)
A15: =Projections!A33
A17: New subscribers | E17: =if(E2>=Projections!$D$28,E12*Projections!$B$36,0) | F17: =if(F2>=Projections!$D$28,F12*Projections!$B$36,0) | G17: =if(G2>=Projections!$D$28,G12*Projections!$B$36,0) | H17: =if(H2>=Projections!$D$28,H12*Projections!$B$36,0) | I17: =if(I2>=Projections!$D$28,I12*Projections!$B$36,0) | J17: =if(J2>=Projections!$D$28,J12*Projections!$B$36,0) | K17: =if(K2>=Projections!$D$28,K12*Projections!$B$36,0) | L17: =if(L2>=Projections!$D$28,L12*Projections!$B$36,0) | ... CX17: =if(CX2>=Projections!$D$28,CX12*Projections!$B$36,0)
A18: Churn rate | E18: =IF(E2>=Projections!$D$28,Projections!$B$30,0) | F18: =IF(F2>=Projections!$D$28,Projections!$B$30,0) | G18: =IF(G2>=Projections!$D$28,Projections!$B$30,0) | H18: =IF(H2>=Projections!$D$28,Projections!$B$30,0) | I18: =IF(I2>=Projections!$D$28,Projections!$B$30,0) | J18: =IF(J2>=Projections!$D$28,Projections!$B$30,0) | K18: =IF(K2>=Projections!$D$28,Projections!$B$30,0) | L18: =IF(L2>=Projections!$D$28,Projections!$B$30,0) | ... CX18: =IF(CX2>=Projections!$D$28,Projections!$B$30,0)
A19: Lost subscribers | E19: =D20*E18 | F19: =E20*F18 | G19: =F20*G18 | H19: =G20*H18 | I19: =H20*I18 | J19: =I20*J18 | K19: =J20*K18 | L19: =K20*L18 | ... CX19: =CW20*CX18
A20: Subscribers - End of the period | E20: =D20+E17-E19 | F20: =E20+F17-F19 | G20: =F20+G17-G19 | H20: =G20+H17-H19 | I20: =H20+I17-I19 | J20: =I20+J17-J19 | K20: =J20+K17-K19 | L20: =K20+L17-L19 | ... CX20: =CW20+CX17-CX19
A22: Gross revenue Self-service | E22: =E20*Projections!$B$28 | F22: =F20*Projections!$B$28 | G22: =G20*Projections!$B$28 | H22: =H20*Projections!$B$28 | I22: =I20*Projections!$B$28 | J22: =J20*Projections!$B$28 | K22: =K20*Projections!$B$28 | L22: =L20*Projections!$B$28 | ... CX22: =CX20*Projections!$B$28
A24: =Projections!A39
A26: Leads | E26: =if(E2>=Projections!$C$42,E12*Projections!$B$45,0) | F26: =if(F2>=Projections!$C$42,F12*Projections!$B$45,0) | G26: =if(G2>=Projections!$C$42,G12*Projections!$B$45,0) | H26: =if(H2>=Projections!$C$42,H12*Projections!$B$45,0) | I26: =if(I2>=Projections!$C$42,I12*Projections!$B$45,0) | J26: =if(J2>=Projections!$C$42,J12*Projections!$B$45,0) | K26: =if(K2>=Projections!$C$42,K12*Projections!$B$45,0) | L26: =if(L2>=Projections!$C$42,L12*Projections!$B$45,0) | ... CX26: =if(CX2>=Projections!$C$42,CX12*Projections!$B$45,0)
A28: New subscribers | E28: =IFERROR(E26*Projections!$B$50,0) | F28: =IFERROR(F26*Projections!$B$50,0) | G28: =IFERROR(G26*Projections!$B$50,0) | H28: =IFERROR(H26*Projections!$B$50,0) | I28: =IFERROR(I26*Projections!$B$50,0) | J28: =IFERROR(J26*Projections!$B$50,0) | K28: =IFERROR(K26*Projections!$B$50,0) | L28: =IFERROR(L26*Projections!$B$50,0) | ... CX28: =IFERROR(CX26*Projections!$B$50,0)
A29: Churn rate | E29: =IF(E2>=Projections!$D$28,Projections!$B$30,0) | F29: =IF(F2>=Projections!$D$28,Projections!$B$30,0) | G29: =IF(G2>=Projections!$D$28,Projections!$B$30,0) | H29: =IF(H2>=Projections!$D$28,Projections!$B$30,0) | I29: =IF(I2>=Projections!$D$28,Projections!$B$30,0) | J29: =IF(J2>=Projections!$D$28,Projections!$B$30,0) | K29: =IF(K2>=Projections!$D$28,Projections!$B$30,0) | L29: =IF(L2>=Projections!$D$28,Projections!$B$30,0) | ... CX29: =IF(CX2>=Projections!$D$28,Projections!$B$30,0)
A30: Lost subscribers | E30: =D31*E29 | F30: =E31*F29 | G30: =F31*G29 | H30: =G31*H29 | I30: =H31*I29 | J30: =I31*J29 | K30: =J31*K29 | L30: =K31*L29 | ... CX30: =CW31*CX29
A31: Subscribers - End of the period | E31: =D31+E28-E30 | F31: =E31+F28-F30 | G31: =F31+G28-G30 | H31: =G31+H28-H30 | I31: =H31+I28-I30 | J31: =I31+J28-J30 | K31: =J31+K28-K30 | L31: =K31+L28-L30 | ... CX31: =CW31+CX28-CX30
A33: Gross revenue Inbound Sales | E33: =E31*Projections!$B$28 | F33: =F31*Projections!$B$28 | G33: =G31*Projections!$B$28 | H33: =H31*Projections!$B$28 | I33: =I31*Projections!$B$28 | J33: =J31*Projections!$B$28 | K33: =K31*Projections!$B$28 | L33: =L31*Projections!$B$28 | ... CX33: =CX31*Projections!$B$28
A35: =Projections!A53
A37: New subscribers | E37: =E87*Projections!$B$62 | F37: =F87*Projections!$B$62 | G37: =G87*Projections!$B$62 | H37: =H87*Projections!$B$62 | I37: =I87*Projections!$B$62 | J37: =J87*Projections!$B$62 | K37: =K87*Projections!$B$62 | L37: =L87*Projections!$B$62 | ... CX37: =CX87*Projections!$B$62
A38: Churn rate | E38: =IF(E2>=Projections!$D$28,Projections!$B$30,0) | F38: =IF(F2>=Projections!$D$28,Projections!$B$30,0) | G38: =IF(G2>=Projections!$D$28,Projections!$B$30,0) | H38: =IF(H2>=Projections!$D$28,Projections!$B$30,0) | I38: =IF(I2>=Projections!$D$28,Projections!$B$30,0) | J38: =IF(J2>=Projections!$D$28,Projections!$B$30,0) | K38: =IF(K2>=Projections!$D$28,Projections!$B$30,0) | L38: =IF(L2>=Projections!$D$28,Projections!$B$30,0) | ... CX38: =IF(CX2>=Projections!$D$28,Projections!$B$30,0)
A39: Lost subscribers | E39: =D40*E38 | F39: =E40*F38 | G39: =F40*G38 | H39: =G40*H38 | I39: =H40*I38 | J39: =I40*J38 | K39: =J40*K38 | L39: =K40*L38 | ... CX39: =CW40*CX38
A40: Subscribers - End of the period | E40: =D40+E37-E39 | F40: =E40+F37-F39 | G40: =F40+G37-G39 | H40: =G40+H37-H39 | I40: =H40+I37-I39 | J40: =I40+J37-J39 | K40: =J40+K37-K39 | L40: =K40+L37-L39 | ... CX40: =CW40+CX37-CX39
A42: Gross revenue Outbound Sales | E42: =E40*Projections!$B$28 | F42: =F40*Projections!$B$28 | G42: =G40*Projections!$B$28 | H42: =H40*Projections!$B$28 | I42: =I40*Projections!$B$28 | J42: =J40*Projections!$B$28 | K42: =K40*Projections!$B$28 | L42: =L40*Projections!$B$28 | ... CX42: =CX40*Projections!$B$28
A44: Total subscribers - End of the period | E44: =E40+E31+E20 | F44: =F40+F31+F20 | G44: =G40+G31+G20 | H44: =H40+H31+H20 | I44: =I40+I31+I20 | J44: =J40+J31+J20 | K44: =K40+K31+K20 | L44: =L40+L31+L20 | ... CX44: =CX40+CX31+CX20
A45: Total gross revenue | E45: =E42+E33+E22 | F45: =F42+F33+F22 | G45: =G42+G33+G22 | H45: =H42+H33+H22 | I45: =I42+I33+I22 | J45: =J42+J33+J22 | K45: =K42+K33+K22 | L45: =L42+L33+L22 | ... CX45: =CX42+CX33+CX22
A47: COGS | E47: =SUM(E49:E50) | F47: =SUM(F49:F50) | G47: =SUM(G49:G50) | H47: =SUM(H49:H50) | I47: =SUM(I49:I50) | J47: =SUM(J49:J50) | K47: =SUM(K49:K50) | L47: =SUM(L49:L50) | ... CX47: =SUM(CX49:CX50)
A49: Hosting | E49: =E44*Projections!$B$68 | F49: =F44*Projections!$B$68 | G49: =G44*Projections!$B$68 | H49: =H44*Projections!$B$68 | I49: =I44*Projections!$B$68 | J49: =J44*Projections!$B$68 | K49: =K44*Projections!$B$68 | L49: =L44*Projections!$B$68 | ... CX49: =CX44*Projections!$B$68
A50: Payments processing | E50: =E45*Projections!$B$67 | F50: =F45*Projections!$B$67 | G50: =G45*Projections!$B$67 | H50: =H45*Projections!$B$67 | I50: =I45*Projections!$B$67 | J50: =J45*Projections!$B$67 | K50: =K45*Projections!$B$67 | L50: =L45*Projections!$B$67 | ... CX50: =CX45*Projections!$B$67
A53: SG&A | E53: =E55+E79+E91+E139+E151 | F53: =F55+F79+F91+F139+F151 | G53: =G55+G79+G91+G139+G151 | H53: =H55+H79+H91+H139+H151 | I53: =I55+I79+I91+I139+I151 | J53: =J55+J79+J91+J139+J151 | K53: =K55+K79+K91+K139+K151 | L53: =L55+L79+L91+L139+L151 | ... CX53: =CX55+CX79+CX91+CX139+CX151
A55: MARKETING | E55: =E57+E65+E68 | F55: =F57+F65+F68 | G55: =G57+G65+G68 | H55: =H57+H65+H68 | I55: =I57+I65+I68 | J55: =J57+J65+J68 | K55: =K57+K65+K68 | L55: =L57+L65+L68 | ... CX55: =CX57+CX65+CX68
A57: =Projections!A75 | B57: Marketing | E57: =SUM(E58:E60) | F57: =SUM(F58:F60) | G57: =SUM(G58:G60) | H57: =SUM(H58:H60) | I57: =SUM(I58:I60) | J57: =SUM(J58:J60) | K57: =SUM(K58:K60) | L57: =SUM(L58:L60) | ... CX57: =SUM(CX58:CX60)
A58: =Projections!A76 | E58: =IF(E$2<Projections!$D76,0,IF(and(E$2>=Projections!$D76,E$2<Projections!$F76),Projections!$B76,if(and(E$2>=Projections!$F76,E$2<Projections!$I76),Projections!$B76+Projections!$G76,if(and(E$2>=Projections!$I76,E$2<Projections!$L76),Projections!$B76+Projections!$G76+Projections!$J76,IF(E$2>=Projections!$L76,Projections!$B76+Projections!$G76+Projections!$J76+Projections!$M76,""))))) | F58: =IF(F$2<Projections!$D76,0,IF(and(F$2>=Projections!$D76,F$2<Projections!$F76),Projections!$B76,if(and(F$2>=Projections!$F76,F$2<Projections!$I76),Projections!$B76+Projections!$G76,if(and(F$2>=Projections!$I76,F$2<Projections!$L76),Projections!$B76+Projections!$G76+Projections!$J76,IF(F$2>=Projections!$L76,Projections!$B76+Projections!$G76+Projections!$J76+Projections!$M76,""))))) | G58: =IF(G$2<Projections!$D76,0,IF(and(G$2>=Projections!$D76,G$2<Projections!$F76),Projections!$B76,if(and(G$2>=Projections!$F76,G$2<Projections!$I76),Projections!$B76+Projections!$G76,if(and(G$2>=Projections!$I76,G$2<Projections!$L76),Projections!$B76+Projections!$G76+Projections!$J76,IF(G$2>=Projections!$L76,Projections!$B76+Projections!$G76+Projections!$J76+Projections!$M76,""))))) | H58: =IF(H$2<Projections!$D76,0,IF(and(H$2>=Projections!$D76,H$2<Projections!$F76),Projections!$B76,if(and(H$2>=Projections!$F76,H$2<Projections!$I76),Projections!$B76+Projections!$G76,if(and(H$2>=Projections!$I76,H$2<Projections!$L76),Projections!$B76+Projections!$G76+Projections!$J76,IF(H$2>=Projections!$L76,Projections!$B76+Projections!$G76+Projections!$J76+Projections!$M76,""))))) | I58: =IF(I$2<Projections!$D76,0,IF(and(I$2>=Projections!$D76,I$2<Projections!$F76),Projections!$B76,if(and(I$2>=Projections!$F76,I$2<Projections!$I76),Projections!$B76+Projections!$G76,if(and(I$2>=Projections!$I76,I$2<Projections!$L76),Projections!$B76+Projections!$G76+Projections!$J76,IF(I$2>=Projections!$L76,Projections!$B76+Projections!$G76+Projections!$J76+Projections!$M76,""))))) | J58: =IF(J$2<Projections!$D76,0,IF(and(J$2>=Projections!$D76,J$2<Projections!$F76),Projections!$B76,if(and(J$2>=Projections!$F76,J$2<Projections!$I76),Projections!$B76+Projections!$G76,if(and(J$2>=Projections!$I76,J$2<Projections!$L76),Projections!$B76+Projections!$G76+Projections!$J76,IF(J$2>=Projections!$L76,Projections!$B76+Projections!$G76+Projections!$J76+Projections!$M76,""))))) | K58: =IF(K$2<Projections!$D76,0,IF(and(K$2>=Projections!$D76,K$2<Projections!$F76),Projections!$B76,if(and(K$2>=Projections!$F76,K$2<Projections!$I76),Projections!$B76+Projections!$G76,if(and(K$2>=Projections!$I76,K$2<Projections!$L76),Projections!$B76+Projections!$G76+Projections!$J76,IF(K$2>=Projections!$L76,Projections!$B76+Projections!$G76+Projections!$J76+Projections!$M76,""))))) | L58: =IF(L$2<Projections!$D76,0,IF(and(L$2>=Projections!$D76,L$2<Projections!$F76),Projections!$B76,if(and(L$2>=Projections!$F76,L$2<Projections!$I76),Projections!$B76+Projections!$G76,if(and(L$2>=Projections!$I76,L$2<Projections!$L76),Projections!$B76+Projections!$G76+Projections!$J76,IF(L$2>=Projections!$L76,Projections!$B76+Projections!$G76+Projections!$J76+Projections!$M76,""))))) | ... CX58: =IF(CX$2<Projections!$D76,0,IF(and(CX$2>=Projections!$D76,CX$2<Projections!$F76),Projections!$B76,if(and(CX$2>=Projections!$F76,CX$2<Projections!$I76),Projections!$B76+Projections!$G76,if(and(CX$2>=Projections!$I76,CX$2<Projections!$L76),Projections!$B76+Projections!$G76+Projections!$J76,IF(CX$2>=Projections!$L76,Projections!$B76+Projections!$G76+Projections!$J76+Projections!$M76,"")))))
A59: =Projections!A77 | E59: =IF(E$2<Projections!$D77,0,IF(and(E$2>=Projections!$D77,E$2<Projections!$F77),Projections!$B77,if(and(E$2>=Projections!$F77,E$2<Projections!$I77),Projections!$B77+Projections!$G77,if(and(E$2>=Projections!$I77,E$2<Projections!$L77),Projections!$B77+Projections!$G77+Projections!$J77,IF(E$2>=Projections!$L77,Projections!$B77+Projections!$G77+Projections!$J77+Projections!$M77,""))))) | F59: =IF(F$2<Projections!$D77,0,IF(and(F$2>=Projections!$D77,F$2<Projections!$F77),Projections!$B77,if(and(F$2>=Projections!$F77,F$2<Projections!$I77),Projections!$B77+Projections!$G77,if(and(F$2>=Projections!$I77,F$2<Projections!$L77),Projections!$B77+Projections!$G77+Projections!$J77,IF(F$2>=Projections!$L77,Projections!$B77+Projections!$G77+Projections!$J77+Projections!$M77,""))))) | G59: =IF(G$2<Projections!$D77,0,IF(and(G$2>=Projections!$D77,G$2<Projections!$F77),Projections!$B77,if(and(G$2>=Projections!$F77,G$2<Projections!$I77),Projections!$B77+Projections!$G77,if(and(G$2>=Projections!$I77,G$2<Projections!$L77),Projections!$B77+Projections!$G77+Projections!$J77,IF(G$2>=Projections!$L77,Projections!$B77+Projections!$G77+Projections!$J77+Projections!$M77,""))))) | H59: =IF(H$2<Projections!$D77,0,IF(and(H$2>=Projections!$D77,H$2<Projections!$F77),Projections!$B77,if(and(H$2>=Projections!$F77,H$2<Projections!$I77),Projections!$B77+Projections!$G77,if(and(H$2>=Projections!$I77,H$2<Projections!$L77),Projections!$B77+Projections!$G77+Projections!$J77,IF(H$2>=Projections!$L77,Projections!$B77+Projections!$G77+Projections!$J77+Projections!$M77,""))))) | I59: =IF(I$2<Projections!$D77,0,IF(and(I$2>=Projections!$D77,I$2<Projections!$F77),Projections!$B77,if(and(I$2>=Projections!$F77,I$2<Projections!$I77),Projections!$B77+Projections!$G77,if(and(I$2>=Projections!$I77,I$2<Projections!$L77),Projections!$B77+Projections!$G77+Projections!$J77,IF(I$2>=Projections!$L77,Projections!$B77+Projections!$G77+Projections!$J77+Projections!$M77,""))))) | J59: =IF(J$2<Projections!$D77,0,IF(and(J$2>=Projections!$D77,J$2<Projections!$F77),Projections!$B77,if(and(J$2>=Projections!$F77,J$2<Projections!$I77),Projections!$B77+Projections!$G77,if(and(J$2>=Projections!$I77,J$2<Projections!$L77),Projections!$B77+Projections!$G77+Projections!$J77,IF(J$2>=Projections!$L77,Projections!$B77+Projections!$G77+Projections!$J77+Projections!$M77,""))))) | K59: =IF(K$2<Projections!$D77,0,IF(and(K$2>=Projections!$D77,K$2<Projections!$F77),Projections!$B77,if(and(K$2>=Projections!$F77,K$2<Projections!$I77),Projections!$B77+Projections!$G77,if(and(K$2>=Projections!$I77,K$2<Projections!$L77),Projections!$B77+Projections!$G77+Projections!$J77,IF(K$2>=Projections!$L77,Projections!$B77+Projections!$G77+Projections!$J77+Projections!$M77,""))))) | L59: =IF(L$2<Projections!$D77,0,IF(and(L$2>=Projections!$D77,L$2<Projections!$F77),Projections!$B77,if(and(L$2>=Projections!$F77,L$2<Projections!$I77),Projections!$B77+Projections!$G77,if(and(L$2>=Projections!$I77,L$2<Projections!$L77),Projections!$B77+Projections!$G77+Projections!$J77,IF(L$2>=Projections!$L77,Projections!$B77+Projections!$G77+Projections!$J77+Projections!$M77,""))))) | ... CX59: =IF(CX$2<Projections!$D77,0,IF(and(CX$2>=Projections!$D77,CX$2<Projections!$F77),Projections!$B77,if(and(CX$2>=Projections!$F77,CX$2<Projections!$I77),Projections!$B77+Projections!$G77,if(and(CX$2>=Projections!$I77,CX$2<Projections!$L77),Projections!$B77+Projections!$G77+Projections!$J77,IF(CX$2>=Projections!$L77,Projections!$B77+Projections!$G77+Projections!$J77+Projections!$M77,"")))))
A60: =Projections!A78 | E60: =IF(E$2<Projections!$D78,0,IF(and(E$2>=Projections!$D78,E$2<Projections!$F78),Projections!$B78,if(and(E$2>=Projections!$F78,E$2<Projections!$I78),Projections!$B78+Projections!$G78,if(and(E$2>=Projections!$I78,E$2<Projections!$L78),Projections!$B78+Projections!$G78+Projections!$J78,IF(E$2>=Projections!$L78,Projections!$B78+Projections!$G78+Projections!$J78+Projections!$M78,""))))) | F60: =IF(F$2<Projections!$D78,0,IF(and(F$2>=Projections!$D78,F$2<Projections!$F78),Projections!$B78,if(and(F$2>=Projections!$F78,F$2<Projections!$I78),Projections!$B78+Projections!$G78,if(and(F$2>=Projections!$I78,F$2<Projections!$L78),Projections!$B78+Projections!$G78+Projections!$J78,IF(F$2>=Projections!$L78,Projections!$B78+Projections!$G78+Projections!$J78+Projections!$M78,""))))) | G60: =IF(G$2<Projections!$D78,0,IF(and(G$2>=Projections!$D78,G$2<Projections!$F78),Projections!$B78,if(and(G$2>=Projections!$F78,G$2<Projections!$I78),Projections!$B78+Projections!$G78,if(and(G$2>=Projections!$I78,G$2<Projections!$L78),Projections!$B78+Projections!$G78+Projections!$J78,IF(G$2>=Projections!$L78,Projections!$B78+Projections!$G78+Projections!$J78+Projections!$M78,""))))) | H60: =IF(H$2<Projections!$D78,0,IF(and(H$2>=Projections!$D78,H$2<Projections!$F78),Projections!$B78,if(and(H$2>=Projections!$F78,H$2<Projections!$I78),Projections!$B78+Projections!$G78,if(and(H$2>=Projections!$I78,H$2<Projections!$L78),Projections!$B78+Projections!$G78+Projections!$J78,IF(H$2>=Projections!$L78,Projections!$B78+Projections!$G78+Projections!$J78+Projections!$M78,""))))) | I60: =IF(I$2<Projections!$D78,0,IF(and(I$2>=Projections!$D78,I$2<Projections!$F78),Projections!$B78,if(and(I$2>=Projections!$F78,I$2<Projections!$I78),Projections!$B78+Projections!$G78,if(and(I$2>=Projections!$I78,I$2<Projections!$L78),Projections!$B78+Projections!$G78+Projections!$J78,IF(I$2>=Projections!$L78,Projections!$B78+Projections!$G78+Projections!$J78+Projections!$M78,""))))) | J60: =IF(J$2<Projections!$D78,0,IF(and(J$2>=Projections!$D78,J$2<Projections!$F78),Projections!$B78,if(and(J$2>=Projections!$F78,J$2<Projections!$I78),Projections!$B78+Projections!$G78,if(and(J$2>=Projections!$I78,J$2<Projections!$L78),Projections!$B78+Projections!$G78+Projections!$J78,IF(J$2>=Projections!$L78,Projections!$B78+Projections!$G78+Projections!$J78+Projections!$M78,""))))) | K60: =IF(K$2<Projections!$D78,0,IF(and(K$2>=Projections!$D78,K$2<Projections!$F78),Projections!$B78,if(and(K$2>=Projections!$F78,K$2<Projections!$I78),Projections!$B78+Projections!$G78,if(and(K$2>=Projections!$I78,K$2<Projections!$L78),Projections!$B78+Projections!$G78+Projections!$J78,IF(K$2>=Projections!$L78,Projections!$B78+Projections!$G78+Projections!$J78+Projections!$M78,""))))) | L60: =IF(L$2<Projections!$D78,0,IF(and(L$2>=Projections!$D78,L$2<Projections!$F78),Projections!$B78,if(and(L$2>=Projections!$F78,L$2<Projections!$I78),Projections!$B78+Projections!$G78,if(and(L$2>=Projections!$I78,L$2<Projections!$L78),Projections!$B78+Projections!$G78+Projections!$J78,IF(L$2>=Projections!$L78,Projections!$B78+Projections!$G78+Projections!$J78+Projections!$M78,""))))) | ... CX60: =IF(CX$2<Projections!$D78,0,IF(and(CX$2>=Projections!$D78,CX$2<Projections!$F78),Projections!$B78,if(and(CX$2>=Projections!$F78,CX$2<Projections!$I78),Projections!$B78+Projections!$G78,if(and(CX$2>=Projections!$I78,CX$2<Projections!$L78),Projections!$B78+Projections!$G78+Projections!$J78,IF(CX$2>=Projections!$L78,Projections!$B78+Projections!$G78+Projections!$J78+Projections!$M78,"")))))
A64: Direct response campaigns
A65: Budget | B65: Marketing | D65: =IF(D2<Projections!$D$19,0,IF(and(D2>=Projections!$D$19,D2<Projections!$F$19),Projections!$B$19,if(and(D2>=Projections!$F$19,D2<Projections!$I$19),Projections!$B$19+Projections!$G$19,if(and(D2>=Projections!$I$19,D2<Projections!$L$19),Projections!$B$19+Projections!$G$19+Projections!$J$19,IF(D2>=Projections!$L$19,Projections!$B$19+Projections!$G$19+Projections!$J$19+Projections!$M$19,""))))) | E65: =IF(E$2<Projections!$D$19,0,IF(and(E$2>=Projections!$D$19,E$2<Projections!$F$19),Projections!$B$19,if(and(E$2>=Projections!$F$19,E$2<Projections!$I$19),Projections!$B$19+Projections!$G$19,if(and(E$2>=Projections!$I$19,E$2<Projections!$L$19),Projections!$B$19+Projections!$G$19+Projections!$J$19,IF(E$2>=Projections!$L$19,Projections!$B$19+Projections!$G$19+Projections!$J$19+Projections!$M$19,""))))) | F65: =IF(F2<Projections!$D$19,0,IF(and(F2>=Projections!$D$19,F2<Projections!$F$19),Projections!$B$19,if(and(F2>=Projections!$F$19,F2<Projections!$I$19),Projections!$B$19+Projections!$G$19,if(and(F2>=Projections!$I$19,F2<Projections!$L$19),Projections!$B$19+Projections!$G$19+Projections!$J$19,IF(F2>=Projections!$L$19,Projections!$B$19+Projections!$G$19+Projections!$J$19+Projections!$M$19,""))))) | G65: =IF(G2<Projections!$D$19,0,IF(and(G2>=Projections!$D$19,G2<Projections!$F$19),Projections!$B$19,if(and(G2>=Projections!$F$19,G2<Projections!$I$19),Projections!$B$19+Projections!$G$19,if(and(G2>=Projections!$I$19,G2<Projections!$L$19),Projections!$B$19+Projections!$G$19+Projections!$J$19,IF(G2>=Projections!$L$19,Projections!$B$19+Projections!$G$19+Projections!$J$19+Projections!$M$19,""))))) | H65: =IF(H2<Projections!$D$19,0,IF(and(H2>=Projections!$D$19,H2<Projections!$F$19),Projections!$B$19,if(and(H2>=Projections!$F$19,H2<Projections!$I$19),Projections!$B$19+Projections!$G$19,if(and(H2>=Projections!$I$19,H2<Projections!$L$19),Projections!$B$19+Projections!$G$19+Projections!$J$19,IF(H2>=Projections!$L$19,Projections!$B$19+Projections!$G$19+Projections!$J$19+Projections!$M$19,""))))) | I65: =IF(I2<Projections!$D$19,0,IF(and(I2>=Projections!$D$19,I2<Projections!$F$19),Projections!$B$19,if(and(I2>=Projections!$F$19,I2<Projections!$I$19),Projections!$B$19+Projections!$G$19,if(and(I2>=Projections!$I$19,I2<Projections!$L$19),Projections!$B$19+Projections!$G$19+Projections!$J$19,IF(I2>=Projections!$L$19,Projections!$B$19+Projections!$G$19+Projections!$J$19+Projections!$M$19,""))))) | J65: =IF(J2<Projections!$D$19,0,IF(and(J2>=Projections!$D$19,J2<Projections!$F$19),Projections!$B$19,if(and(J2>=Projections!$F$19,J2<Projections!$I$19),Projections!$B$19+Projections!$G$19,if(and(J2>=Projections!$I$19,J2<Projections!$L$19),Projections!$B$19+Projections!$G$19+Projections!$J$19,IF(J2>=Projections!$L$19,Projections!$B$19+Projections!$G$19+Projections!$J$19+Projections!$M$19,""))))) | K65: =IF(K2<Projections!$D$19,0,IF(and(K2>=Projections!$D$19,K2<Projections!$F$19),Projections!$B$19,if(and(K2>=Projections!$F$19,K2<Projections!$I$19),Projections!$B$19+Projections!$G$19,if(and(K2>=Projections!$I$19,K2<Projections!$L$19),Projections!$B$19+Projections!$G$19+Projections!$J$19,IF(K2>=Projections!$L$19,Projections!$B$19+Projections!$G$19+Projections!$J$19+Projections!$M$19,""))))) | L65: =IF(L2<Projections!$D$19,0,IF(and(L2>=Projections!$D$19,L2<Projections!$F$19),Projections!$B$19,if(and(L2>=Projections!$F$19,L2<Projections!$I$19),Projections!$B$19+Projections!$G$19,if(and(L2>=Projections!$I$19,L2<Projections!$L$19),Projections!$B$19+Projections!$G$19+Projections!$J$19,IF(L2>=Projections!$L$19,Projections!$B$19+Projections!$G$19+Projections!$J$19+Projections!$M$19,""))))) | M65: =IF(M2<Projections!$D$19,0,IF(and(M2>=Projections!$D$19,M2<Projections!$F$19),Projections!$B$19,if(and(M2>=Projections!$F$19,M2<Projections!$I$19),Projections!$B$19+Projections!$G$19,if(and(M2>=Projections!$I$19,M2<Projections!$L$19),Projections!$B$19+Projections!$G$19+Projections!$J$19,IF(M2>=Projections!$L$19,Projections!$B$19+Projections!$G$19+Projections!$J$19+Projections!$M$19,""))))) | ... CX65: =IF(CX2<Projections!$D$19,0,IF(and(CX2>=Projections!$D$19,CX2<Projections!$F$19),Projections!$B$19,if(and(CX2>=Projections!$F$19,CX2<Projections!$I$19),Projections!$B$19+Projections!$G$19,if(and(CX2>=Projections!$I$19,CX2<Projections!$L$19),Projections!$B$19+Projections!$G$19+Projections!$J$19,IF(CX2>=Projections!$L$19,Projections!$B$19+Projections!$G$19+Projections!$J$19+Projections!$M$19,"")))))
A68: Other marketing expenses | B68: Marketing | E68: =SUM(E69:E76) | F68: =SUM(F69:F76) | G68: =SUM(G69:G76) | H68: =SUM(H69:H76) | I68: =SUM(I69:I76) | J68: =SUM(J69:J76) | K68: =SUM(K69:K76) | L68: =SUM(L69:L76) | ... CX68: =SUM(CX69:CX76)
A69: =Projections!A82 | E69: =IF(E$2>=Projections!$D82,Projections!$B82,0) | F69: =IF(F$2>=Projections!$D82,Projections!$B82,0) | G69: =IF(G$2>=Projections!$D82,Projections!$B82,0) | H69: =IF(H$2>=Projections!$D82,Projections!$B82,0) | I69: =IF(I$2>=Projections!$D82,Projections!$B82,0) | J69: =IF(J$2>=Projections!$D82,Projections!$B82,0) | K69: =IF(K$2>=Projections!$D82,Projections!$B82,0) | L69: =IF(L$2>=Projections!$D82,Projections!$B82,0) | ... CX69: =IF(CX$2>=Projections!$D82,Projections!$B82,0)
A70: =Projections!A83 | E70: =IF(E$2>=Projections!$D83,Projections!$B83,0) | F70: =IF(F$2>=Projections!$D83,Projections!$B83,0) | G70: =IF(G$2>=Projections!$D83,Projections!$B83,0) | H70: =IF(H$2>=Projections!$D83,Projections!$B83,0) | I70: =IF(I$2>=Projections!$D83,Projections!$B83,0) | J70: =IF(J$2>=Projections!$D83,Projections!$B83,0) | K70: =IF(K$2>=Projections!$D83,Projections!$B83,0) | L70: =IF(L$2>=Projections!$D83,Projections!$B83,0) | ... CX70: =IF(CX$2>=Projections!$D83,Projections!$B83,0)
A71: =Projections!A84 | E71: =IF(E$2>=Projections!$D84,Projections!$B84,0) | F71: =IF(F$2>=Projections!$D84,Projections!$B84,0) | G71: =IF(G$2>=Projections!$D84,Projections!$B84,0) | H71: =IF(H$2>=Projections!$D84,Projections!$B84,0) | I71: =IF(I$2>=Projections!$D84,Projections!$B84,0) | J71: =IF(J$2>=Projections!$D84,Projections!$B84,0) | K71: =IF(K$2>=Projections!$D84,Projections!$B84,0) | L71: =IF(L$2>=Projections!$D84,Projections!$B84,0) | ... CX71: =IF(CX$2>=Projections!$D84,Projections!$B84,0)
A72: =Projections!A85 | E72: =IF(E$2>=Projections!$D85,Projections!$B85,0) | F72: =IF(F$2>=Projections!$D85,Projections!$B85,0) | G72: =IF(G$2>=Projections!$D85,Projections!$B85,0) | H72: =IF(H$2>=Projections!$D85,Projections!$B85,0) | I72: =IF(I$2>=Projections!$D85,Projections!$B85,0) | J72: =IF(J$2>=Projections!$D85,Projections!$B85,0) | K72: =IF(K$2>=Projections!$D85,Projections!$B85,0) | L72: =IF(L$2>=Projections!$D85,Projections!$B85,0) | ... CX72: =IF(CX$2>=Projections!$D85,Projections!$B85,0)
A73: =Projections!A86 | E73: =IF(E$2>=Projections!$D86,Projections!$B86,0) | F73: =IF(F$2>=Projections!$D86,Projections!$B86,0) | G73: =IF(G$2>=Projections!$D86,Projections!$B86,0) | H73: =IF(H$2>=Projections!$D86,Projections!$B86,0) | I73: =IF(I$2>=Projections!$D86,Projections!$B86,0) | J73: =IF(J$2>=Projections!$D86,Projections!$B86,0) | K73: =IF(K$2>=Projections!$D86,Projections!$B86,0) | L73: =IF(L$2>=Projections!$D86,Projections!$B86,0) | ... CX73: =IF(CX$2>=Projections!$D86,Projections!$B86,0)
A74: =Projections!A87 | E74: =IF(E$2>=Projections!$D87,Projections!$B87,0) | F74: =IF(F$2>=Projections!$D87,Projections!$B87,0) | G74: =IF(G$2>=Projections!$D87,Projections!$B87,0) | H74: =IF(H$2>=Projections!$D87,Projections!$B87,0) | I74: =IF(I$2>=Projections!$D87,Projections!$B87,0) | J74: =IF(J$2>=Projections!$D87,Projections!$B87,0) | K74: =IF(K$2>=Projections!$D87,Projections!$B87,0) | L74: =IF(L$2>=Projections!$D87,Projections!$B87,0) | ... CX74: =IF(CX$2>=Projections!$D87,Projections!$B87,0)
A75: =Projections!A88 | E75: =IF(E$2>=Projections!$D88,Projections!$B88,0) | F75: =IF(F$2>=Projections!$D88,Projections!$B88,0) | G75: =IF(G$2>=Projections!$D88,Projections!$B88,0) | H75: =IF(H$2>=Projections!$D88,Projections!$B88,0) | I75: =IF(I$2>=Projections!$D88,Projections!$B88,0) | J75: =IF(J$2>=Projections!$D88,Projections!$B88,0) | K75: =IF(K$2>=Projections!$D88,Projections!$B88,0) | L75: =IF(L$2>=Projections!$D88,Projections!$B88,0) | ... CX75: =IF(CX$2>=Projections!$D88,Projections!$B88,0)
A76: =Projections!A89 | E76: =IF(E$2>=Projections!$D89,Projections!$B89,0) | F76: =IF(F$2>=Projections!$D89,Projections!$B89,0) | G76: =IF(G$2>=Projections!$D89,Projections!$B89,0) | H76: =IF(H$2>=Projections!$D89,Projections!$B89,0) | I76: =IF(I$2>=Projections!$D89,Projections!$B89,0) | J76: =IF(J$2>=Projections!$D89,Projections!$B89,0) | K76: =IF(K$2>=Projections!$D89,Projections!$B89,0) | L76: =IF(L$2>=Projections!$D89,Projections!$B89,0) | ... CX76: =IF(CX$2>=Projections!$D89,Projections!$B89,0)
A77: =Projections!A90
A79: SALES | E79: =E84+E89 | F79: =F84+F89 | G79: =G84+G89 | H79: =H84+H89 | I79: =I84+I89 | J79: =J84+J89 | K79: =K84+K89 | L79: =L84+L89 | ... CX79: =CX84+CX89
A81: Inbound Sales Managers
A82: Number of Inbound Managers | E82: =ROUNDUP(E26/Projections!$B$49,0) | F82: =ROUNDUP(F26/Projections!$B$49,0) | G82: =ROUNDUP(G26/Projections!$B$49,0) | H82: =ROUNDUP(H26/Projections!$B$49,0) | I82: =ROUNDUP(I26/Projections!$B$49,0) | J82: =ROUNDUP(J26/Projections!$B$49,0) | K82: =ROUNDUP(K26/Projections!$B$49,0) | L82: =ROUNDUP(L26/Projections!$B$49,0) | ... CX82: =ROUNDUP(CX26/Projections!$B$49,0)
A83: Cost per manager | E83: =IF(E$2=Payroll!$I45,Payroll!$F45,IF(E$2>Payroll!$I45,Payroll!$F45*((1+Payroll!$J45)^(ROUNDDOWN(DATEDIF(Payroll!$I45,E$2,"M")/Payroll!$K45,0))),0)) | F83: =IF(F$2=Payroll!$I45,Payroll!$F45,IF(F$2>Payroll!$I45,Payroll!$F45*((1+Payroll!$J45)^(ROUNDDOWN(DATEDIF(Payroll!$I45,F$2,"M")/Payroll!$K45,0))),0)) | G83: =IF(G$2=Payroll!$I45,Payroll!$F45,IF(G$2>Payroll!$I45,Payroll!$F45*((1+Payroll!$J45)^(ROUNDDOWN(DATEDIF(Payroll!$I45,G$2,"M")/Payroll!$K45,0))),0)) | H83: =IF(H$2=Payroll!$I45,Payroll!$F45,IF(H$2>Payroll!$I45,Payroll!$F45*((1+Payroll!$J45)^(ROUNDDOWN(DATEDIF(Payroll!$I45,H$2,"M")/Payroll!$K45,0))),0)) | I83: =IF(I$2=Payroll!$I45,Payroll!$F45,IF(I$2>Payroll!$I45,Payroll!$F45*((1+Payroll!$J45)^(ROUNDDOWN(DATEDIF(Payroll!$I45,I$2,"M")/Payroll!$K45,0))),0)) | J83: =IF(J$2=Payroll!$I45,Payroll!$F45,IF(J$2>Payroll!$I45,Payroll!$F45*((1+Payroll!$J45)^(ROUNDDOWN(DATEDIF(Payroll!$I45,J$2,"M")/Payroll!$K45,0))),0)) | K83: =IF(K$2=Payroll!$I45,Payroll!$F45,IF(K$2>Payroll!$I45,Payroll!$F45*((1+Payroll!$J45)^(ROUNDDOWN(DATEDIF(Payroll!$I45,K$2,"M")/Payroll!$K45,0))),0)) | L83: =IF(L$2=Payroll!$I45,Payroll!$F45,IF(L$2>Payroll!$I45,Payroll!$F45*((1+Payroll!$J45)^(ROUNDDOWN(DATEDIF(Payroll!$I45,L$2,"M")/Payroll!$K45,0))),0)) | ... CX83: =IF(CX$2=Payroll!$I45,Payroll!$F45,IF(CX$2>Payroll!$I45,Payroll!$F45*((1+Payroll!$J45)^(ROUNDDOWN(DATEDIF(Payroll!$I45,CX$2,"M")/Payroll!$K45,0))),0))
A84: Total cost | E84: =E82*E83 | F84: =F82*F83 | G84: =G82*G83 | H84: =H82*H83 | I84: =I82*I83 | J84: =J82*J83 | K84: =K82*K83 | L84: =L82*L83 | ... CX84: =CX82*CX83
A86: Outbound Sales Managers
A87: Number of Outbound Managers | E87: =IF(E2=Projections!$C$56,Projections!$B$58,if(E2>Projections!$C$56,MIN(Projections!$B$60,D87+IF(mod(DATEDIF(Projections!$C$56,E2,"M"),Projections!$B$59)=0,1,0)),0)) | F87: =IF(F2=Projections!$C$56,Projections!$B$58,if(F2>Projections!$C$56,MIN(Projections!$B$60,E87+IF(mod(DATEDIF(Projections!$C$56,F2,"M"),Projections!$B$59)=0,1,0)),0)) | G87: =IF(G2=Projections!$C$56,Projections!$B$58,if(G2>Projections!$C$56,MIN(Projections!$B$60,F87+IF(mod(DATEDIF(Projections!$C$56,G2,"M"),Projections!$B$59)=0,1,0)),0)) | H87: =IF(H2=Projections!$C$56,Projections!$B$58,if(H2>Projections!$C$56,MIN(Projections!$B$60,G87+IF(mod(DATEDIF(Projections!$C$56,H2,"M"),Projections!$B$59)=0,1,0)),0)) | I87: =IF(I2=Projections!$C$56,Projections!$B$58,if(I2>Projections!$C$56,MIN(Projections!$B$60,H87+IF(mod(DATEDIF(Projections!$C$56,I2,"M"),Projections!$B$59)=0,1,0)),0)) | J87: =IF(J2=Projections!$C$56,Projections!$B$58,if(J2>Projections!$C$56,MIN(Projections!$B$60,I87+IF(mod(DATEDIF(Projections!$C$56,J2,"M"),Projections!$B$59)=0,1,0)),0)) | K87: =IF(K2=Projections!$C$56,Projections!$B$58,if(K2>Projections!$C$56,MIN(Projections!$B$60,J87+IF(mod(DATEDIF(Projections!$C$56,K2,"M"),Projections!$B$59)=0,1,0)),0)) | L87: =IF(L2=Projections!$C$56,Projections!$B$58,if(L2>Projections!$C$56,MIN(Projections!$B$60,K87+IF(mod(DATEDIF(Projections!$C$56,L2,"M"),Projections!$B$59)=0,1,0)),0)) | ... CX87: =IF(CX2=Projections!$C$56,Projections!$B$58,if(CX2>Projections!$C$56,MIN(Projections!$B$60,CW87+IF(mod(DATEDIF(Projections!$C$56,CX2,"M"),Projections!$B$59)=0,1,0)),0))
A88: Cost per manager | E88: =IF(E$2=Payroll!$I46,Payroll!$F46,IF(E$2>Payroll!$I46,Payroll!$F46*((1+Payroll!$J46)^(ROUNDDOWN(DATEDIF(Payroll!$I46,E$2,"M")/Payroll!$K46,0))),0)) | F88: =IF(F$2=Payroll!$I46,Payroll!$F46,IF(F$2>Payroll!$I46,Payroll!$F46*((1+Payroll!$J46)^(ROUNDDOWN(DATEDIF(Payroll!$I46,F$2,"M")/Payroll!$K46,0))),0)) | G88: =IF(G$2=Payroll!$I46,Payroll!$F46,IF(G$2>Payroll!$I46,Payroll!$F46*((1+Payroll!$J46)^(ROUNDDOWN(DATEDIF(Payroll!$I46,G$2,"M")/Payroll!$K46,0))),0)) | H88: =IF(H$2=Payroll!$I46,Payroll!$F46,IF(H$2>Payroll!$I46,Payroll!$F46*((1+Payroll!$J46)^(ROUNDDOWN(DATEDIF(Payroll!$I46,H$2,"M")/Payroll!$K46,0))),0)) | I88: =IF(I$2=Payroll!$I46,Payroll!$F46,IF(I$2>Payroll!$I46,Payroll!$F46*((1+Payroll!$J46)^(ROUNDDOWN(DATEDIF(Payroll!$I46,I$2,"M")/Payroll!$K46,0))),0)) | J88: =IF(J$2=Payroll!$I46,Payroll!$F46,IF(J$2>Payroll!$I46,Payroll!$F46*((1+Payroll!$J46)^(ROUNDDOWN(DATEDIF(Payroll!$I46,J$2,"M")/Payroll!$K46,0))),0)) | K88: =IF(K$2=Payroll!$I46,Payroll!$F46,IF(K$2>Payroll!$I46,Payroll!$F46*((1+Payroll!$J46)^(ROUNDDOWN(DATEDIF(Payroll!$I46,K$2,"M")/Payroll!$K46,0))),0)) | L88: =IF(L$2=Payroll!$I46,Payroll!$F46,IF(L$2>Payroll!$I46,Payroll!$F46*((1+Payroll!$J46)^(ROUNDDOWN(DATEDIF(Payroll!$I46,L$2,"M")/Payroll!$K46,0))),0)) | ... CX88: =IF(CX$2=Payroll!$I46,Payroll!$F46,IF(CX$2>Payroll!$I46,Payroll!$F46*((1+Payroll!$J46)^(ROUNDDOWN(DATEDIF(Payroll!$I46,CX$2,"M")/Payroll!$K46,0))),0))
A89: Total cost | E89: =E88*E87 | F89: =F88*F87 | G89: =G88*G87 | H89: =H88*H87 | I89: =I88*I87 | J89: =J88*J87 | K89: =K88*K87 | L89: =L88*L87 | ... CX89: =CX88*CX87
A91: PAYROLL | E91: =E92+E104+E115+E127 | F91: =F92+F104+F115+F127 | G91: =G92+G104+G115+G127 | H91: =H92+H104+H115+H127 | I91: =I92+I104+I115+I127 | J91: =J92+J104+J115+J127 | K91: =K92+K104+K115+K127 | L91: =L92+L104+L115+L127 | ... CX91: =CX92+CX104+CX115+CX127
A92: IT | B92: Development | E92: =SUM(E93:E102) | F92: =SUM(F93:F102) | G92: =SUM(G93:G102) | H92: =SUM(H93:H102) | I92: =SUM(I93:I102) | J92: =SUM(J93:J102) | K92: =SUM(K93:K102) | L92: =SUM(L93:L102) | ... CX92: =SUM(CX93:CX102)
A93: =Payroll!A17 | E93: =IF(E$2=Payroll!$I17,Payroll!$F17,IF(E$2>Payroll!$I17,Payroll!$F17*((1+Payroll!$J17)^(ROUNDDOWN(DATEDIF(Payroll!$I17,E$2,"M")/Payroll!$K17,0))),0)) | F93: =IF(F$2=Payroll!$I17,Payroll!$F17,IF(F$2>Payroll!$I17,Payroll!$F17*((1+Payroll!$J17)^(ROUNDDOWN(DATEDIF(Payroll!$I17,F$2,"M")/Payroll!$K17,0))),0)) | G93: =IF(G$2=Payroll!$I17,Payroll!$F17,IF(G$2>Payroll!$I17,Payroll!$F17*((1+Payroll!$J17)^(ROUNDDOWN(DATEDIF(Payroll!$I17,G$2,"M")/Payroll!$K17,0))),0)) | H93: =IF(H$2=Payroll!$I17,Payroll!$F17,IF(H$2>Payroll!$I17,Payroll!$F17*((1+Payroll!$J17)^(ROUNDDOWN(DATEDIF(Payroll!$I17,H$2,"M")/Payroll!$K17,0))),0)) | I93: =IF(I$2=Payroll!$I17,Payroll!$F17,IF(I$2>Payroll!$I17,Payroll!$F17*((1+Payroll!$J17)^(ROUNDDOWN(DATEDIF(Payroll!$I17,I$2,"M")/Payroll!$K17,0))),0)) | J93: =IF(J$2=Payroll!$I17,Payroll!$F17,IF(J$2>Payroll!$I17,Payroll!$F17*((1+Payroll!$J17)^(ROUNDDOWN(DATEDIF(Payroll!$I17,J$2,"M")/Payroll!$K17,0))),0)) | K93: =IF(K$2=Payroll!$I17,Payroll!$F17,IF(K$2>Payroll!$I17,Payroll!$F17*((1+Payroll!$J17)^(ROUNDDOWN(DATEDIF(Payroll!$I17,K$2,"M")/Payroll!$K17,0))),0)) | L93: =IF(L$2=Payroll!$I17,Payroll!$F17,IF(L$2>Payroll!$I17,Payroll!$F17*((1+Payroll!$J17)^(ROUNDDOWN(DATEDIF(Payroll!$I17,L$2,"M")/Payroll!$K17,0))),0)) | ... CX93: =IF(CX$2=Payroll!$I17,Payroll!$F17,IF(CX$2>Payroll!$I17,Payroll!$F17*((1+Payroll!$J17)^(ROUNDDOWN(DATEDIF(Payroll!$I17,CX$2,"M")/Payroll!$K17,0))),0))
A94: =Payroll!A18 | E94: =IF(E$2=Payroll!$I18,Payroll!$F18,IF(E$2>Payroll!$I18,Payroll!$F18*((1+Payroll!$J18)^(ROUNDDOWN(DATEDIF(Payroll!$I18,E$2,"M")/Payroll!$K18,0))),0)) | F94: =IF(F$2=Payroll!$I18,Payroll!$F18,IF(F$2>Payroll!$I18,Payroll!$F18*((1+Payroll!$J18)^(ROUNDDOWN(DATEDIF(Payroll!$I18,F$2,"M")/Payroll!$K18,0))),0)) | G94: =IF(G$2=Payroll!$I18,Payroll!$F18,IF(G$2>Payroll!$I18,Payroll!$F18*((1+Payroll!$J18)^(ROUNDDOWN(DATEDIF(Payroll!$I18,G$2,"M")/Payroll!$K18,0))),0)) | H94: =IF(H$2=Payroll!$I18,Payroll!$F18,IF(H$2>Payroll!$I18,Payroll!$F18*((1+Payroll!$J18)^(ROUNDDOWN(DATEDIF(Payroll!$I18,H$2,"M")/Payroll!$K18,0))),0)) | I94: =IF(I$2=Payroll!$I18,Payroll!$F18,IF(I$2>Payroll!$I18,Payroll!$F18*((1+Payroll!$J18)^(ROUNDDOWN(DATEDIF(Payroll!$I18,I$2,"M")/Payroll!$K18,0))),0)) | J94: =IF(J$2=Payroll!$I18,Payroll!$F18,IF(J$2>Payroll!$I18,Payroll!$F18*((1+Payroll!$J18)^(ROUNDDOWN(DATEDIF(Payroll!$I18,J$2,"M")/Payroll!$K18,0))),0)) | K94: =IF(K$2=Payroll!$I18,Payroll!$F18,IF(K$2>Payroll!$I18,Payroll!$F18*((1+Payroll!$J18)^(ROUNDDOWN(DATEDIF(Payroll!$I18,K$2,"M")/Payroll!$K18,0))),0)) | L94: =IF(L$2=Payroll!$I18,Payroll!$F18,IF(L$2>Payroll!$I18,Payroll!$F18*((1+Payroll!$J18)^(ROUNDDOWN(DATEDIF(Payroll!$I18,L$2,"M")/Payroll!$K18,0))),0)) | ... CX94: =IF(CX$2=Payroll!$I18,Payroll!$F18,IF(CX$2>Payroll!$I18,Payroll!$F18*((1+Payroll!$J18)^(ROUNDDOWN(DATEDIF(Payroll!$I18,CX$2,"M")/Payroll!$K18,0))),0))
A95: =Payroll!A19 | E95: =IF(E$2=Payroll!$I19,Payroll!$F19,IF(E$2>Payroll!$I19,Payroll!$F19*((1+Payroll!$J19)^(ROUNDDOWN(DATEDIF(Payroll!$I19,E$2,"M")/Payroll!$K19,0))),0)) | F95: =IF(F$2=Payroll!$I19,Payroll!$F19,IF(F$2>Payroll!$I19,Payroll!$F19*((1+Payroll!$J19)^(ROUNDDOWN(DATEDIF(Payroll!$I19,F$2,"M")/Payroll!$K19,0))),0)) | G95: =IF(G$2=Payroll!$I19,Payroll!$F19,IF(G$2>Payroll!$I19,Payroll!$F19*((1+Payroll!$J19)^(ROUNDDOWN(DATEDIF(Payroll!$I19,G$2,"M")/Payroll!$K19,0))),0)) | H95: =IF(H$2=Payroll!$I19,Payroll!$F19,IF(H$2>Payroll!$I19,Payroll!$F19*((1+Payroll!$J19)^(ROUNDDOWN(DATEDIF(Payroll!$I19,H$2,"M")/Payroll!$K19,0))),0)) | I95: =IF(I$2=Payroll!$I19,Payroll!$F19,IF(I$2>Payroll!$I19,Payroll!$F19*((1+Payroll!$J19)^(ROUNDDOWN(DATEDIF(Payroll!$I19,I$2,"M")/Payroll!$K19,0))),0)) | J95: =IF(J$2=Payroll!$I19,Payroll!$F19,IF(J$2>Payroll!$I19,Payroll!$F19*((1+Payroll!$J19)^(ROUNDDOWN(DATEDIF(Payroll!$I19,J$2,"M")/Payroll!$K19,0))),0)) | K95: =IF(K$2=Payroll!$I19,Payroll!$F19,IF(K$2>Payroll!$I19,Payroll!$F19*((1+Payroll!$J19)^(ROUNDDOWN(DATEDIF(Payroll!$I19,K$2,"M")/Payroll!$K19,0))),0)) | L95: =IF(L$2=Payroll!$I19,Payroll!$F19,IF(L$2>Payroll!$I19,Payroll!$F19*((1+Payroll!$J19)^(ROUNDDOWN(DATEDIF(Payroll!$I19,L$2,"M")/Payroll!$K19,0))),0)) | ... CX95: =IF(CX$2=Payroll!$I19,Payroll!$F19,IF(CX$2>Payroll!$I19,Payroll!$F19*((1+Payroll!$J19)^(ROUNDDOWN(DATEDIF(Payroll!$I19,CX$2,"M")/Payroll!$K19,0))),0))
A96: =Payroll!A20 | E96: =IF(E$2=Payroll!$I20,Payroll!$F20,IF(E$2>Payroll!$I20,Payroll!$F20*((1+Payroll!$J20)^(ROUNDDOWN(DATEDIF(Payroll!$I20,E$2,"M")/Payroll!$K20,0))),0)) | F96: =IF(F$2=Payroll!$I20,Payroll!$F20,IF(F$2>Payroll!$I20,Payroll!$F20*((1+Payroll!$J20)^(ROUNDDOWN(DATEDIF(Payroll!$I20,F$2,"M")/Payroll!$K20,0))),0)) | G96: =IF(G$2=Payroll!$I20,Payroll!$F20,IF(G$2>Payroll!$I20,Payroll!$F20*((1+Payroll!$J20)^(ROUNDDOWN(DATEDIF(Payroll!$I20,G$2,"M")/Payroll!$K20,0))),0)) | H96: =IF(H$2=Payroll!$I20,Payroll!$F20,IF(H$2>Payroll!$I20,Payroll!$F20*((1+Payroll!$J20)^(ROUNDDOWN(DATEDIF(Payroll!$I20,H$2,"M")/Payroll!$K20,0))),0)) | I96: =IF(I$2=Payroll!$I20,Payroll!$F20,IF(I$2>Payroll!$I20,Payroll!$F20*((1+Payroll!$J20)^(ROUNDDOWN(DATEDIF(Payroll!$I20,I$2,"M")/Payroll!$K20,0))),0)) | J96: =IF(J$2=Payroll!$I20,Payroll!$F20,IF(J$2>Payroll!$I20,Payroll!$F20*((1+Payroll!$J20)^(ROUNDDOWN(DATEDIF(Payroll!$I20,J$2,"M")/Payroll!$K20,0))),0)) | K96: =IF(K$2=Payroll!$I20,Payroll!$F20,IF(K$2>Payroll!$I20,Payroll!$F20*((1+Payroll!$J20)^(ROUNDDOWN(DATEDIF(Payroll!$I20,K$2,"M")/Payroll!$K20,0))),0)) | L96: =IF(L$2=Payroll!$I20,Payroll!$F20,IF(L$2>Payroll!$I20,Payroll!$F20*((1+Payroll!$J20)^(ROUNDDOWN(DATEDIF(Payroll!$I20,L$2,"M")/Payroll!$K20,0))),0)) | ... CX96: =IF(CX$2=Payroll!$I20,Payroll!$F20,IF(CX$2>Payroll!$I20,Payroll!$F20*((1+Payroll!$J20)^(ROUNDDOWN(DATEDIF(Payroll!$I20,CX$2,"M")/Payroll!$K20,0))),0))
A97: =Payroll!A21 | E97: =IF(E$2=Payroll!$I21,Payroll!$F21,IF(E$2>Payroll!$I21,Payroll!$F21*((1+Payroll!$J21)^(ROUNDDOWN(DATEDIF(Payroll!$I21,E$2,"M")/Payroll!$K21,0))),0)) | F97: =IF(F$2=Payroll!$I21,Payroll!$F21,IF(F$2>Payroll!$I21,Payroll!$F21*((1+Payroll!$J21)^(ROUNDDOWN(DATEDIF(Payroll!$I21,F$2,"M")/Payroll!$K21,0))),0)) | G97: =IF(G$2=Payroll!$I21,Payroll!$F21,IF(G$2>Payroll!$I21,Payroll!$F21*((1+Payroll!$J21)^(ROUNDDOWN(DATEDIF(Payroll!$I21,G$2,"M")/Payroll!$K21,0))),0)) | H97: =IF(H$2=Payroll!$I21,Payroll!$F21,IF(H$2>Payroll!$I21,Payroll!$F21*((1+Payroll!$J21)^(ROUNDDOWN(DATEDIF(Payroll!$I21,H$2,"M")/Payroll!$K21,0))),0)) | I97: =IF(I$2=Payroll!$I21,Payroll!$F21,IF(I$2>Payroll!$I21,Payroll!$F21*((1+Payroll!$J21)^(ROUNDDOWN(DATEDIF(Payroll!$I21,I$2,"M")/Payroll!$K21,0))),0)) | J97: =IF(J$2=Payroll!$I21,Payroll!$F21,IF(J$2>Payroll!$I21,Payroll!$F21*((1+Payroll!$J21)^(ROUNDDOWN(DATEDIF(Payroll!$I21,J$2,"M")/Payroll!$K21,0))),0)) | K97: =IF(K$2=Payroll!$I21,Payroll!$F21,IF(K$2>Payroll!$I21,Payroll!$F21*((1+Payroll!$J21)^(ROUNDDOWN(DATEDIF(Payroll!$I21,K$2,"M")/Payroll!$K21,0))),0)) | L97: =IF(L$2=Payroll!$I21,Payroll!$F21,IF(L$2>Payroll!$I21,Payroll!$F21*((1+Payroll!$J21)^(ROUNDDOWN(DATEDIF(Payroll!$I21,L$2,"M")/Payroll!$K21,0))),0)) | ... CX97: =IF(CX$2=Payroll!$I21,Payroll!$F21,IF(CX$2>Payroll!$I21,Payroll!$F21*((1+Payroll!$J21)^(ROUNDDOWN(DATEDIF(Payroll!$I21,CX$2,"M")/Payroll!$K21,0))),0))
A98: =Payroll!A22 | E98: =IF(E$2=Payroll!$I22,Payroll!$F22,IF(E$2>Payroll!$I22,Payroll!$F22*((1+Payroll!$J22)^(ROUNDDOWN(DATEDIF(Payroll!$I22,E$2,"M")/Payroll!$K22,0))),0)) | F98: =IF(F$2=Payroll!$I22,Payroll!$F22,IF(F$2>Payroll!$I22,Payroll!$F22*((1+Payroll!$J22)^(ROUNDDOWN(DATEDIF(Payroll!$I22,F$2,"M")/Payroll!$K22,0))),0)) | G98: =IF(G$2=Payroll!$I22,Payroll!$F22,IF(G$2>Payroll!$I22,Payroll!$F22*((1+Payroll!$J22)^(ROUNDDOWN(DATEDIF(Payroll!$I22,G$2,"M")/Payroll!$K22,0))),0)) | H98: =IF(H$2=Payroll!$I22,Payroll!$F22,IF(H$2>Payroll!$I22,Payroll!$F22*((1+Payroll!$J22)^(ROUNDDOWN(DATEDIF(Payroll!$I22,H$2,"M")/Payroll!$K22,0))),0)) | I98: =IF(I$2=Payroll!$I22,Payroll!$F22,IF(I$2>Payroll!$I22,Payroll!$F22*((1+Payroll!$J22)^(ROUNDDOWN(DATEDIF(Payroll!$I22,I$2,"M")/Payroll!$K22,0))),0)) | J98: =IF(J$2=Payroll!$I22,Payroll!$F22,IF(J$2>Payroll!$I22,Payroll!$F22*((1+Payroll!$J22)^(ROUNDDOWN(DATEDIF(Payroll!$I22,J$2,"M")/Payroll!$K22,0))),0)) | K98: =IF(K$2=Payroll!$I22,Payroll!$F22,IF(K$2>Payroll!$I22,Payroll!$F22*((1+Payroll!$J22)^(ROUNDDOWN(DATEDIF(Payroll!$I22,K$2,"M")/Payroll!$K22,0))),0)) | L98: =IF(L$2=Payroll!$I22,Payroll!$F22,IF(L$2>Payroll!$I22,Payroll!$F22*((1+Payroll!$J22)^(ROUNDDOWN(DATEDIF(Payroll!$I22,L$2,"M")/Payroll!$K22,0))),0)) | ... CX98: =IF(CX$2=Payroll!$I22,Payroll!$F22,IF(CX$2>Payroll!$I22,Payroll!$F22*((1+Payroll!$J22)^(ROUNDDOWN(DATEDIF(Payroll!$I22,CX$2,"M")/Payroll!$K22,0))),0))
A99: =Payroll!A23 | E99: =IF(E$2=Payroll!$I23,Payroll!$F23,IF(E$2>Payroll!$I23,Payroll!$F23*((1+Payroll!$J23)^(ROUNDDOWN(DATEDIF(Payroll!$I23,E$2,"M")/Payroll!$K23,0))),0)) | F99: =IF(F$2=Payroll!$I23,Payroll!$F23,IF(F$2>Payroll!$I23,Payroll!$F23*((1+Payroll!$J23)^(ROUNDDOWN(DATEDIF(Payroll!$I23,F$2,"M")/Payroll!$K23,0))),0)) | G99: =IF(G$2=Payroll!$I23,Payroll!$F23,IF(G$2>Payroll!$I23,Payroll!$F23*((1+Payroll!$J23)^(ROUNDDOWN(DATEDIF(Payroll!$I23,G$2,"M")/Payroll!$K23,0))),0)) | H99: =IF(H$2=Payroll!$I23,Payroll!$F23,IF(H$2>Payroll!$I23,Payroll!$F23*((1+Payroll!$J23)^(ROUNDDOWN(DATEDIF(Payroll!$I23,H$2,"M")/Payroll!$K23,0))),0)) | I99: =IF(I$2=Payroll!$I23,Payroll!$F23,IF(I$2>Payroll!$I23,Payroll!$F23*((1+Payroll!$J23)^(ROUNDDOWN(DATEDIF(Payroll!$I23,I$2,"M")/Payroll!$K23,0))),0)) | J99: =IF(J$2=Payroll!$I23,Payroll!$F23,IF(J$2>Payroll!$I23,Payroll!$F23*((1+Payroll!$J23)^(ROUNDDOWN(DATEDIF(Payroll!$I23,J$2,"M")/Payroll!$K23,0))),0)) | K99: =IF(K$2=Payroll!$I23,Payroll!$F23,IF(K$2>Payroll!$I23,Payroll!$F23*((1+Payroll!$J23)^(ROUNDDOWN(DATEDIF(Payroll!$I23,K$2,"M")/Payroll!$K23,0))),0)) | L99: =IF(L$2=Payroll!$I23,Payroll!$F23,IF(L$2>Payroll!$I23,Payroll!$F23*((1+Payroll!$J23)^(ROUNDDOWN(DATEDIF(Payroll!$I23,L$2,"M")/Payroll!$K23,0))),0)) | ... CX99: =IF(CX$2=Payroll!$I23,Payroll!$F23,IF(CX$2>Payroll!$I23,Payroll!$F23*((1+Payroll!$J23)^(ROUNDDOWN(DATEDIF(Payroll!$I23,CX$2,"M")/Payroll!$K23,0))),0))
A100: =Payroll!A24 | E100: =IF(E$2=Payroll!$I24,Payroll!$F24,IF(E$2>Payroll!$I24,Payroll!$F24*((1+Payroll!$J24)^(ROUNDDOWN(DATEDIF(Payroll!$I24,E$2,"M")/Payroll!$K24,0))),0)) | F100: =IF(F$2=Payroll!$I24,Payroll!$F24,IF(F$2>Payroll!$I24,Payroll!$F24*((1+Payroll!$J24)^(ROUNDDOWN(DATEDIF(Payroll!$I24,F$2,"M")/Payroll!$K24,0))),0)) | G100: =IF(G$2=Payroll!$I24,Payroll!$F24,IF(G$2>Payroll!$I24,Payroll!$F24*((1+Payroll!$J24)^(ROUNDDOWN(DATEDIF(Payroll!$I24,G$2,"M")/Payroll!$K24,0))),0)) | H100: =IF(H$2=Payroll!$I24,Payroll!$F24,IF(H$2>Payroll!$I24,Payroll!$F24*((1+Payroll!$J24)^(ROUNDDOWN(DATEDIF(Payroll!$I24,H$2,"M")/Payroll!$K24,0))),0)) | I100: =IF(I$2=Payroll!$I24,Payroll!$F24,IF(I$2>Payroll!$I24,Payroll!$F24*((1+Payroll!$J24)^(ROUNDDOWN(DATEDIF(Payroll!$I24,I$2,"M")/Payroll!$K24,0))),0)) | J100: =IF(J$2=Payroll!$I24,Payroll!$F24,IF(J$2>Payroll!$I24,Payroll!$F24*((1+Payroll!$J24)^(ROUNDDOWN(DATEDIF(Payroll!$I24,J$2,"M")/Payroll!$K24,0))),0)) | K100: =IF(K$2=Payroll!$I24,Payroll!$F24,IF(K$2>Payroll!$I24,Payroll!$F24*((1+Payroll!$J24)^(ROUNDDOWN(DATEDIF(Payroll!$I24,K$2,"M")/Payroll!$K24,0))),0)) | L100: =IF(L$2=Payroll!$I24,Payroll!$F24,IF(L$2>Payroll!$I24,Payroll!$F24*((1+Payroll!$J24)^(ROUNDDOWN(DATEDIF(Payroll!$I24,L$2,"M")/Payroll!$K24,0))),0)) | ... CX100: =IF(CX$2=Payroll!$I24,Payroll!$F24,IF(CX$2>Payroll!$I24,Payroll!$F24*((1+Payroll!$J24)^(ROUNDDOWN(DATEDIF(Payroll!$I24,CX$2,"M")/Payroll!$K24,0))),0))
A101: =Payroll!A25 | E101: =IF(E$2=Payroll!$I25,Payroll!$F25,IF(E$2>Payroll!$I25,Payroll!$F25*((1+Payroll!$J25)^(ROUNDDOWN(DATEDIF(Payroll!$I25,E$2,"M")/Payroll!$K25,0))),0)) | F101: =IF(F$2=Payroll!$I25,Payroll!$F25,IF(F$2>Payroll!$I25,Payroll!$F25*((1+Payroll!$J25)^(ROUNDDOWN(DATEDIF(Payroll!$I25,F$2,"M")/Payroll!$K25,0))),0)) | G101: =IF(G$2=Payroll!$I25,Payroll!$F25,IF(G$2>Payroll!$I25,Payroll!$F25*((1+Payroll!$J25)^(ROUNDDOWN(DATEDIF(Payroll!$I25,G$2,"M")/Payroll!$K25,0))),0)) | H101: =IF(H$2=Payroll!$I25,Payroll!$F25,IF(H$2>Payroll!$I25,Payroll!$F25*((1+Payroll!$J25)^(ROUNDDOWN(DATEDIF(Payroll!$I25,H$2,"M")/Payroll!$K25,0))),0)) | I101: =IF(I$2=Payroll!$I25,Payroll!$F25,IF(I$2>Payroll!$I25,Payroll!$F25*((1+Payroll!$J25)^(ROUNDDOWN(DATEDIF(Payroll!$I25,I$2,"M")/Payroll!$K25,0))),0)) | J101: =IF(J$2=Payroll!$I25,Payroll!$F25,IF(J$2>Payroll!$I25,Payroll!$F25*((1+Payroll!$J25)^(ROUNDDOWN(DATEDIF(Payroll!$I25,J$2,"M")/Payroll!$K25,0))),0)) | K101: =IF(K$2=Payroll!$I25,Payroll!$F25,IF(K$2>Payroll!$I25,Payroll!$F25*((1+Payroll!$J25)^(ROUNDDOWN(DATEDIF(Payroll!$I25,K$2,"M")/Payroll!$K25,0))),0)) | L101: =IF(L$2=Payroll!$I25,Payroll!$F25,IF(L$2>Payroll!$I25,Payroll!$F25*((1+Payroll!$J25)^(ROUNDDOWN(DATEDIF(Payroll!$I25,L$2,"M")/Payroll!$K25,0))),0)) | ... CX101: =IF(CX$2=Payroll!$I25,Payroll!$F25,IF(CX$2>Payroll!$I25,Payroll!$F25*((1+Payroll!$J25)^(ROUNDDOWN(DATEDIF(Payroll!$I25,CX$2,"M")/Payroll!$K25,0))),0))
A102: =Payroll!A28 | E102: =IF(E$2=Payroll!$I28,Payroll!$F28,IF(E$2>Payroll!$I28,Payroll!$F28*((1+Payroll!$J28)^(ROUNDDOWN(DATEDIF(Payroll!$I28,E$2,"M")/Payroll!$K28,0))),0)) | F102: =IF(F$2=Payroll!$I28,Payroll!$F28,IF(F$2>Payroll!$I28,Payroll!$F28*((1+Payroll!$J28)^(ROUNDDOWN(DATEDIF(Payroll!$I28,F$2,"M")/Payroll!$K28,0))),0)) | G102: =IF(G$2=Payroll!$I28,Payroll!$F28,IF(G$2>Payroll!$I28,Payroll!$F28*((1+Payroll!$J28)^(ROUNDDOWN(DATEDIF(Payroll!$I28,G$2,"M")/Payroll!$K28,0))),0)) | H102: =IF(H$2=Payroll!$I28,Payroll!$F28,IF(H$2>Payroll!$I28,Payroll!$F28*((1+Payroll!$J28)^(ROUNDDOWN(DATEDIF(Payroll!$I28,H$2,"M")/Payroll!$K28,0))),0)) | I102: =IF(I$2=Payroll!$I28,Payroll!$F28,IF(I$2>Payroll!$I28,Payroll!$F28*((1+Payroll!$J28)^(ROUNDDOWN(DATEDIF(Payroll!$I28,I$2,"M")/Payroll!$K28,0))),0)) | J102: =IF(J$2=Payroll!$I28,Payroll!$F28,IF(J$2>Payroll!$I28,Payroll!$F28*((1+Payroll!$J28)^(ROUNDDOWN(DATEDIF(Payroll!$I28,J$2,"M")/Payroll!$K28,0))),0)) | K102: =IF(K$2=Payroll!$I28,Payroll!$F28,IF(K$2>Payroll!$I28,Payroll!$F28*((1+Payroll!$J28)^(ROUNDDOWN(DATEDIF(Payroll!$I28,K$2,"M")/Payroll!$K28,0))),0)) | L102: =IF(L$2=Payroll!$I28,Payroll!$F28,IF(L$2>Payroll!$I28,Payroll!$F28*((1+Payroll!$J28)^(ROUNDDOWN(DATEDIF(Payroll!$I28,L$2,"M")/Payroll!$K28,0))),0)) | ... CX102: =IF(CX$2=Payroll!$I28,Payroll!$F28,IF(CX$2>Payroll!$I28,Payroll!$F28*((1+Payroll!$J28)^(ROUNDDOWN(DATEDIF(Payroll!$I28,CX$2,"M")/Payroll!$K28,0))),0))
A104: =Payroll!A5 | B104: Operations | E104: =SUM(E105:E107) | F104: =SUM(F105:F107) | G104: =SUM(G105:G107) | H104: =SUM(H105:H107) | I104: =SUM(I105:I107) | J104: =SUM(J105:J107) | K104: =SUM(K105:K107) | L104: =SUM(L105:L107) | ... CX104: =SUM(CX105:CX107)
A105: =Payroll!A6 | E105: =IF(E$2=Payroll!$I6,Payroll!$F6,IF(E$2>Payroll!$I6,Payroll!$F6*((1+Payroll!$J6)^(ROUNDDOWN(DATEDIF(Payroll!$I6,E$2,"M")/Payroll!$K6,0))),0)) | F105: =IF(F$2=Payroll!$I6,Payroll!$F6,IF(F$2>Payroll!$I6,Payroll!$F6*((1+Payroll!$J6)^(ROUNDDOWN(DATEDIF(Payroll!$I6,F$2,"M")/Payroll!$K6,0))),0)) | G105: =IF(G$2=Payroll!$I6,Payroll!$F6,IF(G$2>Payroll!$I6,Payroll!$F6*((1+Payroll!$J6)^(ROUNDDOWN(DATEDIF(Payroll!$I6,G$2,"M")/Payroll!$K6,0))),0)) | H105: =IF(H$2=Payroll!$I6,Payroll!$F6,IF(H$2>Payroll!$I6,Payroll!$F6*((1+Payroll!$J6)^(ROUNDDOWN(DATEDIF(Payroll!$I6,H$2,"M")/Payroll!$K6,0))),0)) | I105: =IF(I$2=Payroll!$I6,Payroll!$F6,IF(I$2>Payroll!$I6,Payroll!$F6*((1+Payroll!$J6)^(ROUNDDOWN(DATEDIF(Payroll!$I6,I$2,"M")/Payroll!$K6,0))),0)) | J105: =IF(J$2=Payroll!$I6,Payroll!$F6,IF(J$2>Payroll!$I6,Payroll!$F6*((1+Payroll!$J6)^(ROUNDDOWN(DATEDIF(Payroll!$I6,J$2,"M")/Payroll!$K6,0))),0)) | K105: =IF(K$2=Payroll!$I6,Payroll!$F6,IF(K$2>Payroll!$I6,Payroll!$F6*((1+Payroll!$J6)^(ROUNDDOWN(DATEDIF(Payroll!$I6,K$2,"M")/Payroll!$K6,0))),0)) | L105: =IF(L$2=Payroll!$I6,Payroll!$F6,IF(L$2>Payroll!$I6,Payroll!$F6*((1+Payroll!$J6)^(ROUNDDOWN(DATEDIF(Payroll!$I6,L$2,"M")/Payroll!$K6,0))),0)) | ... CX105: =IF(CX$2=Payroll!$I6,Payroll!$F6,IF(CX$2>Payroll!$I6,Payroll!$F6*((1+Payroll!$J6)^(ROUNDDOWN(DATEDIF(Payroll!$I6,CX$2,"M")/Payroll!$K6,0))),0))
A106: =Payroll!A7 | E106: =IF(E$2=Payroll!$I7,Payroll!$F7,IF(E$2>Payroll!$I7,Payroll!$F7*((1+Payroll!$J7)^(ROUNDDOWN(DATEDIF(Payroll!$I7,E$2,"M")/Payroll!$K7,0))),0)) | F106: =IF(F$2=Payroll!$I7,Payroll!$F7,IF(F$2>Payroll!$I7,Payroll!$F7*((1+Payroll!$J7)^(ROUNDDOWN(DATEDIF(Payroll!$I7,F$2,"M")/Payroll!$K7,0))),0)) | G106: =IF(G$2=Payroll!$I7,Payroll!$F7,IF(G$2>Payroll!$I7,Payroll!$F7*((1+Payroll!$J7)^(ROUNDDOWN(DATEDIF(Payroll!$I7,G$2,"M")/Payroll!$K7,0))),0)) | H106: =IF(H$2=Payroll!$I7,Payroll!$F7,IF(H$2>Payroll!$I7,Payroll!$F7*((1+Payroll!$J7)^(ROUNDDOWN(DATEDIF(Payroll!$I7,H$2,"M")/Payroll!$K7,0))),0)) | I106: =IF(I$2=Payroll!$I7,Payroll!$F7,IF(I$2>Payroll!$I7,Payroll!$F7*((1+Payroll!$J7)^(ROUNDDOWN(DATEDIF(Payroll!$I7,I$2,"M")/Payroll!$K7,0))),0)) | J106: =IF(J$2=Payroll!$I7,Payroll!$F7,IF(J$2>Payroll!$I7,Payroll!$F7*((1+Payroll!$J7)^(ROUNDDOWN(DATEDIF(Payroll!$I7,J$2,"M")/Payroll!$K7,0))),0)) | K106: =IF(K$2=Payroll!$I7,Payroll!$F7,IF(K$2>Payroll!$I7,Payroll!$F7*((1+Payroll!$J7)^(ROUNDDOWN(DATEDIF(Payroll!$I7,K$2,"M")/Payroll!$K7,0))),0)) | L106: =IF(L$2=Payroll!$I7,Payroll!$F7,IF(L$2>Payroll!$I7,Payroll!$F7*((1+Payroll!$J7)^(ROUNDDOWN(DATEDIF(Payroll!$I7,L$2,"M")/Payroll!$K7,0))),0)) | ... CX106: =IF(CX$2=Payroll!$I7,Payroll!$F7,IF(CX$2>Payroll!$I7,Payroll!$F7*((1+Payroll!$J7)^(ROUNDDOWN(DATEDIF(Payroll!$I7,CX$2,"M")/Payroll!$K7,0))),0))
A107: =Payroll!A8 | E107: =IF(E$2=Payroll!$I8,Payroll!$F8,IF(E$2>Payroll!$I8,Payroll!$F8*((1+Payroll!$J8)^(ROUNDDOWN(DATEDIF(Payroll!$I8,E$2,"M")/Payroll!$K8,0))),0)) | F107: =IF(F$2=Payroll!$I8,Payroll!$F8,IF(F$2>Payroll!$I8,Payroll!$F8*((1+Payroll!$J8)^(ROUNDDOWN(DATEDIF(Payroll!$I8,F$2,"M")/Payroll!$K8,0))),0)) | G107: =IF(G$2=Payroll!$I8,Payroll!$F8,IF(G$2>Payroll!$I8,Payroll!$F8*((1+Payroll!$J8)^(ROUNDDOWN(DATEDIF(Payroll!$I8,G$2,"M")/Payroll!$K8,0))),0)) | H107: =IF(H$2=Payroll!$I8,Payroll!$F8,IF(H$2>Payroll!$I8,Payroll!$F8*((1+Payroll!$J8)^(ROUNDDOWN(DATEDIF(Payroll!$I8,H$2,"M")/Payroll!$K8,0))),0)) | I107: =IF(I$2=Payroll!$I8,Payroll!$F8,IF(I$2>Payroll!$I8,Payroll!$F8*((1+Payroll!$J8)^(ROUNDDOWN(DATEDIF(Payroll!$I8,I$2,"M")/Payroll!$K8,0))),0)) | J107: =IF(J$2=Payroll!$I8,Payroll!$F8,IF(J$2>Payroll!$I8,Payroll!$F8*((1+Payroll!$J8)^(ROUNDDOWN(DATEDIF(Payroll!$I8,J$2,"M")/Payroll!$K8,0))),0)) | K107: =IF(K$2=Payroll!$I8,Payroll!$F8,IF(K$2>Payroll!$I8,Payroll!$F8*((1+Payroll!$J8)^(ROUNDDOWN(DATEDIF(Payroll!$I8,K$2,"M")/Payroll!$K8,0))),0)) | L107: =IF(L$2=Payroll!$I8,Payroll!$F8,IF(L$2>Payroll!$I8,Payroll!$F8*((1+Payroll!$J8)^(ROUNDDOWN(DATEDIF(Payroll!$I8,L$2,"M")/Payroll!$K8,0))),0)) | ... CX107: =IF(CX$2=Payroll!$I8,Payroll!$F8,IF(CX$2>Payroll!$I8,Payroll!$F8*((1+Payroll!$J8)^(ROUNDDOWN(DATEDIF(Payroll!$I8,CX$2,"M")/Payroll!$K8,0))),0))
A108: =Payroll!A9 | E108: =IF(E$2=Payroll!$I9,Payroll!$F9,IF(E$2>Payroll!$I9,Payroll!$F9*((1+Payroll!$J9)^(ROUNDDOWN(DATEDIF(Payroll!$I9,E$2,"M")/Payroll!$K9,0))),0)) | F108: =IF(F$2=Payroll!$I9,Payroll!$F9,IF(F$2>Payroll!$I9,Payroll!$F9*((1+Payroll!$J9)^(ROUNDDOWN(DATEDIF(Payroll!$I9,F$2,"M")/Payroll!$K9,0))),0)) | G108: =IF(G$2=Payroll!$I9,Payroll!$F9,IF(G$2>Payroll!$I9,Payroll!$F9*((1+Payroll!$J9)^(ROUNDDOWN(DATEDIF(Payroll!$I9,G$2,"M")/Payroll!$K9,0))),0)) | H108: =IF(H$2=Payroll!$I9,Payroll!$F9,IF(H$2>Payroll!$I9,Payroll!$F9*((1+Payroll!$J9)^(ROUNDDOWN(DATEDIF(Payroll!$I9,H$2,"M")/Payroll!$K9,0))),0)) | I108: =IF(I$2=Payroll!$I9,Payroll!$F9,IF(I$2>Payroll!$I9,Payroll!$F9*((1+Payroll!$J9)^(ROUNDDOWN(DATEDIF(Payroll!$I9,I$2,"M")/Payroll!$K9,0))),0)) | J108: =IF(J$2=Payroll!$I9,Payroll!$F9,IF(J$2>Payroll!$I9,Payroll!$F9*((1+Payroll!$J9)^(ROUNDDOWN(DATEDIF(Payroll!$I9,J$2,"M")/Payroll!$K9,0))),0)) | K108: =IF(K$2=Payroll!$I9,Payroll!$F9,IF(K$2>Payroll!$I9,Payroll!$F9*((1+Payroll!$J9)^(ROUNDDOWN(DATEDIF(Payroll!$I9,K$2,"M")/Payroll!$K9,0))),0)) | L108: =IF(L$2=Payroll!$I9,Payroll!$F9,IF(L$2>Payroll!$I9,Payroll!$F9*((1+Payroll!$J9)^(ROUNDDOWN(DATEDIF(Payroll!$I9,L$2,"M")/Payroll!$K9,0))),0)) | ... CX108: =IF(CX$2=Payroll!$I9,Payroll!$F9,IF(CX$2>Payroll!$I9,Payroll!$F9*((1+Payroll!$J9)^(ROUNDDOWN(DATEDIF(Payroll!$I9,CX$2,"M")/Payroll!$K9,0))),0))
A109: =Payroll!A10 | E109: =IF(E$2=Payroll!$I10,Payroll!$F10,IF(E$2>Payroll!$I10,Payroll!$F10*((1+Payroll!$J10)^(ROUNDDOWN(DATEDIF(Payroll!$I10,E$2,"M")/Payroll!$K10,0))),0)) | F109: =IF(F$2=Payroll!$I10,Payroll!$F10,IF(F$2>Payroll!$I10,Payroll!$F10*((1+Payroll!$J10)^(ROUNDDOWN(DATEDIF(Payroll!$I10,F$2,"M")/Payroll!$K10,0))),0)) | G109: =IF(G$2=Payroll!$I10,Payroll!$F10,IF(G$2>Payroll!$I10,Payroll!$F10*((1+Payroll!$J10)^(ROUNDDOWN(DATEDIF(Payroll!$I10,G$2,"M")/Payroll!$K10,0))),0)) | H109: =IF(H$2=Payroll!$I10,Payroll!$F10,IF(H$2>Payroll!$I10,Payroll!$F10*((1+Payroll!$J10)^(ROUNDDOWN(DATEDIF(Payroll!$I10,H$2,"M")/Payroll!$K10,0))),0)) | I109: =IF(I$2=Payroll!$I10,Payroll!$F10,IF(I$2>Payroll!$I10,Payroll!$F10*((1+Payroll!$J10)^(ROUNDDOWN(DATEDIF(Payroll!$I10,I$2,"M")/Payroll!$K10,0))),0)) | J109: =IF(J$2=Payroll!$I10,Payroll!$F10,IF(J$2>Payroll!$I10,Payroll!$F10*((1+Payroll!$J10)^(ROUNDDOWN(DATEDIF(Payroll!$I10,J$2,"M")/Payroll!$K10,0))),0)) | K109: =IF(K$2=Payroll!$I10,Payroll!$F10,IF(K$2>Payroll!$I10,Payroll!$F10*((1+Payroll!$J10)^(ROUNDDOWN(DATEDIF(Payroll!$I10,K$2,"M")/Payroll!$K10,0))),0)) | L109: =IF(L$2=Payroll!$I10,Payroll!$F10,IF(L$2>Payroll!$I10,Payroll!$F10*((1+Payroll!$J10)^(ROUNDDOWN(DATEDIF(Payroll!$I10,L$2,"M")/Payroll!$K10,0))),0)) | ... CX109: =IF(CX$2=Payroll!$I10,Payroll!$F10,IF(CX$2>Payroll!$I10,Payroll!$F10*((1+Payroll!$J10)^(ROUNDDOWN(DATEDIF(Payroll!$I10,CX$2,"M")/Payroll!$K10,0))),0))
A110: =Payroll!A11 | E110: =IF(E$2=Payroll!$I11,Payroll!$F11,IF(E$2>Payroll!$I11,Payroll!$F11*((1+Payroll!$J11)^(ROUNDDOWN(DATEDIF(Payroll!$I11,E$2,"M")/Payroll!$K11,0))),0)) | F110: =IF(F$2=Payroll!$I11,Payroll!$F11,IF(F$2>Payroll!$I11,Payroll!$F11*((1+Payroll!$J11)^(ROUNDDOWN(DATEDIF(Payroll!$I11,F$2,"M")/Payroll!$K11,0))),0)) | G110: =IF(G$2=Payroll!$I11,Payroll!$F11,IF(G$2>Payroll!$I11,Payroll!$F11*((1+Payroll!$J11)^(ROUNDDOWN(DATEDIF(Payroll!$I11,G$2,"M")/Payroll!$K11,0))),0)) | H110: =IF(H$2=Payroll!$I11,Payroll!$F11,IF(H$2>Payroll!$I11,Payroll!$F11*((1+Payroll!$J11)^(ROUNDDOWN(DATEDIF(Payroll!$I11,H$2,"M")/Payroll!$K11,0))),0)) | I110: =IF(I$2=Payroll!$I11,Payroll!$F11,IF(I$2>Payroll!$I11,Payroll!$F11*((1+Payroll!$J11)^(ROUNDDOWN(DATEDIF(Payroll!$I11,I$2,"M")/Payroll!$K11,0))),0)) | J110: =IF(J$2=Payroll!$I11,Payroll!$F11,IF(J$2>Payroll!$I11,Payroll!$F11*((1+Payroll!$J11)^(ROUNDDOWN(DATEDIF(Payroll!$I11,J$2,"M")/Payroll!$K11,0))),0)) | K110: =IF(K$2=Payroll!$I11,Payroll!$F11,IF(K$2>Payroll!$I11,Payroll!$F11*((1+Payroll!$J11)^(ROUNDDOWN(DATEDIF(Payroll!$I11,K$2,"M")/Payroll!$K11,0))),0)) | L110: =IF(L$2=Payroll!$I11,Payroll!$F11,IF(L$2>Payroll!$I11,Payroll!$F11*((1+Payroll!$J11)^(ROUNDDOWN(DATEDIF(Payroll!$I11,L$2,"M")/Payroll!$K11,0))),0)) | ... CX110: =IF(CX$2=Payroll!$I11,Payroll!$F11,IF(CX$2>Payroll!$I11,Payroll!$F11*((1+Payroll!$J11)^(ROUNDDOWN(DATEDIF(Payroll!$I11,CX$2,"M")/Payroll!$K11,0))),0))
A111: =Payroll!A12 | E111: =IF(E$2=Payroll!$I12,Payroll!$F12,IF(E$2>Payroll!$I12,Payroll!$F12*((1+Payroll!$J12)^(ROUNDDOWN(DATEDIF(Payroll!$I12,E$2,"M")/Payroll!$K12,0))),0)) | F111: =IF(F$2=Payroll!$I12,Payroll!$F12,IF(F$2>Payroll!$I12,Payroll!$F12*((1+Payroll!$J12)^(ROUNDDOWN(DATEDIF(Payroll!$I12,F$2,"M")/Payroll!$K12,0))),0)) | G111: =IF(G$2=Payroll!$I12,Payroll!$F12,IF(G$2>Payroll!$I12,Payroll!$F12*((1+Payroll!$J12)^(ROUNDDOWN(DATEDIF(Payroll!$I12,G$2,"M")/Payroll!$K12,0))),0)) | H111: =IF(H$2=Payroll!$I12,Payroll!$F12,IF(H$2>Payroll!$I12,Payroll!$F12*((1+Payroll!$J12)^(ROUNDDOWN(DATEDIF(Payroll!$I12,H$2,"M")/Payroll!$K12,0))),0)) | I111: =IF(I$2=Payroll!$I12,Payroll!$F12,IF(I$2>Payroll!$I12,Payroll!$F12*((1+Payroll!$J12)^(ROUNDDOWN(DATEDIF(Payroll!$I12,I$2,"M")/Payroll!$K12,0))),0)) | J111: =IF(J$2=Payroll!$I12,Payroll!$F12,IF(J$2>Payroll!$I12,Payroll!$F12*((1+Payroll!$J12)^(ROUNDDOWN(DATEDIF(Payroll!$I12,J$2,"M")/Payroll!$K12,0))),0)) | K111: =IF(K$2=Payroll!$I12,Payroll!$F12,IF(K$2>Payroll!$I12,Payroll!$F12*((1+Payroll!$J12)^(ROUNDDOWN(DATEDIF(Payroll!$I12,K$2,"M")/Payroll!$K12,0))),0)) | L111: =IF(L$2=Payroll!$I12,Payroll!$F12,IF(L$2>Payroll!$I12,Payroll!$F12*((1+Payroll!$J12)^(ROUNDDOWN(DATEDIF(Payroll!$I12,L$2,"M")/Payroll!$K12,0))),0)) | ... CX111: =IF(CX$2=Payroll!$I12,Payroll!$F12,IF(CX$2>Payroll!$I12,Payroll!$F12*((1+Payroll!$J12)^(ROUNDDOWN(DATEDIF(Payroll!$I12,CX$2,"M")/Payroll!$K12,0))),0))
A112: =Payroll!A13 | E112: =IF(E$2=Payroll!$I13,Payroll!$F13,IF(E$2>Payroll!$I13,Payroll!$F13*((1+Payroll!$J13)^(ROUNDDOWN(DATEDIF(Payroll!$I13,E$2,"M")/Payroll!$K13,0))),0)) | F112: =IF(F$2=Payroll!$I13,Payroll!$F13,IF(F$2>Payroll!$I13,Payroll!$F13*((1+Payroll!$J13)^(ROUNDDOWN(DATEDIF(Payroll!$I13,F$2,"M")/Payroll!$K13,0))),0)) | G112: =IF(G$2=Payroll!$I13,Payroll!$F13,IF(G$2>Payroll!$I13,Payroll!$F13*((1+Payroll!$J13)^(ROUNDDOWN(DATEDIF(Payroll!$I13,G$2,"M")/Payroll!$K13,0))),0)) | H112: =IF(H$2=Payroll!$I13,Payroll!$F13,IF(H$2>Payroll!$I13,Payroll!$F13*((1+Payroll!$J13)^(ROUNDDOWN(DATEDIF(Payroll!$I13,H$2,"M")/Payroll!$K13,0))),0)) | I112: =IF(I$2=Payroll!$I13,Payroll!$F13,IF(I$2>Payroll!$I13,Payroll!$F13*((1+Payroll!$J13)^(ROUNDDOWN(DATEDIF(Payroll!$I13,I$2,"M")/Payroll!$K13,0))),0)) | J112: =IF(J$2=Payroll!$I13,Payroll!$F13,IF(J$2>Payroll!$I13,Payroll!$F13*((1+Payroll!$J13)^(ROUNDDOWN(DATEDIF(Payroll!$I13,J$2,"M")/Payroll!$K13,0))),0)) | K112: =IF(K$2=Payroll!$I13,Payroll!$F13,IF(K$2>Payroll!$I13,Payroll!$F13*((1+Payroll!$J13)^(ROUNDDOWN(DATEDIF(Payroll!$I13,K$2,"M")/Payroll!$K13,0))),0)) | L112: =IF(L$2=Payroll!$I13,Payroll!$F13,IF(L$2>Payroll!$I13,Payroll!$F13*((1+Payroll!$J13)^(ROUNDDOWN(DATEDIF(Payroll!$I13,L$2,"M")/Payroll!$K13,0))),0)) | ... CX112: =IF(CX$2=Payroll!$I13,Payroll!$F13,IF(CX$2>Payroll!$I13,Payroll!$F13*((1+Payroll!$J13)^(ROUNDDOWN(DATEDIF(Payroll!$I13,CX$2,"M")/Payroll!$K13,0))),0))
A113: =Payroll!A14 | E113: =IF(E$2=Payroll!$I14,Payroll!$F14,IF(E$2>Payroll!$I14,Payroll!$F14*((1+Payroll!$J14)^(ROUNDDOWN(DATEDIF(Payroll!$I14,E$2,"M")/Payroll!$K14,0))),0)) | F113: =IF(F$2=Payroll!$I14,Payroll!$F14,IF(F$2>Payroll!$I14,Payroll!$F14*((1+Payroll!$J14)^(ROUNDDOWN(DATEDIF(Payroll!$I14,F$2,"M")/Payroll!$K14,0))),0)) | G113: =IF(G$2=Payroll!$I14,Payroll!$F14,IF(G$2>Payroll!$I14,Payroll!$F14*((1+Payroll!$J14)^(ROUNDDOWN(DATEDIF(Payroll!$I14,G$2,"M")/Payroll!$K14,0))),0)) | H113: =IF(H$2=Payroll!$I14,Payroll!$F14,IF(H$2>Payroll!$I14,Payroll!$F14*((1+Payroll!$J14)^(ROUNDDOWN(DATEDIF(Payroll!$I14,H$2,"M")/Payroll!$K14,0))),0)) | I113: =IF(I$2=Payroll!$I14,Payroll!$F14,IF(I$2>Payroll!$I14,Payroll!$F14*((1+Payroll!$J14)^(ROUNDDOWN(DATEDIF(Payroll!$I14,I$2,"M")/Payroll!$K14,0))),0)) | J113: =IF(J$2=Payroll!$I14,Payroll!$F14,IF(J$2>Payroll!$I14,Payroll!$F14*((1+Payroll!$J14)^(ROUNDDOWN(DATEDIF(Payroll!$I14,J$2,"M")/Payroll!$K14,0))),0)) | K113: =IF(K$2=Payroll!$I14,Payroll!$F14,IF(K$2>Payroll!$I14,Payroll!$F14*((1+Payroll!$J14)^(ROUNDDOWN(DATEDIF(Payroll!$I14,K$2,"M")/Payroll!$K14,0))),0)) | L113: =IF(L$2=Payroll!$I14,Payroll!$F14,IF(L$2>Payroll!$I14,Payroll!$F14*((1+Payroll!$J14)^(ROUNDDOWN(DATEDIF(Payroll!$I14,L$2,"M")/Payroll!$K14,0))),0)) | ... CX113: =IF(CX$2=Payroll!$I14,Payroll!$F14,IF(CX$2>Payroll!$I14,Payroll!$F14*((1+Payroll!$J14)^(ROUNDDOWN(DATEDIF(Payroll!$I14,CX$2,"M")/Payroll!$K14,0))),0))
A115: =Payroll!A30 | B115: Marketing | E115: =SUM(E116:E125) | F115: =SUM(F116:F125) | G115: =SUM(G116:G125) | H115: =SUM(H116:H125) | I115: =SUM(I116:I125) | J115: =SUM(J116:J125) | K115: =SUM(K116:K125) | L115: =SUM(L116:L125) | ... CX115: =SUM(CX116:CX125)
A116: =Payroll!A31 | E116: =IF(E$2=Payroll!$I31,Payroll!$F31,IF(E$2>Payroll!$I31,Payroll!$F31*((1+Payroll!$J31)^(ROUNDDOWN(DATEDIF(Payroll!$I31,E$2,"M")/Payroll!$K31,0))),0)) | F116: =IF(F$2=Payroll!$I31,Payroll!$F31,IF(F$2>Payroll!$I31,Payroll!$F31*((1+Payroll!$J31)^(ROUNDDOWN(DATEDIF(Payroll!$I31,F$2,"M")/Payroll!$K31,0))),0)) | G116: =IF(G$2=Payroll!$I31,Payroll!$F31,IF(G$2>Payroll!$I31,Payroll!$F31*((1+Payroll!$J31)^(ROUNDDOWN(DATEDIF(Payroll!$I31,G$2,"M")/Payroll!$K31,0))),0)) | H116: =IF(H$2=Payroll!$I31,Payroll!$F31,IF(H$2>Payroll!$I31,Payroll!$F31*((1+Payroll!$J31)^(ROUNDDOWN(DATEDIF(Payroll!$I31,H$2,"M")/Payroll!$K31,0))),0)) | I116: =IF(I$2=Payroll!$I31,Payroll!$F31,IF(I$2>Payroll!$I31,Payroll!$F31*((1+Payroll!$J31)^(ROUNDDOWN(DATEDIF(Payroll!$I31,I$2,"M")/Payroll!$K31,0))),0)) | J116: =IF(J$2=Payroll!$I31,Payroll!$F31,IF(J$2>Payroll!$I31,Payroll!$F31*((1+Payroll!$J31)^(ROUNDDOWN(DATEDIF(Payroll!$I31,J$2,"M")/Payroll!$K31,0))),0)) | K116: =IF(K$2=Payroll!$I31,Payroll!$F31,IF(K$2>Payroll!$I31,Payroll!$F31*((1+Payroll!$J31)^(ROUNDDOWN(DATEDIF(Payroll!$I31,K$2,"M")/Payroll!$K31,0))),0)) | L116: =IF(L$2=Payroll!$I31,Payroll!$F31,IF(L$2>Payroll!$I31,Payroll!$F31*((1+Payroll!$J31)^(ROUNDDOWN(DATEDIF(Payroll!$I31,L$2,"M")/Payroll!$K31,0))),0)) | ... CX116: =IF(CX$2=Payroll!$I31,Payroll!$F31,IF(CX$2>Payroll!$I31,Payroll!$F31*((1+Payroll!$J31)^(ROUNDDOWN(DATEDIF(Payroll!$I31,CX$2,"M")/Payroll!$K31,0))),0))
A117: =Payroll!A32 | E117: =IF(E$2=Payroll!$I32,Payroll!$F32,IF(E$2>Payroll!$I32,Payroll!$F32*((1+Payroll!$J32)^(ROUNDDOWN(DATEDIF(Payroll!$I32,E$2,"M")/Payroll!$K32,0))),0)) | F117: =IF(F$2=Payroll!$I32,Payroll!$F32,IF(F$2>Payroll!$I32,Payroll!$F32*((1+Payroll!$J32)^(ROUNDDOWN(DATEDIF(Payroll!$I32,F$2,"M")/Payroll!$K32,0))),0)) | G117: =IF(G$2=Payroll!$I32,Payroll!$F32,IF(G$2>Payroll!$I32,Payroll!$F32*((1+Payroll!$J32)^(ROUNDDOWN(DATEDIF(Payroll!$I32,G$2,"M")/Payroll!$K32,0))),0)) | H117: =IF(H$2=Payroll!$I32,Payroll!$F32,IF(H$2>Payroll!$I32,Payroll!$F32*((1+Payroll!$J32)^(ROUNDDOWN(DATEDIF(Payroll!$I32,H$2,"M")/Payroll!$K32,0))),0)) | I117: =IF(I$2=Payroll!$I32,Payroll!$F32,IF(I$2>Payroll!$I32,Payroll!$F32*((1+Payroll!$J32)^(ROUNDDOWN(DATEDIF(Payroll!$I32,I$2,"M")/Payroll!$K32,0))),0)) | J117: =IF(J$2=Payroll!$I32,Payroll!$F32,IF(J$2>Payroll!$I32,Payroll!$F32*((1+Payroll!$J32)^(ROUNDDOWN(DATEDIF(Payroll!$I32,J$2,"M")/Payroll!$K32,0))),0)) | K117: =IF(K$2=Payroll!$I32,Payroll!$F32,IF(K$2>Payroll!$I32,Payroll!$F32*((1+Payroll!$J32)^(ROUNDDOWN(DATEDIF(Payroll!$I32,K$2,"M")/Payroll!$K32,0))),0)) | L117: =IF(L$2=Payroll!$I32,Payroll!$F32,IF(L$2>Payroll!$I32,Payroll!$F32*((1+Payroll!$J32)^(ROUNDDOWN(DATEDIF(Payroll!$I32,L$2,"M")/Payroll!$K32,0))),0)) | ... CX117: =IF(CX$2=Payroll!$I32,Payroll!$F32,IF(CX$2>Payroll!$I32,Payroll!$F32*((1+Payroll!$J32)^(ROUNDDOWN(DATEDIF(Payroll!$I32,CX$2,"M")/Payroll!$K32,0))),0))
A118: =Payroll!A33 | E118: =IF(E$2=Payroll!$I33,Payroll!$F33,IF(E$2>Payroll!$I33,Payroll!$F33*((1+Payroll!$J33)^(ROUNDDOWN(DATEDIF(Payroll!$I33,E$2,"M")/Payroll!$K33,0))),0)) | F118: =IF(F$2=Payroll!$I33,Payroll!$F33,IF(F$2>Payroll!$I33,Payroll!$F33*((1+Payroll!$J33)^(ROUNDDOWN(DATEDIF(Payroll!$I33,F$2,"M")/Payroll!$K33,0))),0)) | G118: =IF(G$2=Payroll!$I33,Payroll!$F33,IF(G$2>Payroll!$I33,Payroll!$F33*((1+Payroll!$J33)^(ROUNDDOWN(DATEDIF(Payroll!$I33,G$2,"M")/Payroll!$K33,0))),0)) | H118: =IF(H$2=Payroll!$I33,Payroll!$F33,IF(H$2>Payroll!$I33,Payroll!$F33*((1+Payroll!$J33)^(ROUNDDOWN(DATEDIF(Payroll!$I33,H$2,"M")/Payroll!$K33,0))),0)) | I118: =IF(I$2=Payroll!$I33,Payroll!$F33,IF(I$2>Payroll!$I33,Payroll!$F33*((1+Payroll!$J33)^(ROUNDDOWN(DATEDIF(Payroll!$I33,I$2,"M")/Payroll!$K33,0))),0)) | J118: =IF(J$2=Payroll!$I33,Payroll!$F33,IF(J$2>Payroll!$I33,Payroll!$F33*((1+Payroll!$J33)^(ROUNDDOWN(DATEDIF(Payroll!$I33,J$2,"M")/Payroll!$K33,0))),0)) | K118: =IF(K$2=Payroll!$I33,Payroll!$F33,IF(K$2>Payroll!$I33,Payroll!$F33*((1+Payroll!$J33)^(ROUNDDOWN(DATEDIF(Payroll!$I33,K$2,"M")/Payroll!$K33,0))),0)) | L118: =IF(L$2=Payroll!$I33,Payroll!$F33,IF(L$2>Payroll!$I33,Payroll!$F33*((1+Payroll!$J33)^(ROUNDDOWN(DATEDIF(Payroll!$I33,L$2,"M")/Payroll!$K33,0))),0)) | ... CX118: =IF(CX$2=Payroll!$I33,Payroll!$F33,IF(CX$2>Payroll!$I33,Payroll!$F33*((1+Payroll!$J33)^(ROUNDDOWN(DATEDIF(Payroll!$I33,CX$2,"M")/Payroll!$K33,0))),0))
A119: =Payroll!A34 | E119: =IF(E$2=Payroll!$I34,Payroll!$F34,IF(E$2>Payroll!$I34,Payroll!$F34*((1+Payroll!$J34)^(ROUNDDOWN(DATEDIF(Payroll!$I34,E$2,"M")/Payroll!$K34,0))),0)) | F119: =IF(F$2=Payroll!$I34,Payroll!$F34,IF(F$2>Payroll!$I34,Payroll!$F34*((1+Payroll!$J34)^(ROUNDDOWN(DATEDIF(Payroll!$I34,F$2,"M")/Payroll!$K34,0))),0)) | G119: =IF(G$2=Payroll!$I34,Payroll!$F34,IF(G$2>Payroll!$I34,Payroll!$F34*((1+Payroll!$J34)^(ROUNDDOWN(DATEDIF(Payroll!$I34,G$2,"M")/Payroll!$K34,0))),0)) | H119: =IF(H$2=Payroll!$I34,Payroll!$F34,IF(H$2>Payroll!$I34,Payroll!$F34*((1+Payroll!$J34)^(ROUNDDOWN(DATEDIF(Payroll!$I34,H$2,"M")/Payroll!$K34,0))),0)) | I119: =IF(I$2=Payroll!$I34,Payroll!$F34,IF(I$2>Payroll!$I34,Payroll!$F34*((1+Payroll!$J34)^(ROUNDDOWN(DATEDIF(Payroll!$I34,I$2,"M")/Payroll!$K34,0))),0)) | J119: =IF(J$2=Payroll!$I34,Payroll!$F34,IF(J$2>Payroll!$I34,Payroll!$F34*((1+Payroll!$J34)^(ROUNDDOWN(DATEDIF(Payroll!$I34,J$2,"M")/Payroll!$K34,0))),0)) | K119: =IF(K$2=Payroll!$I34,Payroll!$F34,IF(K$2>Payroll!$I34,Payroll!$F34*((1+Payroll!$J34)^(ROUNDDOWN(DATEDIF(Payroll!$I34,K$2,"M")/Payroll!$K34,0))),0)) | L119: =IF(L$2=Payroll!$I34,Payroll!$F34,IF(L$2>Payroll!$I34,Payroll!$F34*((1+Payroll!$J34)^(ROUNDDOWN(DATEDIF(Payroll!$I34,L$2,"M")/Payroll!$K34,0))),0)) | ... CX119: =IF(CX$2=Payroll!$I34,Payroll!$F34,IF(CX$2>Payroll!$I34,Payroll!$F34*((1+Payroll!$J34)^(ROUNDDOWN(DATEDIF(Payroll!$I34,CX$2,"M")/Payroll!$K34,0))),0))
A120: =Payroll!A35 | E120: =IF(E$2=Payroll!$I35,Payroll!$F35,IF(E$2>Payroll!$I35,Payroll!$F35*((1+Payroll!$J35)^(ROUNDDOWN(DATEDIF(Payroll!$I35,E$2,"M")/Payroll!$K35,0))),0)) | F120: =IF(F$2=Payroll!$I35,Payroll!$F35,IF(F$2>Payroll!$I35,Payroll!$F35*((1+Payroll!$J35)^(ROUNDDOWN(DATEDIF(Payroll!$I35,F$2,"M")/Payroll!$K35,0))),0)) | G120: =IF(G$2=Payroll!$I35,Payroll!$F35,IF(G$2>Payroll!$I35,Payroll!$F35*((1+Payroll!$J35)^(ROUNDDOWN(DATEDIF(Payroll!$I35,G$2,"M")/Payroll!$K35,0))),0)) | H120: =IF(H$2=Payroll!$I35,Payroll!$F35,IF(H$2>Payroll!$I35,Payroll!$F35*((1+Payroll!$J35)^(ROUNDDOWN(DATEDIF(Payroll!$I35,H$2,"M")/Payroll!$K35,0))),0)) | I120: =IF(I$2=Payroll!$I35,Payroll!$F35,IF(I$2>Payroll!$I35,Payroll!$F35*((1+Payroll!$J35)^(ROUNDDOWN(DATEDIF(Payroll!$I35,I$2,"M")/Payroll!$K35,0))),0)) | J120: =IF(J$2=Payroll!$I35,Payroll!$F35,IF(J$2>Payroll!$I35,Payroll!$F35*((1+Payroll!$J35)^(ROUNDDOWN(DATEDIF(Payroll!$I35,J$2,"M")/Payroll!$K35,0))),0)) | K120: =IF(K$2=Payroll!$I35,Payroll!$F35,IF(K$2>Payroll!$I35,Payroll!$F35*((1+Payroll!$J35)^(ROUNDDOWN(DATEDIF(Payroll!$I35,K$2,"M")/Payroll!$K35,0))),0)) | L120: =IF(L$2=Payroll!$I35,Payroll!$F35,IF(L$2>Payroll!$I35,Payroll!$F35*((1+Payroll!$J35)^(ROUNDDOWN(DATEDIF(Payroll!$I35,L$2,"M")/Payroll!$K35,0))),0)) | ... CX120: =IF(CX$2=Payroll!$I35,Payroll!$F35,IF(CX$2>Payroll!$I35,Payroll!$F35*((1+Payroll!$J35)^(ROUNDDOWN(DATEDIF(Payroll!$I35,CX$2,"M")/Payroll!$K35,0))),0))
A121: =Payroll!A36 | E121: =IF(E$2=Payroll!$I36,Payroll!$F36,IF(E$2>Payroll!$I36,Payroll!$F36*((1+Payroll!$J36)^(ROUNDDOWN(DATEDIF(Payroll!$I36,E$2,"M")/Payroll!$K36,0))),0)) | F121: =IF(F$2=Payroll!$I36,Payroll!$F36,IF(F$2>Payroll!$I36,Payroll!$F36*((1+Payroll!$J36)^(ROUNDDOWN(DATEDIF(Payroll!$I36,F$2,"M")/Payroll!$K36,0))),0)) | G121: =IF(G$2=Payroll!$I36,Payroll!$F36,IF(G$2>Payroll!$I36,Payroll!$F36*((1+Payroll!$J36)^(ROUNDDOWN(DATEDIF(Payroll!$I36,G$2,"M")/Payroll!$K36,0))),0)) | H121: =IF(H$2=Payroll!$I36,Payroll!$F36,IF(H$2>Payroll!$I36,Payroll!$F36*((1+Payroll!$J36)^(ROUNDDOWN(DATEDIF(Payroll!$I36,H$2,"M")/Payroll!$K36,0))),0)) | I121: =IF(I$2=Payroll!$I36,Payroll!$F36,IF(I$2>Payroll!$I36,Payroll!$F36*((1+Payroll!$J36)^(ROUNDDOWN(DATEDIF(Payroll!$I36,I$2,"M")/Payroll!$K36,0))),0)) | J121: =IF(J$2=Payroll!$I36,Payroll!$F36,IF(J$2>Payroll!$I36,Payroll!$F36*((1+Payroll!$J36)^(ROUNDDOWN(DATEDIF(Payroll!$I36,J$2,"M")/Payroll!$K36,0))),0)) | K121: =IF(K$2=Payroll!$I36,Payroll!$F36,IF(K$2>Payroll!$I36,Payroll!$F36*((1+Payroll!$J36)^(ROUNDDOWN(DATEDIF(Payroll!$I36,K$2,"M")/Payroll!$K36,0))),0)) | L121: =IF(L$2=Payroll!$I36,Payroll!$F36,IF(L$2>Payroll!$I36,Payroll!$F36*((1+Payroll!$J36)^(ROUNDDOWN(DATEDIF(Payroll!$I36,L$2,"M")/Payroll!$K36,0))),0)) | ... CX121: =IF(CX$2=Payroll!$I36,Payroll!$F36,IF(CX$2>Payroll!$I36,Payroll!$F36*((1+Payroll!$J36)^(ROUNDDOWN(DATEDIF(Payroll!$I36,CX$2,"M")/Payroll!$K36,0))),0))
A122: =Payroll!A37 | E122: =IF(E$2=Payroll!$I37,Payroll!$F37,IF(E$2>Payroll!$I37,Payroll!$F37*((1+Payroll!$J37)^(ROUNDDOWN(DATEDIF(Payroll!$I37,E$2,"M")/Payroll!$K37,0))),0)) | F122: =IF(F$2=Payroll!$I37,Payroll!$F37,IF(F$2>Payroll!$I37,Payroll!$F37*((1+Payroll!$J37)^(ROUNDDOWN(DATEDIF(Payroll!$I37,F$2,"M")/Payroll!$K37,0))),0)) | G122: =IF(G$2=Payroll!$I37,Payroll!$F37,IF(G$2>Payroll!$I37,Payroll!$F37*((1+Payroll!$J37)^(ROUNDDOWN(DATEDIF(Payroll!$I37,G$2,"M")/Payroll!$K37,0))),0)) | H122: =IF(H$2=Payroll!$I37,Payroll!$F37,IF(H$2>Payroll!$I37,Payroll!$F37*((1+Payroll!$J37)^(ROUNDDOWN(DATEDIF(Payroll!$I37,H$2,"M")/Payroll!$K37,0))),0)) | I122: =IF(I$2=Payroll!$I37,Payroll!$F37,IF(I$2>Payroll!$I37,Payroll!$F37*((1+Payroll!$J37)^(ROUNDDOWN(DATEDIF(Payroll!$I37,I$2,"M")/Payroll!$K37,0))),0)) | J122: =IF(J$2=Payroll!$I37,Payroll!$F37,IF(J$2>Payroll!$I37,Payroll!$F37*((1+Payroll!$J37)^(ROUNDDOWN(DATEDIF(Payroll!$I37,J$2,"M")/Payroll!$K37,0))),0)) | K122: =IF(K$2=Payroll!$I37,Payroll!$F37,IF(K$2>Payroll!$I37,Payroll!$F37*((1+Payroll!$J37)^(ROUNDDOWN(DATEDIF(Payroll!$I37,K$2,"M")/Payroll!$K37,0))),0)) | L122: =IF(L$2=Payroll!$I37,Payroll!$F37,IF(L$2>Payroll!$I37,Payroll!$F37*((1+Payroll!$J37)^(ROUNDDOWN(DATEDIF(Payroll!$I37,L$2,"M")/Payroll!$K37,0))),0)) | ... CX122: =IF(CX$2=Payroll!$I37,Payroll!$F37,IF(CX$2>Payroll!$I37,Payroll!$F37*((1+Payroll!$J37)^(ROUNDDOWN(DATEDIF(Payroll!$I37,CX$2,"M")/Payroll!$K37,0))),0))
A123: =Payroll!A38 | E123: =IF(E$2=Payroll!$I38,Payroll!$F38,IF(E$2>Payroll!$I38,Payroll!$F38*((1+Payroll!$J38)^(ROUNDDOWN(DATEDIF(Payroll!$I38,E$2,"M")/Payroll!$K38,0))),0)) | F123: =IF(F$2=Payroll!$I38,Payroll!$F38,IF(F$2>Payroll!$I38,Payroll!$F38*((1+Payroll!$J38)^(ROUNDDOWN(DATEDIF(Payroll!$I38,F$2,"M")/Payroll!$K38,0))),0)) | G123: =IF(G$2=Payroll!$I38,Payroll!$F38,IF(G$2>Payroll!$I38,Payroll!$F38*((1+Payroll!$J38)^(ROUNDDOWN(DATEDIF(Payroll!$I38,G$2,"M")/Payroll!$K38,0))),0)) | H123: =IF(H$2=Payroll!$I38,Payroll!$F38,IF(H$2>Payroll!$I38,Payroll!$F38*((1+Payroll!$J38)^(ROUNDDOWN(DATEDIF(Payroll!$I38,H$2,"M")/Payroll!$K38,0))),0)) | I123: =IF(I$2=Payroll!$I38,Payroll!$F38,IF(I$2>Payroll!$I38,Payroll!$F38*((1+Payroll!$J38)^(ROUNDDOWN(DATEDIF(Payroll!$I38,I$2,"M")/Payroll!$K38,0))),0)) | J123: =IF(J$2=Payroll!$I38,Payroll!$F38,IF(J$2>Payroll!$I38,Payroll!$F38*((1+Payroll!$J38)^(ROUNDDOWN(DATEDIF(Payroll!$I38,J$2,"M")/Payroll!$K38,0))),0)) | K123: =IF(K$2=Payroll!$I38,Payroll!$F38,IF(K$2>Payroll!$I38,Payroll!$F38*((1+Payroll!$J38)^(ROUNDDOWN(DATEDIF(Payroll!$I38,K$2,"M")/Payroll!$K38,0))),0)) | L123: =IF(L$2=Payroll!$I38,Payroll!$F38,IF(L$2>Payroll!$I38,Payroll!$F38*((1+Payroll!$J38)^(ROUNDDOWN(DATEDIF(Payroll!$I38,L$2,"M")/Payroll!$K38,0))),0)) | ... CX123: =IF(CX$2=Payroll!$I38,Payroll!$F38,IF(CX$2>Payroll!$I38,Payroll!$F38*((1+Payroll!$J38)^(ROUNDDOWN(DATEDIF(Payroll!$I38,CX$2,"M")/Payroll!$K38,0))),0))
A127: =Payroll!A48 | E127: =SUM(E128:E133) | F127: =SUM(F128:F133) | G127: =SUM(G128:G133) | H127: =SUM(H128:H133) | I127: =SUM(I128:I133) | J127: =SUM(J128:J133) | K127: =SUM(K128:K133) | L127: =SUM(L128:L133) | ... CX127: =SUM(CX128:CX133)
A128: =Payroll!A49 | E128: =IF(E$2=Payroll!$I49,Payroll!$F49,IF(E$2>Payroll!$I49,Payroll!$F49*((1+Payroll!$J49)^(ROUNDDOWN(DATEDIF(Payroll!$I49,E$2,"M")/Payroll!$K49,0))),0)) | F128: =IF(F$2=Payroll!$I49,Payroll!$F49,IF(F$2>Payroll!$I49,Payroll!$F49*((1+Payroll!$J49)^(ROUNDDOWN(DATEDIF(Payroll!$I49,F$2,"M")/Payroll!$K49,0))),0)) | G128: =IF(G$2=Payroll!$I49,Payroll!$F49,IF(G$2>Payroll!$I49,Payroll!$F49*((1+Payroll!$J49)^(ROUNDDOWN(DATEDIF(Payroll!$I49,G$2,"M")/Payroll!$K49,0))),0)) | H128: =IF(H$2=Payroll!$I49,Payroll!$F49,IF(H$2>Payroll!$I49,Payroll!$F49*((1+Payroll!$J49)^(ROUNDDOWN(DATEDIF(Payroll!$I49,H$2,"M")/Payroll!$K49,0))),0)) | I128: =IF(I$2=Payroll!$I49,Payroll!$F49,IF(I$2>Payroll!$I49,Payroll!$F49*((1+Payroll!$J49)^(ROUNDDOWN(DATEDIF(Payroll!$I49,I$2,"M")/Payroll!$K49,0))),0)) | J128: =IF(J$2=Payroll!$I49,Payroll!$F49,IF(J$2>Payroll!$I49,Payroll!$F49*((1+Payroll!$J49)^(ROUNDDOWN(DATEDIF(Payroll!$I49,J$2,"M")/Payroll!$K49,0))),0)) | K128: =IF(K$2=Payroll!$I49,Payroll!$F49,IF(K$2>Payroll!$I49,Payroll!$F49*((1+Payroll!$J49)^(ROUNDDOWN(DATEDIF(Payroll!$I49,K$2,"M")/Payroll!$K49,0))),0)) | L128: =IF(L$2=Payroll!$I49,Payroll!$F49,IF(L$2>Payroll!$I49,Payroll!$F49*((1+Payroll!$J49)^(ROUNDDOWN(DATEDIF(Payroll!$I49,L$2,"M")/Payroll!$K49,0))),0)) | ... CX128: =IF(CX$2=Payroll!$I49,Payroll!$F49,IF(CX$2>Payroll!$I49,Payroll!$F49*((1+Payroll!$J49)^(ROUNDDOWN(DATEDIF(Payroll!$I49,CX$2,"M")/Payroll!$K49,0))),0))
A129: =Payroll!A52 | E129: =IF(E$2=Payroll!$I52,Payroll!$F52,IF(E$2>Payroll!$I52,Payroll!$F52*((1+Payroll!$J52)^(ROUNDDOWN(DATEDIF(Payroll!$I52,E$2,"M")/Payroll!$K52,0))),0)) | F129: =IF(F$2=Payroll!$I52,Payroll!$F52,IF(F$2>Payroll!$I52,Payroll!$F52*((1+Payroll!$J52)^(ROUNDDOWN(DATEDIF(Payroll!$I52,F$2,"M")/Payroll!$K52,0))),0)) | G129: =IF(G$2=Payroll!$I52,Payroll!$F52,IF(G$2>Payroll!$I52,Payroll!$F52*((1+Payroll!$J52)^(ROUNDDOWN(DATEDIF(Payroll!$I52,G$2,"M")/Payroll!$K52,0))),0)) | H129: =IF(H$2=Payroll!$I52,Payroll!$F52,IF(H$2>Payroll!$I52,Payroll!$F52*((1+Payroll!$J52)^(ROUNDDOWN(DATEDIF(Payroll!$I52,H$2,"M")/Payroll!$K52,0))),0)) | I129: =IF(I$2=Payroll!$I52,Payroll!$F52,IF(I$2>Payroll!$I52,Payroll!$F52*((1+Payroll!$J52)^(ROUNDDOWN(DATEDIF(Payroll!$I52,I$2,"M")/Payroll!$K52,0))),0)) | J129: =IF(J$2=Payroll!$I52,Payroll!$F52,IF(J$2>Payroll!$I52,Payroll!$F52*((1+Payroll!$J52)^(ROUNDDOWN(DATEDIF(Payroll!$I52,J$2,"M")/Payroll!$K52,0))),0)) | K129: =IF(K$2=Payroll!$I52,Payroll!$F52,IF(K$2>Payroll!$I52,Payroll!$F52*((1+Payroll!$J52)^(ROUNDDOWN(DATEDIF(Payroll!$I52,K$2,"M")/Payroll!$K52,0))),0)) | L129: =IF(L$2=Payroll!$I52,Payroll!$F52,IF(L$2>Payroll!$I52,Payroll!$F52*((1+Payroll!$J52)^(ROUNDDOWN(DATEDIF(Payroll!$I52,L$2,"M")/Payroll!$K52,0))),0)) | ... CX129: =IF(CX$2=Payroll!$I52,Payroll!$F52,IF(CX$2>Payroll!$I52,Payroll!$F52*((1+Payroll!$J52)^(ROUNDDOWN(DATEDIF(Payroll!$I52,CX$2,"M")/Payroll!$K52,0))),0))
A130: =Payroll!A53 | E130: =IF(E$2=Payroll!$I53,Payroll!$F53,IF(E$2>Payroll!$I53,Payroll!$F53*((1+Payroll!$J53)^(ROUNDDOWN(DATEDIF(Payroll!$I53,E$2,"M")/Payroll!$K53,0))),0)) | F130: =IF(F$2=Payroll!$I53,Payroll!$F53,IF(F$2>Payroll!$I53,Payroll!$F53*((1+Payroll!$J53)^(ROUNDDOWN(DATEDIF(Payroll!$I53,F$2,"M")/Payroll!$K53,0))),0)) | G130: =IF(G$2=Payroll!$I53,Payroll!$F53,IF(G$2>Payroll!$I53,Payroll!$F53*((1+Payroll!$J53)^(ROUNDDOWN(DATEDIF(Payroll!$I53,G$2,"M")/Payroll!$K53,0))),0)) | H130: =IF(H$2=Payroll!$I53,Payroll!$F53,IF(H$2>Payroll!$I53,Payroll!$F53*((1+Payroll!$J53)^(ROUNDDOWN(DATEDIF(Payroll!$I53,H$2,"M")/Payroll!$K53,0))),0)) | I130: =IF(I$2=Payroll!$I53,Payroll!$F53,IF(I$2>Payroll!$I53,Payroll!$F53*((1+Payroll!$J53)^(ROUNDDOWN(DATEDIF(Payroll!$I53,I$2,"M")/Payroll!$K53,0))),0)) | J130: =IF(J$2=Payroll!$I53,Payroll!$F53,IF(J$2>Payroll!$I53,Payroll!$F53*((1+Payroll!$J53)^(ROUNDDOWN(DATEDIF(Payroll!$I53,J$2,"M")/Payroll!$K53,0))),0)) | K130: =IF(K$2=Payroll!$I53,Payroll!$F53,IF(K$2>Payroll!$I53,Payroll!$F53*((1+Payroll!$J53)^(ROUNDDOWN(DATEDIF(Payroll!$I53,K$2,"M")/Payroll!$K53,0))),0)) | L130: =IF(L$2=Payroll!$I53,Payroll!$F53,IF(L$2>Payroll!$I53,Payroll!$F53*((1+Payroll!$J53)^(ROUNDDOWN(DATEDIF(Payroll!$I53,L$2,"M")/Payroll!$K53,0))),0)) | ... CX130: =IF(CX$2=Payroll!$I53,Payroll!$F53,IF(CX$2>Payroll!$I53,Payroll!$F53*((1+Payroll!$J53)^(ROUNDDOWN(DATEDIF(Payroll!$I53,CX$2,"M")/Payroll!$K53,0))),0))
A131: =Payroll!A54 | E131: =IF(E$2=Payroll!$I54,Payroll!$F54,IF(E$2>Payroll!$I54,Payroll!$F54*((1+Payroll!$J54)^(ROUNDDOWN(DATEDIF(Payroll!$I54,E$2,"M")/Payroll!$K54,0))),0)) | F131: =IF(F$2=Payroll!$I54,Payroll!$F54,IF(F$2>Payroll!$I54,Payroll!$F54*((1+Payroll!$J54)^(ROUNDDOWN(DATEDIF(Payroll!$I54,F$2,"M")/Payroll!$K54,0))),0)) | G131: =IF(G$2=Payroll!$I54,Payroll!$F54,IF(G$2>Payroll!$I54,Payroll!$F54*((1+Payroll!$J54)^(ROUNDDOWN(DATEDIF(Payroll!$I54,G$2,"M")/Payroll!$K54,0))),0)) | H131: =IF(H$2=Payroll!$I54,Payroll!$F54,IF(H$2>Payroll!$I54,Payroll!$F54*((1+Payroll!$J54)^(ROUNDDOWN(DATEDIF(Payroll!$I54,H$2,"M")/Payroll!$K54,0))),0)) | I131: =IF(I$2=Payroll!$I54,Payroll!$F54,IF(I$2>Payroll!$I54,Payroll!$F54*((1+Payroll!$J54)^(ROUNDDOWN(DATEDIF(Payroll!$I54,I$2,"M")/Payroll!$K54,0))),0)) | J131: =IF(J$2=Payroll!$I54,Payroll!$F54,IF(J$2>Payroll!$I54,Payroll!$F54*((1+Payroll!$J54)^(ROUNDDOWN(DATEDIF(Payroll!$I54,J$2,"M")/Payroll!$K54,0))),0)) | K131: =IF(K$2=Payroll!$I54,Payroll!$F54,IF(K$2>Payroll!$I54,Payroll!$F54*((1+Payroll!$J54)^(ROUNDDOWN(DATEDIF(Payroll!$I54,K$2,"M")/Payroll!$K54,0))),0)) | L131: =IF(L$2=Payroll!$I54,Payroll!$F54,IF(L$2>Payroll!$I54,Payroll!$F54*((1+Payroll!$J54)^(ROUNDDOWN(DATEDIF(Payroll!$I54,L$2,"M")/Payroll!$K54,0))),0)) | ... CX131: =IF(CX$2=Payroll!$I54,Payroll!$F54,IF(CX$2>Payroll!$I54,Payroll!$F54*((1+Payroll!$J54)^(ROUNDDOWN(DATEDIF(Payroll!$I54,CX$2,"M")/Payroll!$K54,0))),0))
A132: =Payroll!A55 | E132: =IF(E$2=Payroll!$I55,Payroll!$F55,IF(E$2>Payroll!$I55,Payroll!$F55*((1+Payroll!$J55)^(ROUNDDOWN(DATEDIF(Payroll!$I55,E$2,"M")/Payroll!$K55,0))),0)) | F132: =IF(F$2=Payroll!$I55,Payroll!$F55,IF(F$2>Payroll!$I55,Payroll!$F55*((1+Payroll!$J55)^(ROUNDDOWN(DATEDIF(Payroll!$I55,F$2,"M")/Payroll!$K55,0))),0)) | G132: =IF(G$2=Payroll!$I55,Payroll!$F55,IF(G$2>Payroll!$I55,Payroll!$F55*((1+Payroll!$J55)^(ROUNDDOWN(DATEDIF(Payroll!$I55,G$2,"M")/Payroll!$K55,0))),0)) | H132: =IF(H$2=Payroll!$I55,Payroll!$F55,IF(H$2>Payroll!$I55,Payroll!$F55*((1+Payroll!$J55)^(ROUNDDOWN(DATEDIF(Payroll!$I55,H$2,"M")/Payroll!$K55,0))),0)) | I132: =IF(I$2=Payroll!$I55,Payroll!$F55,IF(I$2>Payroll!$I55,Payroll!$F55*((1+Payroll!$J55)^(ROUNDDOWN(DATEDIF(Payroll!$I55,I$2,"M")/Payroll!$K55,0))),0)) | J132: =IF(J$2=Payroll!$I55,Payroll!$F55,IF(J$2>Payroll!$I55,Payroll!$F55*((1+Payroll!$J55)^(ROUNDDOWN(DATEDIF(Payroll!$I55,J$2,"M")/Payroll!$K55,0))),0)) | K132: =IF(K$2=Payroll!$I55,Payroll!$F55,IF(K$2>Payroll!$I55,Payroll!$F55*((1+Payroll!$J55)^(ROUNDDOWN(DATEDIF(Payroll!$I55,K$2,"M")/Payroll!$K55,0))),0)) | L132: =IF(L$2=Payroll!$I55,Payroll!$F55,IF(L$2>Payroll!$I55,Payroll!$F55*((1+Payroll!$J55)^(ROUNDDOWN(DATEDIF(Payroll!$I55,L$2,"M")/Payroll!$K55,0))),0)) | ... CX132: =IF(CX$2=Payroll!$I55,Payroll!$F55,IF(CX$2>Payroll!$I55,Payroll!$F55*((1+Payroll!$J55)^(ROUNDDOWN(DATEDIF(Payroll!$I55,CX$2,"M")/Payroll!$K55,0))),0))
A133: =Payroll!A56 | E133: =IF(E$2=Payroll!$I56,Payroll!$F56,IF(E$2>Payroll!$I56,Payroll!$F56*((1+Payroll!$J56)^(ROUNDDOWN(DATEDIF(Payroll!$I56,E$2,"M")/Payroll!$K56,0))),0)) | F133: =IF(F$2=Payroll!$I56,Payroll!$F56,IF(F$2>Payroll!$I56,Payroll!$F56*((1+Payroll!$J56)^(ROUNDDOWN(DATEDIF(Payroll!$I56,F$2,"M")/Payroll!$K56,0))),0)) | G133: =IF(G$2=Payroll!$I56,Payroll!$F56,IF(G$2>Payroll!$I56,Payroll!$F56*((1+Payroll!$J56)^(ROUNDDOWN(DATEDIF(Payroll!$I56,G$2,"M")/Payroll!$K56,0))),0)) | H133: =IF(H$2=Payroll!$I56,Payroll!$F56,IF(H$2>Payroll!$I56,Payroll!$F56*((1+Payroll!$J56)^(ROUNDDOWN(DATEDIF(Payroll!$I56,H$2,"M")/Payroll!$K56,0))),0)) | I133: =IF(I$2=Payroll!$I56,Payroll!$F56,IF(I$2>Payroll!$I56,Payroll!$F56*((1+Payroll!$J56)^(ROUNDDOWN(DATEDIF(Payroll!$I56,I$2,"M")/Payroll!$K56,0))),0)) | J133: =IF(J$2=Payroll!$I56,Payroll!$F56,IF(J$2>Payroll!$I56,Payroll!$F56*((1+Payroll!$J56)^(ROUNDDOWN(DATEDIF(Payroll!$I56,J$2,"M")/Payroll!$K56,0))),0)) | K133: =IF(K$2=Payroll!$I56,Payroll!$F56,IF(K$2>Payroll!$I56,Payroll!$F56*((1+Payroll!$J56)^(ROUNDDOWN(DATEDIF(Payroll!$I56,K$2,"M")/Payroll!$K56,0))),0)) | L133: =IF(L$2=Payroll!$I56,Payroll!$F56,IF(L$2>Payroll!$I56,Payroll!$F56*((1+Payroll!$J56)^(ROUNDDOWN(DATEDIF(Payroll!$I56,L$2,"M")/Payroll!$K56,0))),0)) | ... CX133: =IF(CX$2=Payroll!$I56,Payroll!$F56,IF(CX$2>Payroll!$I56,Payroll!$F56*((1+Payroll!$J56)^(ROUNDDOWN(DATEDIF(Payroll!$I56,CX$2,"M")/Payroll!$K56,0))),0))
A134: =Payroll!A57
A135: =Payroll!A58
...

Sheet Unit economics
A1: =Settings!B4
A2: Month | C2: ='Monthly forecast'!D2 | D2: ='Monthly forecast'!E2 | E2: =EDATE(D2,1) | F2: =EDATE(E2,1) | G2: =EDATE(F2,1) | H2: =EDATE(G2,1) | I2: =EDATE(H2,1) | J2: =EDATE(I2,1) | K2: =EDATE(J2,1) | L2: =EDATE(K2,1) | ... CW2: =EDATE(CV2,1)
A4: ='Monthly forecast'!A15
A6: Subscription price per month | C6: =IF(C2>=Projections!$D$28,Projections!$B$28,0) | D6: =IF(D2>=Projections!$D$28,Projections!$B$28,0) | E6: =IF(E2>=Projections!$D$28,Projections!$B$28,0) | F6: =IF(F2>=Projections!$D$28,Projections!$B$28,0) | G6: =IF(G2>=Projections!$D$28,Projections!$B$28,0) | H6: =IF(H2>=Projections!$D$28,Projections!$B$28,0) | I6: =IF(I2>=Projections!$D$28,Projections!$B$28,0) | J6: =IF(J2>=Projections!$D$28,Projections!$B$28,0) | ... CW6: =IF(CW2>=Projections!$D$28,Projections!$B$28,0)
A7: ARPPU | C7: =C6 | D7: =D6 | E7: =E6 | F7: =F6 | G7: =G6 | H7: =H6 | I7: =I6 | J7: =J6 | ... CW7: =CW6
A9: Churn | C9: ='Monthly forecast'!D18 | D9: ='Monthly forecast'!E18 | E9: ='Monthly forecast'!F18 | F9: ='Monthly forecast'!G18 | G9: ='Monthly forecast'!H18 | H9: ='Monthly forecast'!I18 | I9: ='Monthly forecast'!J18 | J9: ='Monthly forecast'!K18 | ... CW9: ='Monthly forecast'!CX18
A10: LT (Ilifetime) | C10: =IFERROR(1/C9,0) | D10: =IFERROR(1/D9,0) | E10: =IFERROR(1/E9,0) | F10: =IFERROR(1/F9,0) | G10: =IFERROR(1/G9,0) | H10: =IFERROR(1/H9,0) | I10: =IFERROR(1/I9,0) | J10: =IFERROR(1/J9,0) | ... CW10: =IFERROR(1/CW9,0)
A12: LTV | C12: =C7*C10 | D12: =D7*D10 | E12: =E7*E10 | F12: =F7*F10 | G12: =G7*G10 | H12: =H7*H10 | I12: =I7*I10 | J12: =J7*J10 | ... CW12: =CW7*CW10
A13: LTV 3 month | C13: =C7*3 | D13: =D7*3 | E13: =E7*3 | F13: =F7*3 | G13: =G7*3 | H13: =H7*3 | I13: =I7*3 | J13: =J7*3 | ... CW13: =CW7*3
A14: LTV 6 month | C14: =C7*6 | D14: =D7*6 | E14: =E7*6 | F14: =F7*6 | G14: =G7*6 | H14: =H7*6 | I14: =I7*6 | J14: =J7*6 | ... CW14: =CW7*6
A15: LTV 12 month | C15: =C7*12 | D15: =D7*12 | E15: =E7*12 | F15: =F7*12 | G15: =G7*12 | H15: =H7*12 | I15: =I7*12 | J15: =J7*12 | ... CW15: =CW7*12
A17: pCAC (CAC paid channels) | D17: ='Monthly forecast'!E10/Projections!$B$36 | E17: ='Monthly forecast'!F10/Projections!$B$36 | F17: ='Monthly forecast'!G10/Projections!$B$36 | G17: ='Monthly forecast'!H10/Projections!$B$36 | H17: ='Monthly forecast'!I10/Projections!$B$36 | I17: ='Monthly forecast'!J10/Projections!$B$36 | J17: ='Monthly forecast'!K10/Projections!$B$36 | K17: ='Monthly forecast'!L10/Projections!$B$36 | ... CW17: ='Monthly forecast'!CX10/Projections!$B$36
A18: LTV/CAC | D18: =D12/D$17 | E18: =E12/E$17 | F18: =F12/F$17 | G18: =G12/G$17 | H18: =H12/H$17 | I18: =I12/I$17 | J18: =J12/J$17 | K18: =K12/K$17 | ... CW18: =CW12/CW$17
A19: LTV 3 month/CAC | D19: =D13/D$17 | E19: =E13/E$17 | F19: =F13/F$17 | G19: =G13/G$17 | H19: =H13/H$17 | I19: =I13/I$17 | J19: =J13/J$17 | K19: =K13/K$17 | ... CW19: =CW13/CW$17
A20: LTV 6 month/CAC | D20: =D14/D$17 | E20: =E14/E$17 | F20: =F14/F$17 | G20: =G14/G$17 | H20: =H14/H$17 | I20: =I14/I$17 | J20: =J14/J$17 | K20: =K14/K$17 | ... CW20: =CW14/CW$17
A21: LTV 12 month/CAC | D21: =D15/D$17 | E21: =E15/E$17 | F21: =F15/F$17 | G21: =G15/G$17 | H21: =H15/H$17 | I21: =I15/I$17 | J21: =J15/J$17 | K21: =K15/K$17 | ... CW21: =CW15/CW$17
A24: ='Monthly forecast'!A24
A26: Subscription price per month | C26: =IF(C2>=Projections!$D$28,Projections!$B$28,0) | D26: =IF(D2>=Projections!$D$28,Projections!$B$28,0) | E26: =IF(E2>=Projections!$D$28,Projections!$B$28,0) | F26: =IF(F2>=Projections!$D$28,Projections!$B$28,0) | G26: =IF(G2>=Projections!$D$28,Projections!$B$28,0) | H26: =IF(H2>=Projections!$D$28,Projections!$B$28,0) | I26: =IF(I2>=Projections!$D$28,Projections!$B$28,0) | J26: =IF(J2>=Projections!$D$28,Projections!$B$28,0) | ... CW26: =IF(CW2>=Projections!$D$28,Projections!$B$28,0)
A27: ARPPU | C27: =C26 | D27: =D26 | E27: =E26 | F27: =F26 | G27: =G26 | H27: =H26 | I27: =I26 | J27: =J26 | ... CW27: =CW26
A29: Churn | C29: ='Monthly forecast'!D38 | D29: ='Monthly forecast'!E29 | E29: ='Monthly forecast'!F29 | F29: ='Monthly forecast'!G29 | G29: ='Monthly forecast'!H29 | H29: ='Monthly forecast'!I29 | I29: ='Monthly forecast'!J29 | J29: ='Monthly forecast'!K29 | K29: ='Monthly forecast'!L29 | ... CW29: ='Monthly forecast'!CX29
A30: LT (Ilifetime) | C30: =IFERROR(1/C29,0) | D30: =IFERROR(1/D29,0) | E30: =IFERROR(1/E29,0) | F30: =IFERROR(1/F29,0) | G30: =IFERROR(1/G29,0) | H30: =IFERROR(1/H29,0) | I30: =IFERROR(1/I29,0) | J30: =IFERROR(1/J29,0) | ... CW30: =IFERROR(1/CW29,0)
A32: LTV | C32: =C27*C30 | D32: =D27*D30 | E32: =E27*E30 | F32: =F27*F30 | G32: =G27*G30 | H32: =H27*H30 | I32: =I27*I30 | J32: =J27*J30 | ... CW32: =CW27*CW30
A33: LTV 3 month | C33: =C27*3 | D33: =D27*3 | E33: =E27*3 | F33: =F27*3 | G33: =G27*3 | H33: =H27*3 | I33: =I27*3 | J33: =J27*3 | ... CW33: =CW27*3
A34: LTV 6 month | C34: =C27*6 | D34: =D27*6 | E34: =E27*6 | F34: =F27*6 | G34: =G27*6 | H34: =H27*6 | I34: =I27*6 | J34: =J27*6 | ... CW34: =CW27*6
A35: LTV 12 month | C35: =C27*12 | D35: =D27*12 | E35: =E27*12 | F35: =F27*12 | G35: =G27*12 | H35: =H27*12 | I35: =I27*12 | J35: =J27*12 | ... CW35: =CW27*12
A37: Marketing Costs | D37: ='Monthly forecast'!E10/Projections!$B$45/Projections!$B$50 | E37: ='Monthly forecast'!F10/Projections!$B$45/Projections!$B$50 | F37: ='Monthly forecast'!G10/Projections!$B$45/Projections!$B$50 | G37: ='Monthly forecast'!H10/Projections!$B$45/Projections!$B$50 | H37: ='Monthly forecast'!I10/Projections!$B$45/Projections!$B$50 | I37: ='Monthly forecast'!J10/Projections!$B$45/Projections!$B$50 | J37: ='Monthly forecast'!K10/Projections!$B$45/Projections!$B$50 | K37: ='Monthly forecast'!L10/Projections!$B$45/Projections!$B$50 | ... CW37: ='Monthly forecast'!CX10/Projections!$B$45/Projections!$B$50
A38: Cost of Inbound Sales Managers team | D38: ='Monthly forecast'!E83/(Projections!$B$49*Projections!$B$50) | E38: ='Monthly forecast'!F83/(Projections!$B$49*Projections!$B$50) | F38: ='Monthly forecast'!G83/(Projections!$B$49*Projections!$B$50) | G38: ='Monthly forecast'!H83/(Projections!$B$49*Projections!$B$50) | H38: ='Monthly forecast'!I83/(Projections!$B$49*Projections!$B$50) | I38: ='Monthly forecast'!J83/(Projections!$B$49*Projections!$B$50) | J38: ='Monthly forecast'!K83/(Projections!$B$49*Projections!$B$50) | K38: ='Monthly forecast'!L83/(Projections!$B$49*Projections!$B$50) | ... CW38: ='Monthly forecast'!CX83/(Projections!$B$49*Projections!$B$50)
A39: CAC | D39: =D37+D38 | E39: =E37+E38 | F39: =F37+F38 | G39: =G37+G38 | H39: =H37+H38 | I39: =I37+I38 | J39: =J37+J38 | K39: =K37+K38 | ... CW39: =CW37+CW38
A41: LTV/CAC | D41: =D32/D39 | E41: =E32/E39 | F41: =F32/F39 | G41: =G32/G39 | H41: =H32/H39 | I41: =I32/I39 | J41: =J32/J39 | K41: =K32/K39 | ... CV41: =CV32/CV39
A42: LTV 3 month/CAC | D42: =D33/D$39 | E42: =E33/E$39 | F42: =F33/F$39 | G42: =G33/G$39 | H42: =H33/H$39 | I42: =I33/I$39 | J42: =J33/J$39 | K42: =K33/K$39 | ... CW42: =CW33/CW$39
A43: LTV 6 month/CAC | D43: =D34/D$39 | E43: =E34/E$39 | F43: =F34/F$39 | G43: =G34/G$39 | H43: =H34/H$39 | I43: =I34/I$39 | J43: =J34/J$39 | K43: =K34/K$39 | ... CW43: =CW34/CW$39
A44: LTV 12 month/CAC | D44: =D35/D$39 | E44: =E35/E$39 | F44: =F35/F$39 | G44: =G35/G$39 | H44: =H35/H$39 | I44: =I35/I$39 | J44: =J35/J$39 | K44: =K35/K$39 | ... CW44: =CW35/CW$39
A46: ='Monthly forecast'!A35
A48: Subscription price per month | C48: =IF(C2>=Projections!$D$28,Projections!$B$28,0) | D48: =IF(D2>=Projections!$D$28,Projections!$B$28,0) | E48: =IF(E2>=Projections!$D$28,Projections!$B$28,0) | F48: =IF(F2>=Projections!$D$28,Projections!$B$28,0) | G48: =IF(G2>=Projections!$D$28,Projections!$B$28,0) | H48: =IF(H2>=Projections!$D$28,Projections!$B$28,0) | I48: =IF(I2>=Projections!$D$28,Projections!$B$28,0) | J48: =IF(J2>=Projections!$D$28,Projections!$B$28,0) | ... CW48: =IF(CW2>=Projections!$D$28,Projections!$B$28,0)
A49: ARPPU | C49: =C48 | D49: =D48 | E49: =E48 | F49: =F48 | G49: =G48 | H49: =H48 | I49: =I48 | J49: =J48 | ... CW49: =CW48
A51: Churn | C51: ='Monthly forecast'!D60 | D51: ='Monthly forecast'!E38 | E51: ='Monthly forecast'!F38 | F51: ='Monthly forecast'!G38 | G51: ='Monthly forecast'!H38 | H51: ='Monthly forecast'!I38 | I51: ='Monthly forecast'!J38 | J51: ='Monthly forecast'!K38 | K51: ='Monthly forecast'!L38 | ... CW51: ='Monthly forecast'!CX38
A52: LT (Ilifetime) | C52: =IFERROR(1/C51,0) | D52: =IFERROR(1/D51,0) | E52: =IFERROR(1/E51,0) | F52: =IFERROR(1/F51,0) | G52: =IFERROR(1/G51,0) | H52: =IFERROR(1/H51,0) | I52: =IFERROR(1/I51,0) | J52: =IFERROR(1/J51,0) | ... CW52: =IFERROR(1/CW51,0)
A54: LTV | C54: =C49*C52 | D54: =D49*D52 | E54: =E49*E52 | F54: =F49*F52 | G54: =G49*G52 | H54: =H49*H52 | I54: =I49*I52 | J54: =J49*J52 | ... CW54: =CW49*CW52
A55: LTV 3 month | C55: =C49*3 | D55: =D49*3 | E55: =E49*3 | F55: =F49*3 | G55: =G49*3 | H55: =H49*3 | I55: =I49*3 | J55: =J49*3 | ... CW55: =CW49*3
A56: LTV 6 month | C56: =C49*6 | D56: =D49*6 | E56: =E49*6 | F56: =F49*6 | G56: =G49*6 | H56: =H49*6 | I56: =I49*6 | J56: =J49*6 | ... CW56: =CW49*6
A57: LTV 12 month | C57: =C49*12 | D57: =D49*12 | E57: =E49*12 | F57: =F49*12 | G57: =G49*12 | H57: =H49*12 | I57: =I49*12 | J57: =J49*12 | ... CW57: =CW49*12
A59: CAC - Cost of Outbound Sales Managers | D59: 90 | E59: 90 | F59: 90 | G59: 90 | H59: 90 | I59: 90 | J59: 120 | K59: 120 | L59: 120 | M59: 120 | N59: 120 | O59: 120 | P59: 150 | Q59: 150 | R59: 150 | S59: 150 | T59: 150 | U59: 150 | V59: 150 | W59: 150 | X59: 150 | Y59: 150 | Z59: 150 | AA59: 150 | AB59: 150 | AC59: 150 | AD59: 150 | AE59: 150 | AF59: 150 | AG59: 150 | AH59: 150 | AI59: 150 | AJ59: 150 | AK59: 150 | AL59: 150 | AM59: 150 | AN59: 150 | AO59: 150 | AP59: 150 | AQ59: 150 | AR59: 150 | AS59: 150 | AT59: 150 | AU59: 150 | AV59: 150 | AW59: 150 | AX59: 150 | AY59: 150 | AZ59: 150 | BA59: 150 | BB59: 150 | BC59: 150 | BD59: 150 | BE59: 150 | BF59: 150 | BG59: 150 | BH59: 150 | BI59: 150 | BJ59: 150 | BK59: 150 | BL59: 150 | BM59: 150 | BN59: 150 | BO59: 150 | BP59: 150 | BQ59: 150 | BR59: 150 | BS59: 150 | BT59: 150 | BU59: 150 | BV59: 150 | BW59: 150 | BX59: 150 | BY59: 150 | BZ59: 150 | CA59: 150 | CB59: 150 | CC59: 150 | CD59: 150 | CE59: 150 | CF59: 150 | CG59: 150 | CH59: 150 | CI59: 150 | CJ59: 150 | CK59: 150 | CL59: 150 | CM59: 150 | CN59: 150 | CO59: 150 | CP59: 150 | CQ59: 150 | CR59: 150 | CS59: 150 | CT59: 150 | CU59: 150 | CV59: 150 | CW59: 150
A60: LTV/CAC | D60: =IFERROR(D54/D$59, "-") | E60: =IFERROR(E54/E$59, "-") | F60: =IFERROR(F54/F$59, "-") | G60: =IFERROR(G54/G$59, "-") | H60: =IFERROR(H54/H$59, "-") | I60: =IFERROR(I54/I$59, "-") | J60: =IFERROR(J54/J$59, "-") | K60: =IFERROR(K54/K$59, "-") | ... CW60: =IFERROR(CW54/CW$59, "-")
A61: LTV 3 month/CAC | D61: =IFERROR(D55/D$59, "-") | E61: =IFERROR(E55/E$59, "-") | F61: =IFERROR(F55/F$59, "-") | G61: =IFERROR(G55/G$59, "-") | H61: =IFERROR(H55/H$59, "-") | I61: =IFERROR(I55/I$59, "-") | J61: =IFERROR(J55/J$59, "-") | K61: =IFERROR(K55/K$59, "-") | ... CW61: =IFERROR(CW55/CW$59, "-")
A62: LTV 6 month/CAC | D62: =IFERROR(D56/D$59, "-") | E62: =IFERROR(E56/E$59, "-") | F62: =IFERROR(F56/F$59, "-") | G62: =IFERROR(G56/G$59, "-") | H62: =IFERROR(H56/H$59, "-") | I62: =IFERROR(I56/I$59, "-") | J62: =IFERROR(J56/J$59, "-") | K62: =IFERROR(K56/K$59, "-") | ... CW62: =IFERROR(CW56/CW$59, "-")
A63: LTV 12 month/CAC | D63: =IFERROR(D57/D$59, "-") | E63: =IFERROR(E57/E$59, "-") | F63: =IFERROR(F57/F$59, "-") | G63: =IFERROR(G57/G$59, "-") | H63: =IFERROR(H57/H$59, "-") | I63: =IFERROR(I57/I$59, "-") | J63: =IFERROR(J57/J$59, "-") | K63: =IFERROR(K57/K$59, "-") | ... CW63: =IFERROR(CW57/CW$59, "-")

Sheet P&L | Cash Flow | Balance
A1: =Settings!B4
A2: Month | C2: =EDATE(D2,-1) | D2: =Projections!$B$4 | E2: =EDATE(D2,1) | F2: =EDATE(E2,1) | G2: =EDATE(F2,1) | H2: =EDATE(G2,1) | I2: =EDATE(H2,1) | J2: =EDATE(I2,1) | K2: =EDATE(J2,1) | L2: =EDATE(K2,1) | ... CW2: =EDATE(CV2,1)
A4: P&L
A6: REVENUE | C6: =C7 | D6: =SUM(D7:D9) | E6: =SUM(E7:E9) | F6: =SUM(F7:F9) | G6: =SUM(G7:G9) | H6: =SUM(H7:H9) | I6: =SUM(I7:I9) | J6: =SUM(J7:J9) | K6: =SUM(K7:K9) | ... CW6: =SUM(CW7:CW9)
A7: ='Monthly forecast'!A15 | C7: ='Monthly forecast'!D22 | D7: ='Monthly forecast'!E22 | E7: ='Monthly forecast'!F22 | F7: ='Monthly forecast'!G22 | G7: ='Monthly forecast'!H22 | H7: ='Monthly forecast'!I22 | I7: ='Monthly forecast'!J22 | J7: ='Monthly forecast'!K22 | ... CW7: ='Monthly forecast'!CX22
A8: ='Monthly forecast'!A24 | C8: ='Monthly forecast'!D33 | D8: ='Monthly forecast'!E33 | E8: ='Monthly forecast'!F33 | F8: ='Monthly forecast'!G33 | G8: ='Monthly forecast'!H33 | H8: ='Monthly forecast'!I33 | I8: ='Monthly forecast'!J33 | J8: ='Monthly forecast'!K33 | ... CW8: ='Monthly forecast'!CX33
A9: ='Monthly forecast'!A35 | C9: ='Monthly forecast'!D42 | D9: ='Monthly forecast'!E42 | E9: ='Monthly forecast'!F42 | F9: ='Monthly forecast'!G42 | G9: ='Monthly forecast'!H42 | H9: ='Monthly forecast'!I42 | I9: ='Monthly forecast'!J42 | J9: ='Monthly forecast'!K42 | ... CW9: ='Monthly forecast'!CX42
A11: COGS | C11: ='Monthly forecast'!D47 | D11: ='Monthly forecast'!E47 | E11: ='Monthly forecast'!F47 | F11: ='Monthly forecast'!G47 | G11: ='Monthly forecast'!H47 | H11: ='Monthly forecast'!I47 | I11: ='Monthly forecast'!J47 | J11: ='Monthly forecast'!K47 | ... CW11: ='Monthly forecast'!CX47
A12: Gross profit | C12: =C6-C11 | D12: =D6-D11 | E12: =E6-E11 | F12: =F6-F11 | G12: =G6-G11 | H12: =H6-H11 | I12: =I6-I11 | J12: =J6-J11 | ... CW12: =CW6-CW11
A13: Gross margin | C13: =iferror(C12/#REF!,0) | D13: =iferror(D12/#REF!,0) | E13: =iferror(E12/#REF!,0) | F13: =iferror(F12/#REF!,0) | G13: =iferror(G12/#REF!,0) | H13: =iferror(H12/#REF!,0) | I13: =iferror(I12/#REF!,0) | J13: =iferror(J12/#REF!,0) | ... CW13: =iferror(CW12/#REF!,0)
A15: SG&A | C15: ='Monthly forecast'!D53 | D15: ='Monthly forecast'!E53 | E15: ='Monthly forecast'!F53 | F15: ='Monthly forecast'!G53 | G15: ='Monthly forecast'!H53 | H15: ='Monthly forecast'!I53 | I15: ='Monthly forecast'!J53 | J15: ='Monthly forecast'!K53 | ... CW15: ='Monthly forecast'!CX53
A17: EBITDA | C17: =C12-C15 | D17: =D12-D15 | E17: =E12-E15 | F17: =F12-F15 | G17: =G12-G15 | H17: =H12-H15 | I17: =I12-I15 | J17: =J12-J15 | ... CW17: =CW12-CW15
A18: EBITDA, % | C18: =iferror(C17/#REF!,0) | D18: =iferror(D17/#REF!,0) | E18: =iferror(E17/#REF!,0) | F18: =iferror(F17/#REF!,0) | G18: =iferror(G17/#REF!,0) | H18: =iferror(H17/#REF!,0) | I18: =iferror(I17/#REF!,0) | J18: =iferror(J17/#REF!,0) | ... CW18: =iferror(CW17/#REF!,0)
A20: Depreciation | C20: ='Monthly forecast'!D169 | D20: ='Monthly forecast'!E169 | E20: ='Monthly forecast'!F169 | F20: ='Monthly forecast'!G169 | G20: ='Monthly forecast'!H169 | H20: ='Monthly forecast'!I169 | I20: ='Monthly forecast'!J169 | J20: ='Monthly forecast'!K169 | ... CW20: ='Monthly forecast'!CX169
A21: Interest
A23: Tax base | C23: =C17-C20-C21 | D23: =D17-D20-D21 | E23: =E17-E20-E21 | F23: =F17-F20-F21 | G23: =G17-G20-G21 | H23: =H17-H20-H21 | I23: =I17-I20-I21 | J23: =J17-J20-J21 | ... CW23: =CW17-CW20-CW21
A25: Tax fee, % | C25: =Settings!$B$7 | D25: =Settings!$B$7 | E25: =Settings!$B$7 | F25: =Settings!$B$7 | G25: =Settings!$B$7 | H25: =Settings!$B$7 | I25: =Settings!$B$7 | J25: =Settings!$B$7 | ... CW25: =Settings!$B$7
A26: Taxes | C26: =IF(C23>0,C23*C25,0) | D26: =IF(D23>0,D23*D25,0) | E26: =IF(E23>0,E23*E25,0) | F26: =IF(F23>0,F23*F25,0) | G26: =IF(G23>0,G23*G25,0) | H26: =IF(H23>0,H23*H25,0) | I26: =IF(I23>0,I23*I25,0) | J26: =IF(J23>0,J23*J25,0) | ... CW26: =IF(CW23>0,CW23*CW25,0)
A28: Net income | C28: =C17-C20-C21-C26 | D28: =D17-D20-D21-D26 | E28: =E17-E20-E21-E26 | F28: =F17-F20-F21-F26 | G28: =G17-G20-G21-G26 | H28: =H17-H20-H21-H26 | I28: =I17-I20-I21-I26 | J28: =J17-J20-J21-J26 | ... CW28: =CW17-CW20-CW21-CW26
A29: Net margin | C29: =IFERROR(C28/#REF!,0) | D29: =IFERROR(D28/#REF!,0) | E29: =IFERROR(E28/#REF!,0) | F29: =IFERROR(F28/#REF!,0) | G29: =IFERROR(G28/#REF!,0) | H29: =IFERROR(H28/#REF!,0) | I29: =IFERROR(I28/#REF!,0) | J29: =IFERROR(J28/#REF!,0) | ... CW29: =IFERROR(CW28/#REF!,0)
A32: CASH FLOW
A34: Cash at the beginning of month | C34: =Settings!$B$10 | D34: =C39 | E34: =D39 | F34: =E39 | G34: =F39 | H34: =G39 | I34: =H39 | J34: =I39 | K34: =J39 | ... CW34: =CV39
A35: Fundraising
A36: Cash flow from Operations | C36: =C28+C20 | D36: =D28+D20 | E36: =E28+E20 | F36: =F28+F20 | G36: =G28+G20 | H36: =H28+H20 | I36: =I28+I20 | J36: =J28+J20 | ... CW36: =CW28+CW20
A37: Cash flow from Investing | C37: =-'Monthly forecast'!D160 | D37: =-'Monthly forecast'!E160 | E37: =-'Monthly forecast'!F160 | F37: =-'Monthly forecast'!G160 | G37: =-'Monthly forecast'!H160 | H37: =-'Monthly forecast'!I160 | I37: =-'Monthly forecast'!J160 | J37: =-'Monthly forecast'!K160 | ... CW37: =-'Monthly forecast'!CX160
A38: Cash flow from Financing
A39: Cash at the end of month | C39: =C34+C35+C36+C37+C38 | D39: =D34+D35+D36+D37+D38 | E39: =E34+E35+E36+E37+E38 | F39: =F34+F35+F36+F37+F38 | G39: =G34+G35+G36+G37+G38 | H39: =H34+H35+H36+H37+H38 | I39: =I34+I35+I36+I37+I38 | J39: =J34+J35+J36+J37+J38 | ... CW39: =CW34+CW35+CW36+CW37+CW38
A43: BALANCE SHEET
A45: ASSETS
A46: Cash | C46: =C39 | D46: =D39 | E46: =E39 | F46: =F39 | G46: =G39 | H46: =H39 | I46: =I39 | J46: =J39 | ... CW46: =CW39
A47: Accounts receivable
A48: Inventory
A49: Property & Equipment | C49: =C37-C20 | D49: =C49-D37-D20 | E49: =D49-E37-E20 | F49: =E49-F37-F20 | G49: =F49-G37-G20 | H49: =G49-H37-H20 | I49: =H49-I37-I20 | J49: =I49-J37-J20 | K49: =J49-K37-K20 | ... CW49: =CV49-CW37-CW20
A50: Total assets | C50: =ROUND(SUM(C46:C49),0) | D50: =ROUND(SUM(D46:D49),0) | E50: =ROUND(SUM(E46:E49),0) | F50: =ROUND(SUM(F46:F49),0) | G50: =ROUND(SUM(G46:G49),0) | H50: =ROUND(SUM(H46:H49),0) | I50: =ROUND(SUM(I46:I49),0) | J50: =ROUND(SUM(J46:J49),0) | ... CW50: =ROUND(SUM(CW46:CW49),0)
A53: LIABILITIES
A54: Accounts payable
A55: Debt | C55: =C35 | D55: =C55 | E55: =D55 | F55: =E55 | G55: =F55 | H55: =G55 | I55: =H55 | J55: =I55 | K55: =J55 | ... CW55: =CV55
A56: Total liabilities | C56: =SUM(C54:C55) | D56: =SUM(D54:D55) | E56: =SUM(E54:E55) | F56: =SUM(F54:F55) | G56: =SUM(G54:G55) | H56: =SUM(H54:H55) | I56: =SUM(I54:I55) | J56: =SUM(J54:J55) | ... CW56: =SUM(CW54:CW55)
A58: SHAREHOLDER'S EQUITY
A59: Equity capital | C59: =Settings!$B$10 | D59: =C59 | E59: =D59 | F59: =E59 | G59: =F59 | H59: =G59 | I59: =H59 | J59: =I59 | K59: =J59 | ... CW59: =CV59
A60: Retained earnings | C60: =C28 | D60: =C60+D28 | E60: =D60+E28 | F60: =E60+F28 | G60: =F60+G28 | H60: =G60+H28 | I60: =H60+I28 | J60: =I60+J28 | K60: =J60+K28 | ... CW60: =CV60+CW28
A61: Shareholder's equity | C61: =SUM(C59:C60) | D61: =SUM(D59:D60) | E61: =SUM(E59:E60) | F61: =SUM(F59:F60) | G61: =SUM(G59:G60) | H61: =SUM(H59:H60) | I61: =SUM(I59:I60) | J61: =SUM(J59:J60) | ... CW61: =SUM(CW59:CW60)
A62: Total liabilities & Shareholder's equity | C62: =ROUND(C56+C61,0) | D62: =ROUND(D56+D61,0) | E62: =ROUND(E56+E61,0) | F62: =ROUND(F56+F61,0) | G62: =ROUND(G56+G61,0) | H62: =ROUND(H56+H61,0) | I62: =ROUND(I56+I61,0) | J62: =ROUND(J56+J61,0) | ... CW62: =ROUND(CW56+CW61,0)
A64: Balance sheet check | C64: =C62-C50 | D64: =D62-D50 | E64: =E62-E50 | F64: =F62-F50 | G64: =G62-G50 | H64: =H62-H50 | I64: =I62-I50 | J64: =J62-J50 | ... CW64: =CW62-CW50

Sheet Cap Table
B1: =Settings!B4
B3: Foundation | G3: Round 1 | L3: Round 2 | Q3: Round 3
B4: Date | C4: =Roadmap!C7 | G4: Date | H4: 45444 | L4: Date | M4: 45809 | Q4: Date | R4: 46174
B6: Company Valuation | G6: Company Valuation | L6: Company Valuation | Q6: Company Valuation
C7: Value | D7: Share Price | E7: Number of Shares | H7: Value | I7: Share Price | J7: Number of Shares | M7: Value | N7: Share Price | O7: Number of Shares | R7: Value | S7: Share Price | T7: Number of Shares
B8: Valuation | C8: 0 | D8: =C8/E8 | E8: 1000000 | G8: Valuation | H8: 1000000 | I8: =H8/J8 | J8: 1000000 | L8: Valuation | M8: 5000000 | N8: =M8/O8 | O8: =J11 | Q8: Valuation | R8: 10000000 | S8: =R8/T8 | T8: =O11
G9: New Capital Raised | H9: =SUM(H20:H23) | I9: =I8 | J9: =H9/I8 | L9: New Capital Raised | M9: =SUM(M15:M27) | N9: =N8 | O9: =M9/N8 | Q9: New Capital Raised | R9: =SUM(R15:R29) | S9: =S8 | T9: =R9/S8
G10: Post-money Valuation | H10: =H8+H9 | L10: Post-money Valuation | M10: =M8+M9 | Q10: Post-money Valuation | R10: =R8+R9
B11: Total | E11: =E8+E9 | G11: Total | J11: =J8+J9 | L11: Total | O11: =O8+O9 | Q11: Total | T11: =T8+T9
B13: Company Ownership Capitalization Table | G13: Company Ownership Capitalization Table | L13: Company Ownership Capitalization Table | Q13: Company Ownership Capitalization Table
C14: Capital | D14: Number of Shares | E14: % of Ownership | H14: Capital Raised in this Round | I14: Number of Shares | J14: % of Ownership | M14: Capital Raised in this Round | N14: Number of Shares | O14: % of Ownership | R14: Capital Raised in this Round | S14: Number of Shares | T14: % of Ownership
B15: Founder 1 | C15: 0 | D15: =$E$8*E15 | E15: 0.35 | G15: Founder 1 | H15: 0 | I15: =D15 | J15: =I15/$J$11 | L15: Founder 1 | M15: 0 | N15: =IF(M15>0,I15+(M15/$N$9),I15) | O15: =N15/$O$11 | Q15: Founder 1 | R15: 0 | S15: =IF(R15>0,N15+(R15/$S$9),N15) | T15: =S15/$T$11
B16: Founder 2 | C16: 0 | D16: =$E$8*E16 | E16: 0.35 | G16: Founder 2 | H16: 0 | I16: =D16 | J16: =I16/$J$11 | L16: Founder 2 | M16: 0 | N16: =IF(M16>0,I16+(M16/$N$9),I16) | O16: =N16/$O$11 | Q16: Founder 2 | R16: 0 | S16: =IF(R16>0,N16+(R16/$S$9),N16) | T16: =S16/$T$11
B17: Founder 3 | C17: 0 | D17: =$E$8*E17 | E17: 0.24 | G17: Founder 3 | H17: 0 | I17: =D17 | J17: =I17/$J$11 | L17: Founder 3 | M17: 0 | N17: =IF(M17>0,I17+(M17/$N$9),I17) | O17: =N17/$O$11 | Q17: Founder 3 | R17: 0 | S17: =IF(R17>0,N17+(R17/$S$9),N17) | T17: =S17/$T$11
B18: Key Employees | C18: 0 | D18: =$E$8*E18 | E18: 0.05 | G18: Key Employees | H18: 0 | I18: =D18 | J18: =I18/$J$11 | L18: Key Employees | M18: 0 | N18: =IF(M18>0,I18+(M18/$N$9),I18) | O18: =N18/$O$11 | Q18: Key Employees | R18: 0 | S18: =IF(R18>0,N18+(R18/$S$9),N18) | T18: =S18/$T$11
B19: Advisors | C19: 0 | D19: =$E$8*E19 | E19: 0.01 | G19: Advisors | H19: 0 | I19: =D19 | J19: =I19/$J$11 | L19: Advisors | M19: 0 | N19: =IF(M19>0,I19+(M19/$N$9),I19) | O19: =N19/$O$11 | Q19: Advisors | R19: 0 | S19: =IF(R19>0,N19+(R19/$S$9),N19) | T19: =S19/$T$11
G20: Investor 1 | H20: 500000 | I20: =H20/$I$9 | J20: =I20/$J$11 | L20: Investor 1 | M20: 100000 | N20: =IF(M20>0,I20+(M20/$N$9),I20) | O20: =N20/$O$11 | Q20: Investor 1 | R20: 0 | S20: =IF(R20>0,N20+(R20/$S$9),N20) | T20: =S20/$T$11
G21: Investor 2 | H21: 300000 | I21: =H21/$I$9 | J21: =I21/$J$11 | L21: Investor 2 | M21: 0 | N21: =IF(M21>0,I21+(M21/$N$9),I21) | O21: =N21/$O$11 | Q21: Investor 2 | R21: 500000 | S21: =IF(R21>0,N21+(R21/$S$9),N21) | T21: =S21/$T$11
G22: Investor 3 | H22: 100000 | I22: =H22/$I$9 | J22: =I22/$J$11 | L22: Investor 3 | M22: 200000 | N22: =IF(M22>0,I22+(M22/$N$9),I22) | O22: =N22/$O$11 | Q22: Investor 3 | R22: 0 | S22: =IF(R22>0,N22+(R22/$S$9),N22) | T22: =S22/$T$11
G23: Investor 4 | H23: 100000 | I23: =H23/$I$9 | J23: =I23/$J$11 | L23: Investor 4 | M23: 0 | N23: =IF(M23>0,I23+(M23/$N$9),I23) | O23: =N23/$O$11 | Q23: Investor 4 | R23: 0 | S23: =IF(R23>0,N23+(R23/$S$9),N23) | T23: =S23/$T$11
I24: =SUM(I15:I23) | L24: Investor 5 | M24: 600000 | N24: =M24/$N$9 | O24: =N24/$O$11 | Q24: Investor 5 | R24: 0 | S24: =IF(R24>0,N24+(R24/$S$9),N24) | T24: =S24/$T$11
L25: Investor 6 | M25: 500000 | N25: =M25/$N$9 | O25: =N25/$O$11 | Q25: Investor 6 | R25: 0 | S25: =IF(R25>0,N25+(R25/$S$9),N25) | T25: =S25/$T$11
L26: Investor 7 | M26: 300000 | N26: =M26/$N$9 | O26: =N26/$O$11 | Q26: Investor 7 | R26: 0 | S26: =IF(R26>0,N26+(R26/$S$9),N26) | T26: =S26/$T$11
L27: Investor 8 | M27: 600000 | N27: =M27/$N$9 | O27: =N27/$O$11 | Q27: Investor 8 | R27: 0 | S27: =IF(R27>0,N27+(R27/$S$9),N27) | T27: =S27/$T$11
N28: =SUM(N15:N27) | Q28: Investor 9 | R28: 1000000 | S28: =R28/$S$9 | T28: =S28/$T$11
Q29: Investor 10 | R29: 500000 | S29: =R29/$S$9 | T29: =S29/$T$11
S30: =SUM(S15:S29)

Sheet Dividends
B1: =Settings!B4
C3: ='For Pitchdeck'!C2 | E3: ='For Pitchdeck'!D2 | G3: ='For Pitchdeck'!E2 | I3: ='For Pitchdeck'!F2 | K3: ='For Pitchdeck'!G2
A4: 1 | B4: Net Income | C4: ='For Pitchdeck'!C8 | E4: ='For Pitchdeck'!D8 | G4: ='For Pitchdeck'!E8 | I4: ='For Pitchdeck'!F8 | K4: ='For Pitchdeck'!G8
C6: =C3 | E6: =E3 | G6: =G3 | I6: =I3 | K6: =K3
C7: Share | D7: Dividends | E7: Share | F7: Dividends | G7: Share | H7: Dividends | I7: Share | J7: Dividends | K7: Share | L7: Dividends
B8: ='Cap Table'!Q15 | C8: =IFS($C$6<YEAR('Cap Table'!$C$4),0,and($C$6=YEAR('Cap Table'!$C$4),YEAR('Cap Table'!$H$4)-YEAR('Cap Table'!$C$4)>0),'Cap Table'!$E15,and($C$6=YEAR('Cap Table'!$H$4),YEAR('Cap Table'!$M$4)-YEAR('Cap Table'!$H$4>0)),'Cap Table'!$J15,and($C$6=YEAR('Cap Table'!$M$4),YEAR('Cap Table'!$R$4)-YEAR('Cap Table'!$M$4>0)),'Cap Table'!$O15,$C$6>=YEAR('Cap Table'!$R$4),'Cap Table'!$T15) | D8: =if(and($C$4>0,$A$4>0),$C$4*C8,if(and($C$4>0,$A$4<0),($C$4+$A$4)*C8,0)) | E8: =IFS($E$6<YEAR('Cap Table'!$C$4),0,and($E$6=YEAR('Cap Table'!$C$4),YEAR('Cap Table'!$H$4)-YEAR('Cap Table'!$C$4)>0),'Cap Table'!$E15,and($E$6=YEAR('Cap Table'!$H$4),YEAR('Cap Table'!$M$4)-YEAR('Cap Table'!$H$4>0)),'Cap Table'!$J15,and($E$6=YEAR('Cap Table'!$M$4),YEAR('Cap Table'!$R$4)-YEAR('Cap Table'!$M$4>0)),'Cap Table'!$O15,$E$6>=YEAR('Cap Table'!$R$4),'Cap Table'!$T15) | F8: =if(and($E$4>0,$C$4>0),$E$4*E8,if(and($E$4>0,$C$4<0),($E$4+$C$4)*E8,0)) | G8: =IFS($G$6<YEAR('Cap Table'!$C$4),0,and($G$6=YEAR('Cap Table'!$C$4),YEAR('Cap Table'!$H$4)-YEAR('Cap Table'!$C$4)>0),'Cap Table'!$E15,and($G$6=YEAR('Cap Table'!$H$4),YEAR('Cap Table'!$M$4)-YEAR('Cap Table'!$H$4>0)),'Cap Table'!$J15,and($G$6=YEAR('Cap Table'!$M$4),YEAR('Cap Table'!$R$4)-YEAR('Cap Table'!$M$4>0)),'Cap Table'!$O15,$G$6>=YEAR('Cap Table'!$R$4),'Cap Table'!$T15) | H8: =if(and($G$4>0,$E$4>0),$G$4*G8,if(and($G$4>0,$E$4<0),($G$4+$E$4)*G8,0)) | I8: =IFS($I$6<YEAR('Cap Table'!$C$4),0,and($I$6=YEAR('Cap Table'!$C$4),YEAR('Cap Table'!$H$4)-YEAR('Cap Table'!$C$4)>0),'Cap Table'!$E15,and($I$6=YEAR('Cap Table'!$H$4),YEAR('Cap Table'!$M$4)-YEAR('Cap Table'!$H$4>0)),'Cap Table'!$J15,and($I$6=YEAR('Cap Table'!$M$4),YEAR('Cap Table'!$R$4)-YEAR('Cap Table'!$M$4>0)),'Cap Table'!$O15,$I$6>=YEAR('Cap Table'!$R$4),'Cap Table'!$T15) | J8: =if(and($I$4>0,$G$4>0),$I$4*I8,if(and($I$4>0,$G$4<0),($I$4+$G$4)*I8,0)) | K8: =IFS($K$6<YEAR('Cap Table'!$C$4),0,and($K$6=YEAR('Cap Table'!$C$4),YEAR('Cap Table'!$H$4)-YEAR('Cap Table'!$C$4)>0),'Cap Table'!$E15,and($K$6=YEAR('Cap Table'!$H$4),YEAR('Cap Table'!$M$4)-YEAR('Cap Table'!$H$4>0)),'Cap Table'!$J15,and($K$6=YEAR('Cap Table'!$M$4),YEAR('Cap Table'!$R$4)-YEAR('Cap Table'!$M$4>0)),'Cap Table'!$O15,$K$6>=YEAR('Cap Table'!$R$4),'Cap Table'!$T15) | L8: =if(and($K$4>0,$I$4>0),$K$4*K8,if(and($K$4>0,$I$4<0),($K$4+$I$4)*K8,0))
B9: ='Cap Table'!Q16 | C9: =IFS($C$6<YEAR('Cap Table'!$C$4),0,and($C$6=YEAR('Cap Table'!$C$4),YEAR('Cap Table'!$H$4)-YEAR('Cap Table'!$C$4)>0),'Cap Table'!$E16,and($C$6=YEAR('Cap Table'!$H$4),YEAR('Cap Table'!$M$4)-YEAR('Cap Table'!$H$4>0)),'Cap Table'!$J16,and($C$6=YEAR('Cap Table'!$M$4),YEAR('Cap Table'!$R$4)-YEAR('Cap Table'!$M$4>0)),'Cap Table'!$O16,$C$6>=YEAR('Cap Table'!$R$4),'Cap Table'!$T16) | D9: =if(and($C$4>0,$A$4>0),$C$4*C9,if(and($C$4>0,$A$4<0),($C$4+$A$4)*C9,0)) | E9: =IFS($E$6<YEAR('Cap Table'!$C$4),0,and($E$6=YEAR('Cap Table'!$C$4),YEAR('Cap Table'!$H$4)-YEAR('Cap Table'!$C$4)>0),'Cap Table'!$E16,and($E$6=YEAR('Cap Table'!$H$4),YEAR('Cap Table'!$M$4)-YEAR('Cap Table'!$H$4>0)),'Cap Table'!$J16,and($E$6=YEAR('Cap Table'!$M$4),YEAR('Cap Table'!$R$4)-YEAR('Cap Table'!$M$4>0)),'Cap Table'!$O16,$E$6>=YEAR('Cap Table'!$R$4),'Cap Table'!$T16) | F9: =if(and($E$4>0,$C$4>0),$E$4*E9,if(and($E$4>0,$C$4<0),($E$4+$C$4)*E9,0)) | G9: =IFS($G$6<YEAR('Cap Table'!$C$4),0,and($G$6=YEAR('Cap Table'!$C$4),YEAR('Cap Table'!$H$4)-YEAR('Cap Table'!$C$4)>0),'Cap Table'!$E16,and($G$6=YEAR('Cap Table'!$H$4),YEAR('Cap Table'!$M$4)-YEAR('Cap Table'!$H$4>0)),'Cap Table'!$J16,and($G$6=YEAR('Cap Table'!$M$4),YEAR('Cap Table'!$R$4)-YEAR('Cap Table'!$M$4>0)),'Cap Table'!$O16,$G$6>=YEAR('Cap Table'!$R$4),'Cap Table'!$T16) | H9: =if(and($G$4>0,$E$4>0),$G$4*G9,if(and($G$4>0,$E$4<0),($G$4+$E$4)*G9,0)) | I9: =IFS($I$6<YEAR('Cap Table'!$C$4),0,and($I$6=YEAR('Cap Table'!$C$4),YEAR('Cap Table'!$H$4)-YEAR('Cap Table'!$C$4)>0),'Cap Table'!$E16,and($I$6=YEAR('Cap Table'!$H$4),YEAR('Cap Table'!$M$4)-YEAR('Cap Table'!$H$4>0)),'Cap Table'!$J16,and($I$6=YEAR('Cap Table'!$M$4),YEAR('Cap Table'!$R$4)-YEAR('Cap Table'!$M$4>0)),'Cap Table'!$O16,$I$6>=YEAR('Cap Table'!$R$4),'Cap Table'!$T16) | J9: =if(and($I$4>0,$G$4>0),$I$4*I9,if(and($I$4>0,$G$4<0),($I$4+$G$4)*I9,0)) | K9: =IFS($K$6<YEAR('Cap Table'!$C$4),0,and($K$6=YEAR('Cap Table'!$C$4),YEAR('Cap Table'!$H$4)-YEAR('Cap Table'!$C$4)>0),'Cap Table'!$E16,and($K$6=YEAR('Cap Table'!$H$4),YEAR('Cap Table'!$M$4)-YEAR('Cap Table'!$H$4>0)),'Cap Table'!$J16,and($K$6=YEAR('Cap Table'!$M$4),YEAR('Cap Table'!$R$4)-YEAR('Cap Table'!$M$4>0)),'Cap Table'!$O16,$K$6>=YEAR('Cap Table'!$R$4),'Cap Table'!$T16) | L9: =if(and($K$4>0,$I$4>0),$K$4*K9,if(and($K$4>0,$I$4<0),($K$4+$I$4)*K9,0))
B10: ='Cap Table'!Q17 | C10: =IFS($C$6<YEAR('Cap Table'!$C$4),0,and($C$6=YEAR('Cap Table'!$C$4),YEAR('Cap Table'!$H$4)-YEAR('Cap Table'!$C$4)>0),'Cap Table'!$E17,and($C$6=YEAR('Cap Table'!$H$4),YEAR('Cap Table'!$M$4)-YEAR('Cap Table'!$H$4>0)),'Cap Table'!$J17,and($C$6=YEAR('Cap Table'!$M$4),YEAR('Cap Table'!$R$4)-YEAR('Cap Table'!$M$4>0)),'Cap Table'!$O17,$C$6>=YEAR('Cap Table'!$R$4),'Cap Table'!$T17) | D10: =if(and($C$4>0,$A$4>0),$C$4*C10,if(and($C$4>0,$A$4<0),($C$4+$A$4)*C10,0)) | E10: =IFS($E$6<YEAR('Cap Table'!$C$4),0,and($E$6=YEAR('Cap Table'!$C$4),YEAR('Cap Table'!$H$4)-YEAR('Cap Table'!$C$4)>0),'Cap Table'!$E17,and($E$6=YEAR('Cap Table'!$H$4),YEAR('Cap Table'!$M$4)-YEAR('Cap Table'!$H$4>0)),'Cap Table'!$J17,and($E$6=YEAR('Cap Table'!$M$4),YEAR('Cap Table'!$R$4)-YEAR('Cap Table'!$M$4>0)),'Cap Table'!$O17,$E$6>=YEAR('Cap Table'!$R$4),'Cap Table'!$T17) | F10: =if(and($E$4>0,$C$4>0),$E$4*E10,if(and($E$4>0,$C$4<0),($E$4+$C$4)*E10,0)) | G10: =IFS($G$6<YEAR('Cap Table'!$C$4),0,and($G$6=YEAR('Cap Table'!$C$4),YEAR('Cap Table'!$H$4)-YEAR('Cap Table'!$C$4)>0),'Cap Table'!$E17,and($G$6=YEAR('Cap Table'!$H$4),YEAR('Cap Table'!$M$4)-YEAR('Cap Table'!$H$4>0)),'Cap Table'!$J17,and($G$6=YEAR('Cap Table'!$M$4),YEAR('Cap Table'!$R$4)-YEAR('Cap Table'!$M$4>0)),'Cap Table'!$O17,$G$6>=YEAR('Cap Table'!$R$4),'Cap Table'!$T17) | H10: =if(and($G$4>0,$E$4>0),$G$4*G10,if(and($G$4>0,$E$4<0),($G$4+$E$4)*G10,0)) | I10: =IFS($I$6<YEAR('Cap Table'!$C$4),0,and($I$6=YEAR('Cap Table'!$C$4),YEAR('Cap Table'!$H$4)-YEAR('Cap Table'!$C$4)>0),'Cap Table'!$E17,and($I$6=YEAR('Cap Table'!$H$4),YEAR('Cap Table'!$M$4)-YEAR('Cap Table'!$H$4>0)),'Cap Table'!$J17,and($I$6=YEAR('Cap Table'!$M$4),YEAR('Cap Table'!$R$4)-YEAR('Cap Table'!$M$4>0)),'Cap Table'!$O17,$I$6>=YEAR('Cap Table'!$R$4),'Cap Table'!$T17) | J10: =if(and($I$4>0,$G$4>0),$I$4*I10,if(and($I$4>0,$G$4<0),($I$4+$G$4)*I10,0)) | K10: =IFS($K$6<YEAR('Cap Table'!$C$4),0,and($K$6=YEAR('Cap Table'!$C$4),YEAR('Cap Table'!$H$4)-YEAR('Cap Table'!$C$4)>0),'Cap Table'!$E17,and($K$6=YEAR('Cap Table'!$H$4),YEAR('Cap Table'!$M$4)-YEAR('Cap Table'!$H$4>0)),'Cap Table'!$J17,and($K$6=YEAR('Cap Table'!$M$4),YEAR('Cap Table'!$R$4)-YEAR('Cap Table'!$M$4>0)),'Cap Table'!$O17,$K$6>=YEAR('Cap Table'!$R$4),'Cap Table'!$T17) | L10: =if(and($K$4>0,$I$4>0),$K$4*K10,if(and($K$4>0,$I$4<0),($K$4+$I$4)*K10,0))
B11: ='Cap Table'!Q18 | C11: =IFS($C$6<YEAR('Cap Table'!$C$4),0,and($C$6=YEAR('Cap Table'!$C$4),YEAR('Cap Table'!$H$4)-YEAR('Cap Table'!$C$4)>0),'Cap Table'!$E18,and($C$6=YEAR('Cap Table'!$H$4),YEAR('Cap Table'!$M$4)-YEAR('Cap Table'!$H$4>0)),'Cap Table'!$J18,and($C$6=YEAR('Cap Table'!$M$4),YEAR('Cap Table'!$R$4)-YEAR('Cap Table'!$M$4>0)),'Cap Table'!$O18,$C$6>=YEAR('Cap Table'!$R$4),'Cap Table'!$T18) | D11: =if(and($C$4>0,$A$4>0),$C$4*C11,if(and($C$4>0,$A$4<0),($C$4+$A$4)*C11,0)) | E11: =IFS($E$6<YEAR('Cap Table'!$C$4),0,and($E$6=YEAR('Cap Table'!$C$4),YEAR('Cap Table'!$H$4)-YEAR('Cap Table'!$C$4)>0),'Cap Table'!$E18,and($E$6=YEAR('Cap Table'!$H$4),YEAR('Cap Table'!$M$4)-YEAR('Cap Table'!$H$4>0)),'Cap Table'!$J18,and($E$6=YEAR('Cap Table'!$M$4),YEAR('Cap Table'!$R$4)-YEAR('Cap Table'!$M$4>0)),'Cap Table'!$O18,$E$6>=YEAR('Cap Table'!$R$4),'Cap Table'!$T18) | F11: =if(and($E$4>0,$C$4>0),$E$4*E11,if(and($E$4>0,$C$4<0),($E$4+$C$4)*E11,0)) | G11: =IFS($G$6<YEAR('Cap Table'!$C$4),0,and($G$6=YEAR('Cap Table'!$C$4),YEAR('Cap Table'!$H$4)-YEAR('Cap Table'!$C$4)>0),'Cap Table'!$E18,and($G$6=YEAR('Cap Table'!$H$4),YEAR('Cap Table'!$M$4)-YEAR('Cap Table'!$H$4>0)),'Cap Table'!$J18,and($G$6=YEAR('Cap Table'!$M$4),YEAR('Cap Table'!$R$4)-YEAR('Cap Table'!$M$4>0)),'Cap Table'!$O18,$G$6>=YEAR('Cap Table'!$R$4),'Cap Table'!$T18) | H11: =if(and($G$4>0,$E$4>0),$G$4*G11,if(and($G$4>0,$E$4<0),($G$4+$E$4)*G11,0)) | I11: =IFS($I$6<YEAR('Cap Table'!$C$4),0,and($I$6=YEAR('Cap Table'!$C$4),YEAR('Cap Table'!$H$4)-YEAR('Cap Table'!$C$4)>0),'Cap Table'!$E18,and($I$6=YEAR('Cap Table'!$H$4),YEAR('Cap Table'!$M$4)-YEAR('Cap Table'!$H$4>0)),'Cap Table'!$J18,and($I$6=YEAR('Cap Table'!$M$4),YEAR('Cap Table'!$R$4)-YEAR('Cap Table'!$M$4>0)),'Cap Table'!$O18,$I$6>=YEAR('Cap Table'!$R$4),'Cap Table'!$T18) | J11: =if(and($I$4>0,$G$4>0),$I$4*I11,if(and($I$4>0,$G$4<0),($I$4+$G$4)*I11,0)) | K11: =IFS($K$6<YEAR('Cap Table'!$C$4),0,and($K$6=YEAR('Cap Table'!$C$4),YEAR('Cap Table'!$H$4)-YEAR('Cap Table'!$C$4)>0),'Cap Table'!$E18,and($K$6=YEAR('Cap Table'!$H$4),YEAR('Cap Table'!$M$4)-YEAR('Cap Table'!$H$4>0)),'Cap Table'!$J18,and($K$6=YEAR('Cap Table'!$M$4),YEAR('Cap Table'!$R$4)-YEAR('Cap Table'!$M$4>0)),'Cap Table'!$O18,$K$6>=YEAR('Cap Table'!$R$4),'Cap Table'!$T18) | L11: =if(and($K$4>0,$I$4>0),$K$4*K11,if(and($K$4>0,$I$4<0),($K$4+$I$4)*K11,0))
B12: ='Cap Table'!Q19 | C12: =IFS($C$6<YEAR('Cap Table'!$C$4),0,and($C$6=YEAR('Cap Table'!$C$4),YEAR('Cap Table'!$H$4)-YEAR('Cap Table'!$C$4)>0),'Cap Table'!$E19,and($C$6=YEAR('Cap Table'!$H$4),YEAR('Cap Table'!$M$4)-YEAR('Cap Table'!$H$4>0)),'Cap Table'!$J19,and($C$6=YEAR('Cap Table'!$M$4),YEAR('Cap Table'!$R$4)-YEAR('Cap Table'!$M$4>0)),'Cap Table'!$O19,$C$6>=YEAR('Cap Table'!$R$4),'Cap Table'!$T19) | D12: =if(and($C$4>0,$A$4>0),$C$4*C12,if(and($C$4>0,$A$4<0),($C$4+$A$4)*C12,0)) | E12: =IFS($E$6<YEAR('Cap Table'!$C$4),0,and($E$6=YEAR('Cap Table'!$C$4),YEAR('Cap Table'!$H$4)-YEAR('Cap Table'!$C$4)>0),'Cap Table'!$E19,and($E$6=YEAR('Cap Table'!$H$4),YEAR('Cap Table'!$M$4)-YEAR('Cap Table'!$H$4>0)),'Cap Table'!$J19,and($E$6=YEAR('Cap Table'!$M$4),YEAR('Cap Table'!$R$4)-YEAR('Cap Table'!$M$4>0)),'Cap Table'!$O19,$E$6>=YEAR('Cap Table'!$R$4),'Cap Table'!$T19) | F12: =if(and($E$4>0,$C$4>0),$E$4*E12,if(and($E$4>0,$C$4<0),($E$4+$C$4)*E12,0)) | G12: =IFS($G$6<YEAR('Cap Table'!$C$4),0,and($G$6=YEAR('Cap Table'!$C$4),YEAR('Cap Table'!$H$4)-YEAR('Cap Table'!$C$4)>0),'Cap Table'!$E19,and($G$6=YEAR('Cap Table'!$H$4),YEAR('Cap Table'!$M$4)-YEAR('Cap Table'!$H$4>0)),'Cap Table'!$J19,and($G$6=YEAR('Cap Table'!$M$4),YEAR('Cap Table'!$R$4)-YEAR('Cap Table'!$M$4>0)),'Cap Table'!$O19,$G$6>=YEAR('Cap Table'!$R$4),'Cap Table'!$T19) | H12: =if(and($G$4>0,$E$4>0),$G$4*G12,if(and($G$4>0,$E$4<0),($G$4+$E$4)*G12,0)) | I12: =IFS($I$6<YEAR('Cap Table'!$C$4),0,and($I$6=YEAR('Cap Table'!$C$4),YEAR('Cap Table'!$H$4)-YEAR('Cap Table'!$C$4)>0),'Cap Table'!$E19,and($I$6=YEAR('Cap Table'!$H$4),YEAR('Cap Table'!$M$4)-YEAR('Cap Table'!$H$4>0)),'Cap Table'!$J19,and($I$6=YEAR('Cap Table'!$M$4),YEAR('Cap Table'!$R$4)-YEAR('Cap Table'!$M$4>0)),'Cap Table'!$O19,$I$6>=YEAR('Cap Table'!$R$4),'Cap Table'!$T19) | J12: =if(and($I$4>0,$G$4>0),$I$4*I12,if(and($I$4>0,$G$4<0),($I$4+$G$4)*I12,0)) | K12: =IFS($K$6<YEAR('Cap Table'!$C$4),0,and($K$6=YEAR('Cap Table'!$C$4),YEAR('Cap Table'!$H$4)-YEAR('Cap Table'!$C$4)>0),'Cap Table'!$E19,and($K$6=YEAR('Cap Table'!$H$4),YEAR('Cap Table'!$M$4)-YEAR('Cap Table'!$H$4>0)),'Cap Table'!$J19,and($K$6=YEAR('Cap Table'!$M$4),YEAR('Cap Table'!$R$4)-YEAR('Cap Table'!$M$4>0)),'Cap Table'!$O19,$K$6>=YEAR('Cap Table'!$R$4),'Cap Table'!$T19) | L12: =if(and($K$4>0,$I$4>0),$K$4*K12,if(and($K$4>0,$I$4<0),($K$4+$I$4)*K12,0))
B13: ='Cap Table'!Q20 | C13: =IFS($C$6<YEAR('Cap Table'!$C$4),0,and($C$6=YEAR('Cap Table'!$C$4),YEAR('Cap Table'!$H$4)-YEAR('Cap Table'!$C$4)>0),'Cap Table'!$E20,and($C$6=YEAR('Cap Table'!$H$4),YEAR('Cap Table'!$M$4)-YEAR('Cap Table'!$H$4>0)),'Cap Table'!$J20,and($C$6=YEAR('Cap Table'!$M$4),YEAR('Cap Table'!$R$4)-YEAR('Cap Table'!$M$4>0)),'Cap Table'!$O20,$C$6>=YEAR('Cap Table'!$R$4),'Cap Table'!$T20) | D13: =if(and($C$4>0,$A$4>0),$C$4*C13,if(and($C$4>0,$A$4<0),($C$4+$A$4)*C13,0)) | E13: =IFS($E$6<YEAR('Cap Table'!$C$4),0,and($E$6=YEAR('Cap Table'!$C$4),YEAR('Cap Table'!$H$4)-YEAR('Cap Table'!$C$4)>0),'Cap Table'!$E20,and($E$6=YEAR('Cap Table'!$H$4),YEAR('Cap Table'!$M$4)-YEAR('Cap Table'!$H$4>0)),'Cap Table'!$J20,and($E$6=YEAR('Cap Table'!$M$4),YEAR('Cap Table'!$R$4)-YEAR('Cap Table'!$M$4>0)),'Cap Table'!$O20,$E$6>=YEAR('Cap Table'!$R$4),'Cap Table'!$T20) | F13: =if(and($E$4>0,$C$4>0),$E$4*E13,if(and($E$4>0,$C$4<0),($E$4+$C$4)*E13,0)) | G13: =IFS($G$6<YEAR('Cap Table'!$C$4),0,and($G$6=YEAR('Cap Table'!$C$4),YEAR('Cap Table'!$H$4)-YEAR('Cap Table'!$C$4)>0),'Cap Table'!$E20,and($G$6=YEAR('Cap Table'!$H$4),YEAR('Cap Table'!$M$4)-YEAR('Cap Table'!$H$4>0)),'Cap Table'!$J20,and($G$6=YEAR('Cap Table'!$M$4),YEAR('Cap Table'!$R$4)-YEAR('Cap Table'!$M$4>0)),'Cap Table'!$O20,$G$6>=YEAR('Cap Table'!$R$4),'Cap Table'!$T20) | H13: =if(and($G$4>0,$E$4>0),$G$4*G13,if(and($G$4>0,$E$4<0),($G$4+$E$4)*G13,0)) | I13: =IFS($I$6<YEAR('Cap Table'!$C$4),0,and($I$6=YEAR('Cap Table'!$C$4),YEAR('Cap Table'!$H$4)-YEAR('Cap Table'!$C$4)>0),'Cap Table'!$E20,and($I$6=YEAR('Cap Table'!$H$4),YEAR('Cap Table'!$M$4)-YEAR('Cap Table'!$H$4>0)),'Cap Table'!$J20,and($I$6=YEAR('Cap Table'!$M$4),YEAR('Cap Table'!$R$4)-YEAR('Cap Table'!$M$4>0)),'Cap Table'!$O20,$I$6>=YEAR('Cap Table'!$R$4),'Cap Table'!$T20) | J13: =if(and($I$4>0,$G$4>0),$I$4*I13,if(and($I$4>0,$G$4<0),($I$4+$G$4)*I13,0)) | K13: =IFS($K$6<YEAR('Cap Table'!$C$4),0,and($K$6=YEAR('Cap Table'!$C$4),YEAR('Cap Table'!$H$4)-YEAR('Cap Table'!$C$4)>0),'Cap Table'!$E20,and($K$6=YEAR('Cap Table'!$H$4),YEAR('Cap Table'!$M$4)-YEAR('Cap Table'!$H$4>0)),'Cap Table'!$J20,and($K$6=YEAR('Cap Table'!$M$4),YEAR('Cap Table'!$R$4)-YEAR('Cap Table'!$M$4>0)),'Cap Table'!$O20,$K$6>=YEAR('Cap Table'!$R$4),'Cap Table'!$T20) | L13: =if(and($K$4>0,$I$4>0),$K$4*K13,if(and($K$4>0,$I$4<0),($K$4+$I$4)*K13,0))
B14: ='Cap Table'!Q21 | C14: =IFS($C$6<YEAR('Cap Table'!$C$4),0,and($C$6=YEAR('Cap Table'!$C$4),YEAR('Cap Table'!$H$4)-YEAR('Cap Table'!$C$4)>0),'Cap Table'!$E21,and($C$6=YEAR('Cap Table'!$H$4),YEAR('Cap Table'!$M$4)-YEAR('Cap Table'!$H$4>0)),'Cap Table'!$J21,and($C$6=YEAR('Cap Table'!$M$4),YEAR('Cap Table'!$R$4)-YEAR('Cap Table'!$M$4>0)),'Cap Table'!$O21,$C$6>=YEAR('Cap Table'!$R$4),'Cap Table'!$T21) | D14: =if(and($C$4>0,$A$4>0),$C$4*C14,if(and($C$4>0,$A$4<0),($C$4+$A$4)*C14,0)) | E14: =IFS($E$6<YEAR('Cap Table'!$C$4),0,and($E$6=YEAR('Cap Table'!$C$4),YEAR('Cap Table'!$H$4)-YEAR('Cap Table'!$C$4)>0),'Cap Table'!$E21,and($E$6=YEAR('Cap Table'!$H$4),YEAR('Cap Table'!$M$4)-YEAR('Cap Table'!$H$4>0)),'Cap Table'!$J21,and($E$6=YEAR('Cap Table'!$M$4),YEAR('Cap Table'!$R$4)-YEAR('Cap Table'!$M$4>0)),'Cap Table'!$O21,$E$6>=YEAR('Cap Table'!$R$4),'Cap Table'!$T21) | F14: =if(and($E$4>0,$C$4>0),$E$4*E14,if(and($E$4>0,$C$4<0),($E$4+$C$4)*E14,0)) | G14: =IFS($G$6<YEAR('Cap Table'!$C$4),0,and($G$6=YEAR('Cap Table'!$C$4),YEAR('Cap Table'!$H$4)-YEAR('Cap Table'!$C$4)>0),'Cap Table'!$E21,and($G$6=YEAR('Cap Table'!$H$4),YEAR('Cap Table'!$M$4)-YEAR('Cap Table'!$H$4>0)),'Cap Table'!$J21,and($G$6=YEAR('Cap Table'!$M$4),YEAR('Cap Table'!$R$4)-YEAR('Cap Table'!$M$4>0)),'Cap Table'!$O21,$G$6>=YEAR('Cap Table'!$R$4),'Cap Table'!$T21) | H14: =if(and($G$4>0,$E$4>0),$G$4*G14,if(and($G$4>0,$E$4<0),($G$4+$E$4)*G14,0)) | I14: =IFS($I$6<YEAR('Cap Table'!$C$4),0,and($I$6=YEAR('Cap Table'!$C$4),YEAR('Cap Table'!$H$4)-YEAR('Cap Table'!$C$4)>0),'Cap Table'!$E21,and($I$6=YEAR('Cap Table'!$H$4),YEAR('Cap Table'!$M$4)-YEAR('Cap Table'!$H$4>0)),'Cap Table'!$J21,and($I$6=YEAR('Cap Table'!$M$4),YEAR('Cap Table'!$R$4)-YEAR('Cap Table'!$M$4>0)),'Cap Table'!$O21,$I$6>=YEAR('Cap Table'!$R$4),'Cap Table'!$T21) | J14: =if(and($I$4>0,$G$4>0),$I$4*I14,if(and($I$4>0,$G$4<0),($I$4+$G$4)*I14,0)) | K14: =IFS($K$6<YEAR('Cap Table'!$C$4),0,and($K$6=YEAR('Cap Table'!$C$4),YEAR('Cap Table'!$H$4)-YEAR('Cap Table'!$C$4)>0),'Cap Table'!$E21,and($K$6=YEAR('Cap Table'!$H$4),YEAR('Cap Table'!$M$4)-YEAR('Cap Table'!$H$4>0)),'Cap Table'!$J21,and($K$6=YEAR('Cap Table'!$M$4),YEAR('Cap Table'!$R$4)-YEAR('Cap Table'!$M$4>0)),'Cap Table'!$O21,$K$6>=YEAR('Cap Table'!$R$4),'Cap Table'!$T21) | L14: =if(and($K$4>0,$I$4>0),$K$4*K14,if(and($K$4>0,$I$4<0),($K$4+$I$4)*K14,0))
B15: ='Cap Table'!Q22 | C15: =IFS($C$6<YEAR('Cap Table'!$C$4),0,and($C$6=YEAR('Cap Table'!$C$4),YEAR('Cap Table'!$H$4)-YEAR('Cap Table'!$C$4)>0),'Cap Table'!$E22,and($C$6=YEAR('Cap Table'!$H$4),YEAR('Cap Table'!$M$4)-YEAR('Cap Table'!$H$4>0)),'Cap Table'!$J22,and($C$6=YEAR('Cap Table'!$M$4),YEAR('Cap Table'!$R$4)-YEAR('Cap Table'!$M$4>0)),'Cap Table'!$O22,$C$6>=YEAR('Cap Table'!$R$4),'Cap Table'!$T22) | D15: =if(and($C$4>0,$A$4>0),$C$4*C15,if(and($C$4>0,$A$4<0),($C$4+$A$4)*C15,0)) | E15: =IFS($E$6<YEAR('Cap Table'!$C$4),0,and($E$6=YEAR('Cap Table'!$C$4),YEAR('Cap Table'!$H$4)-YEAR('Cap Table'!$C$4)>0),'Cap Table'!$E22,and($E$6=YEAR('Cap Table'!$H$4),YEAR('Cap Table'!$M$4)-YEAR('Cap Table'!$H$4>0)),'Cap Table'!$J22,and($E$6=YEAR('Cap Table'!$M$4),YEAR('Cap Table'!$R$4)-YEAR('Cap Table'!$M$4>0)),'Cap Table'!$O22,$E$6>=YEAR('Cap Table'!$R$4),'Cap Table'!$T22) | F15: =if(and($E$4>0,$C$4>0),$E$4*E15,if(and($E$4>0,$C$4<0),($E$4+$C$4)*E15,0)) | G15: =IFS($G$6<YEAR('Cap Table'!$C$4),0,and($G$6=YEAR('Cap Table'!$C$4),YEAR('Cap Table'!$H$4)-YEAR('Cap Table'!$C$4)>0),'Cap Table'!$E22,and($G$6=YEAR('Cap Table'!$H$4),YEAR('Cap Table'!$M$4)-YEAR('Cap Table'!$H$4>0)),'Cap Table'!$J22,and($G$6=YEAR('Cap Table'!$M$4),YEAR('Cap Table'!$R$4)-YEAR('Cap Table'!$M$4>0)),'Cap Table'!$O22,$G$6>=YEAR('Cap Table'!$R$4),'Cap Table'!$T22) | H15: =if(and($G$4>0,$E$4>0),$G$4*G15,if(and($G$4>0,$E$4<0),($G$4+$E$4)*G15,0)) | I15: =IFS($I$6<YEAR('Cap Table'!$C$4),0,and($I$6=YEAR('Cap Table'!$C$4),YEAR('Cap Table'!$H$4)-YEAR('Cap Table'!$C$4)>0),'Cap Table'!$E22,and($I$6=YEAR('Cap Table'!$H$4),YEAR('Cap Table'!$M$4)-YEAR('Cap Table'!$H$4>0)),'Cap Table'!$J22,and($I$6=YEAR('Cap Table'!$M$4),YEAR('Cap Table'!$R$4)-YEAR('Cap Table'!$M$4>0)),'Cap Table'!$O22,$I$6>=YEAR('Cap Table'!$R$4),'Cap Table'!$T22) | J15: =if(and($I$4>0,$G$4>0),$I$4*I15,if(and($I$4>0,$G$4<0),($I$4+$G$4)*I15,0)) | K15: =IFS($K$6<YEAR('Cap Table'!$C$4),0,and($K$6=YEAR('Cap Table'!$C$4),YEAR('Cap Table'!$H$4)-YEAR('Cap Table'!$C$4)>0),'Cap Table'!$E22,and($K$6=YEAR('Cap Table'!$H$4),YEAR('Cap Table'!$M$4)-YEAR('Cap Table'!$H$4>0)),'Cap Table'!$J22,and($K$6=YEAR('Cap Table'!$M$4),YEAR('Cap Table'!$R$4)-YEAR('Cap Table'!$M$4>0)),'Cap Table'!$O22,$K$6>=YEAR('Cap Table'!$R$4),'Cap Table'!$T22) | L15: =if(and($K$4>0,$I$4>0),$K$4*K15,if(and($K$4>0,$I$4<0),($K$4+$I$4)*K15,0))
B16: ='Cap Table'!Q23 | C16: =IFS($C$6<YEAR('Cap Table'!$C$4),0,and($C$6=YEAR('Cap Table'!$C$4),YEAR('Cap Table'!$H$4)-YEAR('Cap Table'!$C$4)>0),'Cap Table'!$E23,and($C$6=YEAR('Cap Table'!$H$4),YEAR('Cap Table'!$M$4)-YEAR('Cap Table'!$H$4>0)),'Cap Table'!$J23,and($C$6=YEAR('Cap Table'!$M$4),YEAR('Cap Table'!$R$4)-YEAR('Cap Table'!$M$4>0)),'Cap Table'!$O23,$C$6>=YEAR('Cap Table'!$R$4),'Cap Table'!$T23) | D16: =if(and($C$4>0,$A$4>0),$C$4*C16,if(and($C$4>0,$A$4<0),($C$4+$A$4)*C16,0)) | E16: =IFS($E$6<YEAR('Cap Table'!$C$4),0,and($E$6=YEAR('Cap Table'!$C$4),YEAR('Cap Table'!$H$4)-YEAR('Cap Table'!$C$4)>0),'Cap Table'!$E23,and($E$6=YEAR('Cap Table'!$H$4),YEAR('Cap Table'!$M$4)-YEAR('Cap Table'!$H$4>0)),'Cap Table'!$J23,and($E$6=YEAR('Cap Table'!$M$4),YEAR('Cap Table'!$R$4)-YEAR('Cap Table'!$M$4>0)),'Cap Table'!$O23,$E$6>=YEAR('Cap Table'!$R$4),'Cap Table'!$T23) | F16: =if(and($E$4>0,$C$4>0),$E$4*E16,if(and($E$4>0,$C$4<0),($E$4+$C$4)*E16,0)) | G16: =IFS($G$6<YEAR('Cap Table'!$C$4),0,and($G$6=YEAR('Cap Table'!$C$4),YEAR('Cap Table'!$H$4)-YEAR('Cap Table'!$C$4)>0),'Cap Table'!$E23,and($G$6=YEAR('Cap Table'!$H$4),YEAR('Cap Table'!$M$4)-YEAR('Cap Table'!$H$4>0)),'Cap Table'!$J23,and($G$6=YEAR('Cap Table'!$M$4),YEAR('Cap Table'!$R$4)-YEAR('Cap Table'!$M$4>0)),'Cap Table'!$O23,$G$6>=YEAR('Cap Table'!$R$4),'Cap Table'!$T23) | H16: =if(and($G$4>0,$E$4>0),$G$4*G16,if(and($G$4>0,$E$4<0),($G$4+$E$4)*G16,0)) | I16: =IFS($I$6<YEAR('Cap Table'!$C$4),0,and($I$6=YEAR('Cap Table'!$C$4),YEAR('Cap Table'!$H$4)-YEAR('Cap Table'!$C$4)>0),'Cap Table'!$E23,and($I$6=YEAR('Cap Table'!$H$4),YEAR('Cap Table'!$M$4)-YEAR('Cap Table'!$H$4>0)),'Cap Table'!$J23,and($I$6=YEAR('Cap Table'!$M$4),YEAR('Cap Table'!$R$4)-YEAR('Cap Table'!$M$4>0)),'Cap Table'!$O23,$I$6>=YEAR('Cap Table'!$R$4),'Cap Table'!$T23) | J16: =if(and($I$4>0,$G$4>0),$I$4*I16,if(and($I$4>0,$G$4<0),($I$4+$G$4)*I16,0)) | K16: =IFS($K$6<YEAR('Cap Table'!$C$4),0,and($K$6=YEAR('Cap Table'!$C$4),YEAR('Cap Table'!$H$4)-YEAR('Cap Table'!$C$4)>0),'Cap Table'!$E23,and($K$6=YEAR('Cap Table'!$H$4),YEAR('Cap Table'!$M$4)-YEAR('Cap Table'!$H$4>0)),'Cap Table'!$J23,and($K$6=YEAR('Cap Table'!$M$4),YEAR('Cap Table'!$R$4)-YEAR('Cap Table'!$M$4>0)),'Cap Table'!$O23,$K$6>=YEAR('Cap Table'!$R$4),'Cap Table'!$T23) | L16: =if(and($K$4>0,$I$4>0),$K$4*K16,if(and($K$4>0,$I$4<0),($K$4+$I$4)*K16,0))
B17: ='Cap Table'!Q24 | C17: =IFS($C$6<YEAR('Cap Table'!$C$4),0,and($C$6=YEAR('Cap Table'!$C$4),YEAR('Cap Table'!$H$4)-YEAR('Cap Table'!$C$4)>0),'Cap Table'!$E24,and($C$6=YEAR('Cap Table'!$H$4),YEAR('Cap Table'!$M$4)-YEAR('Cap Table'!$H$4>0)),'Cap Table'!$J24,and($C$6=YEAR('Cap Table'!$M$4),YEAR('Cap Table'!$R$4)-YEAR('Cap Table'!$M$4>0)),'Cap Table'!$O24,$C$6>=YEAR('Cap Table'!$R$4),'Cap Table'!$T24) | D17: =if(and($C$4>0,$A$4>0),$C$4*C17,if(and($C$4>0,$A$4<0),($C$4+$A$4)*C17,0)) | E17: =IFS($E$6<YEAR('Cap Table'!$C$4),0,and($E$6=YEAR('Cap Table'!$C$4),YEAR('Cap Table'!$H$4)-YEAR('Cap Table'!$C$4)>0),'Cap Table'!$E24,and($E$6=YEAR('Cap Table'!$H$4),YEAR('Cap Table'!$M$4)-YEAR('Cap Table'!$H$4>0)),'Cap Table'!$J24,and($E$6=YEAR('Cap Table'!$M$4),YEAR('Cap Table'!$R$4)-YEAR('Cap Table'!$M$4>0)),'Cap Table'!$O24,$E$6>=YEAR('Cap Table'!$R$4),'Cap Table'!$T24) | F17: =if(and($E$4>0,$C$4>0),$E$4*E17,if(and($E$4>0,$C$4<0),($E$4+$C$4)*E17,0)) | G17: =IFS($G$6<YEAR('Cap Table'!$C$4),0,and($G$6=YEAR('Cap Table'!$C$4),YEAR('Cap Table'!$H$4)-YEAR('Cap Table'!$C$4)>0),'Cap Table'!$E24,and($G$6=YEAR('Cap Table'!$H$4),YEAR('Cap Table'!$M$4)-YEAR('Cap Table'!$H$4>0)),'Cap Table'!$J24,and($G$6=YEAR('Cap Table'!$M$4),YEAR('Cap Table'!$R$4)-YEAR('Cap Table'!$M$4>0)),'Cap Table'!$O24,$G$6>=YEAR('Cap Table'!$R$4),'Cap Table'!$T24) | H17: =if(and($G$4>0,$E$4>0),$G$4*G17,if(and($G$4>0,$E$4<0),($G$4+$E$4)*G17,0)) | I17: =IFS($I$6<YEAR('Cap Table'!$C$4),0,and($I$6=YEAR('Cap Table'!$C$4),YEAR('Cap Table'!$H$4)-YEAR('Cap Table'!$C$4)>0),'Cap Table'!$E24,and($I$6=YEAR('Cap Table'!$H$4),YEAR('Cap Table'!$M$4)-YEAR('Cap Table'!$H$4>0)),'Cap Table'!$J24,and($I$6=YEAR('Cap Table'!$M$4),YEAR('Cap Table'!$R$4)-YEAR('Cap Table'!$M$4>0)),'Cap Table'!$O24,$I$6>=YEAR('Cap Table'!$R$4),'Cap Table'!$T24) | J17: =if(and($I$4>0,$G$4>0),$I$4*I17,if(and($I$4>0,$G$4<0),($I$4+$G$4)*I17,0)) | K17: =IFS($K$6<YEAR('Cap Table'!$C$4),0,and($K$6=YEAR('Cap Table'!$C$4),YEAR('Cap Table'!$H$4)-YEAR('Cap Table'!$C$4)>0),'Cap Table'!$E24,and($K$6=YEAR('Cap Table'!$H$4),YEAR('Cap Table'!$M$4)-YEAR('Cap Table'!$H$4>0)),'Cap Table'!$J24,and($K$6=YEAR('Cap Table'!$M$4),YEAR('Cap Table'!$R$4)-YEAR('Cap Table'!$M$4>0)),'Cap Table'!$O24,$K$6>=YEAR('Cap Table'!$R$4),'Cap Table'!$T24) | L17: =if(and($K$4>0,$I$4>0),$K$4*K17,if(and($K$4>0,$I$4<0),($K$4+$I$4)*K17,0))
B18: ='Cap Table'!Q25 | C18: =IFS($C$6<YEAR('Cap Table'!$C$4),0,and($C$6=YEAR('Cap Table'!$C$4),YEAR('Cap Table'!$H$4)-YEAR('Cap Table'!$C$4)>0),'Cap Table'!$E25,and($C$6=YEAR('Cap Table'!$H$4),YEAR('Cap Table'!$M$4)-YEAR('Cap Table'!$H$4>0)),'Cap Table'!$J25,and($C$6=YEAR('Cap Table'!$M$4),YEAR('Cap Table'!$R$4)-YEAR('Cap Table'!$M$4>0)),'Cap Table'!$O25,$C$6>=YEAR('Cap Table'!$R$4),'Cap Table'!$T25) | D18: =if(and($C$4>0,$A$4>0),$C$4*C18,if(and($C$4>0,$A$4<0),($C$4+$A$4)*C18,0)) | E18: =IFS($E$6<YEAR('Cap Table'!$C$4),0,and($E$6=YEAR('Cap Table'!$C$4),YEAR('Cap Table'!$H$4)-YEAR('Cap Table'!$C$4)>0),'Cap Table'!$E25,and($E$6=YEAR('Cap Table'!$H$4),YEAR('Cap Table'!$M$4)-YEAR('Cap Table'!$H$4>0)),'Cap Table'!$J25,and($E$6=YEAR('Cap Table'!$M$4),YEAR('Cap Table'!$R$4)-YEAR('Cap Table'!$M$4>0)),'Cap Table'!$O25,$E$6>=YEAR('Cap Table'!$R$4),'Cap Table'!$T25) | F18: =if(and($E$4>0,$C$4>0),$E$4*E18,if(and($E$4>0,$C$4<0),($E$4+$C$4)*E18,0)) | G18: =IFS($G$6<YEAR('Cap Table'!$C$4),0,and($G$6=YEAR('Cap Table'!$C$4),YEAR('Cap Table'!$H$4)-YEAR('Cap Table'!$C$4)>0),'Cap Table'!$E25,and($G$6=YEAR('Cap Table'!$H$4),YEAR('Cap Table'!$M$4)-YEAR('Cap Table'!$H$4>0)),'Cap Table'!$J25,and($G$6=YEAR('Cap Table'!$M$4),YEAR('Cap Table'!$R$4)-YEAR('Cap Table'!$M$4>0)),'Cap Table'!$O25,$G$6>=YEAR('Cap Table'!$R$4),'Cap Table'!$T25) | H18: =if(and($G$4>0,$E$4>0),$G$4*G18,if(and($G$4>0,$E$4<0),($G$4+$E$4)*G18,0)) | I18: =IFS($I$6<YEAR('Cap Table'!$C$4),0,and($I$6=YEAR('Cap Table'!$C$4),YEAR('Cap Table'!$H$4)-YEAR('Cap Table'!$C$4)>0),'Cap Table'!$E25,and($I$6=YEAR('Cap Table'!$H$4),YEAR('Cap Table'!$M$4)-YEAR('Cap Table'!$H$4>0)),'Cap Table'!$J25,and($I$6=YEAR('Cap Table'!$M$4),YEAR('Cap Table'!$R$4)-YEAR('Cap Table'!$M$4>0)),'Cap Table'!$O25,$I$6>=YEAR('Cap Table'!$R$4),'Cap Table'!$T25) | J18: =if(and($I$4>0,$G$4>0),$I$4*I18,if(and($I$4>0,$G$4<0),($I$4+$G$4)*I18,0)) | K18: =IFS($K$6<YEAR('Cap Table'!$C$4),0,and($K$6=YEAR('Cap Table'!$C$4),YEAR('Cap Table'!$H$4)-YEAR('Cap Table'!$C$4)>0),'Cap Table'!$E25,and($K$6=YEAR('Cap Table'!$H$4),YEAR('Cap Table'!$M$4)-YEAR('Cap Table'!$H$4>0)),'Cap Table'!$J25,and($K$6=YEAR('Cap Table'!$M$4),YEAR('Cap Table'!$R$4)-YEAR('Cap Table'!$M$4>0)),'Cap Table'!$O25,$K$6>=YEAR('Cap Table'!$R$4),'Cap Table'!$T25) | L18: =if(and($K$4>0,$I$4>0),$K$4*K18,if(and($K$4>0,$I$4<0),($K$4+$I$4)*K18,0))
B19: ='Cap Table'!Q26 | C19: =IFS($C$6<YEAR('Cap Table'!$C$4),0,and($C$6=YEAR('Cap Table'!$C$4),YEAR('Cap Table'!$H$4)-YEAR('Cap Table'!$C$4)>0),'Cap Table'!$E26,and($C$6=YEAR('Cap Table'!$H$4),YEAR('Cap Table'!$M$4)-YEAR('Cap Table'!$H$4>0)),'Cap Table'!$J26,and($C$6=YEAR('Cap Table'!$M$4),YEAR('Cap Table'!$R$4)-YEAR('Cap Table'!$M$4>0)),'Cap Table'!$O26,$C$6>=YEAR('Cap Table'!$R$4),'Cap Table'!$T26) | D19: =if(and($C$4>0,$A$4>0),$C$4*C19,if(and($C$4>0,$A$4<0),($C$4+$A$4)*C19,0)) | E19: =IFS($E$6<YEAR('Cap Table'!$C$4),0,and($E$6=YEAR('Cap Table'!$C$4),YEAR('Cap Table'!$H$4)-YEAR('Cap Table'!$C$4)>0),'Cap Table'!$E26,and($E$6=YEAR('Cap Table'!$H$4),YEAR('Cap Table'!$M$4)-YEAR('Cap Table'!$H$4>0)),'Cap Table'!$J26,and($E$6=YEAR('Cap Table'!$M$4),YEAR('Cap Table'!$R$4)-YEAR('Cap Table'!$M$4>0)),'Cap Table'!$O26,$E$6>=YEAR('Cap Table'!$R$4),'Cap Table'!$T26) | F19: =if(and($E$4>0,$C$4>0),$E$4*E19,if(and($E$4>0,$C$4<0),($E$4+$C$4)*E19,0)) | G19: =IFS($G$6<YEAR('Cap Table'!$C$4),0,and($G$6=YEAR('Cap Table'!$C$4),YEAR('Cap Table'!$H$4)-YEAR('Cap Table'!$C$4)>0),'Cap Table'!$E26,and($G$6=YEAR('Cap Table'!$H$4),YEAR('Cap Table'!$M$4)-YEAR('Cap Table'!$H$4>0)),'Cap Table'!$J26,and($G$6=YEAR('Cap Table'!$M$4),YEAR('Cap Table'!$R$4)-YEAR('Cap Table'!$M$4>0)),'Cap Table'!$O26,$G$6>=YEAR('Cap Table'!$R$4),'Cap Table'!$T26) | H19: =if(and($G$4>0,$E$4>0),$G$4*G19,if(and($G$4>0,$E$4<0),($G$4+$E$4)*G19,0)) | I19: =IFS($I$6<YEAR('Cap Table'!$C$4),0,and($I$6=YEAR('Cap Table'!$C$4),YEAR('Cap Table'!$H$4)-YEAR('Cap Table'!$C$4)>0),'Cap Table'!$E26,and($I$6=YEAR('Cap Table'!$H$4),YEAR('Cap Table'!$M$4)-YEAR('Cap Table'!$H$4>0)),'Cap Table'!$J26,and($I$6=YEAR('Cap Table'!$M$4),YEAR('Cap Table'!$R$4)-YEAR('Cap Table'!$M$4>0)),'Cap Table'!$O26,$I$6>=YEAR('Cap Table'!$R$4),'Cap Table'!$T26) | J19: =if(and($I$4>0,$G$4>0),$I$4*I19,if(and($I$4>0,$G$4<0),($I$4+$G$4)*I19,0)) | K19: =IFS($K$6<YEAR('Cap Table'!$C$4),0,and($K$6=YEAR('Cap Table'!$C$4),YEAR('Cap Table'!$H$4)-YEAR('Cap Table'!$C$4)>0),'Cap Table'!$E26,and($K$6=YEAR('Cap Table'!$H$4),YEAR('Cap Table'!$M$4)-YEAR('Cap Table'!$H$4>0)),'Cap Table'!$J26,and($K$6=YEAR('Cap Table'!$M$4),YEAR('Cap Table'!$R$4)-YEAR('Cap Table'!$M$4>0)),'Cap Table'!$O26,$K$6>=YEAR('Cap Table'!$R$4),'Cap Table'!$T26) | L19: =if(and($K$4>0,$I$4>0),$K$4*K19,if(and($K$4>0,$I$4<0),($K$4+$I$4)*K19,0))
... B22: ='Cap Table'!Q29 | C22: =IFS($C$6<YEAR('Cap Table'!$C$4),0,and($C$6=YEAR('Cap Table'!$C$4),YEAR('Cap Table'!$H$4)-YEAR('Cap Table'!$C$4)>0),'Cap Table'!$E29,and($C$6=YEAR('Cap Table'!$H$4),YEAR('Cap Table'!$M$4)-YEAR('Cap Table'!$H$4>0)),'Cap Table'!$J29,and($C$6=YEAR('Cap Table'!$M$4),YEAR('Cap Table'!$R$4)-YEAR('Cap Table'!$M$4>0)),'Cap Table'!$O29,$C$6>=YEAR('Cap Table'!$R$4),'Cap Table'!$T29) | D22: =if(and($C$4>0,$A$4>0),$C$4*C22,if(and($C$4>0,$A$4<0),($C$4+$A$4)*C22,0)) | E22: =IFS($E$6<YEAR('Cap Table'!$C$4),0,and($E$6=YEAR('Cap Table'!$C$4),YEAR('Cap Table'!$H$4)-YEAR('Cap Table'!$C$4)>0),'Cap Table'!$E29,and($E$6=YEAR('Cap Table'!$H$4),YEAR('Cap Table'!$M$4)-YEAR('Cap Table'!$H$4>0)),'Cap Table'!$J29,and($E$6=YEAR('Cap Table'!$M$4),YEAR('Cap Table'!$R$4)-YEAR('Cap Table'!$M$4>0)),'Cap Table'!$O29,$E$6>=YEAR('Cap Table'!$R$4),'Cap Table'!$T29) | F22: =if(and($E$4>0,$C$4>0),$E$4*E22,if(and($E$4>0,$C$4<0),($E$4+$C$4)*E22,0)) | G22: =IFS($G$6<YEAR('Cap Table'!$C$4),0,and($G$6=YEAR('Cap Table'!$C$4),YEAR('Cap Table'!$H$4)-YEAR('Cap Table'!$C$4)>0),'Cap Table'!$E29,and($G$6=YEAR('Cap Table'!$H$4),YEAR('Cap Table'!$M$4)-YEAR('Cap Table'!$H$4>0)),'Cap Table'!$J29,and($G$6=YEAR('Cap Table'!$M$4),YEAR('Cap Table'!$R$4)-YEAR('Cap Table'!$M$4>0)),'Cap Table'!$O29,$G$6>=YEAR('Cap Table'!$R$4),'Cap Table'!$T29) | H22: =if(and($G$4>0,$E$4>0),$G$4*G22,if(and($G$4>0,$E$4<0),($G$4+$E$4)*G22,0)) | I22: =IFS($I$6<YEAR('Cap Table'!$C$4),0,and($I$6=YEAR('Cap Table'!$C$4),YEAR('Cap Table'!$H$4)-YEAR('Cap Table'!$C$4)>0),'Cap Table'!$E29,and($I$6=YEAR('Cap Table'!$H$4),YEAR('Cap Table'!$M$4)-YEAR('Cap Table'!$H$4>0)),'Cap Table'!$J29,and($I$6=YEAR('Cap Table'!$M$4),YEAR('Cap Table'!$R$4)-YEAR('Cap Table'!$M$4>0)),'Cap Table'!$O29,$I$6>=YEAR('Cap Table'!$R$4),'Cap Table'!$T29) | J22: =if(and($I$4>0,$G$4>0),$I$4*I22,if(and($I$4>0,$G$4<0),($I$4+$G$4)*I22,0)) | K22: =IFS($K$6<YEAR('Cap Table'!$C$4),0,and($K$6=YEAR('Cap Table'!$C$4),YEAR('Cap Table'!$H$4)-YEAR('Cap Table'!$C$4)>0),'Cap Table'!$E29,and($K$6=YEAR('Cap Table'!$H$4),YEAR('Cap Table'!$M$4)-YEAR('Cap Table'!$H$4>0)),'Cap Table'!$J29,and($K$6=YEAR('Cap Table'!$M$4),YEAR('Cap Table'!$R$4)-YEAR('Cap Table'!$M$4>0)),'Cap Table'!$O29,$K$6>=YEAR('Cap Table'!$R$4),'Cap Table'!$T29) | L22: =if(and($K$4>0,$I$4>0),$K$4*K22,if(and($K$4>0,$I$4<0),($K$4+$I$4)*K22,0))
B23: ='Cap Table'!Q30 | E23: =IFS($E$6<YEAR('Cap Table'!$C$4),0,and($E$6=YEAR('Cap Table'!$C$4),YEAR('Cap Table'!$H$4)-YEAR('Cap Table'!$C$4)>0),'Cap Table'!$E30,and($E$6=YEAR('Cap Table'!$H$4),YEAR('Cap Table'!$M$4)-YEAR('Cap Table'!$H$4>0)),'Cap Table'!$J30,and($E$6=YEAR('Cap Table'!$M$4),YEAR('Cap Table'!$R$4)-YEAR('Cap Table'!$M$4>0)),'Cap Table'!$O30,$E$6>=YEAR('Cap Table'!$R$4),'Cap Table'!$T30)

Sheet Exit Scenarios
B1: =Settings!B4
B3: Expected Exit Scenario | C3: Strategic acquasition
B5: Target valuation | C5: 40000000
B7: Expected Year of Exit | C7: 2027
B9: Shareholder | C9: Share | D9: Capital Invested | E9: Exit | F9: ROI
B10: =Dividends!B8 | C10: ='Cap Table'!T15 | D10: =SUMIF('Cap Table'!$B$15:$B$19,B10,'Cap Table'!$C$15:$C$19)+SUMIF('Cap Table'!$G$15:$G$23,B10,'Cap Table'!$H$15:$H$23)+SUMIF('Cap Table'!$L$15:$L$27,B10,'Cap Table'!$M$15:$M$27)+SUMIF('Cap Table'!$Q$15:$Q$29,B10,'Cap Table'!$R$15:$R$29) | E10: =$C$5*C10
B11: =Dividends!B9 | C11: ='Cap Table'!T16 | D11: =SUMIF('Cap Table'!$B$15:$B$19,B11,'Cap Table'!$C$15:$C$19)+SUMIF('Cap Table'!$G$15:$G$23,B11,'Cap Table'!$H$15:$H$23)+SUMIF('Cap Table'!$L$15:$L$27,B11,'Cap Table'!$M$15:$M$27)+SUMIF('Cap Table'!$Q$15:$Q$29,B11,'Cap Table'!$R$15:$R$29) | E11: =$C$5*C11
B12: =Dividends!B10 | C12: ='Cap Table'!T17 | D12: =SUMIF('Cap Table'!$B$15:$B$19,B12,'Cap Table'!$C$15:$C$19)+SUMIF('Cap Table'!$G$15:$G$23,B12,'Cap Table'!$H$15:$H$23)+SUMIF('Cap Table'!$L$15:$L$27,B12,'Cap Table'!$M$15:$M$27)+SUMIF('Cap Table'!$Q$15:$Q$29,B12,'Cap Table'!$R$15:$R$29) | E12: =$C$5*C12
B13: =Dividends!B11 | C13: ='Cap Table'!T18 | D13: =SUMIF('Cap Table'!$B$15:$B$19,B13,'Cap Table'!$C$15:$C$19)+SUMIF('Cap Table'!$G$15:$G$23,B13,'Cap Table'!$H$15:$H$23)+SUMIF('Cap Table'!$L$15:$L$27,B13,'Cap Table'!$M$15:$M$27)+SUMIF('Cap Table'!$Q$15:$Q$29,B13,'Cap Table'!$R$15:$R$29) | E13: =$C$5*C13
B14: =Dividends!B12 | C14: ='Cap Table'!T19 | D14: =SUMIF('Cap Table'!$B$15:$B$19,B14,'Cap Table'!$C$15:$C$19)+SUMIF('Cap Table'!$G$15:$G$23,B14,'Cap Table'!$H$15:$H$23)+SUMIF('Cap Table'!$L$15:$L$27,B14,'Cap Table'!$M$15:$M$27)+SUMIF('Cap Table'!$Q$15:$Q$29,B14,'Cap Table'!$R$15:$R$29) | E14: =$C$5*C14
B15: =Dividends!B13 | C15: ='Cap Table'!T20 | D15: =SUMIF('Cap Table'!$B$15:$B$19,B15,'Cap Table'!$C$15:$C$19)+SUMIF('Cap Table'!$G$15:$G$23,B15,'Cap Table'!$H$15:$H$23)+SUMIF('Cap Table'!$L$15:$L$27,B15,'Cap Table'!$M$15:$M$27)+SUMIF('Cap Table'!$Q$15:$Q$29,B15,'Cap Table'!$R$15:$R$29) | E15: =$C$5*C15 | F15: =(E15-D15)/D15
B16: =Dividends!B14 | C16: ='Cap Table'!T21 | D16: =SUMIF('Cap Table'!$B$15:$B$19,B16,'Cap Table'!$C$15:$C$19)+SUMIF('Cap Table'!$G$15:$G$23,B16,'Cap Table'!$H$15:$H$23)+SUMIF('Cap Table'!$L$15:$L$27,B16,'Cap Table'!$M$15:$M$27)+SUMIF('Cap Table'!$Q$15:$Q$29,B16,'Cap Table'!$R$15:$R$29) | E16: =$C$5*C16 | F16: =(E16-D16)/D16
B17: =Dividends!B15 | C17: ='Cap Table'!T22 | D17: =SUMIF('Cap Table'!$B$15:$B$19,B17,'Cap Table'!$C$15:$C$19)+SUMIF('Cap Table'!$G$15:$G$23,B17,'Cap Table'!$H$15:$H$23)+SUMIF('Cap Table'!$L$15:$L$27,B17,'Cap Table'!$M$15:$M$27)+SUMIF('Cap Table'!$Q$15:$Q$29,B17,'Cap Table'!$R$15:$R$29) | E17: =$C$5*C17 | F17: =(E17-D17)/D17
B18: =Dividends!B16 | C18: ='Cap Table'!T23 | D18: =SUMIF('Cap Table'!$B$15:$B$19,B18,'Cap Table'!$C$15:$C$19)+SUMIF('Cap Table'!$G$15:$G$23,B18,'Cap Table'!$H$15:$H$23)+SUMIF('Cap Table'!$L$15:$L$27,B18,'Cap Table'!$M$15:$M$27)+SUMIF('Cap Table'!$Q$15:$Q$29,B18,'Cap Table'!$R$15:$R$29) | E18: =$C$5*C18 | F18: =(E18-D18)/D18
B19: =Dividends!B17 | C19: ='Cap Table'!T24 | D19: =SUMIF('Cap Table'!$B$15:$B$19,B19,'Cap Table'!$C$15:$C$19)+SUMIF('Cap Table'!$G$15:$G$23,B19,'Cap Table'!$H$15:$H$23)+SUMIF('Cap Table'!$L$15:$L$27,B19,'Cap Table'!$M$15:$M$27)+SUMIF('Cap Table'!$Q$15:$Q$29,B19,'Cap Table'!$R$15:$R$29) | E19: =$C$5*C19 | F19: =(E19-D19)/D19
B20: =Dividends!B18 | C20: ='Cap Table'!T25 | D20: =SUMIF('Cap Table'!$B$15:$B$19,B20,'Cap Table'!$C$15:$C$19)+SUMIF('Cap Table'!$G$15:$G$23,B20,'Cap Table'!$H$15:$H$23)+SUMIF('Cap Table'!$L$15:$L$27,B20,'Cap Table'!$M$15:$M$27)+SUMIF('Cap Table'!$Q$15:$Q$29,B20,'Cap Table'!$R$15:$R$29) | E20: =$C$5*C20 | F20: =(E20-D20)/D20
B21: =Dividends!B19 | C21: ='Cap Table'!T26 | D21: =SUMIF('Cap Table'!$B$15:$B$19,B21,'Cap Table'!$C$15:$C$19)+SUMIF('Cap Table'!$G$15:$G$23,B21,'Cap Table'!$H$15:$H$23)+SUMIF('Cap Table'!$L$15:$L$27,B21,'Cap Table'!$M$15:$M$27)+SUMIF('Cap Table'!$Q$15:$Q$29,B21,'Cap Table'!$R$15:$R$29) | E21: =$C$5*C21 | F21: =(E21-D21)/D21
B22: =Dividends!B20 | C22: ='Cap Table'!T27 | D22: =SUMIF('Cap Table'!$B$15:$B$19,B22,'Cap Table'!$C$15:$C$19)+SUMIF('Cap Table'!$G$15:$G$23,B22,'Cap Table'!$H$15:$H$23)+SUMIF('Cap Table'!$L$15:$L$27,B22,'Cap Table'!$M$15:$M$27)+SUMIF('Cap Table'!$Q$15:$Q$29,B22,'Cap Table'!$R$15:$R$29) | E22: =$C$5*C22 | F22: =(E22-D22)/D22
B23: =Dividends!B21 | C23: ='Cap Table'!T28 | D23: =SUMIF('Cap Table'!$B$15:$B$19,B23,'Cap Table'!$C$15:$C$19)+SUMIF('Cap Table'!$G$15:$G$23,B23,'Cap Table'!$H$15:$H$23)+SUMIF('Cap Table'!$L$15:$L$27,B23,'Cap Table'!$M$15:$M$27)+SUMIF('Cap Table'!$Q$15:$Q$29,B23,'Cap Table'!$R$15:$R$29) | E23: =$C$5*C23 | F23: =(E23-D23)/D23
B24: =Dividends!B22 | C24: ='Cap Table'!T29 | D24: =SUMIF('Cap Table'!$B$15:$B$19,B24,'Cap Table'!$C$15:$C$19)+SUMIF('Cap Table'!$G$15:$G$23,B24,'Cap Table'!$H$15:$H$23)+SUMIF('Cap Table'!$L$15:$L$27,B24,'Cap Table'!$M$15:$M$27)+SUMIF('Cap Table'!$Q$15:$Q$29,B24,'Cap Table'!$R$15:$R$29) | E24: =$C$5*C24 | F24: =(E24-D24)/D24
B25: =Dividends!B23

Sheet Data for charts
A1: =Settings!B4
A2: Month | B2: =EDATE(C2,-1) | C2: =Projections!$B$4 | D2: =EDATE(C2,1) | E2: =EDATE(D2,1) | F2: =EDATE(E2,1) | G2: =EDATE(F2,1) | H2: =EDATE(G2,1) | I2: =EDATE(H2,1) | J2: =EDATE(I2,1) | K2: =EDATE(J2,1) | ... CV2: =EDATE(CU2,1)
A4: USE OF FUNDS
A5: Development | B5: =SUMIF('Monthly forecast'!$B:$B,$A$5,'Monthly forecast'!D:D) | C5: =SUMIF('Monthly forecast'!$B:$B,$A$5,'Monthly forecast'!E:E) | D5: =SUMIF('Monthly forecast'!$B:$B,$A$5,'Monthly forecast'!F:F) | E5: =SUMIF('Monthly forecast'!$B:$B,$A$5,'Monthly forecast'!G:G) | F5: =SUMIF('Monthly forecast'!$B:$B,$A$5,'Monthly forecast'!H:H) | G5: =SUMIF('Monthly forecast'!$B:$B,$A$5,'Monthly forecast'!I:I) | H5: =SUMIF('Monthly forecast'!$B:$B,$A$5,'Monthly forecast'!J:J) | I5: =SUMIF('Monthly forecast'!$B:$B,$A$5,'Monthly forecast'!K:K) | J5: =SUMIF('Monthly forecast'!$B:$B,$A$5,'Monthly forecast'!L:L) | K5: =SUMIF('Monthly forecast'!$B:$B,$A$5,'Monthly forecast'!M:M) | L5: =SUMIF('Monthly forecast'!$B:$B,$A$5,'Monthly forecast'!N:N) | M5: =SUMIF('Monthly forecast'!$B:$B,$A$5,'Monthly forecast'!O:O) | N5: =SUMIF('Monthly forecast'!$B:$B,$A$5,'Monthly forecast'!P:P) | O5: =SUMIF('Monthly forecast'!$B:$B,$A$5,'Monthly forecast'!Q:Q) | P5: =SUMIF('Monthly forecast'!$B:$B,$A$5,'Monthly forecast'!R:R) | Q5: =SUMIF('Monthly forecast'!$B:$B,$A$5,'Monthly forecast'!S:S) | R5: =SUMIF('Monthly forecast'!$B:$B,$A$5,'Monthly forecast'!T:T) | S5: =SUMIF('Monthly forecast'!$B:$B,$A$5,'Monthly forecast'!U:U) | T5: =SUMIF('Monthly forecast'!$B:$B,$A$5,'Monthly forecast'!V:V) | U5: =SUMIF('Monthly forecast'!$B:$B,$A$5,'Monthly forecast'!W:W) | V5: =SUMIF('Monthly forecast'!$B:$B,$A$5,'Monthly forecast'!X:X) | W5: =SUMIF('Monthly forecast'!$B:$B,$A$5,'Monthly forecast'!Y:Y) | X5: =SUMIF('Monthly forecast'!$B:$B,$A$5,'Monthly forecast'!Z:Z) | Y5: =SUMIF('Monthly forecast'!$B:$B,$A$5,'Monthly forecast'!AA:AA) | Z5: =SUMIF('Monthly forecast'!$B:$B,$A$5,'Monthly forecast'!AB:AB) | AA5: =SUMIF('Monthly forecast'!$B:$B,$A$5,'Monthly forecast'!AC:AC) | AB5: =SUMIF('Monthly forecast'!$B:$B,$A$5,'Monthly forecast'!AD:AD) | AC5: =SUMIF('Monthly forecast'!$B:$B,$A$5,'Monthly forecast'!AE:AE) | AD5: =SUMIF('Monthly forecast'!$B:$B,$A$5,'Monthly forecast'!AF:AF) | AE5: =SUMIF('Monthly forecast'!$B:$B,$A$5,'Monthly forecast'!AG:AG) | AF5: =SUMIF('Monthly forecast'!$B:$B,$A$5,'Monthly forecast'!AH:AH) | AG5: =SUMIF('Monthly forecast'!$B:$B,$A$5,'Monthly forecast'!AI:AI) | AH5: =SUMIF('Monthly forecast'!$B:$B,$A$5,'Monthly forecast'!AJ:AJ) | AI5: =SUMIF('Monthly forecast'!$B:$B,$A$5,'Monthly forecast'!AK:AK) | AJ5: =SUMIF('Monthly forecast'!$B:$B,$A$5,'Monthly forecast'!AL:AL) | AK5: =SUMIF('Monthly forecast'!$B:$B,$A$5,'Monthly forecast'!AM:AM) | AL5: =SUMIF('Monthly forecast'!$B:$B,$A$5,'Monthly forecast'!AN:AN) | AM5: =SUMIF('Monthly forecast'!$B:$B,$A$5,'Monthly forecast'!AO:AO) | AN5: =SUMIF('Monthly forecast'!$B:$B,$A$5,'Monthly forecast'!AP:AP) | AO5: =SUMIF('Monthly forecast'!$B:$B,$A$5,'Monthly forecast'!AQ:AQ) | AP5: =SUMIF('Monthly forecast'!$B:$B,$A$5,'Monthly forecast'!AR:AR) | AQ5: =SUMIF('Monthly forecast'!$B:$B,$A$5,'Monthly forecast'!AS:AS) | AR5: =SUMIF('Monthly forecast'!$B:$B,$A$5,'Monthly forecast'!AT:AT) | AS5: =SUMIF('Monthly forecast'!$B:$B,$A$5,'Monthly forecast'!AU:AU) | AT5: =SUMIF('Monthly forecast'!$B:$B,$A$5,'Monthly forecast'!AV:AV) | AU5: =SUMIF('Monthly forecast'!$B:$B,$A$5,'Monthly forecast'!AW:AW) | AV5: =SUMIF('Monthly forecast'!$B:$B,$A$5,'Monthly forecast'!AX:AX) | AW5: =SUMIF('Monthly forecast'!$B:$B,$A$5,'Monthly forecast'!AY:AY) | AX5: =SUMIF('Monthly forecast'!$B:$B,$A$5,'Monthly forecast'!AZ:AZ) | AY5: =SUMIF('Monthly forecast'!$B:$B,$A$5,'Monthly forecast'!BA:BA) | AZ5: =SUMIF('Monthly forecast'!$B:$B,$A$5,'Monthly forecast'!BB:BB) | BA5: =SUMIF('Monthly forecast'!$B:$B,$A$5,'Monthly forecast'!BC:BC) | BB5: =SUMIF('Monthly forecast'!$B:$B,$A$5,'Monthly forecast'!BD:BD) | BC5: =SUMIF('Monthly forecast'!$B:$B,$A$5,'Monthly forecast'!BE:BE) | BD5: =SUMIF('Monthly forecast'!$B:$B,$A$5,'Monthly forecast'!BF:BF) | BE5: =SUMIF('Monthly forecast'!$B:$B,$A$5,'Monthly forecast'!BG:BG) | BF5: =SUMIF('Monthly forecast'!$B:$B,$A$5,'Monthly forecast'!BH:BH) | BG5: =SUMIF('Monthly forecast'!$B:$B,$A$5,'Monthly forecast'!BI:BI) | BH5: =SUMIF('Monthly forecast'!$B:$B,$A$5,'Monthly forecast'!BJ:BJ) | BI5: =SUMIF('Monthly forecast'!$B:$B,$A$5,'Monthly forecast'!BK:BK) | BJ5: =SUMIF('Monthly forecast'!$B:$B,$A$5,'Monthly forecast'!BL:BL) | BK5: =SUMIF('Monthly forecast'!$B:$B,$A$5,'Monthly forecast'!BM:BM) | BL5: =SUMIF('Monthly forecast'!$B:$B,$A$5,'Monthly forecast'!BN:BN) | BM5: =SUMIF('Monthly forecast'!$B:$B,$A$5,'Monthly forecast'!BO:BO) | BN5: =SUMIF('Monthly forecast'!$B:$B,$A$5,'Monthly forecast'!BP:BP) | BO5: =SUMIF('Monthly forecast'!$B:$B,$A$5,'Monthly forecast'!BQ:BQ) | BP5: =SUMIF('Monthly forecast'!$B:$B,$A$5,'Monthly forecast'!BR:BR) | BQ5: =SUMIF('Monthly forecast'!$B:$B,$A$5,'Monthly forecast'!BS:BS) | BR5: =SUMIF('Monthly forecast'!$B:$B,$A$5,'Monthly forecast'!BT:BT) | BS5: =SUMIF('Monthly forecast'!$B:$B,$A$5,'Monthly forecast'!BU:BU) | BT5: =SUMIF('Monthly forecast'!$B:$B,$A$5,'Monthly forecast'!BV:BV) | BU5: =SUMIF('Monthly forecast'!$B:$B,$A$5,'Monthly forecast'!BW:BW) | BV5: =SUMIF('Monthly forecast'!$B:$B,$A$5,'Monthly forecast'!BX:BX) | BW5: =SUMIF('Monthly forecast'!$B:$B,$A$5,'Monthly forecast'!BY:BY) | BX5: =SUMIF('Monthly forecast'!$B:$B,$A$5,'Monthly forecast'!BZ:BZ) | BY5: =SUMIF('Monthly forecast'!$B:$B,$A$5,'Monthly forecast'!CA:CA) | BZ5: =SUMIF('Monthly forecast'!$B:$B,$A$5,'Monthly forecast'!CB:CB) | CA5: =SUMIF('Monthly forecast'!$B:$B,$A$5,'Monthly forecast'!CC:CC) | CB5: =SUMIF('Monthly forecast'!$B:$B,$A$5,'Monthly forecast'!CD:CD) | CC5: =SUMIF('Monthly forecast'!$B:$B,$A$5,'Monthly forecast'!CE:CE) | CD5: =SUMIF('Monthly forecast'!$B:$B,$A$5,'Monthly forecast'!CF:CF) | CE5: =SUMIF('Monthly forecast'!$B:$B,$A$5,'Monthly forecast'!CG:CG) | CF5: =SUMIF('Monthly forecast'!$B:$B,$A$5,'Monthly forecast'!CH:CH) | CG5: =SUMIF('Monthly forecast'!$B:$B,$A$5,'Monthly forecast'!CI:CI) | CH5: =SUMIF('Monthly forecast'!$B:$B,$A$5,'Monthly forecast'!CJ:CJ) | CI5: =SUMIF('Monthly forecast'!$B:$B,$A$5,'Monthly forecast'!CK:CK) | CJ5: =SUMIF('Monthly forecast'!$B:$B,$A$5,'Monthly forecast'!CL:CL) | CK5: =SUMIF('Monthly forecast'!$B:$B,$A$5,'Monthly forecast'!CM:CM) | CL5: =SUMIF('Monthly forecast'!$B:$B,$A$5,'Monthly forecast'!CN:CN) | CM5: =SUMIF('Monthly forecast'!$B:$B,$A$5,'Monthly forecast'!CO:CO) | CN5: =SUMIF('Monthly forecast'!$B:$B,$A$5,'Monthly forecast'!CP:CP) | CO5: =SUMIF('Monthly forecast'!$B:$B,$A$5,'Monthly forecast'!CQ:CQ) | CP5: =SUMIF('Monthly forecast'!$B:$B,$A$5,'Monthly forecast'!CR:CR) | CQ5: =SUMIF('Monthly forecast'!$B:$B,$A$5,'Monthly forecast'!CS:CS) | CR5: =SUMIF('Monthly forecast'!$B:$B,$A$5,'Monthly forecast'!CT:CT) | CS5: =SUMIF('Monthly forecast'!$B:$B,$A$5,'Monthly forecast'!CU:CU) | CT5: =SUMIF('Monthly forecast'!$B:$B,$A$5,'Monthly forecast'!CV:CV) | CU5: =SUMIF('Monthly forecast'!$B:$B,$A$5,'Monthly forecast'!CW:CW) | CV5: =SUMIF('Monthly forecast'!$B:$B,$A$5,'Monthly forecast'!CX:CX)
A6: Marketing | B6: =SUMIF('Monthly forecast'!$B:$B,$A$6,'Monthly forecast'!D:D) | C6: =SUMIF('Monthly forecast'!$B:$B,$A$6,'Monthly forecast'!E:E) | D6: =SUMIF('Monthly forecast'!$B:$B,$A$6,'Monthly forecast'!F:F) | E6: =SUMIF('Monthly forecast'!$B:$B,$A$6,'Monthly forecast'!G:G) | F6: =SUMIF('Monthly forecast'!$B:$B,$A$6,'Monthly forecast'!H:H) | G6: =SUMIF('Monthly forecast'!$B:$B,$A$6,'Monthly forecast'!I:I) | H6: =SUMIF('Monthly forecast'!$B:$B,$A$6,'Monthly forecast'!J:J) | I6: =SUMIF('Monthly forecast'!$B:$B,$A$6,'Monthly forecast'!K:K) | J6: =SUMIF('Monthly forecast'!$B:$B,$A$6,'Monthly forecast'!L:L) | K6: =SUMIF('Monthly forecast'!$B:$B,$A$6,'Monthly forecast'!M:M) | L6: =SUMIF('Monthly forecast'!$B:$B,$A$6,'Monthly forecast'!N:N) | M6: =SUMIF('Monthly forecast'!$B:$B,$A$6,'Monthly forecast'!O:O) | N6: =SUMIF('Monthly forecast'!$B:$B,$A$6,'Monthly forecast'!P:P) | O6: =SUMIF('Monthly forecast'!$B:$B,$A$6,'Monthly forecast'!Q:Q) | P6: =SUMIF('Monthly forecast'!$B:$B,$A$6,'Monthly forecast'!R:R) | Q6: =SUMIF('Monthly forecast'!$B:$B,$A$6,'Monthly forecast'!S:S) | R6: =SUMIF('Monthly forecast'!$B:$B,$A$6,'Monthly forecast'!T:T) | S6: =SUMIF('Monthly forecast'!$B:$B,$A$6,'Monthly forecast'!U:U) | T6: =SUMIF('Monthly forecast'!$B:$B,$A$6,'Monthly forecast'!V:V) | U6: =SUMIF('Monthly forecast'!$B:$B,$A$6,'Monthly forecast'!W:W) | V6: =SUMIF('Monthly forecast'!$B:$B,$A$6,'Monthly forecast'!X:X) | W6: =SUMIF('Monthly forecast'!$B:$B,$A$6,'Monthly forecast'!Y:Y) | X6: =SUMIF('Monthly forecast'!$B:$B,$A$6,'Monthly forecast'!Z:Z) | Y6: =SUMIF('Monthly forecast'!$B:$B,$A$6,'Monthly forecast'!AA:AA) | Z6: =SUMIF('Monthly forecast'!$B:$B,$A$6,'Monthly forecast'!AB:AB) | AA6: =SUMIF('Monthly forecast'!$B:$B,$A$6,'Monthly forecast'!AC:AC) | AB6: =SUMIF('Monthly forecast'!$B:$B,$A$6,'Monthly forecast'!AD:AD) | AC6: =SUMIF('Monthly forecast'!$B:$B,$A$6,'Monthly forecast'!AE:AE) | AD6: =SUMIF('Monthly forecast'!$B:$B,$A$6,'Monthly forecast'!AF:AF) | AE6: =SUMIF('Monthly forecast'!$B:$B,$A$6,'Monthly forecast'!AG:AG) | AF6: =SUMIF('Monthly forecast'!$B:$B,$A$6,'Monthly forecast'!AH:AH) | AG6: =SUMIF('Monthly forecast'!$B:$B,$A$6,'Monthly forecast'!AI:AI) | AH6: =SUMIF('Monthly forecast'!$B:$B,$A$6,'Monthly forecast'!AJ:AJ) | AI6: =SUMIF('Monthly forecast'!$B:$B,$A$6,'Monthly forecast'!AK:AK) | AJ6: =SUMIF('Monthly forecast'!$B:$B,$A$6,'Monthly forecast'!AL:AL) | AK6: =SUMIF('Monthly forecast'!$B:$B,$A$6,'Monthly forecast'!AM:AM) | AL6: =SUMIF('Monthly forecast'!$B:$B,$A$6,'Monthly forecast'!AN:AN) | AM6: =SUMIF('Monthly forecast'!$B:$B,$A$6,'Monthly forecast'!AO:AO) | AN6: =SUMIF('Monthly forecast'!$B:$B,$A$6,'Monthly forecast'!AP:AP) | AO6: =SUMIF('Monthly forecast'!$B:$B,$A$6,'Monthly forecast'!AQ:AQ) | AP6: =SUMIF('Monthly forecast'!$B:$B,$A$6,'Monthly forecast'!AR:AR) | AQ6: =SUMIF('Monthly forecast'!$B:$B,$A$6,'Monthly forecast'!AS:AS) | AR6: =SUMIF('Monthly forecast'!$B:$B,$A$6,'Monthly forecast'!AT:AT) | AS6: =SUMIF('Monthly forecast'!$B:$B,$A$6,'Monthly forecast'!AU:AU) | AT6: =SUMIF('Monthly forecast'!$B:$B,$A$6,'Monthly forecast'!AV:AV) | AU6: =SUMIF('Monthly forecast'!$B:$B,$A$6,'Monthly forecast'!AW:AW) | AV6: =SUMIF('Monthly forecast'!$B:$B,$A$6,'Monthly forecast'!AX:AX) | AW6: =SUMIF('Monthly forecast'!$B:$B,$A$6,'Monthly forecast'!AY:AY) | AX6: =SUMIF('Monthly forecast'!$B:$B,$A$6,'Monthly forecast'!AZ:AZ) | AY6: =SUMIF('Monthly forecast'!$B:$B,$A$6,'Monthly forecast'!BA:BA) | AZ6: =SUMIF('Monthly forecast'!$B:$B,$A$6,'Monthly forecast'!BB:BB) | BA6: =SUMIF('Monthly forecast'!$B:$B,$A$6,'Monthly forecast'!BC:BC) | BB6: =SUMIF('Monthly forecast'!$B:$B,$A$6,'Monthly forecast'!BD:BD) | BC6: =SUMIF('Monthly forecast'!$B:$B,$A$6,'Monthly forecast'!BE:BE) | BD6: =SUMIF('Monthly forecast'!$B:$B,$A$6,'Monthly forecast'!BF:BF) | BE6: =SUMIF('Monthly forecast'!$B:$B,$A$6,'Monthly forecast'!BG:BG) | BF6: =SUMIF('Monthly forecast'!$B:$B,$A$6,'Monthly forecast'!BH:BH) | BG6: =SUMIF('Monthly forecast'!$B:$B,$A$6,'Monthly forecast'!BI:BI) | BH6: =SUMIF('Monthly forecast'!$B:$B,$A$6,'Monthly forecast'!BJ:BJ) | BI6: =SUMIF('Monthly forecast'!$B:$B,$A$6,'Monthly forecast'!BK:BK) | BJ6: =SUMIF('Monthly forecast'!$B:$B,$A$6,'Monthly forecast'!BL:BL) | BK6: =SUMIF('Monthly forecast'!$B:$B,$A$6,'Monthly forecast'!BM:BM) | BL6: =SUMIF('Monthly forecast'!$B:$B,$A$6,'Monthly forecast'!BN:BN) | BM6: =SUMIF('Monthly forecast'!$B:$B,$A$6,'Monthly forecast'!BO:BO) | BN6: =SUMIF('Monthly forecast'!$B:$B,$A$6,'Monthly forecast'!BP:BP) | BO6: =SUMIF('Monthly forecast'!$B:$B,$A$6,'Monthly forecast'!BQ:BQ) | BP6: =SUMIF('Monthly forecast'!$B:$B,$A$6,'Monthly forecast'!BR:BR) | BQ6: =SUMIF('Monthly forecast'!$B:$B,$A$6,'Monthly forecast'!BS:BS) | BR6: =SUMIF('Monthly forecast'!$B:$B,$A$6,'Monthly forecast'!BT:BT) | BS6: =SUMIF('Monthly forecast'!$B:$B,$A$6,'Monthly forecast'!BU:BU) | BT6: =SUMIF('Monthly forecast'!$B:$B,$A$6,'Monthly forecast'!BV:BV) | BU6: =SUMIF('Monthly forecast'!$B:$B,$A$6,'Monthly forecast'!BW:BW) | BV6: =SUMIF('Monthly forecast'!$B:$B,$A$6,'Monthly forecast'!BX:BX) | BW6: =SUMIF('Monthly forecast'!$B:$B,$A$6,'Monthly forecast'!BY:BY) | BX6: =SUMIF('Monthly forecast'!$B:$B,$A$6,'Monthly forecast'!BZ:BZ) | BY6: =SUMIF('Monthly forecast'!$B:$B,$A$6,'Monthly forecast'!CA:CA) | BZ6: =SUMIF('Monthly forecast'!$B:$B,$A$6,'Monthly forecast'!CB:CB) | CA6: =SUMIF('Monthly forecast'!$B:$B,$A$6,'Monthly forecast'!CC:CC) | CB6: =SUMIF('Monthly forecast'!$B:$B,$A$6,'Monthly forecast'!CD:CD) | CC6: =SUMIF('Monthly forecast'!$B:$B,$A$6,'Monthly forecast'!CE:CE) | CD6: =SUMIF('Monthly forecast'!$B:$B,$A$6,'Monthly forecast'!CF:CF) | CE6: =SUMIF('Monthly forecast'!$B:$B,$A$6,'Monthly forecast'!CG:CG) | CF6: =SUMIF('Monthly forecast'!$B:$B,$A$6,'Monthly forecast'!CH:CH) | CG6: =SUMIF('Monthly forecast'!$B:$B,$A$6,'Monthly forecast'!CI:CI) | CH6: =SUMIF('Monthly forecast'!$B:$B,$A$6,'Monthly forecast'!CJ:CJ) | CI6: =SUMIF('Monthly forecast'!$B:$B,$A$6,'Monthly forecast'!CK:CK) | CJ6: =SUMIF('Monthly forecast'!$B:$B,$A$6,'Monthly forecast'!CL:CL) | CK6: =SUMIF('Monthly forecast'!$B:$B,$A$6,'Monthly forecast'!CM:CM) | CL6: =SUMIF('Monthly forecast'!$B:$B,$A$6,'Monthly forecast'!CN:CN) | CM6: =SUMIF('Monthly forecast'!$B:$B,$A$6,'Monthly forecast'!CO:CO) | CN6: =SUMIF('Monthly forecast'!$B:$B,$A$6,'Monthly forecast'!CP:CP) | CO6: =SUMIF('Monthly forecast'!$B:$B,$A$6,'Monthly forecast'!CQ:CQ) | CP6: =SUMIF('Monthly forecast'!$B:$B,$A$6,'Monthly forecast'!CR:CR) | CQ6: =SUMIF('Monthly forecast'!$B:$B,$A$6,'Monthly forecast'!CS:CS) | CR6: =SUMIF('Monthly forecast'!$B:$B,$A$6,'Monthly forecast'!CT:CT) | CS6: =SUMIF('Monthly forecast'!$B:$B,$A$6,'Monthly forecast'!CU:CU) | CT6: =SUMIF('Monthly forecast'!$B:$B,$A$6,'Monthly forecast'!CV:CV) | CU6: =SUMIF('Monthly forecast'!$B:$B,$A$6,'Monthly forecast'!CW:CW) | CV6: =SUMIF('Monthly forecast'!$B:$B,$A$6,'Monthly forecast'!CX:CX)
