Workbook

Sheet Description
B1: Сайт: | C1: https://anastasianikolaeva.com/ | D1: Телеграм: | E1: https://t.me/anikolayeva
C2: Материалы этого файла могут быть использованы только лицом, купившим данный материал на сайте https://anastasianikolaeva.com/, в целях индивидуального обучения и развития своих бизнес-проектов. Массовое распространение данного материала, продажа и передача 3м лицам являются нарушением авторского права. Если вы хотите порекомендовать материалы своим коллегам, партнерам и друзьям, поделитесь ссылкой на сайт: https://anastasianikolaeva.com/
B3: Если вы хотите получить консультацию или заказать разработку финансовой модели для вашей компании, запишитесь на пробную бесплатную консультацию здесь: https://anastasianikolaeva.com/#expressform
B4: Финансовая модель
B6: Данный шаблон разработан для прогнозирования доходов и расходов компании, продающей цифровые решения по модели "Подписка". Мы рассматриваем 3 потока дохода, которые основаны на способе привлечения клиентов: наиболее популярных способа монетизации для такого продукта: "Самостоятельное приобретение подписки", "Входящие продажи" и "Исходящие продажи". Эта финансовая модель позволяет спрогнозировать точку безубыточности и оценить сумму необходимых инвестиций. Модель автоматически рассчитывает прогноз для вашего бизнеса во вкладках "Monthly forecast", "P&L | Cash Flow | Balance", "Unit Economics" и визуализирует их в "Charts" "For Pitchdeck" на основании данных, введенных на вкладках "Settings", "Roadmap", "Payroll", "Projections".
B9: Инструкции
B11: 1000 | D11: Синим шрифтом выделены поля, куда вносятся данные.
B12: 2000 | D12: Черным шрифтом выделены поля, в которых вычисления производятся по формулам.
B13: Incorporation | D13: В выпадающих списках заданы списки параметров, выбор которых влияет на расчеты в модели.
B14: Вкладка "Setting" | D14: В этой вкладке задаются общие параметры бизнеса. На основании указанных здесь налоговых ставок рассчитывается налог на прибыль во вкладке "P&L and Cash Flow" и налог на заработную плату во вкладке "Payroll".
B15: Вкладка "Roadmap" | D15: В этой вкладке перечисляются события дорожной карты бизнеса, которые будут влиять на динамику доходов и расходов компании. Здесь нужно перечислить такие события и указать их плановые даты. Даты можно задать, указав, через сколько месяцев после привлечения инвестиций произойдет событие. Перечисленные в этой вкладке события попадают в выпадающие списки на вкладках "Payroll" и "Projections". Благодаря этому вы можете привязывать появление новых затрат или доходов и найм определенных сотрудников к событиям в вашей дорожной карте. В зависимости от выбранного события во вкладках "Payroll" и "Projections" автоматически проставляются даты, начиная с которых возникают отдельные доходы и расходы, а во вкладке "Monthly Forecast" начинают учитываться эти данные с нужного месяца.
B16: Вкладка "Payroll" | D16: В этой вкладке вносятся все позиции наемных сотрудников, которые неоходимы вашему бизнесу, их зарплаты, события, при которых они нанимаются, и динамика увеличения зарплат. Здесь нужно внести названия должностей, размер зарплат, выбрать событие из дорожной карты, при котором происходит найм, указать планируемый процент ежегодного увеличения зарплат. Общие затраты на сотрудника с учетом налогов рассчитаются на основании ставки, указанной в "Settings", даты найма проставятся из "Roadmap" на основании выбранного события.
B17: Вкладка "Projections" | D17: В этой вкладке вносятся вводные данные для формирования всех потоков доходов и расходов. Здесь перечисляются все статьи доходов и расходов, задаются их значения, стартовые даты, периодичность и методы расчета динамики. При этом начало возникновения различных статей доходов и расходов связано с событиями дорожной карты, а генерация доходов зависит от прямых расходов, приводящих к продажам. На основании внесенных здесь значений формируется прогноз во вкладке "Monthly forecast".
B18: Вкладка "Monthly Forecast" | D18: В этой вкладке формируется подробный финансовый прогноз бизнеса по месяцам. Все расчеты производятся на основании данных, внесенных во вкладки "Settings", "Roadmap", "Payroll", "Projections" по заданным формулам. В этой вкладке ничего вносить не нужно.
B19: Вкладка "Unit Economics" | D19: В этой вкладке формируется расчет юнит экономики отдельно для каждого варианта монетизации. Расчитывается LTV продукта, CAC (стоимость привлечения клиента), отношение LTV к CAC.
B20: Вкладка "P&L and Cash Flow" | D20: В этой вкладке формируются финансовые отчеты P&L (Прибыли и убытки) и Cash Flow (Денежный поток) по месяцам. Все расчеты производятся на основании данных вкладки "Monthly forecast" по заданным формулам. В этой вкладке ничего вносить не нужно.
B21: Вкладка "For Pitchdeck" | D21: В этой вкладке формируется таблица с динамикой выручки, операционной прибыли (EBITDA) и чистой прибыли по годам и строятся графики для лаконичной визуализации. Таблицу и график из этой вкладки можно скопировать на слайд с финансовой информацией питчдека вашего проекта для презентации инвесторам и партнерам.
B22: Вкладка "Cap Table" | D22: В этой вкладке вносится информация о всех держателях акций компании, привлеченных инвестициях по раундам, планируемой оценке стоимости компании и рассчитываются доли всех участников в динамике по раундам.
B23: Вкладка "Dividends" | D23: В этой вкладке рассчитываются начисленные дивиденды по годам для всех держателей акций компании исходя из прогнозируемой чистой прибыли в соответствии с долями, указанными на вкладке "Cap Table".
B24: Вкладка "Exit scenarios" | D24: В этой вкладке описывается предполагаемый сценарий выхода из компании (как пример приводится продажа компании в виде стратегического поглощения), задается планируемая стоимость продажи компании и предполагаемый год сделки. Рассчитывается доход каждого владельца акций компании при условии продажи всех акции, сумма вложенных инвестиций и ROI при выходе.
... B26: Вкладка "Data for Charts" | D26: Вспомогательная вкладка для упрощения создания графиков для вкладки "Charts". Вынесение данных, для которых необходима визуализация, на отдельную вкладку, помогает избежать ошибок и сделать модель понятнее как для команды проекта, так и для внешних партнеров (например, инвесторов). Все данные расчитываются по формулам на основании остальных вкладок. При необходимости, вы можете вынести сюда и другие метрики, по которым хотите постоить дополнительные графики для вашего бизнеса.

Sheet Settings
A2: GENERAL SETTINGS
A4: Company name | B4: Healthy4U
A5: Currency | B5: USD
A6: Country of incorporation | B6: Israel
A7: Income tax rate | B7: 0.23
A8: Payroll tax rate | B8: 0.35
A9: Tax Payment Month | B9: 3
A10: Cash in bank at start | B10: 0

Sheet Roadmap
A1: =Settings!$B$4 -> Healthy4U
A2: ROADMAP
A4: Growth driving events
B6: Type | C6: Date | D6: Months after seed round
A7: Incorporation | B7: incorporation | C7: 45139 | D7: 0
A8: B2B solution: MVP release | B8: new product | C8: 45884 | D8: 0
A9: B2B solution: 5 clients | B9: monetization | C9: 45899 | D9: 0
A10: Pre-seed round money transfer | B10: fundraising | C10: 45901 | D10: 0
A11: B2B solution: v.1 release | B11: new feature | C11: =if(D11>0,EDATE($C$10,D11),"not set") -> 45962 | D11: 2
A12: Android App for B2B | B12: new feature | C12: =if(D12>0,EDATE($C$11,D12),"not set") -> 46082 | D12: 4
A13: B2B solution: 50 clients | B13: monetization | C13: =if(D13>0,EDATE($C$11,D13),"not set") -> 46143 | D13: 6
A14: B2B solution: 100 clients | B14: fundraising | C14: =if(D14>0,EDATE($C$11,D14),"not set") -> 46235 | D14: 9
A15: Seed round money transfer | B15: fundraising | C15: =if(D15>0,EDATE($C$11,D15),"not set") -> 46266 | D15: 10
A16: EU expansion | B16: new region | C16: =if(D16>0,EDATE($C$11,D16),"not set") -> 46327 | D16: 12

Sheet Payroll
A1: =Settings!$B$4 -> Healthy4U
A2: PAYROLL
D4: Monthly salary | E4: Payroll taxes | F4: Monthly cost to company | G4: Annaul salary | H4: Start event in the roadmap | I4: Hire date | J4: Annual salary increase
A5: Administrative
A6: CEO | D6: 5000 | E6: =Settings!$B$8 -> 0.35 | F6: =D6/(1-E6) -> 7692.3077 | G6: =D6*12 -> 60000 | H6: Pre-seed round money transfer | I6: =IFERROR(VLOOKUP(H6,Roadmap!$A$7:$D$110,3,0),"not set, choose the event") -> 45901 | J6: 0.02 | K6: 12
A7: CFO | D7: 0 | E7: =Settings!$B$8 -> 0.35 | F7: =D7/(1-E7) -> 0 | G7: =D7*12 -> 0 | H7: B2B solution: 5 clients | I7: =IFERROR(VLOOKUP(H7,Roadmap!$A$7:$D$110,3,0),"not set, choose the event") -> 45899 | J7: 0 | K7: 12
A8: COO | D8: 0 | E8: =Settings!$B$8 -> 0.35 | F8: =D8/(1-E8) -> 0 | G8: =D8*12 -> 0 | H8: B2B solution: 100 clients | I8: =IFERROR(VLOOKUP(H8,Roadmap!$A$7:$D$110,3,0),"not set, choose the event") -> 46235 | J8: 0 | K8: 12
A9: HRD | D9: 0 | E9: =Settings!$B$8 -> 0.35 | F9: =D9/(1-E9) -> 0 | G9: =D9*12 -> 0 | I9: =IFERROR(VLOOKUP(H9,Roadmap!$A$7:$D$110,3,0),"not set, choose the event") -> not set, choose the event | J9: 0 | K9: 12
A10: Operations Coordinator / Office Manager | D10: 0 | E10: =Settings!$B$8 -> 0.35 | F10: =D10/(1-E10) -> 0 | G10: =D10*12 -> 0 | I10: =IFERROR(VLOOKUP(H10,Roadmap!$A$7:$D$110,3,0),"not set, choose the event") -> not set, choose the event | J10: 0 | K10: 12
A11: Employee 1 | D11: 0 | E11: =Settings!$B$8 -> 0.35 | F11: =D11/(1-E11) -> 0 | G11: =D11*12 -> 0 | I11: =IFERROR(VLOOKUP(H11,Roadmap!$A$7:$D$110,3,0),"not set, choose the event") -> not set, choose the event | J11: 0 | K11: 12
A12: Employee 2 | D12: 0 | E12: =Settings!$B$8 -> 0.35 | F12: =D12/(1-E12) -> 0 | G12: =D12*12 -> 0 | I12: =IFERROR(VLOOKUP(H12,Roadmap!$A$7:$D$110,3,0),"not set, choose the event") -> not set, choose the event | J12: 0 | K12: 12
A13: Employee 3 | D13: 0 | E13: =Settings!$B$8 -> 0.35 | F13: =D13/(1-E13) -> 0 | G13: =D13*12 -> 0 | I13: =IFERROR(VLOOKUP(H13,Roadmap!$A$7:$D$110,3,0),"not set, choose the event") -> not set, choose the event | J13: 0 | K13: 12
A14: Employee 4 | D14: 0 | E14: =Settings!$B$8 -> 0.35 | F14: =D14/(1-E14) -> 0 | G14: =D14*12 -> 0 | I14: =IFERROR(VLOOKUP(H14,Roadmap!$A$7:$D$110,3,0),"not set, choose the event") -> not set, choose the event | J14: 0 | K14: 12
A16: IT
A17: CTO | D17: 10000 | E17: =Settings!$B$8 -> 0.35 | F17: =D17/(1-E17) -> 15384.615 | G17: =D17*12 -> 120000 | H17: Seed round money transfer | I17: =IFERROR(VLOOKUP(H17,Roadmap!$A$7:$D$110,3,0),"not set, choose the event") -> 46266 | J17: 0 | K17: 12
A18: Developer frontend | D18: 4000 | E18: =Settings!$B$8 -> 0.35 | F18: =D18/(1-E18) -> 6153.8462 | G18: =D18*12 -> 48000 | H18: Seed round money transfer | I18: =IFERROR(VLOOKUP(H18,Roadmap!$A$7:$D$110,3,0),"not set, choose the event") -> 46266 | J18: 0.04 | K18: 12
A19: Developer backend | D19: 0 | E19: =Settings!$B$8 -> 0.35 | F19: =D19/(1-E19) -> 0 | G19: =D19*12 -> 0 | I19: =IFERROR(VLOOKUP(H19,Roadmap!$A$7:$D$110,3,0),"not set, choose the event") -> not set, choose the event | J19: 0 | K19: 12
A20: Developer fullstack | D20: 0 | E20: =Settings!$B$8 -> 0.35 | F20: =D20/(1-E20) -> 0 | G20: =D20*12 -> 0 | I20: =IFERROR(VLOOKUP(H20,Roadmap!$A$7:$D$110,3,0),"not set, choose the event") -> not set, choose the event | J20: 0 | K20: 12
A21: UX designer | D21: 3500 | E21: =Settings!$B$8 -> 0.35 | F21: =D21/(1-E21) -> 5384.6154 | G21: =D21*12 -> 42000 | I21: =IFERROR(VLOOKUP(H21,Roadmap!$A$7:$D$110,3,0),"not set, choose the event") -> not set, choose the event | J21: 0 | K21: 12
A22: Product manager | D22: 0 | E22: =Settings!$B$8 -> 0.35 | F22: =D22/(1-E22) -> 0 | G22: =D22*12 -> 0 | I22: =IFERROR(VLOOKUP(H22,Roadmap!$A$7:$D$110,3,0),"not set, choose the event") -> not set, choose the event | J22: 0 | K22: 12
A23: DevOps | D23: 0 | E23: =Settings!$B$8 -> 0.35 | F23: =D23/(1-E23) -> 0 | G23: =D23*12 -> 0 | I23: =IFERROR(VLOOKUP(H23,Roadmap!$A$7:$D$110,3,0),"not set, choose the event") -> not set, choose the event | J23: 0 | K23: 12
A24: Project Manager | D24: 0 | E24: =Settings!$B$8 -> 0.35 | F24: =D24/(1-E24) -> 0 | G24: =D24*12 -> 0 | I24: =IFERROR(VLOOKUP(H24,Roadmap!$A$7:$D$110,3,0),"not set, choose the event") -> not set, choose the event | J24: 0 | K24: 12
A25: Developer cross-platform | D25: 0 | E25: =Settings!$B$8 -> 0.35 | F25: =D25/(1-E25) -> 0 | G25: =D25*12 -> 0 | I25: =IFERROR(VLOOKUP(H25,Roadmap!$A$7:$D$110,3,0),"not set, choose the event") -> not set, choose the event | J25: 0 | K25: 12
A26: QA | D26: 0 | E26: =Settings!$B$8 -> 0.35 | F26: =D26/(1-E26) -> 0 | G26: =D26*12 -> 0 | I26: =IFERROR(VLOOKUP(H26,Roadmap!$A$7:$D$110,3,0),"not set, choose the event") -> not set, choose the event | J26: 0 | K26: 12
A27: Security engineer | D27: 0 | E27: =Settings!$B$8 -> 0.35 | F27: =D27/(1-E27) -> 0 | G27: =D27*12 -> 0 | I27: =IFERROR(VLOOKUP(H27,Roadmap!$A$7:$D$110,3,0),"not set, choose the event") -> not set, choose the event | J27: 0 | K27: 12
A28: Employee 4 | D28: 0 | E28: =Settings!$B$8 -> 0.35 | F28: =D28/(1-E28) -> 0 | G28: =D28*12 -> 0 | I28: =IFERROR(VLOOKUP(H28,Roadmap!$A$7:$D$110,3,0),"not set, choose the event") -> not set, choose the event | J28: 0 | K28: 12
A30: Marketing
A31: Head of Marketing | D31: 3000 | E31: =Settings!$B$8 -> 0.35 | F31: =D31/(1-E31) -> 4615.3846 | G31: =D31*12 -> 36000 | H31: Seed round money transfer | I31: =IFERROR(VLOOKUP(H31,Roadmap!$A$7:$D$110,3,0),"not set, choose the event") -> 46266 | J31: 0.04 | K31: 12
A32: Content Marketing Manager | D32: 0 | E32: =Settings!$B$8 -> 0.35 | F32: =D32/(1-E32) -> 0 | G32: =D32*12 -> 0 | I32: =IFERROR(VLOOKUP(H32,Roadmap!$A$7:$D$110,3,0),"not set, choose the event") -> not set, choose the event | J32: 0 | K32: 12
A33: Performance Marketing Manager | D33: 0 | E33: =Settings!$B$8 -> 0.35 | F33: =D33/(1-E33) -> 0 | G33: =D33*12 -> 0 | I33: =IFERROR(VLOOKUP(H33,Roadmap!$A$7:$D$110,3,0),"not set, choose the event") -> not set, choose the event | J33: 0 | K33: 12
A34: Community Manager / SMM | D34: 0 | E34: =Settings!$B$8 -> 0.35 | F34: =D34/(1-E34) -> 0 | G34: =D34*12 -> 0 | I34: =IFERROR(VLOOKUP(H34,Roadmap!$A$7:$D$110,3,0),"not set, choose the event") -> not set, choose the event | J34: 0 | K34: 12
A35: PR / Comms Manager | D35: 0 | E35: =Settings!$B$8 -> 0.35 | F35: =D35/(1-E35) -> 0 | G35: =D35*12 -> 0 | I35: =IFERROR(VLOOKUP(H35,Roadmap!$A$7:$D$110,3,0),"not set, choose the event") -> not set, choose the event | J35: 0 | K35: 12
A36: Marketing Designer | D36: 0 | E36: =Settings!$B$8 -> 0.35 | F36: =D36/(1-E36) -> 0 | G36: =D36*12 -> 0 | I36: =IFERROR(VLOOKUP(H36,Roadmap!$A$7:$D$110,3,0),"not set, choose the event") -> not set, choose the event | J36: 0 | K36: 12
A37: Employee 3 | D37: 0 | E37: =Settings!$B$8 -> 0.35 | F37: =D37/(1-E37) -> 0 | G37: =D37*12 -> 0 | I37: =IFERROR(VLOOKUP(H37,Roadmap!$A$7:$D$110,3,0),"not set, choose the event") -> not set, choose the event | J37: 0 | K37: 12
A38: Employee 4 | D38: 0 | E38: =Settings!$B$8 -> 0.35 | F38: =D38/(1-E38) -> 0 | G38: =D38*12 -> 0 | I38: =IFERROR(VLOOKUP(H38,Roadmap!$A$7:$D$110,3,0),"not set, choose the event") -> not set, choose the event | J38: 0 | K38: 12
A40: Sales
A41: Head of Sales | D41: 5000 | E41: =Settings!$B$8 -> 0.35 | F41: =D41/(1-E41) -> 7692.3077 | G41: =D41*12 -> 60000 | H41: Incorporation | I41: =IFERROR(VLOOKUP(H41,Roadmap!$A$7:$D$110,3,0),"not set, choose the event") -> 45139 | J41: 0.02 | K41: 12
A42: BDM | D42: 5000 | E42: =Settings!$B$8 -> 0.35 | F42: =D42/(1-E42) -> 7692.3077 | G42: =D42*12 -> 60000 | H42: Incorporation | I42: =IFERROR(VLOOKUP(H42,Roadmap!$A$7:$D$110,3,0),"not set, choose the event") -> 45139 | J42: 0.02 | K42: 12
A43: Partnerships Manager | D43: 1000 | E43: =Settings!$B$8 -> 0.35 | F43: =D43/(1-E43) -> 1538.4615 | G43: =D43*12 -> 12000 | H43: Incorporation | I43: =IFERROR(VLOOKUP(H43,Roadmap!$A$7:$D$110,3,0),"not set, choose the event") -> 45139 | J43: 0.02 | K43: 12
A44: Inbound Sales Manager | D44: 1000 | E44: =Settings!$B$8 -> 0.35 | F44: =D44/(1-E44) -> 1538.4615 | G44: =D44*12 -> 12000 | H44: Incorporation | I44: =IFERROR(VLOOKUP(H44,Roadmap!$A$7:$D$110,3,0),"not set, choose the event") -> 45139 | J44: 0.02 | K44: 12
A45: SDR | D45: 1000 | E45: =Settings!$B$8 -> 0.35 | F45: =D45/(1-E45) -> 1538.4615 | G45: =D45*12 -> 12000 | H45: Incorporation | I45: =IFERROR(VLOOKUP(H45,Roadmap!$A$7:$D$110,3,0),"not set, choose the event") -> 45139 | J45: 0.02 | K45: 12
A46: Employee | D46: 0 | E46: =Settings!$B$8 -> 0.35 | F46: =D46/(1-E46) -> 0 | G46: =D46*12 -> 0 | H46: Incorporation | I46: =IFERROR(VLOOKUP(H46,Roadmap!$A$7:$D$110,3,0),"not set, choose the event") -> 45139 | J46: 0.02 | K46: 12
A48: Customer Success & Support
A49: Head of Customer Success | D49: 1000 | E49: =Settings!$B$8 -> 0.35 | F49: =D49/(1-E49) -> 1538.4615 | G49: =D49*12 -> 12000 | H49: Seed round money transfer | I49: =IFERROR(VLOOKUP(H49,Roadmap!$A$7:$D$110,3,0),"not set, choose the event") -> 46266 | J49: 0 | K49: 12
A50: Customer Success / Account Manager | D50: 1000 | E50: =Settings!$B$8 -> 0.35 | F50: =D50/(1-E50) -> 1538.4615 | G50: =D50*12 -> 12000 | H50: Seed round money transfer | I50: =IFERROR(VLOOKUP(H50,Roadmap!$A$7:$D$110,3,0),"not set, choose the event") -> 46266 | J50: 0 | K50: 12
A51: Onboarding manager | D51: 0 | E51: =Settings!$B$8 -> 0.35 | F51: =D51/(1-E51) -> 0 | G51: =D51*12 -> 0 | I51: =IFERROR(VLOOKUP(H51,Roadmap!$A$7:$D$110,3,0),"not set, choose the event") -> not set, choose the event | J51: 0 | K51: 12
A52: Technical Support Specialist 1 | D52: 0 | E52: =Settings!$B$8 -> 0.35 | F52: =D52/(1-E52) -> 0 | G52: =D52*12 -> 0 | I52: =IFERROR(VLOOKUP(H52,Roadmap!$A$7:$D$110,3,0),"not set, choose the event") -> not set, choose the event | J52: 0 | K52: 12
A53: Technical Support Specialist 2 | D53: 0 | E53: =Settings!$B$8 -> 0.35 | F53: =D53/(1-E53) -> 0 | G53: =D53*12 -> 0 | I53: =IFERROR(VLOOKUP(H53,Roadmap!$A$7:$D$110,3,0),"not set, choose the event") -> not set, choose the event | J53: 0 | K53: 12
A54: Project manager CS | D54: 0 | E54: =Settings!$B$8 -> 0.35 | F54: =D54/(1-E54) -> 0 | G54: =D54*12 -> 0 | I54: =IFERROR(VLOOKUP(H54,Roadmap!$A$7:$D$110,3,0),"not set, choose the event") -> not set, choose the event | J54: 0 | K54: 12
A55: Account Manager | D55: 8000 | E55: =Settings!$B$8 -> 0.35 | F55: =D55/(1-E55) -> 12307.692 | G55: =D55*12 -> 96000 | H55: B2B solution: 50 clients | I55: =IFERROR(VLOOKUP(H55,Roadmap!$A$7:$D$110,3,0),"not set, choose the event") -> 46143 | J55: 0 | K55: 12
A56: Employee 4 | D56: 0 | E56: =Settings!$B$8 -> 0.35 | F56: =D56/(1-E56) -> 0 | G56: =D56*12 -> 0 | I56: =IFERROR(VLOOKUP(H56,Roadmap!$A$7:$D$110,3,0),"not set, choose the event") -> not set, choose the event | J56: 0 | K56: 12

Sheet Projections
A1: =Settings!$B$4 -> Healthy4U
A2: START
A4: INCORPORATION | B4: =Roadmap!C7 -> 45139
A5: SEED ROUND MONEY TRANSFER | B5: =Roadmap!C8 -> 45884
A7: REVENUE
A10: WEBSITE TRAFFIC
A12: Organic traffic | C12: Start event in the roadmap | D12: Date
A13: Traffic first month | B13: 1000 | C13: Incorporation | D13: =IFERROR(VLOOKUP(C13,Roadmap!$A$7:$D$110,3,0),"not set, choose the event") -> 45139
A14: Monthly increase | B14: 0.05
A15: Maximum traffic | B15: 100000
A17: Paid traffic
B18: Budget at start | C18: Start event in the roadmap | D18: Date | E18: Event in the roadmap to increase budget | F18: Date | G18: Additional budget | H18: Event in the roadmap to increase budget | I18: Date | J18: Additional budget | K18: Event in the roadmap to increase budget | L18: Date | M18: Additional budget
A19: Paid traffic marketing budget per month | B19: 1000 | C19: Incorporation | D19: =IFERROR(VLOOKUP(C19,Roadmap!$A$7:$D$110,3,0),"not set, choose the event") -> 45139 | E19: Seed round money transfer | F19: =IFERROR(VLOOKUP(E19,Roadmap!$A$7:$D$110,3,0),"not set, choose the event") -> 46266 | G19: 0 | I19: =IFERROR(VLOOKUP(H19,Roadmap!$A$7:$D$110,3,0),"not set, choose the event") -> not set, choose the event | J19: 0 | L19: =IFERROR(VLOOKUP(K19,Roadmap!$A$7:$D$110,3,0),"not set, choose the event") -> not set, choose the event | M19: 0
A21: CPC (Cost per click) | B21: 3
A22: Monthly decrease of Expected CPC | B22: 0.05
A23: Minimum Expected CPC | B23: 2
A25: BUSINESS MODEL: SUBSCRIPTION
A27: Pricing | C27: Start event in the roadmap | D27: Date
A28: Monthly subscription | B28: 100 | C28: Incorporation | D28: =IFERROR(VLOOKUP(C28,Roadmap!$A$7:$D$110,3,0),"not set, choose the event") -> 45139
A30: Expected monthly churn rate | B30: 0.15
A31: Expected LTV | B31: =iferror(B28/B30,0) -> 666.66667
A33: REVENUE STREAM 1: SELF-SERVICE
A35: Traffic conversion to subscription
A36: Conversion to subscription | B36: 0.005
A37: CAC - paid ads | B37: =B19/(B19/B21*B36) -> 600
A39: REVENUE STREAM 2: INBOUND SALES
B41: Start event in the roadmap | C41: Date
A42: Expected launch | B42: Incorporation | C42: =IFERROR(VLOOKUP(B42,Roadmap!$A$7:$D$110,3,0),"not set, choose the event") -> 45139
A44: Traffic conversion to lead
A45: Conversion to lead | B45: 0.1
A46: CPL (Cost Per Lead) | B46: =B19/(B19/B21*B45) -> 30
A48: Lead to subscription conversion
A49: Leads per Sales Manager per month | B49: 100
A50: Lead to sale conversion | B50: 0.1
A53: REVENUE STREAM 3: OUTBOUND SALES
B55: Start event in the roadmap | C55: Date
A56: Expected launch | B56: Incorporation | C56: =IFERROR(VLOOKUP(B56,Roadmap!$A$7:$D$110,3,0),"not set, choose the event") -> 45139
A58: Number of outbound sales managers first month | B58: 1
A59: Hiring frequency, months | B59: 3
A60: Max number of outbound sales managers | B60: 10
A62: Deals closed per Sales Manager per month | B62: 2
A65: COGS
A67: Payments processing | B67: 0.01
A68: Hosting costs per subscriber per month | B68: 2
A71: SG&A
A73: MARKETING
A75: Brand awareness campaigns | C75: Start event in the roadmap | D75: Date | E75: Event in the roadmap to increase budget | F75: Date | G75: Additional budget | H75: Event in the roadmap to increase budget | I75: Date | J75: Additional budget | K75: Event in the roadmap to increase budget | L75: Date | M75: Additional budget
A76: Channel 1 | B76: 2000 | C76: Seed round money transfer | D76: =IFERROR(VLOOKUP(C76,Roadmap!$A$7:$D$110,3,0),"not set, choose the event") -> 46266 | E76: Seed round money transfer | F76: =IFERROR(VLOOKUP(E76,Roadmap!$A$7:$D$110,3,0),"not set, choose the event") -> 46266 | G76: 1000 | I76: =IFERROR(VLOOKUP(H76,Roadmap!$A$7:$D$110,3,0),"not set, choose the event") -> not set, choose the event | J76: 0 | L76: =IFERROR(VLOOKUP(K76,Roadmap!$A$7:$D$110,3,0),"not set, choose the event") -> not set, choose the event | M76: 0
A77: Channel 2 | B77: 0 | D77: =IFERROR(VLOOKUP(C77,Roadmap!$A$7:$D$110,3,0),"not set, choose the event") -> not set, choose the event | E77: Seed round money transfer | F77: =IFERROR(VLOOKUP(E77,Roadmap!$A$7:$D$110,3,0),"not set, choose the event") -> 46266 | G77: 0 | I77: =IFERROR(VLOOKUP(H77,Roadmap!$A$7:$D$110,3,0),"not set, choose the event") -> not set, choose the event | J77: 0 | L77: =IFERROR(VLOOKUP(K77,Roadmap!$A$7:$D$110,3,0),"not set, choose the event") -> not set, choose the event | M77: 0
A78: Channel 3 | B78: 0 | D78: =IFERROR(VLOOKUP(C78,Roadmap!$A$7:$D$110,3,0),"not set, choose the event") -> not set, choose the event | F78: =IFERROR(VLOOKUP(E78,Roadmap!$A$7:$D$110,3,0),"not set, choose the event") -> not set, choose the event | G78: 0 | I78: =IFERROR(VLOOKUP(H78,Roadmap!$A$7:$D$110,3,0),"not set, choose the event") -> not set, choose the event | J78: 0 | L78: =IFERROR(VLOOKUP(K78,Roadmap!$A$7:$D$110,3,0),"not set, choose the event") -> not set, choose the event | M78: 0
A81: Other marketing expenses | C81: Start event in the roadmap | D81: Date
A82: Expense 1 | B82: 0 | D82: =IFERROR(VLOOKUP(C82,Roadmap!$A$7:$D$110,3,0),"not set, choose the event") -> not set, choose the event
A83: Expense 2 | B83: 0 | D83: =IFERROR(VLOOKUP(C83,Roadmap!$A$7:$D$110,3,0),"not set, choose the event") -> not set, choose the event
A84: Expense 3 | B84: 0 | D84: =IFERROR(VLOOKUP(C84,Roadmap!$A$7:$D$110,3,0),"not set, choose the event") -> not set, choose the event
A85: Expense 4 | B85: 0 | D85: =IFERROR(VLOOKUP(C85,Roadmap!$A$7:$D$110,3,0),"not set, choose the event") -> not set, choose the event
A86: Expense 5 | B86: 0 | D86: =IFERROR(VLOOKUP(C86,Roadmap!$A$7:$D$110,3,0),"not set, choose the event") -> not set, choose the event
A87: Expense 6 | B87: 0 | D87: =IFERROR(VLOOKUP(C87,Roadmap!$A$7:$D$110,3,0),"not set, choose the event") -> not set, choose the event
A88: Expense 7 | B88: 0 | D88: =IFERROR(VLOOKUP(C88,Roadmap!$A$7:$D$110,3,0),"not set, choose the event") -> not set, choose the event
A89: Expense 8 | B89: 0 | D89: =IFERROR(VLOOKUP(C89,Roadmap!$A$7:$D$110,3,0),"not set, choose the event") -> not set, choose the event
A92: ADVISORY SERVICES
A93: Legal | C93: Start event in the roadmap | D93: Date
A94: Incorporation | B94: 0 | C94: Incorporation | D94: =IFERROR(VLOOKUP(C94,Roadmap!$A$7:$D$110,3,0),"not set, choose the event") -> 45139 | E94: one-time
A95: Regular legal support | B95: 0 | D95: =IFERROR(VLOOKUP(C95,Roadmap!$A$7:$D$110,3,0),"not set, choose the event") -> not set, choose the event
A97: Accounting&Taxes | C97: Start event in the roadmap | D97: Date
A98: Bookkeeping | B98: 0 | D98: =IFERROR(VLOOKUP(C98,Roadmap!$A$7:$D$110,3,0),"not set, choose the event") -> not set, choose the event | E98: 1
A99: Tax services | D99: =IFERROR(VLOOKUP(C99,Roadmap!$A$7:$D$110,3,0),"not set, choose the event") -> not set, choose the event | E99: 12
A101: Other advisory services | C101: Start event in the roadmap | D101: Date
A102: Expense 1 | B102: 0 | D102: =IFERROR(VLOOKUP(C102,Roadmap!$A$7:$D$110,3,0),"not set, choose the event") -> not set, choose the event
A103: Expense 2 | B103: 0 | D103: =IFERROR(VLOOKUP(C103,Roadmap!$A$7:$D$110,3,0),"not set, choose the event") -> not set, choose the event
A104: Expense 3 | B104: 0 | D104: =IFERROR(VLOOKUP(C104,Roadmap!$A$7:$D$110,3,0),"not set, choose the event") -> not set, choose the event
A107: OTHER ADMINISTRATIVE EXPENSES | C107: Start event in the roadmap | D107: Date
A108: Office | B108: 3000 | C108: Incorporation | D108: =IFERROR(VLOOKUP(C108,Roadmap!$A$7:$D$110,3,0),"not set, choose the event") -> 45139
A109: Expense 1 | B109: 0 | D109: =IFERROR(VLOOKUP(C109,Roadmap!$A$7:$D$110,3,0),"not set, choose the event") -> not set, choose the event
A110: Expense 2 | B110: 0 | D110: =IFERROR(VLOOKUP(C110,Roadmap!$A$7:$D$110,3,0),"not set, choose the event") -> not set, choose the event
A111: Expense 3 | B111: 0 | D111: =IFERROR(VLOOKUP(C111,Roadmap!$A$7:$D$110,3,0),"not set, choose the event") -> not set, choose the event
A112: Expense 4 | B112: 0 | D112: =IFERROR(VLOOKUP(C112,Roadmap!$A$7:$D$110,3,0),"not set, choose the event") -> not set, choose the event
A114: CAPEX
A116: The model automatically estimates new computer purchases for new employees | B116: Price per computer | C116: Time for assets to depreciate (in monthes)
B117: 2000 | C117: 24
B119: Price | C119: Time for assets to depreciate (in monthes) | D119: Start event in the roadmap | E119: Date
A120: Asset 1 | B120: 0 | C120: 0 | E120: =IFERROR(VLOOKUP(D120,Roadmap!$A$7:$D$110,3,0),"not set, choose the event") -> not set, choose the event
A121: Asset 2 | B121: 0 | C121: 0 | E121: =IFERROR(VLOOKUP(D121,Roadmap!$A$7:$D$110,3,0),"not set, choose the event") -> not set, choose the event
A122: Asset 3 | B122: 0 | C122: 0 | E122: =IFERROR(VLOOKUP(D122,Roadmap!$A$7:$D$110,3,0),"not set, choose the event") -> not set, choose the event
A123: Asset 4 | B123: 0 | C123: 0 | E123: =IFERROR(VLOOKUP(D123,Roadmap!$A$7:$D$110,3,0),"not set, choose the event") -> not set, choose the event
A124: Asset 5 | B124: 0 | C124: 0 | E124: =IFERROR(VLOOKUP(D124,Roadmap!$A$7:$D$110,3,0),"not set, choose the event") -> not set, choose the event

Sheet Charts
B1: =Settings!$B$4 -> Healthy4U
B2: KEY INDICATORS
B20: CAPITAL
C22: Months to reach break even | D22: =COUNTIF('P&L | Cash Flow | Balance'!28:28,"<=0") -> 8
C24: Capital required | D24: =iferror(-MIN('P&L | Cash Flow | Balance'!39:39),"-") -> 21252.97
B26: REVENUE

Sheet For Pitchdeck
C2: =YEAR('Monthly forecast'!E2) -> 2023 | D2: =C2+1 -> 2024 | E2: =D2+1 -> 2025 | F2: =E2+1 -> 2026 | G2: =F2+1 -> 2027 | I2: * Для слайда питчдека "Финансовый прогноз" ("Financial Forecast") скопируйте таблицу и графики на этом листе, которые показывают динамику выручки и прибыли по годам.
B3: ='P&L | Cash Flow | Balance'!A6 -> REVENUE | C3: =SUM(C4:C6) -> 29606.373 | D3: =SUM(D4:D6) -> 229756.58 | E3: =SUM(E4:E6) -> 444131.73 | F3: =SUM(F4:F6) -> 723504.46 | G3: =SUM(G4:G6) -> 1145002.3
B4: ='P&L | Cash Flow | Balance'!A7 -> REVENUE STREAM 1: SELF-SERVICE | C4: =SUMIFS('P&L | Cash Flow | Balance'!D7:CW7,'P&L | Cash Flow | Balance'!D2:CW2,">="&DATE(C2,1,1),'P&L | Cash Flow | Balance'!D2:CW2,"<="&DATE(C2,12,31)) -> 8857.6073 | D4: =SUMIFS('P&L | Cash Flow | Balance'!E7:CX7,'P&L | Cash Flow | Balance'!E2:CX2,">="&DATE(D2,1,1),'P&L | Cash Flow | Balance'!E2:CX2,"<="&DATE(D2,12,31)) -> 62911.87 | E4: =SUMIFS('P&L | Cash Flow | Balance'!F7:CY7,'P&L | Cash Flow | Balance'!F2:CY2,">="&DATE(E2,1,1),'P&L | Cash Flow | Balance'!F2:CY2,"<="&DATE(E2,12,31)) -> 114345.44 | F4: =SUMIFS('P&L | Cash Flow | Balance'!G7:CZ7,'P&L | Cash Flow | Balance'!G2:CZ2,">="&DATE(F2,1,1),'P&L | Cash Flow | Balance'!G2:CZ2,"<="&DATE(F2,12,31)) -> 191848.79 | G4: =SUMIFS('P&L | Cash Flow | Balance'!H7:DA7,'P&L | Cash Flow | Balance'!H2:DA2,">="&DATE(G2,1,1),'P&L | Cash Flow | Balance'!H2:DA2,"<="&DATE(G2,12,31)) -> 328905.06
B5: ='P&L | Cash Flow | Balance'!A8 -> REVENUE STREAM 2: INBOUND SALES | C5: =SUMIFS('P&L | Cash Flow | Balance'!D8:CW8,'P&L | Cash Flow | Balance'!D2:CW2,">="&DATE(C2,1,1),'P&L | Cash Flow | Balance'!D2:CW2,"<="&DATE(C2,12,31)) -> 17715.215 | D5: =SUMIFS('P&L | Cash Flow | Balance'!E8:CX8,'P&L | Cash Flow | Balance'!E2:CX2,">="&DATE(D2,1,1),'P&L | Cash Flow | Balance'!E2:CX2,"<="&DATE(D2,12,31)) -> 125823.74 | E5: =SUMIFS('P&L | Cash Flow | Balance'!F8:CY8,'P&L | Cash Flow | Balance'!F2:CY2,">="&DATE(E2,1,1),'P&L | Cash Flow | Balance'!F2:CY2,"<="&DATE(E2,12,31)) -> 228690.88 | F5: =SUMIFS('P&L | Cash Flow | Balance'!G8:CZ8,'P&L | Cash Flow | Balance'!G2:CZ2,">="&DATE(F2,1,1),'P&L | Cash Flow | Balance'!G2:CZ2,"<="&DATE(F2,12,31)) -> 383697.59 | G5: =SUMIFS('P&L | Cash Flow | Balance'!H8:DA8,'P&L | Cash Flow | Balance'!H2:DA2,">="&DATE(G2,1,1),'P&L | Cash Flow | Balance'!H2:DA2,"<="&DATE(G2,12,31)) -> 657810.13
B6: ='P&L | Cash Flow | Balance'!A9 -> REVENUE STREAM 3: OUTBOUND SALES | C6: =SUMIFS('P&L | Cash Flow | Balance'!D9:CW9,'P&L | Cash Flow | Balance'!D2:CW2,">="&DATE(C2,1,1),'P&L | Cash Flow | Balance'!D2:CW2,"<="&DATE(C2,12,31)) -> 3033.5512 | D6: =SUMIFS('P&L | Cash Flow | Balance'!E9:CX9,'P&L | Cash Flow | Balance'!E2:CX2,">="&DATE(D2,1,1),'P&L | Cash Flow | Balance'!E2:CX2,"<="&DATE(D2,12,31)) -> 41020.972 | E6: =SUMIFS('P&L | Cash Flow | Balance'!F9:CY9,'P&L | Cash Flow | Balance'!F2:CY2,">="&DATE(E2,1,1),'P&L | Cash Flow | Balance'!F2:CY2,"<="&DATE(E2,12,31)) -> 101095.42 | F6: =SUMIFS('P&L | Cash Flow | Balance'!G9:CZ9,'P&L | Cash Flow | Balance'!G2:CZ2,">="&DATE(F2,1,1),'P&L | Cash Flow | Balance'!G2:CZ2,"<="&DATE(F2,12,31)) -> 147958.08 | G6: =SUMIFS('P&L | Cash Flow | Balance'!H9:DA9,'P&L | Cash Flow | Balance'!H2:DA2,">="&DATE(G2,1,1),'P&L | Cash Flow | Balance'!H2:DA2,"<="&DATE(G2,12,31)) -> 158287.14
B7: ='P&L | Cash Flow | Balance'!A17 -> EBITDA | C7: =SUMIFS('P&L | Cash Flow | Balance'!D17:CW17,'P&L | Cash Flow | Balance'!D2:CW2,">="&DATE(C2,1,1),'P&L | Cash Flow | Balance'!D2:CW2,"<="&DATE(C2,12,31)) -> -6666.4336 | D7: =SUMIFS('P&L | Cash Flow | Balance'!E17:CX17,'P&L | Cash Flow | Balance'!E2:CX2,">="&DATE(D2,1,1),'P&L | Cash Flow | Balance'!E2:CX2,"<="&DATE(D2,12,31)) -> 125171.58 | E7: =SUMIFS('P&L | Cash Flow | Balance'!F17:CY17,'P&L | Cash Flow | Balance'!F2:CY2,">="&DATE(E2,1,1),'P&L | Cash Flow | Balance'!F2:CY2,"<="&DATE(E2,12,31)) -> 274424.4 | F7: =SUMIFS('P&L | Cash Flow | Balance'!G17:CZ17,'P&L | Cash Flow | Balance'!G2:CZ2,">="&DATE(F2,1,1),'P&L | Cash Flow | Balance'!G2:CZ2,"<="&DATE(F2,12,31)) -> 213613.03 | G7: =SUMIFS('P&L | Cash Flow | Balance'!H17:DA17,'P&L | Cash Flow | Balance'!H2:DA2,">="&DATE(G2,1,1),'P&L | Cash Flow | Balance'!H2:DA2,"<="&DATE(G2,12,31)) -> 237514.21
B8: ='P&L | Cash Flow | Balance'!A28 -> Net income | C8: =SUMIFS('P&L | Cash Flow | Balance'!D28:CW28,'P&L | Cash Flow | Balance'!D2:CW2,">="&DATE(C2,1,1),'P&L | Cash Flow | Balance'!D2:CW2,"<="&DATE(C2,12,31)) -> -9535.3768 | D8: =SUMIFS('P&L | Cash Flow | Balance'!E28:CX28,'P&L | Cash Flow | Balance'!E2:CX2,">="&DATE(D2,1,1),'P&L | Cash Flow | Balance'!E2:CX2,"<="&DATE(D2,12,31)) -> 91762.113 | E8: =SUMIFS('P&L | Cash Flow | Balance'!F28:CY28,'P&L | Cash Flow | Balance'!F2:CY2,">="&DATE(E2,1,1),'P&L | Cash Flow | Balance'!F2:CY2,"<="&DATE(E2,12,31)) -> 208098.45 | F8: =SUMIFS('P&L | Cash Flow | Balance'!G28:CZ28,'P&L | Cash Flow | Balance'!G2:CZ2,">="&DATE(F2,1,1),'P&L | Cash Flow | Balance'!G2:CZ2,"<="&DATE(F2,12,31)) -> 159822.02 | G8: =SUMIFS('P&L | Cash Flow | Balance'!H28:DA28,'P&L | Cash Flow | Balance'!H2:DA2,">="&DATE(G2,1,1),'P&L | Cash Flow | Balance'!H2:DA2,"<="&DATE(G2,12,31)) -> 176469.28

Sheet Monthly forecast
A1: =Settings!B4 -> Healthy4U
A2: Month | B2: Expense category | D2: =EDATE(E2,-1) -> 45108 | E2: =Projections!$B$4 -> 45139 | F2: =EDATE(E2,1) -> 45170 | G2: =EDATE(F2,1) -> 45200 | H2: =EDATE(G2,1) -> 45231 | I2: =EDATE(H2,1) -> 45261 | J2: =EDATE(I2,1) -> 45292 | K2: =EDATE(J2,1) -> 45323 | L2: =EDATE(K2,1) -> 45352 | M2: =EDATE(L2,1) -> 45383 | ... CX2: =EDATE(CW2,1) -> 48092
A4: REVENUE
A6: KEY INDICATORS
A8: Traffic | Z8: =N8*(1+Projections!$B$14) -> 0
A9: Organic traffic | E9: =IF(E2=Projections!$D$13,Projections!$B$13,IF(E2>Projections!$D$13,MIN(D9*(1+Projections!$B$14),Projections!$B$15),0)) -> 1000 | F9: =IF(F2=Projections!$D$13,Projections!$B$13,IF(F2>Projections!$D$13,MIN(E9*(1+Projections!$B$14),Projections!$B$15),0)) -> 1050 | G9: =IF(G2=Projections!$D$13,Projections!$B$13,IF(G2>Projections!$D$13,MIN(F9*(1+Projections!$B$14),Projections!$B$15),0)) -> 1102.5 | H9: =IF(H2=Projections!$D$13,Projections!$B$13,IF(H2>Projections!$D$13,MIN(G9*(1+Projections!$B$14),Projections!$B$15),0)) -> 1157.625 | I9: =IF(I2=Projections!$D$13,Projections!$B$13,IF(I2>Projections!$D$13,MIN(H9*(1+Projections!$B$14),Projections!$B$15),0)) -> 1215.5062 | J9: =IF(J2=Projections!$D$13,Projections!$B$13,IF(J2>Projections!$D$13,MIN(I9*(1+Projections!$B$14),Projections!$B$15),0)) -> 1276.2816 | K9: =IF(K2=Projections!$D$13,Projections!$B$13,IF(K2>Projections!$D$13,MIN(J9*(1+Projections!$B$14),Projections!$B$15),0)) -> 1340.0956 | L9: =IF(L2=Projections!$D$13,Projections!$B$13,IF(L2>Projections!$D$13,MIN(K9*(1+Projections!$B$14),Projections!$B$15),0)) -> 1407.1004 | ... CX9: =IF(CX2=Projections!$D$13,Projections!$B$13,IF(CX2>Projections!$D$13,MIN(CW9*(1+Projections!$B$14),Projections!$B$15),0)) -> 100000
A10: CPC | E10: =IF(E2=Projections!$D$19,Projections!$B$21,IF(E2>Projections!$D$19,MAX(Projections!$B$23,D10*(1-Projections!$B$22)),0)) -> 3 | F10: =IF(F2=Projections!$D$19,Projections!$B$21,IF(F2>Projections!$D$19,MAX(Projections!$B$23,E10*(1-Projections!$B$22)),0)) -> 2.85 | G10: =IF(G2=Projections!$D$19,Projections!$B$21,IF(G2>Projections!$D$19,MAX(Projections!$B$23,F10*(1-Projections!$B$22)),0)) -> 2.7075 | H10: =IF(H2=Projections!$D$19,Projections!$B$21,IF(H2>Projections!$D$19,MAX(Projections!$B$23,G10*(1-Projections!$B$22)),0)) -> 2.572125 | I10: =IF(I2=Projections!$D$19,Projections!$B$21,IF(I2>Projections!$D$19,MAX(Projections!$B$23,H10*(1-Projections!$B$22)),0)) -> 2.4435187 | J10: =IF(J2=Projections!$D$19,Projections!$B$21,IF(J2>Projections!$D$19,MAX(Projections!$B$23,I10*(1-Projections!$B$22)),0)) -> 2.3213428 | K10: =IF(K2=Projections!$D$19,Projections!$B$21,IF(K2>Projections!$D$19,MAX(Projections!$B$23,J10*(1-Projections!$B$22)),0)) -> 2.2052757 | L10: =IF(L2=Projections!$D$19,Projections!$B$21,IF(L2>Projections!$D$19,MAX(Projections!$B$23,K10*(1-Projections!$B$22)),0)) -> 2.0950119 | ... CX10: =IF(CX2=Projections!$D$19,Projections!$B$21,IF(CX2>Projections!$D$19,MAX(Projections!$B$23,CW10*(1-Projections!$B$22)),0)) -> 2
A11: Paid traffic | E11: =IFERROR(E65/E10,0) -> 333.33333 | F11: =IFERROR(F65/F10,0) -> 350.87719 | G11: =IFERROR(G65/G10,0) -> 369.34441 | H11: =IFERROR(H65/H10,0) -> 388.78359 | I11: =IFERROR(I65/I10,0) -> 409.24589 | J11: =IFERROR(J65/J10,0) -> 430.78514 | K11: =IFERROR(K65/K10,0) -> 453.45805 | L11: =IFERROR(L65/L10,0) -> 477.32426 | ... CX11: =IFERROR(CX65/CX10,0) -> 500
A12: Total traffic | E12: =SUM(E9:E11) -> 1336.3333 | F12: =SUM(F9:F11) -> 1403.7272 | G12: =SUM(G9:G11) -> 1474.5519 | H12: =SUM(H9:H11) -> 1548.9807 | I12: =SUM(I9:I11) -> 1627.1957 | J12: =SUM(J9:J11) -> 1709.3881 | K12: =SUM(K9:K11) -> 1795.759 | L12: =SUM(L9:L11) -> 1886.5197 | ... CX12: =SUM(CX9:CX11) -> 100502
A15: =Projections!A33 -> REVENUE STREAM 1: SELF-SERVICE
A17: New subscribers | E17: =if(E2>=Projections!$D$28,E12*Projections!$B$36,0) -> 6.6816667 | F17: =if(F2>=Projections!$D$28,F12*Projections!$B$36,0) -> 7.018636 | G17: =if(G2>=Projections!$D$28,G12*Projections!$B$36,0) -> 7.3727596 | H17: =if(H2>=Projections!$D$28,H12*Projections!$B$36,0) -> 7.7449036 | I17: =if(I2>=Projections!$D$28,I12*Projections!$B$36,0) -> 8.1359783 | J17: =if(J2>=Projections!$D$28,J12*Projections!$B$36,0) -> 8.5469403 | K17: =if(K2>=Projections!$D$28,K12*Projections!$B$36,0) -> 8.9787948 | L17: =if(L2>=Projections!$D$28,L12*Projections!$B$36,0) -> 9.4325985 | ... CX17: =if(CX2>=Projections!$D$28,CX12*Projections!$B$36,0) -> 502.51
A18: Churn rate | E18: =IF(E2>=Projections!$D$28,Projections!$B$30,0) -> 0.15 | F18: =IF(F2>=Projections!$D$28,Projections!$B$30,0) -> 0.15 | G18: =IF(G2>=Projections!$D$28,Projections!$B$30,0) -> 0.15 | H18: =IF(H2>=Projections!$D$28,Projections!$B$30,0) -> 0.15 | I18: =IF(I2>=Projections!$D$28,Projections!$B$30,0) -> 0.15 | J18: =IF(J2>=Projections!$D$28,Projections!$B$30,0) -> 0.15 | K18: =IF(K2>=Projections!$D$28,Projections!$B$30,0) -> 0.15 | L18: =IF(L2>=Projections!$D$28,Projections!$B$30,0) -> 0.15 | ... CX18: =IF(CX2>=Projections!$D$28,Projections!$B$30,0) -> 0.15
A19: Lost subscribers | E19: =D20*E18 -> 0 | F19: =E20*F18 -> 1.00225 | G19: =F20*G18 -> 1.9047079 | H19: =G20*H18 -> 2.7249156 | I19: =H20*I18 -> 3.4779138 | J19: =I20*J18 -> 4.1766235 | K19: =J20*K18 -> 4.832171 | L19: =K20*L18 -> 5.4541646 | ... CX19: =CW20*CX18 -> 420.41958
A20: Subscribers - End of the period | E20: =D20+E17-E19 -> 6.6816667 | F20: =E20+F17-F19 -> 12.698053 | G20: =F20+G17-G19 -> 18.166104 | H20: =G20+H17-H19 -> 23.186092 | I20: =H20+I17-I19 -> 27.844157 | J20: =I20+J17-J19 -> 32.214473 | K20: =J20+K17-K19 -> 36.361097 | L20: =K20+L17-L19 -> 40.339531 | ... CX20: =CW20+CX17-CX19 -> 2884.8876
A22: Gross revenue Self-service | E22: =E20*Projections!$B$28 -> 668.16667 | F22: =F20*Projections!$B$28 -> 1269.8053 | G22: =G20*Projections!$B$28 -> 1816.6104 | H22: =H20*Projections!$B$28 -> 2318.6092 | I22: =I20*Projections!$B$28 -> 2784.4157 | J22: =J20*Projections!$B$28 -> 3221.4473 | K22: =K20*Projections!$B$28 -> 3636.1097 | L22: =L20*Projections!$B$28 -> 4033.9531 | ... CX22: =CX20*Projections!$B$28 -> 288488.76
A24: =Projections!A39 -> REVENUE STREAM 2: INBOUND SALES
A26: Leads | E26: =if(E2>=Projections!$C$42,E12*Projections!$B$45,0) -> 133.63333 | F26: =if(F2>=Projections!$C$42,F12*Projections!$B$45,0) -> 140.37272 | G26: =if(G2>=Projections!$C$42,G12*Projections!$B$45,0) -> 147.45519 | H26: =if(H2>=Projections!$C$42,H12*Projections!$B$45,0) -> 154.89807 | I26: =if(I2>=Projections!$C$42,I12*Projections!$B$45,0) -> 162.71957 | J26: =if(J2>=Projections!$C$42,J12*Projections!$B$45,0) -> 170.93881 | K26: =if(K2>=Projections!$C$42,K12*Projections!$B$45,0) -> 179.5759 | L26: =if(L2>=Projections!$C$42,L12*Projections!$B$45,0) -> 188.65197 | ... CX26: =if(CX2>=Projections!$C$42,CX12*Projections!$B$45,0) -> 10050.2
A28: New subscribers | E28: =IFERROR(E26*Projections!$B$50,0) -> 13.363333 | F28: =IFERROR(F26*Projections!$B$50,0) -> 14.037272 | G28: =IFERROR(G26*Projections!$B$50,0) -> 14.745519 | H28: =IFERROR(H26*Projections!$B$50,0) -> 15.489807 | I28: =IFERROR(I26*Projections!$B$50,0) -> 16.271957 | J28: =IFERROR(J26*Projections!$B$50,0) -> 17.093881 | K28: =IFERROR(K26*Projections!$B$50,0) -> 17.95759 | L28: =IFERROR(L26*Projections!$B$50,0) -> 18.865197 | ... CX28: =IFERROR(CX26*Projections!$B$50,0) -> 1005.02
A29: Churn rate | E29: =IF(E2>=Projections!$D$28,Projections!$B$30,0) -> 0.15 | F29: =IF(F2>=Projections!$D$28,Projections!$B$30,0) -> 0.15 | G29: =IF(G2>=Projections!$D$28,Projections!$B$30,0) -> 0.15 | H29: =IF(H2>=Projections!$D$28,Projections!$B$30,0) -> 0.15 | I29: =IF(I2>=Projections!$D$28,Projections!$B$30,0) -> 0.15 | J29: =IF(J2>=Projections!$D$28,Projections!$B$30,0) -> 0.15 | K29: =IF(K2>=Projections!$D$28,Projections!$B$30,0) -> 0.15 | L29: =IF(L2>=Projections!$D$28,Projections!$B$30,0) -> 0.15 | ... CX29: =IF(CX2>=Projections!$D$28,Projections!$B$30,0) -> 0.15
A30: Lost subscribers | E30: =D31*E29 -> 0 | F30: =E31*F29 -> 2.0045 | G30: =F31*G29 -> 3.8094158 | H30: =G31*H29 -> 5.4498313 | I30: =H31*I29 -> 6.9558277 | J30: =I31*J29 -> 8.353247 | K30: =J31*K29 -> 9.664342 | L30: =K31*L29 -> 10.908329 | ... CX30: =CW31*CX29 -> 840.83915
A31: Subscribers - End of the period | E31: =D31+E28-E30 -> 13.363333 | F31: =E31+F28-F30 -> 25.396105 | G31: =F31+G28-G30 -> 36.332209 | H31: =G31+H28-H30 -> 46.372185 | I31: =H31+I28-I30 -> 55.688313 | J31: =I31+J28-J30 -> 64.428947 | K31: =J31+K28-K30 -> 72.722194 | L31: =K31+L28-L30 -> 80.679062 | ... CX31: =CW31+CX28-CX30 -> 5769.7752
A33: Gross revenue Inbound Sales | E33: =E31*Projections!$B$28 -> 1336.3333 | F33: =F31*Projections!$B$28 -> 2539.6105 | G33: =G31*Projections!$B$28 -> 3633.2209 | H33: =H31*Projections!$B$28 -> 4637.2185 | I33: =I31*Projections!$B$28 -> 5568.8313 | J33: =J31*Projections!$B$28 -> 6442.8947 | K33: =K31*Projections!$B$28 -> 7272.2194 | L33: =L31*Projections!$B$28 -> 8067.9062 | ... CX33: =CX31*Projections!$B$28 -> 576977.52
A35: =Projections!A53 -> REVENUE STREAM 3: OUTBOUND SALES
A37: New subscribers | E37: =E87*Projections!$B$62 -> 2 | F37: =F87*Projections!$B$62 -> 2 | G37: =G87*Projections!$B$62 -> 2 | H37: =H87*Projections!$B$62 -> 4 | I37: =I87*Projections!$B$62 -> 4 | J37: =J87*Projections!$B$62 -> 4 | K37: =K87*Projections!$B$62 -> 6 | L37: =L87*Projections!$B$62 -> 6 | ... CX37: =CX87*Projections!$B$62 -> 20
A38: Churn rate | E38: =IF(E2>=Projections!$D$28,Projections!$B$30,0) -> 0.15 | F38: =IF(F2>=Projections!$D$28,Projections!$B$30,0) -> 0.15 | G38: =IF(G2>=Projections!$D$28,Projections!$B$30,0) -> 0.15 | H38: =IF(H2>=Projections!$D$28,Projections!$B$30,0) -> 0.15 | I38: =IF(I2>=Projections!$D$28,Projections!$B$30,0) -> 0.15 | J38: =IF(J2>=Projections!$D$28,Projections!$B$30,0) -> 0.15 | K38: =IF(K2>=Projections!$D$28,Projections!$B$30,0) -> 0.15 | L38: =IF(L2>=Projections!$D$28,Projections!$B$30,0) -> 0.15 | ... CX38: =IF(CX2>=Projections!$D$28,Projections!$B$30,0) -> 0.15
A39: Lost subscribers | E39: =D40*E38 -> 0 | F39: =E40*F38 -> 0.3 | G39: =F40*G38 -> 0.555 | H39: =G40*H38 -> 0.77175 | I39: =H40*I38 -> 1.2559875 | J39: =I40*J38 -> 1.6675894 | K39: =J40*K38 -> 2.017451 | L39: =K40*L38 -> 2.6148333 | ... CX39: =CW40*CX38 -> 19.999941
A40: Subscribers - End of the period | E40: =D40+E37-E39 -> 2 | F40: =E40+F37-F39 -> 3.7 | G40: =F40+G37-G39 -> 5.145 | H40: =G40+H37-H39 -> 8.37325 | I40: =H40+I37-I39 -> 11.117263 | J40: =I40+J37-J39 -> 13.449673 | K40: =J40+K37-K39 -> 17.432222 | L40: =K40+L37-L39 -> 20.817389 | ... CX40: =CW40+CX37-CX39 -> 133.333
A42: Gross revenue Outbound Sales | E42: =E40*Projections!$B$28 -> 200 | F42: =F40*Projections!$B$28 -> 370 | G42: =G40*Projections!$B$28 -> 514.5 | H42: =H40*Projections!$B$28 -> 837.325 | I42: =I40*Projections!$B$28 -> 1111.7262 | J42: =J40*Projections!$B$28 -> 1344.9673 | K42: =K40*Projections!$B$28 -> 1743.2222 | L42: =L40*Projections!$B$28 -> 2081.7389 | ... CX42: =CX40*Projections!$B$28 -> 13333.3
A44: Total subscribers - End of the period | E44: =E40+E31+E20 -> 22.045 | F44: =F40+F31+F20 -> 41.794158 | G44: =G40+G31+G20 -> 59.643313 | H44: =H40+H31+H20 -> 77.931527 | I44: =I40+I31+I20 -> 94.649733 | J44: =J40+J31+J20 -> 110.09309 | K44: =K40+K31+K20 -> 126.51551 | L44: =L40+L31+L20 -> 141.83598 | ... CX44: =CX40+CX31+CX20 -> 8787.9958
A45: Total gross revenue | E45: =E42+E33+E22 -> 2204.5 | F45: =F42+F33+F22 -> 4179.4158 | G45: =G42+G33+G22 -> 5964.3313 | H45: =H42+H33+H22 -> 7793.1527 | I45: =I42+I33+I22 -> 9464.9733 | J45: =J42+J33+J22 -> 11009.309 | K45: =K42+K33+K22 -> 12651.551 | L45: =L42+L33+L22 -> 14183.598 | ... CX45: =CX42+CX33+CX22 -> 878799.58
A47: COGS | E47: =SUM(E49:E50) -> 66.135 | F47: =SUM(F49:F50) -> 125.38247 | G47: =SUM(G49:G50) -> 178.92994 | H47: =SUM(H49:H50) -> 233.79458 | I47: =SUM(I49:I50) -> 283.9492 | J47: =SUM(J49:J50) -> 330.27928 | K47: =SUM(K49:K50) -> 379.54654 | L47: =SUM(L49:L50) -> 425.50795 | ... CX47: =SUM(CX49:CX50) -> 26363.987
A49: Hosting | E49: =E44*Projections!$B$68 -> 44.09 | F49: =F44*Projections!$B$68 -> 83.588316 | G49: =G44*Projections!$B$68 -> 119.28663 | H49: =H44*Projections!$B$68 -> 155.86305 | I49: =I44*Projections!$B$68 -> 189.29947 | J49: =J44*Projections!$B$68 -> 220.18619 | K49: =K44*Projections!$B$68 -> 253.03103 | L49: =L44*Projections!$B$68 -> 283.67196 | ... CX49: =CX44*Projections!$B$68 -> 17575.992
A50: Payments processing | E50: =E45*Projections!$B$67 -> 22.045 | F50: =F45*Projections!$B$67 -> 41.794158 | G50: =G45*Projections!$B$67 -> 59.643313 | H50: =H45*Projections!$B$67 -> 77.931527 | I50: =I45*Projections!$B$67 -> 94.649733 | J50: =J45*Projections!$B$67 -> 110.09309 | K50: =K45*Projections!$B$67 -> 126.51551 | L50: =L45*Projections!$B$67 -> 141.83598 | ... CX50: =CX45*Projections!$B$67 -> 8787.9958
A53: SG&A | E53: =E55+E79+E91+E139+E151 -> 7076.9231 | F53: =F55+F79+F91+F139+F151 -> 7076.9231 | G53: =G55+G79+G91+G139+G151 -> 7076.9231 | H53: =H55+H79+H91+H139+H151 -> 7076.9231 | I53: =I55+I79+I91+I139+I151 -> 7076.9231 | J53: =J55+J79+J91+J139+J151 -> 7076.9231 | K53: =K55+K79+K91+K139+K151 -> 7076.9231 | L53: =L55+L79+L91+L139+L151 -> 7076.9231 | ... CX53: =CX55+CX79+CX91+CX139+CX151 -> 240053.82
A55: MARKETING | E55: =E57+E65+E68 -> 1000 | F55: =F57+F65+F68 -> 1000 | G55: =G57+G65+G68 -> 1000 | H55: =H57+H65+H68 -> 1000 | I55: =I57+I65+I68 -> 1000 | J55: =J57+J65+J68 -> 1000 | K55: =K57+K65+K68 -> 1000 | L55: =L57+L65+L68 -> 1000 | ... CX55: =CX57+CX65+CX68 -> 4000
A57: =Projections!A75 -> Brand awareness campaigns | B57: Marketing | E57: =SUM(E58:E60) -> 0 | F57: =SUM(F58:F60) -> 0 | G57: =SUM(G58:G60) -> 0 | H57: =SUM(H58:H60) -> 0 | I57: =SUM(I58:I60) -> 0 | J57: =SUM(J58:J60) -> 0 | K57: =SUM(K58:K60) -> 0 | L57: =SUM(L58:L60) -> 0 | ... CX57: =SUM(CX58:CX60) -> 3000
A58: =Projections!A76 -> Channel 1 | E58: =IF(E$2<Projections!$D76,0,IF(and(E$2>=Projections!$D76,E$2<Projections!$F76),Projections!$B76,if(and(E$2>=Projections!$F76,E$2<Projections!$I76),Projections!$B76+Projections!$G76,if(and(E$2>=Projections!$I76,E$2<Projections!$L76),Projections!$B76+Projections!$G76+Projections!$J76,IF(E$2>=Projections!$L76,Projections!$B76+Projections!$G76+Projections!$J76+Projections!$M76,""))))) -> 0 | F58: =IF(F$2<Projections!$D76,0,IF(and(F$2>=Projections!$D76,F$2<Projections!$F76),Projections!$B76,if(and(F$2>=Projections!$F76,F$2<Projections!$I76),Projections!$B76+Projections!$G76,if(and(F$2>=Projections!$I76,F$2<Projections!$L76),Projections!$B76+Projections!$G76+Projections!$J76,IF(F$2>=Projections!$L76,Projections!$B76+Projections!$G76+Projections!$J76+Projections!$M76,""))))) -> 0 | G58: =IF(G$2<Projections!$D76,0,IF(and(G$2>=Projections!$D76,G$2<Projections!$F76),Projections!$B76,if(and(G$2>=Projections!$F76,G$2<Projections!$I76),Projections!$B76+Projections!$G76,if(and(G$2>=Projections!$I76,G$2<Projections!$L76),Projections!$B76+Projections!$G76+Projections!$J76,IF(G$2>=Projections!$L76,Projections!$B76+Projections!$G76+Projections!$J76+Projections!$M76,""))))) -> 0 | H58: =IF(H$2<Projections!$D76,0,IF(and(H$2>=Projections!$D76,H$2<Projections!$F76),Projections!$B76,if(and(H$2>=Projections!$F76,H$2<Projections!$I76),Projections!$B76+Projections!$G76,if(and(H$2>=Projections!$I76,H$2<Projections!$L76),Projections!$B76+Projections!$G76+Projections!$J76,IF(H$2>=Projections!$L76,Projections!$B76+Projections!$G76+Projections!$J76+Projections!$M76,""))))) -> 0 | I58: =IF(I$2<Projections!$D76,0,IF(and(I$2>=Projections!$D76,I$2<Projections!$F76),Projections!$B76,if(and(I$2>=Projections!$F76,I$2<Projections!$I76),Projections!$B76+Projections!$G76,if(and(I$2>=Projections!$I76,I$2<Projections!$L76),Projections!$B76+Projections!$G76+Projections!$J76,IF(I$2>=Projections!$L76,Projections!$B76+Projections!$G76+Projections!$J76+Projections!$M76,""))))) -> 0 | J58: =IF(J$2<Projections!$D76,0,IF(and(J$2>=Projections!$D76,J$2<Projections!$F76),Projections!$B76,if(and(J$2>=Projections!$F76,J$2<Projections!$I76),Projections!$B76+Projections!$G76,if(and(J$2>=Projections!$I76,J$2<Projections!$L76),Projections!$B76+Projections!$G76+Projections!$J76,IF(J$2>=Projections!$L76,Projections!$B76+Projections!$G76+Projections!$J76+Projections!$M76,""))))) -> 0 | K58: =IF(K$2<Projections!$D76,0,IF(and(K$2>=Projections!$D76,K$2<Projections!$F76),Projections!$B76,if(and(K$2>=Projections!$F76,K$2<Projections!$I76),Projections!$B76+Projections!$G76,if(and(K$2>=Projections!$I76,K$2<Projections!$L76),Projections!$B76+Projections!$G76+Projections!$J76,IF(K$2>=Projections!$L76,Projections!$B76+Projections!$G76+Projections!$J76+Projections!$M76,""))))) -> 0 | L58: =IF(L$2<Projections!$D76,0,IF(and(L$2>=Projections!$D76,L$2<Projections!$F76),Projections!$B76,if(and(L$2>=Projections!$F76,L$2<Projections!$I76),Projections!$B76+Projections!$G76,if(and(L$2>=Projections!$I76,L$2<Projections!$L76),Projections!$B76+Projections!$G76+Projections!$J76,IF(L$2>=Projections!$L76,Projections!$B76+Projections!$G76+Projections!$J76+Projections!$M76,""))))) -> 0 | ... CX58: =IF(CX$2<Projections!$D76,0,IF(and(CX$2>=Projections!$D76,CX$2<Projections!$F76),Projections!$B76,if(and(CX$2>=Projections!$F76,CX$2<Projections!$I76),Projections!$B76+Projections!$G76,if(and(CX$2>=Projections!$I76,CX$2<Projections!$L76),Projections!$B76+Projections!$G76+Projections!$J76,IF(CX$2>=Projections!$L76,Projections!$B76+Projections!$G76+Projections!$J76+Projections!$M76,""))))) -> 3000
A59: =Projections!A77 -> Channel 2 | E59: =IF(E$2<Projections!$D77,0,IF(and(E$2>=Projections!$D77,E$2<Projections!$F77),Projections!$B77,if(and(E$2>=Projections!$F77,E$2<Projections!$I77),Projections!$B77+Projections!$G77,if(and(E$2>=Projections!$I77,E$2<Projections!$L77),Projections!$B77+Projections!$G77+Projections!$J77,IF(E$2>=Projections!$L77,Projections!$B77+Projections!$G77+Projections!$J77+Projections!$M77,""))))) -> 0 | F59: =IF(F$2<Projections!$D77,0,IF(and(F$2>=Projections!$D77,F$2<Projections!$F77),Projections!$B77,if(and(F$2>=Projections!$F77,F$2<Projections!$I77),Projections!$B77+Projections!$G77,if(and(F$2>=Projections!$I77,F$2<Projections!$L77),Projections!$B77+Projections!$G77+Projections!$J77,IF(F$2>=Projections!$L77,Projections!$B77+Projections!$G77+Projections!$J77+Projections!$M77,""))))) -> 0 | G59: =IF(G$2<Projections!$D77,0,IF(and(G$2>=Projections!$D77,G$2<Projections!$F77),Projections!$B77,if(and(G$2>=Projections!$F77,G$2<Projections!$I77),Projections!$B77+Projections!$G77,if(and(G$2>=Projections!$I77,G$2<Projections!$L77),Projections!$B77+Projections!$G77+Projections!$J77,IF(G$2>=Projections!$L77,Projections!$B77+Projections!$G77+Projections!$J77+Projections!$M77,""))))) -> 0 | H59: =IF(H$2<Projections!$D77,0,IF(and(H$2>=Projections!$D77,H$2<Projections!$F77),Projections!$B77,if(and(H$2>=Projections!$F77,H$2<Projections!$I77),Projections!$B77+Projections!$G77,if(and(H$2>=Projections!$I77,H$2<Projections!$L77),Projections!$B77+Projections!$G77+Projections!$J77,IF(H$2>=Projections!$L77,Projections!$B77+Projections!$G77+Projections!$J77+Projections!$M77,""))))) -> 0 | I59: =IF(I$2<Projections!$D77,0,IF(and(I$2>=Projections!$D77,I$2<Projections!$F77),Projections!$B77,if(and(I$2>=Projections!$F77,I$2<Projections!$I77),Projections!$B77+Projections!$G77,if(and(I$2>=Projections!$I77,I$2<Projections!$L77),Projections!$B77+Projections!$G77+Projections!$J77,IF(I$2>=Projections!$L77,Projections!$B77+Projections!$G77+Projections!$J77+Projections!$M77,""))))) -> 0 | J59: =IF(J$2<Projections!$D77,0,IF(and(J$2>=Projections!$D77,J$2<Projections!$F77),Projections!$B77,if(and(J$2>=Projections!$F77,J$2<Projections!$I77),Projections!$B77+Projections!$G77,if(and(J$2>=Projections!$I77,J$2<Projections!$L77),Projections!$B77+Projections!$G77+Projections!$J77,IF(J$2>=Projections!$L77,Projections!$B77+Projections!$G77+Projections!$J77+Projections!$M77,""))))) -> 0 | K59: =IF(K$2<Projections!$D77,0,IF(and(K$2>=Projections!$D77,K$2<Projections!$F77),Projections!$B77,if(and(K$2>=Projections!$F77,K$2<Projections!$I77),Projections!$B77+Projections!$G77,if(and(K$2>=Projections!$I77,K$2<Projections!$L77),Projections!$B77+Projections!$G77+Projections!$J77,IF(K$2>=Projections!$L77,Projections!$B77+Projections!$G77+Projections!$J77+Projections!$M77,""))))) -> 0 | L59: =IF(L$2<Projections!$D77,0,IF(and(L$2>=Projections!$D77,L$2<Projections!$F77),Projections!$B77,if(and(L$2>=Projections!$F77,L$2<Projections!$I77),Projections!$B77+Projections!$G77,if(and(L$2>=Projections!$I77,L$2<Projections!$L77),Projections!$B77+Projections!$G77+Projections!$J77,IF(L$2>=Projections!$L77,Projections!$B77+Projections!$G77+Projections!$J77+Projections!$M77,""))))) -> 0 | ... CX59: =IF(CX$2<Projections!$D77,0,IF(and(CX$2>=Projections!$D77,CX$2<Projections!$F77),Projections!$B77,if(and(CX$2>=Projections!$F77,CX$2<Projections!$I77),Projections!$B77+Projections!$G77,if(and(CX$2>=Projections!$I77,CX$2<Projections!$L77),Projections!$B77+Projections!$G77+Projections!$J77,IF(CX$2>=Projections!$L77,Projections!$B77+Projections!$G77+Projections!$J77+Projections!$M77,""))))) -> 0
A60: =Projections!A78 -> Channel 3 | E60: =IF(E$2<Projections!$D78,0,IF(and(E$2>=Projections!$D78,E$2<Projections!$F78),Projections!$B78,if(and(E$2>=Projections!$F78,E$2<Projections!$I78),Projections!$B78+Projections!$G78,if(and(E$2>=Projections!$I78,E$2<Projections!$L78),Projections!$B78+Projections!$G78+Projections!$J78,IF(E$2>=Projections!$L78,Projections!$B78+Projections!$G78+Projections!$J78+Projections!$M78,""))))) -> 0 | F60: =IF(F$2<Projections!$D78,0,IF(and(F$2>=Projections!$D78,F$2<Projections!$F78),Projections!$B78,if(and(F$2>=Projections!$F78,F$2<Projections!$I78),Projections!$B78+Projections!$G78,if(and(F$2>=Projections!$I78,F$2<Projections!$L78),Projections!$B78+Projections!$G78+Projections!$J78,IF(F$2>=Projections!$L78,Projections!$B78+Projections!$G78+Projections!$J78+Projections!$M78,""))))) -> 0 | G60: =IF(G$2<Projections!$D78,0,IF(and(G$2>=Projections!$D78,G$2<Projections!$F78),Projections!$B78,if(and(G$2>=Projections!$F78,G$2<Projections!$I78),Projections!$B78+Projections!$G78,if(and(G$2>=Projections!$I78,G$2<Projections!$L78),Projections!$B78+Projections!$G78+Projections!$J78,IF(G$2>=Projections!$L78,Projections!$B78+Projections!$G78+Projections!$J78+Projections!$M78,""))))) -> 0 | H60: =IF(H$2<Projections!$D78,0,IF(and(H$2>=Projections!$D78,H$2<Projections!$F78),Projections!$B78,if(and(H$2>=Projections!$F78,H$2<Projections!$I78),Projections!$B78+Projections!$G78,if(and(H$2>=Projections!$I78,H$2<Projections!$L78),Projections!$B78+Projections!$G78+Projections!$J78,IF(H$2>=Projections!$L78,Projections!$B78+Projections!$G78+Projections!$J78+Projections!$M78,""))))) -> 0 | I60: =IF(I$2<Projections!$D78,0,IF(and(I$2>=Projections!$D78,I$2<Projections!$F78),Projections!$B78,if(and(I$2>=Projections!$F78,I$2<Projections!$I78),Projections!$B78+Projections!$G78,if(and(I$2>=Projections!$I78,I$2<Projections!$L78),Projections!$B78+Projections!$G78+Projections!$J78,IF(I$2>=Projections!$L78,Projections!$B78+Projections!$G78+Projections!$J78+Projections!$M78,""))))) -> 0 | J60: =IF(J$2<Projections!$D78,0,IF(and(J$2>=Projections!$D78,J$2<Projections!$F78),Projections!$B78,if(and(J$2>=Projections!$F78,J$2<Projections!$I78),Projections!$B78+Projections!$G78,if(and(J$2>=Projections!$I78,J$2<Projections!$L78),Projections!$B78+Projections!$G78+Projections!$J78,IF(J$2>=Projections!$L78,Projections!$B78+Projections!$G78+Projections!$J78+Projections!$M78,""))))) -> 0 | K60: =IF(K$2<Projections!$D78,0,IF(and(K$2>=Projections!$D78,K$2<Projections!$F78),Projections!$B78,if(and(K$2>=Projections!$F78,K$2<Projections!$I78),Projections!$B78+Projections!$G78,if(and(K$2>=Projections!$I78,K$2<Projections!$L78),Projections!$B78+Projections!$G78+Projections!$J78,IF(K$2>=Projections!$L78,Projections!$B78+Projections!$G78+Projections!$J78+Projections!$M78,""))))) -> 0 | L60: =IF(L$2<Projections!$D78,0,IF(and(L$2>=Projections!$D78,L$2<Projections!$F78),Projections!$B78,if(and(L$2>=Projections!$F78,L$2<Projections!$I78),Projections!$B78+Projections!$G78,if(and(L$2>=Projections!$I78,L$2<Projections!$L78),Projections!$B78+Projections!$G78+Projections!$J78,IF(L$2>=Projections!$L78,Projections!$B78+Projections!$G78+Projections!$J78+Projections!$M78,""))))) -> 0 | ... CX60: =IF(CX$2<Projections!$D78,0,IF(and(CX$2>=Projections!$D78,CX$2<Projections!$F78),Projections!$B78,if(and(CX$2>=Projections!$F78,CX$2<Projections!$I78),Projections!$B78+Projections!$G78,if(and(CX$2>=Projections!$I78,CX$2<Projections!$L78),Projections!$B78+Projections!$G78+Projections!$J78,IF(CX$2>=Projections!$L78,Projections!$B78+Projections!$G78+Projections!$J78+Projections!$M78,""))))) -> 0
A64: Direct response campaigns
A65: Budget | B65: Marketing | D65: =IF(D2<Projections!$D$19,0,IF(and(D2>=Projections!$D$19,D2<Projections!$F$19),Projections!$B$19,if(and(D2>=Projections!$F$19,D2<Projections!$I$19),Projections!$B$19+Projections!$G$19,if(and(D2>=Projections!$I$19,D2<Projections!$L$19),Projections!$B$19+Projections!$G$19+Projections!$J$19,IF(D2>=Projections!$L$19,Projections!$B$19+Projections!$G$19+Projections!$J$19+Projections!$M$19,""))))) -> 0 | E65: =IF(E$2<Projections!$D$19,0,IF(and(E$2>=Projections!$D$19,E$2<Projections!$F$19),Projections!$B$19,if(and(E$2>=Projections!$F$19,E$2<Projections!$I$19),Projections!$B$19+Projections!$G$19,if(and(E$2>=Projections!$I$19,E$2<Projections!$L$19),Projections!$B$19+Projections!$G$19+Projections!$J$19,IF(E$2>=Projections!$L$19,Projections!$B$19+Projections!$G$19+Projections!$J$19+Projections!$M$19,""))))) -> 1000 | F65: =IF(F2<Projections!$D$19,0,IF(and(F2>=Projections!$D$19,F2<Projections!$F$19),Projections!$B$19,if(and(F2>=Projections!$F$19,F2<Projections!$I$19),Projections!$B$19+Projections!$G$19,if(and(F2>=Projections!$I$19,F2<Projections!$L$19),Projections!$B$19+Projections!$G$19+Projections!$J$19,IF(F2>=Projections!$L$19,Projections!$B$19+Projections!$G$19+Projections!$J$19+Projections!$M$19,""))))) -> 1000 | G65: =IF(G2<Projections!$D$19,0,IF(and(G2>=Projections!$D$19,G2<Projections!$F$19),Projections!$B$19,if(and(G2>=Projections!$F$19,G2<Projections!$I$19),Projections!$B$19+Projections!$G$19,if(and(G2>=Projections!$I$19,G2<Projections!$L$19),Projections!$B$19+Projections!$G$19+Projections!$J$19,IF(G2>=Projections!$L$19,Projections!$B$19+Projections!$G$19+Projections!$J$19+Projections!$M$19,""))))) -> 1000 | H65: =IF(H2<Projections!$D$19,0,IF(and(H2>=Projections!$D$19,H2<Projections!$F$19),Projections!$B$19,if(and(H2>=Projections!$F$19,H2<Projections!$I$19),Projections!$B$19+Projections!$G$19,if(and(H2>=Projections!$I$19,H2<Projections!$L$19),Projections!$B$19+Projections!$G$19+Projections!$J$19,IF(H2>=Projections!$L$19,Projections!$B$19+Projections!$G$19+Projections!$J$19+Projections!$M$19,""))))) -> 1000 | I65: =IF(I2<Projections!$D$19,0,IF(and(I2>=Projections!$D$19,I2<Projections!$F$19),Projections!$B$19,if(and(I2>=Projections!$F$19,I2<Projections!$I$19),Projections!$B$19+Projections!$G$19,if(and(I2>=Projections!$I$19,I2<Projections!$L$19),Projections!$B$19+Projections!$G$19+Projections!$J$19,IF(I2>=Projections!$L$19,Projections!$B$19+Projections!$G$19+Projections!$J$19+Projections!$M$19,""))))) -> 1000 | J65: =IF(J2<Projections!$D$19,0,IF(and(J2>=Projections!$D$19,J2<Projections!$F$19),Projections!$B$19,if(and(J2>=Projections!$F$19,J2<Projections!$I$19),Projections!$B$19+Projections!$G$19,if(and(J2>=Projections!$I$19,J2<Projections!$L$19),Projections!$B$19+Projections!$G$19+Projections!$J$19,IF(J2>=Projections!$L$19,Projections!$B$19+Projections!$G$19+Projections!$J$19+Projections!$M$19,""))))) -> 1000 | K65: =IF(K2<Projections!$D$19,0,IF(and(K2>=Projections!$D$19,K2<Projections!$F$19),Projections!$B$19,if(and(K2>=Projections!$F$19,K2<Projections!$I$19),Projections!$B$19+Projections!$G$19,if(and(K2>=Projections!$I$19,K2<Projections!$L$19),Projections!$B$19+Projections!$G$19+Projections!$J$19,IF(K2>=Projections!$L$19,Projections!$B$19+Projections!$G$19+Projections!$J$19+Projections!$M$19,""))))) -> 1000 | L65: =IF(L2<Projections!$D$19,0,IF(and(L2>=Projections!$D$19,L2<Projections!$F$19),Projections!$B$19,if(and(L2>=Projections!$F$19,L2<Projections!$I$19),Projections!$B$19+Projections!$G$19,if(and(L2>=Projections!$I$19,L2<Projections!$L$19),Projections!$B$19+Projections!$G$19+Projections!$J$19,IF(L2>=Projections!$L$19,Projections!$B$19+Projections!$G$19+Projections!$J$19+Projections!$M$19,""))))) -> 1000 | M65: =IF(M2<Projections!$D$19,0,IF(and(M2>=Projections!$D$19,M2<Projections!$F$19),Projections!$B$19,if(and(M2>=Projections!$F$19,M2<Projections!$I$19),Projections!$B$19+Projections!$G$19,if(and(M2>=Projections!$I$19,M2<Projections!$L$19),Projections!$B$19+Projections!$G$19+Projections!$J$19,IF(M2>=Projections!$L$19,Projections!$B$19+Projections!$G$19+Projections!$J$19+Projections!$M$19,""))))) -> 1000 | ... CX65: =IF(CX2<Projections!$D$19,0,IF(and(CX2>=Projections!$D$19,CX2<Projections!$F$19),Projections!$B$19,if(and(CX2>=Projections!$F$19,CX2<Projections!$I$19),Projections!$B$19+Projections!$G$19,if(and(CX2>=Projections!$I$19,CX2<Projections!$L$19),Projections!$B$19+Projections!$G$19+Projections!$J$19,IF(CX2>=Projections!$L$19,Projections!$B$19+Projections!$G$19+Projections!$J$19+Projections!$M$19,""))))) -> 1000
A68: Other marketing expenses | B68: Marketing | E68: =SUM(E69:E76) -> 0 | F68: =SUM(F69:F76) -> 0 | G68: =SUM(G69:G76) -> 0 | H68: =SUM(H69:H76) -> 0 | I68: =SUM(I69:I76) -> 0 | J68: =SUM(J69:J76) -> 0 | K68: =SUM(K69:K76) -> 0 | L68: =SUM(L69:L76) -> 0 | ... CX68: =SUM(CX69:CX76) -> 0
A69: =Projections!A82 -> Expense 1 | E69: =IF(E$2>=Projections!$D82,Projections!$B82,0) -> 0 | F69: =IF(F$2>=Projections!$D82,Projections!$B82,0) -> 0 | G69: =IF(G$2>=Projections!$D82,Projections!$B82,0) -> 0 | H69: =IF(H$2>=Projections!$D82,Projections!$B82,0) -> 0 | I69: =IF(I$2>=Projections!$D82,Projections!$B82,0) -> 0 | J69: =IF(J$2>=Projections!$D82,Projections!$B82,0) -> 0 | K69: =IF(K$2>=Projections!$D82,Projections!$B82,0) -> 0 | L69: =IF(L$2>=Projections!$D82,Projections!$B82,0) -> 0 | ... CX69: =IF(CX$2>=Projections!$D82,Projections!$B82,0) -> 0
A70: =Projections!A83 -> Expense 2 | E70: =IF(E$2>=Projections!$D83,Projections!$B83,0) -> 0 | F70: =IF(F$2>=Projections!$D83,Projections!$B83,0) -> 0 | G70: =IF(G$2>=Projections!$D83,Projections!$B83,0) -> 0 | H70: =IF(H$2>=Projections!$D83,Projections!$B83,0) -> 0 | I70: =IF(I$2>=Projections!$D83,Projections!$B83,0) -> 0 | J70: =IF(J$2>=Projections!$D83,Projections!$B83,0) -> 0 | K70: =IF(K$2>=Projections!$D83,Projections!$B83,0) -> 0 | L70: =IF(L$2>=Projections!$D83,Projections!$B83,0) -> 0 | ... CX70: =IF(CX$2>=Projections!$D83,Projections!$B83,0) -> 0
A71: =Projections!A84 -> Expense 3 | E71: =IF(E$2>=Projections!$D84,Projections!$B84,0) -> 0 | F71: =IF(F$2>=Projections!$D84,Projections!$B84,0) -> 0 | G71: =IF(G$2>=Projections!$D84,Projections!$B84,0) -> 0 | H71: =IF(H$2>=Projections!$D84,Projections!$B84,0) -> 0 | I71: =IF(I$2>=Projections!$D84,Projections!$B84,0) -> 0 | J71: =IF(J$2>=Projections!$D84,Projections!$B84,0) -> 0 | K71: =IF(K$2>=Projections!$D84,Projections!$B84,0) -> 0 | L71: =IF(L$2>=Projections!$D84,Projections!$B84,0) -> 0 | ... CX71: =IF(CX$2>=Projections!$D84,Projections!$B84,0) -> 0
A72: =Projections!A85 -> Expense 4 | E72: =IF(E$2>=Projections!$D85,Projections!$B85,0) -> 0 | F72: =IF(F$2>=Projections!$D85,Projections!$B85,0) -> 0 | G72: =IF(G$2>=Projections!$D85,Projections!$B85,0) -> 0 | H72: =IF(H$2>=Projections!$D85,Projections!$B85,0) -> 0 | I72: =IF(I$2>=Projections!$D85,Projections!$B85,0) -> 0 | J72: =IF(J$2>=Projections!$D85,Projections!$B85,0) -> 0 | K72: =IF(K$2>=Projections!$D85,Projections!$B85,0) -> 0 | L72: =IF(L$2>=Projections!$D85,Projections!$B85,0) -> 0 | ... CX72: =IF(CX$2>=Projections!$D85,Projections!$B85,0) -> 0
A73: =Projections!A86 -> Expense 5 | E73: =IF(E$2>=Projections!$D86,Projections!$B86,0) -> 0 | F73: =IF(F$2>=Projections!$D86,Projections!$B86,0) -> 0 | G73: =IF(G$2>=Projections!$D86,Projections!$B86,0) -> 0 | H73: =IF(H$2>=Projections!$D86,Projections!$B86,0) -> 0 | I73: =IF(I$2>=Projections!$D86,Projections!$B86,0) -> 0 | J73: =IF(J$2>=Projections!$D86,Projections!$B86,0) -> 0 | K73: =IF(K$2>=Projections!$D86,Projections!$B86,0) -> 0 | L73: =IF(L$2>=Projections!$D86,Projections!$B86,0) -> 0 | ... CX73: =IF(CX$2>=Projections!$D86,Projections!$B86,0) -> 0
A74: =Projections!A87 -> Expense 6 | E74: =IF(E$2>=Projections!$D87,Projections!$B87,0) -> 0 | F74: =IF(F$2>=Projections!$D87,Projections!$B87,0) -> 0 | G74: =IF(G$2>=Projections!$D87,Projections!$B87,0) -> 0 | H74: =IF(H$2>=Projections!$D87,Projections!$B87,0) -> 0 | I74: =IF(I$2>=Projections!$D87,Projections!$B87,0) -> 0 | J74: =IF(J$2>=Projections!$D87,Projections!$B87,0) -> 0 | K74: =IF(K$2>=Projections!$D87,Projections!$B87,0) -> 0 | L74: =IF(L$2>=Projections!$D87,Projections!$B87,0) -> 0 | ... CX74: =IF(CX$2>=Projections!$D87,Projections!$B87,0) -> 0
A75: =Projections!A88 -> Expense 7 | E75: =IF(E$2>=Projections!$D88,Projections!$B88,0) -> 0 | F75: =IF(F$2>=Projections!$D88,Projections!$B88,0) -> 0 | G75: =IF(G$2>=Projections!$D88,Projections!$B88,0) -> 0 | H75: =IF(H$2>=Projections!$D88,Projections!$B88,0) -> 0 | I75: =IF(I$2>=Projections!$D88,Projections!$B88,0) -> 0 | J75: =IF(J$2>=Projections!$D88,Projections!$B88,0) -> 0 | K75: =IF(K$2>=Projections!$D88,Projections!$B88,0) -> 0 | L75: =IF(L$2>=Projections!$D88,Projections!$B88,0) -> 0 | ... CX75: =IF(CX$2>=Projections!$D88,Projections!$B88,0) -> 0
A76: =Projections!A89 -> Expense 8 | E76: =IF(E$2>=Projections!$D89,Projections!$B89,0) -> 0 | F76: =IF(F$2>=Projections!$D89,Projections!$B89,0) -> 0 | G76: =IF(G$2>=Projections!$D89,Projections!$B89,0) -> 0 | H76: =IF(H$2>=Projections!$D89,Projections!$B89,0) -> 0 | I76: =IF(I$2>=Projections!$D89,Projections!$B89,0) -> 0 | J76: =IF(J$2>=Projections!$D89,Projections!$B89,0) -> 0 | K76: =IF(K$2>=Projections!$D89,Projections!$B89,0) -> 0 | L76: =IF(L$2>=Projections!$D89,Projections!$B89,0) -> 0 | ... CX76: =IF(CX$2>=Projections!$D89,Projections!$B89,0) -> 0
A77: =Projections!A90
A79: SALES | E79: =E84+E89 -> 3076.9231 | F79: =F84+F89 -> 3076.9231 | G79: =G84+G89 -> 3076.9231 | H79: =H84+H89 -> 3076.9231 | I79: =I84+I89 -> 3076.9231 | J79: =J84+J89 -> 3076.9231 | K79: =K84+K89 -> 3076.9231 | L79: =L84+L89 -> 3076.9231 | ... CX79: =CX84+CX89 -> 182057.84
A81: Inbound Sales Managers
A82: Number of Inbound Managers | E82: =ROUNDUP(E26/Projections!$B$49,0) -> 2 | F82: =ROUNDUP(F26/Projections!$B$49,0) -> 2 | G82: =ROUNDUP(G26/Projections!$B$49,0) -> 2 | H82: =ROUNDUP(H26/Projections!$B$49,0) -> 2 | I82: =ROUNDUP(I26/Projections!$B$49,0) -> 2 | J82: =ROUNDUP(J26/Projections!$B$49,0) -> 2 | K82: =ROUNDUP(K26/Projections!$B$49,0) -> 2 | L82: =ROUNDUP(L26/Projections!$B$49,0) -> 2 | ... CX82: =ROUNDUP(CX26/Projections!$B$49,0) -> 101
A83: Cost per manager | E83: =IF(E$2=Payroll!$I45,Payroll!$F45,IF(E$2>Payroll!$I45,Payroll!$F45*((1+Payroll!$J45)^(ROUNDDOWN(DATEDIF(Payroll!$I45,E$2,"M")/Payroll!$K45,0))),0)) -> 1538.4615 | F83: =IF(F$2=Payroll!$I45,Payroll!$F45,IF(F$2>Payroll!$I45,Payroll!$F45*((1+Payroll!$J45)^(ROUNDDOWN(DATEDIF(Payroll!$I45,F$2,"M")/Payroll!$K45,0))),0)) -> 1538.4615 | G83: =IF(G$2=Payroll!$I45,Payroll!$F45,IF(G$2>Payroll!$I45,Payroll!$F45*((1+Payroll!$J45)^(ROUNDDOWN(DATEDIF(Payroll!$I45,G$2,"M")/Payroll!$K45,0))),0)) -> 1538.4615 | H83: =IF(H$2=Payroll!$I45,Payroll!$F45,IF(H$2>Payroll!$I45,Payroll!$F45*((1+Payroll!$J45)^(ROUNDDOWN(DATEDIF(Payroll!$I45,H$2,"M")/Payroll!$K45,0))),0)) -> 1538.4615 | I83: =IF(I$2=Payroll!$I45,Payroll!$F45,IF(I$2>Payroll!$I45,Payroll!$F45*((1+Payroll!$J45)^(ROUNDDOWN(DATEDIF(Payroll!$I45,I$2,"M")/Payroll!$K45,0))),0)) -> 1538.4615 | J83: =IF(J$2=Payroll!$I45,Payroll!$F45,IF(J$2>Payroll!$I45,Payroll!$F45*((1+Payroll!$J45)^(ROUNDDOWN(DATEDIF(Payroll!$I45,J$2,"M")/Payroll!$K45,0))),0)) -> 1538.4615 | K83: =IF(K$2=Payroll!$I45,Payroll!$F45,IF(K$2>Payroll!$I45,Payroll!$F45*((1+Payroll!$J45)^(ROUNDDOWN(DATEDIF(Payroll!$I45,K$2,"M")/Payroll!$K45,0))),0)) -> 1538.4615 | L83: =IF(L$2=Payroll!$I45,Payroll!$F45,IF(L$2>Payroll!$I45,Payroll!$F45*((1+Payroll!$J45)^(ROUNDDOWN(DATEDIF(Payroll!$I45,L$2,"M")/Payroll!$K45,0))),0)) -> 1538.4615 | ... CX83: =IF(CX$2=Payroll!$I45,Payroll!$F45,IF(CX$2>Payroll!$I45,Payroll!$F45*((1+Payroll!$J45)^(ROUNDDOWN(DATEDIF(Payroll!$I45,CX$2,"M")/Payroll!$K45,0))),0)) -> 1802.5529
A84: Total cost | E84: =E82*E83 -> 3076.9231 | F84: =F82*F83 -> 3076.9231 | G84: =G82*G83 -> 3076.9231 | H84: =H82*H83 -> 3076.9231 | I84: =I82*I83 -> 3076.9231 | J84: =J82*J83 -> 3076.9231 | K84: =K82*K83 -> 3076.9231 | L84: =L82*L83 -> 3076.9231 | ... CX84: =CX82*CX83 -> 182057.84
A86: Outbound Sales Managers
A87: Number of Outbound Managers | E87: =IF(E2=Projections!$C$56,Projections!$B$58,if(E2>Projections!$C$56,MIN(Projections!$B$60,D87+IF(mod(DATEDIF(Projections!$C$56,E2,"M"),Projections!$B$59)=0,1,0)),0)) -> 1 | F87: =IF(F2=Projections!$C$56,Projections!$B$58,if(F2>Projections!$C$56,MIN(Projections!$B$60,E87+IF(mod(DATEDIF(Projections!$C$56,F2,"M"),Projections!$B$59)=0,1,0)),0)) -> 1 | G87: =IF(G2=Projections!$C$56,Projections!$B$58,if(G2>Projections!$C$56,MIN(Projections!$B$60,F87+IF(mod(DATEDIF(Projections!$C$56,G2,"M"),Projections!$B$59)=0,1,0)),0)) -> 1 | H87: =IF(H2=Projections!$C$56,Projections!$B$58,if(H2>Projections!$C$56,MIN(Projections!$B$60,G87+IF(mod(DATEDIF(Projections!$C$56,H2,"M"),Projections!$B$59)=0,1,0)),0)) -> 2 | I87: =IF(I2=Projections!$C$56,Projections!$B$58,if(I2>Projections!$C$56,MIN(Projections!$B$60,H87+IF(mod(DATEDIF(Projections!$C$56,I2,"M"),Projections!$B$59)=0,1,0)),0)) -> 2 | J87: =IF(J2=Projections!$C$56,Projections!$B$58,if(J2>Projections!$C$56,MIN(Projections!$B$60,I87+IF(mod(DATEDIF(Projections!$C$56,J2,"M"),Projections!$B$59)=0,1,0)),0)) -> 2 | K87: =IF(K2=Projections!$C$56,Projections!$B$58,if(K2>Projections!$C$56,MIN(Projections!$B$60,J87+IF(mod(DATEDIF(Projections!$C$56,K2,"M"),Projections!$B$59)=0,1,0)),0)) -> 3 | L87: =IF(L2=Projections!$C$56,Projections!$B$58,if(L2>Projections!$C$56,MIN(Projections!$B$60,K87+IF(mod(DATEDIF(Projections!$C$56,L2,"M"),Projections!$B$59)=0,1,0)),0)) -> 3 | ... CX87: =IF(CX2=Projections!$C$56,Projections!$B$58,if(CX2>Projections!$C$56,MIN(Projections!$B$60,CW87+IF(mod(DATEDIF(Projections!$C$56,CX2,"M"),Projections!$B$59)=0,1,0)),0)) -> 10
A88: Cost per manager | E88: =IF(E$2=Payroll!$I46,Payroll!$F46,IF(E$2>Payroll!$I46,Payroll!$F46*((1+Payroll!$J46)^(ROUNDDOWN(DATEDIF(Payroll!$I46,E$2,"M")/Payroll!$K46,0))),0)) -> 0 | F88: =IF(F$2=Payroll!$I46,Payroll!$F46,IF(F$2>Payroll!$I46,Payroll!$F46*((1+Payroll!$J46)^(ROUNDDOWN(DATEDIF(Payroll!$I46,F$2,"M")/Payroll!$K46,0))),0)) -> 0 | G88: =IF(G$2=Payroll!$I46,Payroll!$F46,IF(G$2>Payroll!$I46,Payroll!$F46*((1+Payroll!$J46)^(ROUNDDOWN(DATEDIF(Payroll!$I46,G$2,"M")/Payroll!$K46,0))),0)) -> 0 | H88: =IF(H$2=Payroll!$I46,Payroll!$F46,IF(H$2>Payroll!$I46,Payroll!$F46*((1+Payroll!$J46)^(ROUNDDOWN(DATEDIF(Payroll!$I46,H$2,"M")/Payroll!$K46,0))),0)) -> 0 | I88: =IF(I$2=Payroll!$I46,Payroll!$F46,IF(I$2>Payroll!$I46,Payroll!$F46*((1+Payroll!$J46)^(ROUNDDOWN(DATEDIF(Payroll!$I46,I$2,"M")/Payroll!$K46,0))),0)) -> 0 | J88: =IF(J$2=Payroll!$I46,Payroll!$F46,IF(J$2>Payroll!$I46,Payroll!$F46*((1+Payroll!$J46)^(ROUNDDOWN(DATEDIF(Payroll!$I46,J$2,"M")/Payroll!$K46,0))),0)) -> 0 | K88: =IF(K$2=Payroll!$I46,Payroll!$F46,IF(K$2>Payroll!$I46,Payroll!$F46*((1+Payroll!$J46)^(ROUNDDOWN(DATEDIF(Payroll!$I46,K$2,"M")/Payroll!$K46,0))),0)) -> 0 | L88: =IF(L$2=Payroll!$I46,Payroll!$F46,IF(L$2>Payroll!$I46,Payroll!$F46*((1+Payroll!$J46)^(ROUNDDOWN(DATEDIF(Payroll!$I46,L$2,"M")/Payroll!$K46,0))),0)) -> 0 | ... CX88: =IF(CX$2=Payroll!$I46,Payroll!$F46,IF(CX$2>Payroll!$I46,Payroll!$F46*((1+Payroll!$J46)^(ROUNDDOWN(DATEDIF(Payroll!$I46,CX$2,"M")/Payroll!$K46,0))),0)) -> 0
A89: Total cost | E89: =E88*E87 -> 0 | F89: =F88*F87 -> 0 | G89: =G88*G87 -> 0 | H89: =H88*H87 -> 0 | I89: =I88*I87 -> 0 | J89: =J88*J87 -> 0 | K89: =K88*K87 -> 0 | L89: =L88*L87 -> 0 | ... CX89: =CX88*CX87 -> 0
A91: PAYROLL | E91: =E92+E104+E115+E127 -> 0 | F91: =F92+F104+F115+F127 -> 0 | G91: =G92+G104+G115+G127 -> 0 | H91: =H92+H104+H115+H127 -> 0 | I91: =I92+I104+I115+I127 -> 0 | J91: =J92+J104+J115+J127 -> 0 | K91: =K92+K104+K115+K127 -> 0 | L91: =L92+L104+L115+L127 -> 0 | ... CX91: =CX92+CX104+CX115+CX127 -> 50995.973
A92: IT | B92: Development | E92: =SUM(E93:E102) -> 0 | F92: =SUM(F93:F102) -> 0 | G92: =SUM(G93:G102) -> 0 | H92: =SUM(H93:H102) -> 0 | I92: =SUM(I93:I102) -> 0 | J92: =SUM(J93:J102) -> 0 | K92: =SUM(K93:K102) -> 0 | L92: =SUM(L93:L102) -> 0 | ... CX92: =SUM(CX93:CX102) -> 22871.71
A93: =Payroll!A17 -> CTO | E93: =IF(E$2=Payroll!$I17,Payroll!$F17,IF(E$2>Payroll!$I17,Payroll!$F17*((1+Payroll!$J17)^(ROUNDDOWN(DATEDIF(Payroll!$I17,E$2,"M")/Payroll!$K17,0))),0)) -> 0 | F93: =IF(F$2=Payroll!$I17,Payroll!$F17,IF(F$2>Payroll!$I17,Payroll!$F17*((1+Payroll!$J17)^(ROUNDDOWN(DATEDIF(Payroll!$I17,F$2,"M")/Payroll!$K17,0))),0)) -> 0 | G93: =IF(G$2=Payroll!$I17,Payroll!$F17,IF(G$2>Payroll!$I17,Payroll!$F17*((1+Payroll!$J17)^(ROUNDDOWN(DATEDIF(Payroll!$I17,G$2,"M")/Payroll!$K17,0))),0)) -> 0 | H93: =IF(H$2=Payroll!$I17,Payroll!$F17,IF(H$2>Payroll!$I17,Payroll!$F17*((1+Payroll!$J17)^(ROUNDDOWN(DATEDIF(Payroll!$I17,H$2,"M")/Payroll!$K17,0))),0)) -> 0 | I93: =IF(I$2=Payroll!$I17,Payroll!$F17,IF(I$2>Payroll!$I17,Payroll!$F17*((1+Payroll!$J17)^(ROUNDDOWN(DATEDIF(Payroll!$I17,I$2,"M")/Payroll!$K17,0))),0)) -> 0 | J93: =IF(J$2=Payroll!$I17,Payroll!$F17,IF(J$2>Payroll!$I17,Payroll!$F17*((1+Payroll!$J17)^(ROUNDDOWN(DATEDIF(Payroll!$I17,J$2,"M")/Payroll!$K17,0))),0)) -> 0 | K93: =IF(K$2=Payroll!$I17,Payroll!$F17,IF(K$2>Payroll!$I17,Payroll!$F17*((1+Payroll!$J17)^(ROUNDDOWN(DATEDIF(Payroll!$I17,K$2,"M")/Payroll!$K17,0))),0)) -> 0 | L93: =IF(L$2=Payroll!$I17,Payroll!$F17,IF(L$2>Payroll!$I17,Payroll!$F17*((1+Payroll!$J17)^(ROUNDDOWN(DATEDIF(Payroll!$I17,L$2,"M")/Payroll!$K17,0))),0)) -> 0 | ... CX93: =IF(CX$2=Payroll!$I17,Payroll!$F17,IF(CX$2>Payroll!$I17,Payroll!$F17*((1+Payroll!$J17)^(ROUNDDOWN(DATEDIF(Payroll!$I17,CX$2,"M")/Payroll!$K17,0))),0)) -> 15384.615
A94: =Payroll!A18 -> Developer frontend | E94: =IF(E$2=Payroll!$I18,Payroll!$F18,IF(E$2>Payroll!$I18,Payroll!$F18*((1+Payroll!$J18)^(ROUNDDOWN(DATEDIF(Payroll!$I18,E$2,"M")/Payroll!$K18,0))),0)) -> 0 | F94: =IF(F$2=Payroll!$I18,Payroll!$F18,IF(F$2>Payroll!$I18,Payroll!$F18*((1+Payroll!$J18)^(ROUNDDOWN(DATEDIF(Payroll!$I18,F$2,"M")/Payroll!$K18,0))),0)) -> 0 | G94: =IF(G$2=Payroll!$I18,Payroll!$F18,IF(G$2>Payroll!$I18,Payroll!$F18*((1+Payroll!$J18)^(ROUNDDOWN(DATEDIF(Payroll!$I18,G$2,"M")/Payroll!$K18,0))),0)) -> 0 | H94: =IF(H$2=Payroll!$I18,Payroll!$F18,IF(H$2>Payroll!$I18,Payroll!$F18*((1+Payroll!$J18)^(ROUNDDOWN(DATEDIF(Payroll!$I18,H$2,"M")/Payroll!$K18,0))),0)) -> 0 | I94: =IF(I$2=Payroll!$I18,Payroll!$F18,IF(I$2>Payroll!$I18,Payroll!$F18*((1+Payroll!$J18)^(ROUNDDOWN(DATEDIF(Payroll!$I18,I$2,"M")/Payroll!$K18,0))),0)) -> 0 | J94: =IF(J$2=Payroll!$I18,Payroll!$F18,IF(J$2>Payroll!$I18,Payroll!$F18*((1+Payroll!$J18)^(ROUNDDOWN(DATEDIF(Payroll!$I18,J$2,"M")/Payroll!$K18,0))),0)) -> 0 | K94: =IF(K$2=Payroll!$I18,Payroll!$F18,IF(K$2>Payroll!$I18,Payroll!$F18*((1+Payroll!$J18)^(ROUNDDOWN(DATEDIF(Payroll!$I18,K$2,"M")/Payroll!$K18,0))),0)) -> 0 | L94: =IF(L$2=Payroll!$I18,Payroll!$F18,IF(L$2>Payroll!$I18,Payroll!$F18*((1+Payroll!$J18)^(ROUNDDOWN(DATEDIF(Payroll!$I18,L$2,"M")/Payroll!$K18,0))),0)) -> 0 | ... CX94: =IF(CX$2=Payroll!$I18,Payroll!$F18,IF(CX$2>Payroll!$I18,Payroll!$F18*((1+Payroll!$J18)^(ROUNDDOWN(DATEDIF(Payroll!$I18,CX$2,"M")/Payroll!$K18,0))),0)) -> 7487.0948
A95: =Payroll!A19 -> Developer backend | E95: =IF(E$2=Payroll!$I19,Payroll!$F19,IF(E$2>Payroll!$I19,Payroll!$F19*((1+Payroll!$J19)^(ROUNDDOWN(DATEDIF(Payroll!$I19,E$2,"M")/Payroll!$K19,0))),0)) -> 0 | F95: =IF(F$2=Payroll!$I19,Payroll!$F19,IF(F$2>Payroll!$I19,Payroll!$F19*((1+Payroll!$J19)^(ROUNDDOWN(DATEDIF(Payroll!$I19,F$2,"M")/Payroll!$K19,0))),0)) -> 0 | G95: =IF(G$2=Payroll!$I19,Payroll!$F19,IF(G$2>Payroll!$I19,Payroll!$F19*((1+Payroll!$J19)^(ROUNDDOWN(DATEDIF(Payroll!$I19,G$2,"M")/Payroll!$K19,0))),0)) -> 0 | H95: =IF(H$2=Payroll!$I19,Payroll!$F19,IF(H$2>Payroll!$I19,Payroll!$F19*((1+Payroll!$J19)^(ROUNDDOWN(DATEDIF(Payroll!$I19,H$2,"M")/Payroll!$K19,0))),0)) -> 0 | I95: =IF(I$2=Payroll!$I19,Payroll!$F19,IF(I$2>Payroll!$I19,Payroll!$F19*((1+Payroll!$J19)^(ROUNDDOWN(DATEDIF(Payroll!$I19,I$2,"M")/Payroll!$K19,0))),0)) -> 0 | J95: =IF(J$2=Payroll!$I19,Payroll!$F19,IF(J$2>Payroll!$I19,Payroll!$F19*((1+Payroll!$J19)^(ROUNDDOWN(DATEDIF(Payroll!$I19,J$2,"M")/Payroll!$K19,0))),0)) -> 0 | K95: =IF(K$2=Payroll!$I19,Payroll!$F19,IF(K$2>Payroll!$I19,Payroll!$F19*((1+Payroll!$J19)^(ROUNDDOWN(DATEDIF(Payroll!$I19,K$2,"M")/Payroll!$K19,0))),0)) -> 0 | L95: =IF(L$2=Payroll!$I19,Payroll!$F19,IF(L$2>Payroll!$I19,Payroll!$F19*((1+Payroll!$J19)^(ROUNDDOWN(DATEDIF(Payroll!$I19,L$2,"M")/Payroll!$K19,0))),0)) -> 0 | ... CX95: =IF(CX$2=Payroll!$I19,Payroll!$F19,IF(CX$2>Payroll!$I19,Payroll!$F19*((1+Payroll!$J19)^(ROUNDDOWN(DATEDIF(Payroll!$I19,CX$2,"M")/Payroll!$K19,0))),0)) -> 0
A96: =Payroll!A20 -> Developer fullstack | E96: =IF(E$2=Payroll!$I20,Payroll!$F20,IF(E$2>Payroll!$I20,Payroll!$F20*((1+Payroll!$J20)^(ROUNDDOWN(DATEDIF(Payroll!$I20,E$2,"M")/Payroll!$K20,0))),0)) -> 0 | F96: =IF(F$2=Payroll!$I20,Payroll!$F20,IF(F$2>Payroll!$I20,Payroll!$F20*((1+Payroll!$J20)^(ROUNDDOWN(DATEDIF(Payroll!$I20,F$2,"M")/Payroll!$K20,0))),0)) -> 0 | G96: =IF(G$2=Payroll!$I20,Payroll!$F20,IF(G$2>Payroll!$I20,Payroll!$F20*((1+Payroll!$J20)^(ROUNDDOWN(DATEDIF(Payroll!$I20,G$2,"M")/Payroll!$K20,0))),0)) -> 0 | H96: =IF(H$2=Payroll!$I20,Payroll!$F20,IF(H$2>Payroll!$I20,Payroll!$F20*((1+Payroll!$J20)^(ROUNDDOWN(DATEDIF(Payroll!$I20,H$2,"M")/Payroll!$K20,0))),0)) -> 0 | I96: =IF(I$2=Payroll!$I20,Payroll!$F20,IF(I$2>Payroll!$I20,Payroll!$F20*((1+Payroll!$J20)^(ROUNDDOWN(DATEDIF(Payroll!$I20,I$2,"M")/Payroll!$K20,0))),0)) -> 0 | J96: =IF(J$2=Payroll!$I20,Payroll!$F20,IF(J$2>Payroll!$I20,Payroll!$F20*((1+Payroll!$J20)^(ROUNDDOWN(DATEDIF(Payroll!$I20,J$2,"M")/Payroll!$K20,0))),0)) -> 0 | K96: =IF(K$2=Payroll!$I20,Payroll!$F20,IF(K$2>Payroll!$I20,Payroll!$F20*((1+Payroll!$J20)^(ROUNDDOWN(DATEDIF(Payroll!$I20,K$2,"M")/Payroll!$K20,0))),0)) -> 0 | L96: =IF(L$2=Payroll!$I20,Payroll!$F20,IF(L$2>Payroll!$I20,Payroll!$F20*((1+Payroll!$J20)^(ROUNDDOWN(DATEDIF(Payroll!$I20,L$2,"M")/Payroll!$K20,0))),0)) -> 0 | ... CX96: =IF(CX$2=Payroll!$I20,Payroll!$F20,IF(CX$2>Payroll!$I20,Payroll!$F20*((1+Payroll!$J20)^(ROUNDDOWN(DATEDIF(Payroll!$I20,CX$2,"M")/Payroll!$K20,0))),0)) -> 0
A97: =Payroll!A21 -> UX designer | E97: =IF(E$2=Payroll!$I21,Payroll!$F21,IF(E$2>Payroll!$I21,Payroll!$F21*((1+Payroll!$J21)^(ROUNDDOWN(DATEDIF(Payroll!$I21,E$2,"M")/Payroll!$K21,0))),0)) -> 0 | F97: =IF(F$2=Payroll!$I21,Payroll!$F21,IF(F$2>Payroll!$I21,Payroll!$F21*((1+Payroll!$J21)^(ROUNDDOWN(DATEDIF(Payroll!$I21,F$2,"M")/Payroll!$K21,0))),0)) -> 0 | G97: =IF(G$2=Payroll!$I21,Payroll!$F21,IF(G$2>Payroll!$I21,Payroll!$F21*((1+Payroll!$J21)^(ROUNDDOWN(DATEDIF(Payroll!$I21,G$2,"M")/Payroll!$K21,0))),0)) -> 0 | H97: =IF(H$2=Payroll!$I21,Payroll!$F21,IF(H$2>Payroll!$I21,Payroll!$F21*((1+Payroll!$J21)^(ROUNDDOWN(DATEDIF(Payroll!$I21,H$2,"M")/Payroll!$K21,0))),0)) -> 0 | I97: =IF(I$2=Payroll!$I21,Payroll!$F21,IF(I$2>Payroll!$I21,Payroll!$F21*((1+Payroll!$J21)^(ROUNDDOWN(DATEDIF(Payroll!$I21,I$2,"M")/Payroll!$K21,0))),0)) -> 0 | J97: =IF(J$2=Payroll!$I21,Payroll!$F21,IF(J$2>Payroll!$I21,Payroll!$F21*((1+Payroll!$J21)^(ROUNDDOWN(DATEDIF(Payroll!$I21,J$2,"M")/Payroll!$K21,0))),0)) -> 0 | K97: =IF(K$2=Payroll!$I21,Payroll!$F21,IF(K$2>Payroll!$I21,Payroll!$F21*((1+Payroll!$J21)^(ROUNDDOWN(DATEDIF(Payroll!$I21,K$2,"M")/Payroll!$K21,0))),0)) -> 0 | L97: =IF(L$2=Payroll!$I21,Payroll!$F21,IF(L$2>Payroll!$I21,Payroll!$F21*((1+Payroll!$J21)^(ROUNDDOWN(DATEDIF(Payroll!$I21,L$2,"M")/Payroll!$K21,0))),0)) -> 0 | ... CX97: =IF(CX$2=Payroll!$I21,Payroll!$F21,IF(CX$2>Payroll!$I21,Payroll!$F21*((1+Payroll!$J21)^(ROUNDDOWN(DATEDIF(Payroll!$I21,CX$2,"M")/Payroll!$K21,0))),0)) -> 0
A98: =Payroll!A22 -> Product manager | E98: =IF(E$2=Payroll!$I22,Payroll!$F22,IF(E$2>Payroll!$I22,Payroll!$F22*((1+Payroll!$J22)^(ROUNDDOWN(DATEDIF(Payroll!$I22,E$2,"M")/Payroll!$K22,0))),0)) -> 0 | F98: =IF(F$2=Payroll!$I22,Payroll!$F22,IF(F$2>Payroll!$I22,Payroll!$F22*((1+Payroll!$J22)^(ROUNDDOWN(DATEDIF(Payroll!$I22,F$2,"M")/Payroll!$K22,0))),0)) -> 0 | G98: =IF(G$2=Payroll!$I22,Payroll!$F22,IF(G$2>Payroll!$I22,Payroll!$F22*((1+Payroll!$J22)^(ROUNDDOWN(DATEDIF(Payroll!$I22,G$2,"M")/Payroll!$K22,0))),0)) -> 0 | H98: =IF(H$2=Payroll!$I22,Payroll!$F22,IF(H$2>Payroll!$I22,Payroll!$F22*((1+Payroll!$J22)^(ROUNDDOWN(DATEDIF(Payroll!$I22,H$2,"M")/Payroll!$K22,0))),0)) -> 0 | I98: =IF(I$2=Payroll!$I22,Payroll!$F22,IF(I$2>Payroll!$I22,Payroll!$F22*((1+Payroll!$J22)^(ROUNDDOWN(DATEDIF(Payroll!$I22,I$2,"M")/Payroll!$K22,0))),0)) -> 0 | J98: =IF(J$2=Payroll!$I22,Payroll!$F22,IF(J$2>Payroll!$I22,Payroll!$F22*((1+Payroll!$J22)^(ROUNDDOWN(DATEDIF(Payroll!$I22,J$2,"M")/Payroll!$K22,0))),0)) -> 0 | K98: =IF(K$2=Payroll!$I22,Payroll!$F22,IF(K$2>Payroll!$I22,Payroll!$F22*((1+Payroll!$J22)^(ROUNDDOWN(DATEDIF(Payroll!$I22,K$2,"M")/Payroll!$K22,0))),0)) -> 0 | L98: =IF(L$2=Payroll!$I22,Payroll!$F22,IF(L$2>Payroll!$I22,Payroll!$F22*((1+Payroll!$J22)^(ROUNDDOWN(DATEDIF(Payroll!$I22,L$2,"M")/Payroll!$K22,0))),0)) -> 0 | ... CX98: =IF(CX$2=Payroll!$I22,Payroll!$F22,IF(CX$2>Payroll!$I22,Payroll!$F22*((1+Payroll!$J22)^(ROUNDDOWN(DATEDIF(Payroll!$I22,CX$2,"M")/Payroll!$K22,0))),0)) -> 0
A99: =Payroll!A23 -> DevOps | E99: =IF(E$2=Payroll!$I23,Payroll!$F23,IF(E$2>Payroll!$I23,Payroll!$F23*((1+Payroll!$J23)^(ROUNDDOWN(DATEDIF(Payroll!$I23,E$2,"M")/Payroll!$K23,0))),0)) -> 0 | F99: =IF(F$2=Payroll!$I23,Payroll!$F23,IF(F$2>Payroll!$I23,Payroll!$F23*((1+Payroll!$J23)^(ROUNDDOWN(DATEDIF(Payroll!$I23,F$2,"M")/Payroll!$K23,0))),0)) -> 0 | G99: =IF(G$2=Payroll!$I23,Payroll!$F23,IF(G$2>Payroll!$I23,Payroll!$F23*((1+Payroll!$J23)^(ROUNDDOWN(DATEDIF(Payroll!$I23,G$2,"M")/Payroll!$K23,0))),0)) -> 0 | H99: =IF(H$2=Payroll!$I23,Payroll!$F23,IF(H$2>Payroll!$I23,Payroll!$F23*((1+Payroll!$J23)^(ROUNDDOWN(DATEDIF(Payroll!$I23,H$2,"M")/Payroll!$K23,0))),0)) -> 0 | I99: =IF(I$2=Payroll!$I23,Payroll!$F23,IF(I$2>Payroll!$I23,Payroll!$F23*((1+Payroll!$J23)^(ROUNDDOWN(DATEDIF(Payroll!$I23,I$2,"M")/Payroll!$K23,0))),0)) -> 0 | J99: =IF(J$2=Payroll!$I23,Payroll!$F23,IF(J$2>Payroll!$I23,Payroll!$F23*((1+Payroll!$J23)^(ROUNDDOWN(DATEDIF(Payroll!$I23,J$2,"M")/Payroll!$K23,0))),0)) -> 0 | K99: =IF(K$2=Payroll!$I23,Payroll!$F23,IF(K$2>Payroll!$I23,Payroll!$F23*((1+Payroll!$J23)^(ROUNDDOWN(DATEDIF(Payroll!$I23,K$2,"M")/Payroll!$K23,0))),0)) -> 0 | L99: =IF(L$2=Payroll!$I23,Payroll!$F23,IF(L$2>Payroll!$I23,Payroll!$F23*((1+Payroll!$J23)^(ROUNDDOWN(DATEDIF(Payroll!$I23,L$2,"M")/Payroll!$K23,0))),0)) -> 0 | ... CX99: =IF(CX$2=Payroll!$I23,Payroll!$F23,IF(CX$2>Payroll!$I23,Payroll!$F23*((1+Payroll!$J23)^(ROUNDDOWN(DATEDIF(Payroll!$I23,CX$2,"M")/Payroll!$K23,0))),0)) -> 0
A100: =Payroll!A24 -> Project Manager | E100: =IF(E$2=Payroll!$I24,Payroll!$F24,IF(E$2>Payroll!$I24,Payroll!$F24*((1+Payroll!$J24)^(ROUNDDOWN(DATEDIF(Payroll!$I24,E$2,"M")/Payroll!$K24,0))),0)) -> 0 | F100: =IF(F$2=Payroll!$I24,Payroll!$F24,IF(F$2>Payroll!$I24,Payroll!$F24*((1+Payroll!$J24)^(ROUNDDOWN(DATEDIF(Payroll!$I24,F$2,"M")/Payroll!$K24,0))),0)) -> 0 | G100: =IF(G$2=Payroll!$I24,Payroll!$F24,IF(G$2>Payroll!$I24,Payroll!$F24*((1+Payroll!$J24)^(ROUNDDOWN(DATEDIF(Payroll!$I24,G$2,"M")/Payroll!$K24,0))),0)) -> 0 | H100: =IF(H$2=Payroll!$I24,Payroll!$F24,IF(H$2>Payroll!$I24,Payroll!$F24*((1+Payroll!$J24)^(ROUNDDOWN(DATEDIF(Payroll!$I24,H$2,"M")/Payroll!$K24,0))),0)) -> 0 | I100: =IF(I$2=Payroll!$I24,Payroll!$F24,IF(I$2>Payroll!$I24,Payroll!$F24*((1+Payroll!$J24)^(ROUNDDOWN(DATEDIF(Payroll!$I24,I$2,"M")/Payroll!$K24,0))),0)) -> 0 | J100: =IF(J$2=Payroll!$I24,Payroll!$F24,IF(J$2>Payroll!$I24,Payroll!$F24*((1+Payroll!$J24)^(ROUNDDOWN(DATEDIF(Payroll!$I24,J$2,"M")/Payroll!$K24,0))),0)) -> 0 | K100: =IF(K$2=Payroll!$I24,Payroll!$F24,IF(K$2>Payroll!$I24,Payroll!$F24*((1+Payroll!$J24)^(ROUNDDOWN(DATEDIF(Payroll!$I24,K$2,"M")/Payroll!$K24,0))),0)) -> 0 | L100: =IF(L$2=Payroll!$I24,Payroll!$F24,IF(L$2>Payroll!$I24,Payroll!$F24*((1+Payroll!$J24)^(ROUNDDOWN(DATEDIF(Payroll!$I24,L$2,"M")/Payroll!$K24,0))),0)) -> 0 | ... CX100: =IF(CX$2=Payroll!$I24,Payroll!$F24,IF(CX$2>Payroll!$I24,Payroll!$F24*((1+Payroll!$J24)^(ROUNDDOWN(DATEDIF(Payroll!$I24,CX$2,"M")/Payroll!$K24,0))),0)) -> 0
A101: =Payroll!A25 -> Developer cross-platform | E101: =IF(E$2=Payroll!$I25,Payroll!$F25,IF(E$2>Payroll!$I25,Payroll!$F25*((1+Payroll!$J25)^(ROUNDDOWN(DATEDIF(Payroll!$I25,E$2,"M")/Payroll!$K25,0))),0)) -> 0 | F101: =IF(F$2=Payroll!$I25,Payroll!$F25,IF(F$2>Payroll!$I25,Payroll!$F25*((1+Payroll!$J25)^(ROUNDDOWN(DATEDIF(Payroll!$I25,F$2,"M")/Payroll!$K25,0))),0)) -> 0 | G101: =IF(G$2=Payroll!$I25,Payroll!$F25,IF(G$2>Payroll!$I25,Payroll!$F25*((1+Payroll!$J25)^(ROUNDDOWN(DATEDIF(Payroll!$I25,G$2,"M")/Payroll!$K25,0))),0)) -> 0 | H101: =IF(H$2=Payroll!$I25,Payroll!$F25,IF(H$2>Payroll!$I25,Payroll!$F25*((1+Payroll!$J25)^(ROUNDDOWN(DATEDIF(Payroll!$I25,H$2,"M")/Payroll!$K25,0))),0)) -> 0 | I101: =IF(I$2=Payroll!$I25,Payroll!$F25,IF(I$2>Payroll!$I25,Payroll!$F25*((1+Payroll!$J25)^(ROUNDDOWN(DATEDIF(Payroll!$I25,I$2,"M")/Payroll!$K25,0))),0)) -> 0 | J101: =IF(J$2=Payroll!$I25,Payroll!$F25,IF(J$2>Payroll!$I25,Payroll!$F25*((1+Payroll!$J25)^(ROUNDDOWN(DATEDIF(Payroll!$I25,J$2,"M")/Payroll!$K25,0))),0)) -> 0 | K101: =IF(K$2=Payroll!$I25,Payroll!$F25,IF(K$2>Payroll!$I25,Payroll!$F25*((1+Payroll!$J25)^(ROUNDDOWN(DATEDIF(Payroll!$I25,K$2,"M")/Payroll!$K25,0))),0)) -> 0 | L101: =IF(L$2=Payroll!$I25,Payroll!$F25,IF(L$2>Payroll!$I25,Payroll!$F25*((1+Payroll!$J25)^(ROUNDDOWN(DATEDIF(Payroll!$I25,L$2,"M")/Payroll!$K25,0))),0)) -> 0 | ... CX101: =IF(CX$2=Payroll!$I25,Payroll!$F25,IF(CX$2>Payroll!$I25,Payroll!$F25*((1+Payroll!$J25)^(ROUNDDOWN(DATEDIF(Payroll!$I25,CX$2,"M")/Payroll!$K25,0))),0)) -> 0
A102: =Payroll!A28 -> Employee 4 | E102: =IF(E$2=Payroll!$I28,Payroll!$F28,IF(E$2>Payroll!$I28,Payroll!$F28*((1+Payroll!$J28)^(ROUNDDOWN(DATEDIF(Payroll!$I28,E$2,"M")/Payroll!$K28,0))),0)) -> 0 | F102: =IF(F$2=Payroll!$I28,Payroll!$F28,IF(F$2>Payroll!$I28,Payroll!$F28*((1+Payroll!$J28)^(ROUNDDOWN(DATEDIF(Payroll!$I28,F$2,"M")/Payroll!$K28,0))),0)) -> 0 | G102: =IF(G$2=Payroll!$I28,Payroll!$F28,IF(G$2>Payroll!$I28,Payroll!$F28*((1+Payroll!$J28)^(ROUNDDOWN(DATEDIF(Payroll!$I28,G$2,"M")/Payroll!$K28,0))),0)) -> 0 | H102: =IF(H$2=Payroll!$I28,Payroll!$F28,IF(H$2>Payroll!$I28,Payroll!$F28*((1+Payroll!$J28)^(ROUNDDOWN(DATEDIF(Payroll!$I28,H$2,"M")/Payroll!$K28,0))),0)) -> 0 | I102: =IF(I$2=Payroll!$I28,Payroll!$F28,IF(I$2>Payroll!$I28,Payroll!$F28*((1+Payroll!$J28)^(ROUNDDOWN(DATEDIF(Payroll!$I28,I$2,"M")/Payroll!$K28,0))),0)) -> 0 | J102: =IF(J$2=Payroll!$I28,Payroll!$F28,IF(J$2>Payroll!$I28,Payroll!$F28*((1+Payroll!$J28)^(ROUNDDOWN(DATEDIF(Payroll!$I28,J$2,"M")/Payroll!$K28,0))),0)) -> 0 | K102: =IF(K$2=Payroll!$I28,Payroll!$F28,IF(K$2>Payroll!$I28,Payroll!$F28*((1+Payroll!$J28)^(ROUNDDOWN(DATEDIF(Payroll!$I28,K$2,"M")/Payroll!$K28,0))),0)) -> 0 | L102: =IF(L$2=Payroll!$I28,Payroll!$F28,IF(L$2>Payroll!$I28,Payroll!$F28*((1+Payroll!$J28)^(ROUNDDOWN(DATEDIF(Payroll!$I28,L$2,"M")/Payroll!$K28,0))),0)) -> 0 | ... CX102: =IF(CX$2=Payroll!$I28,Payroll!$F28,IF(CX$2>Payroll!$I28,Payroll!$F28*((1+Payroll!$J28)^(ROUNDDOWN(DATEDIF(Payroll!$I28,CX$2,"M")/Payroll!$K28,0))),0)) -> 0
A104: =Payroll!A5 -> Administrative | B104: Operations | E104: =SUM(E105:E107) -> 0 | F104: =SUM(F105:F107) -> 0 | G104: =SUM(G105:G107) -> 0 | H104: =SUM(H105:H107) -> 0 | I104: =SUM(I105:I107) -> 0 | J104: =SUM(J105:J107) -> 0 | K104: =SUM(K105:K107) -> 0 | L104: =SUM(L105:L107) -> 0 | ... CX104: =SUM(CX105:CX107) -> 8662.7878
A105: =Payroll!A6 -> CEO | E105: =IF(E$2=Payroll!$I6,Payroll!$F6,IF(E$2>Payroll!$I6,Payroll!$F6*((1+Payroll!$J6)^(ROUNDDOWN(DATEDIF(Payroll!$I6,E$2,"M")/Payroll!$K6,0))),0)) -> 0 | F105: =IF(F$2=Payroll!$I6,Payroll!$F6,IF(F$2>Payroll!$I6,Payroll!$F6*((1+Payroll!$J6)^(ROUNDDOWN(DATEDIF(Payroll!$I6,F$2,"M")/Payroll!$K6,0))),0)) -> 0 | G105: =IF(G$2=Payroll!$I6,Payroll!$F6,IF(G$2>Payroll!$I6,Payroll!$F6*((1+Payroll!$J6)^(ROUNDDOWN(DATEDIF(Payroll!$I6,G$2,"M")/Payroll!$K6,0))),0)) -> 0 | H105: =IF(H$2=Payroll!$I6,Payroll!$F6,IF(H$2>Payroll!$I6,Payroll!$F6*((1+Payroll!$J6)^(ROUNDDOWN(DATEDIF(Payroll!$I6,H$2,"M")/Payroll!$K6,0))),0)) -> 0 | I105: =IF(I$2=Payroll!$I6,Payroll!$F6,IF(I$2>Payroll!$I6,Payroll!$F6*((1+Payroll!$J6)^(ROUNDDOWN(DATEDIF(Payroll!$I6,I$2,"M")/Payroll!$K6,0))),0)) -> 0 | J105: =IF(J$2=Payroll!$I6,Payroll!$F6,IF(J$2>Payroll!$I6,Payroll!$F6*((1+Payroll!$J6)^(ROUNDDOWN(DATEDIF(Payroll!$I6,J$2,"M")/Payroll!$K6,0))),0)) -> 0 | K105: =IF(K$2=Payroll!$I6,Payroll!$F6,IF(K$2>Payroll!$I6,Payroll!$F6*((1+Payroll!$J6)^(ROUNDDOWN(DATEDIF(Payroll!$I6,K$2,"M")/Payroll!$K6,0))),0)) -> 0 | L105: =IF(L$2=Payroll!$I6,Payroll!$F6,IF(L$2>Payroll!$I6,Payroll!$F6*((1+Payroll!$J6)^(ROUNDDOWN(DATEDIF(Payroll!$I6,L$2,"M")/Payroll!$K6,0))),0)) -> 0 | ... CX105: =IF(CX$2=Payroll!$I6,Payroll!$F6,IF(CX$2>Payroll!$I6,Payroll!$F6*((1+Payroll!$J6)^(ROUNDDOWN(DATEDIF(Payroll!$I6,CX$2,"M")/Payroll!$K6,0))),0)) -> 8662.7878
A106: =Payroll!A7 -> CFO | E106: =IF(E$2=Payroll!$I7,Payroll!$F7,IF(E$2>Payroll!$I7,Payroll!$F7*((1+Payroll!$J7)^(ROUNDDOWN(DATEDIF(Payroll!$I7,E$2,"M")/Payroll!$K7,0))),0)) -> 0 | F106: =IF(F$2=Payroll!$I7,Payroll!$F7,IF(F$2>Payroll!$I7,Payroll!$F7*((1+Payroll!$J7)^(ROUNDDOWN(DATEDIF(Payroll!$I7,F$2,"M")/Payroll!$K7,0))),0)) -> 0 | G106: =IF(G$2=Payroll!$I7,Payroll!$F7,IF(G$2>Payroll!$I7,Payroll!$F7*((1+Payroll!$J7)^(ROUNDDOWN(DATEDIF(Payroll!$I7,G$2,"M")/Payroll!$K7,0))),0)) -> 0 | H106: =IF(H$2=Payroll!$I7,Payroll!$F7,IF(H$2>Payroll!$I7,Payroll!$F7*((1+Payroll!$J7)^(ROUNDDOWN(DATEDIF(Payroll!$I7,H$2,"M")/Payroll!$K7,0))),0)) -> 0 | I106: =IF(I$2=Payroll!$I7,Payroll!$F7,IF(I$2>Payroll!$I7,Payroll!$F7*((1+Payroll!$J7)^(ROUNDDOWN(DATEDIF(Payroll!$I7,I$2,"M")/Payroll!$K7,0))),0)) -> 0 | J106: =IF(J$2=Payroll!$I7,Payroll!$F7,IF(J$2>Payroll!$I7,Payroll!$F7*((1+Payroll!$J7)^(ROUNDDOWN(DATEDIF(Payroll!$I7,J$2,"M")/Payroll!$K7,0))),0)) -> 0 | K106: =IF(K$2=Payroll!$I7,Payroll!$F7,IF(K$2>Payroll!$I7,Payroll!$F7*((1+Payroll!$J7)^(ROUNDDOWN(DATEDIF(Payroll!$I7,K$2,"M")/Payroll!$K7,0))),0)) -> 0 | L106: =IF(L$2=Payroll!$I7,Payroll!$F7,IF(L$2>Payroll!$I7,Payroll!$F7*((1+Payroll!$J7)^(ROUNDDOWN(DATEDIF(Payroll!$I7,L$2,"M")/Payroll!$K7,0))),0)) -> 0 | ... CX106: =IF(CX$2=Payroll!$I7,Payroll!$F7,IF(CX$2>Payroll!$I7,Payroll!$F7*((1+Payroll!$J7)^(ROUNDDOWN(DATEDIF(Payroll!$I7,CX$2,"M")/Payroll!$K7,0))),0)) -> 0
A107: =Payroll!A8 -> COO | E107: =IF(E$2=Payroll!$I8,Payroll!$F8,IF(E$2>Payroll!$I8,Payroll!$F8*((1+Payroll!$J8)^(ROUNDDOWN(DATEDIF(Payroll!$I8,E$2,"M")/Payroll!$K8,0))),0)) -> 0 | F107: =IF(F$2=Payroll!$I8,Payroll!$F8,IF(F$2>Payroll!$I8,Payroll!$F8*((1+Payroll!$J8)^(ROUNDDOWN(DATEDIF(Payroll!$I8,F$2,"M")/Payroll!$K8,0))),0)) -> 0 | G107: =IF(G$2=Payroll!$I8,Payroll!$F8,IF(G$2>Payroll!$I8,Payroll!$F8*((1+Payroll!$J8)^(ROUNDDOWN(DATEDIF(Payroll!$I8,G$2,"M")/Payroll!$K8,0))),0)) -> 0 | H107: =IF(H$2=Payroll!$I8,Payroll!$F8,IF(H$2>Payroll!$I8,Payroll!$F8*((1+Payroll!$J8)^(ROUNDDOWN(DATEDIF(Payroll!$I8,H$2,"M")/Payroll!$K8,0))),0)) -> 0 | I107: =IF(I$2=Payroll!$I8,Payroll!$F8,IF(I$2>Payroll!$I8,Payroll!$F8*((1+Payroll!$J8)^(ROUNDDOWN(DATEDIF(Payroll!$I8,I$2,"M")/Payroll!$K8,0))),0)) -> 0 | J107: =IF(J$2=Payroll!$I8,Payroll!$F8,IF(J$2>Payroll!$I8,Payroll!$F8*((1+Payroll!$J8)^(ROUNDDOWN(DATEDIF(Payroll!$I8,J$2,"M")/Payroll!$K8,0))),0)) -> 0 | K107: =IF(K$2=Payroll!$I8,Payroll!$F8,IF(K$2>Payroll!$I8,Payroll!$F8*((1+Payroll!$J8)^(ROUNDDOWN(DATEDIF(Payroll!$I8,K$2,"M")/Payroll!$K8,0))),0)) -> 0 | L107: =IF(L$2=Payroll!$I8,Payroll!$F8,IF(L$2>Payroll!$I8,Payroll!$F8*((1+Payroll!$J8)^(ROUNDDOWN(DATEDIF(Payroll!$I8,L$2,"M")/Payroll!$K8,0))),0)) -> 0 | ... CX107: =IF(CX$2=Payroll!$I8,Payroll!$F8,IF(CX$2>Payroll!$I8,Payroll!$F8*((1+Payroll!$J8)^(ROUNDDOWN(DATEDIF(Payroll!$I8,CX$2,"M")/Payroll!$K8,0))),0)) -> 0
A108: =Payroll!A9 -> HRD | E108: =IF(E$2=Payroll!$I9,Payroll!$F9,IF(E$2>Payroll!$I9,Payroll!$F9*((1+Payroll!$J9)^(ROUNDDOWN(DATEDIF(Payroll!$I9,E$2,"M")/Payroll!$K9,0))),0)) -> 0 | F108: =IF(F$2=Payroll!$I9,Payroll!$F9,IF(F$2>Payroll!$I9,Payroll!$F9*((1+Payroll!$J9)^(ROUNDDOWN(DATEDIF(Payroll!$I9,F$2,"M")/Payroll!$K9,0))),0)) -> 0 | G108: =IF(G$2=Payroll!$I9,Payroll!$F9,IF(G$2>Payroll!$I9,Payroll!$F9*((1+Payroll!$J9)^(ROUNDDOWN(DATEDIF(Payroll!$I9,G$2,"M")/Payroll!$K9,0))),0)) -> 0 | H108: =IF(H$2=Payroll!$I9,Payroll!$F9,IF(H$2>Payroll!$I9,Payroll!$F9*((1+Payroll!$J9)^(ROUNDDOWN(DATEDIF(Payroll!$I9,H$2,"M")/Payroll!$K9,0))),0)) -> 0 | I108: =IF(I$2=Payroll!$I9,Payroll!$F9,IF(I$2>Payroll!$I9,Payroll!$F9*((1+Payroll!$J9)^(ROUNDDOWN(DATEDIF(Payroll!$I9,I$2,"M")/Payroll!$K9,0))),0)) -> 0 | J108: =IF(J$2=Payroll!$I9,Payroll!$F9,IF(J$2>Payroll!$I9,Payroll!$F9*((1+Payroll!$J9)^(ROUNDDOWN(DATEDIF(Payroll!$I9,J$2,"M")/Payroll!$K9,0))),0)) -> 0 | K108: =IF(K$2=Payroll!$I9,Payroll!$F9,IF(K$2>Payroll!$I9,Payroll!$F9*((1+Payroll!$J9)^(ROUNDDOWN(DATEDIF(Payroll!$I9,K$2,"M")/Payroll!$K9,0))),0)) -> 0 | L108: =IF(L$2=Payroll!$I9,Payroll!$F9,IF(L$2>Payroll!$I9,Payroll!$F9*((1+Payroll!$J9)^(ROUNDDOWN(DATEDIF(Payroll!$I9,L$2,"M")/Payroll!$K9,0))),0)) -> 0 | ... CX108: =IF(CX$2=Payroll!$I9,Payroll!$F9,IF(CX$2>Payroll!$I9,Payroll!$F9*((1+Payroll!$J9)^(ROUNDDOWN(DATEDIF(Payroll!$I9,CX$2,"M")/Payroll!$K9,0))),0)) -> 0
A109: =Payroll!A10 -> Operations Coordinator / Office Manager | E109: =IF(E$2=Payroll!$I10,Payroll!$F10,IF(E$2>Payroll!$I10,Payroll!$F10*((1+Payroll!$J10)^(ROUNDDOWN(DATEDIF(Payroll!$I10,E$2,"M")/Payroll!$K10,0))),0)) -> 0 | F109: =IF(F$2=Payroll!$I10,Payroll!$F10,IF(F$2>Payroll!$I10,Payroll!$F10*((1+Payroll!$J10)^(ROUNDDOWN(DATEDIF(Payroll!$I10,F$2,"M")/Payroll!$K10,0))),0)) -> 0 | G109: =IF(G$2=Payroll!$I10,Payroll!$F10,IF(G$2>Payroll!$I10,Payroll!$F10*((1+Payroll!$J10)^(ROUNDDOWN(DATEDIF(Payroll!$I10,G$2,"M")/Payroll!$K10,0))),0)) -> 0 | H109: =IF(H$2=Payroll!$I10,Payroll!$F10,IF(H$2>Payroll!$I10,Payroll!$F10*((1+Payroll!$J10)^(ROUNDDOWN(DATEDIF(Payroll!$I10,H$2,"M")/Payroll!$K10,0))),0)) -> 0 | I109: =IF(I$2=Payroll!$I10,Payroll!$F10,IF(I$2>Payroll!$I10,Payroll!$F10*((1+Payroll!$J10)^(ROUNDDOWN(DATEDIF(Payroll!$I10,I$2,"M")/Payroll!$K10,0))),0)) -> 0 | J109: =IF(J$2=Payroll!$I10,Payroll!$F10,IF(J$2>Payroll!$I10,Payroll!$F10*((1+Payroll!$J10)^(ROUNDDOWN(DATEDIF(Payroll!$I10,J$2,"M")/Payroll!$K10,0))),0)) -> 0 | K109: =IF(K$2=Payroll!$I10,Payroll!$F10,IF(K$2>Payroll!$I10,Payroll!$F10*((1+Payroll!$J10)^(ROUNDDOWN(DATEDIF(Payroll!$I10,K$2,"M")/Payroll!$K10,0))),0)) -> 0 | L109: =IF(L$2=Payroll!$I10,Payroll!$F10,IF(L$2>Payroll!$I10,Payroll!$F10*((1+Payroll!$J10)^(ROUNDDOWN(DATEDIF(Payroll!$I10,L$2,"M")/Payroll!$K10,0))),0)) -> 0 | ... CX109: =IF(CX$2=Payroll!$I10,Payroll!$F10,IF(CX$2>Payroll!$I10,Payroll!$F10*((1+Payroll!$J10)^(ROUNDDOWN(DATEDIF(Payroll!$I10,CX$2,"M")/Payroll!$K10,0))),0)) -> 0
A110: =Payroll!A11 -> Employee 1 | E110: =IF(E$2=Payroll!$I11,Payroll!$F11,IF(E$2>Payroll!$I11,Payroll!$F11*((1+Payroll!$J11)^(ROUNDDOWN(DATEDIF(Payroll!$I11,E$2,"M")/Payroll!$K11,0))),0)) -> 0 | F110: =IF(F$2=Payroll!$I11,Payroll!$F11,IF(F$2>Payroll!$I11,Payroll!$F11*((1+Payroll!$J11)^(ROUNDDOWN(DATEDIF(Payroll!$I11,F$2,"M")/Payroll!$K11,0))),0)) -> 0 | G110: =IF(G$2=Payroll!$I11,Payroll!$F11,IF(G$2>Payroll!$I11,Payroll!$F11*((1+Payroll!$J11)^(ROUNDDOWN(DATEDIF(Payroll!$I11,G$2,"M")/Payroll!$K11,0))),0)) -> 0 | H110: =IF(H$2=Payroll!$I11,Payroll!$F11,IF(H$2>Payroll!$I11,Payroll!$F11*((1+Payroll!$J11)^(ROUNDDOWN(DATEDIF(Payroll!$I11,H$2,"M")/Payroll!$K11,0))),0)) -> 0 | I110: =IF(I$2=Payroll!$I11,Payroll!$F11,IF(I$2>Payroll!$I11,Payroll!$F11*((1+Payroll!$J11)^(ROUNDDOWN(DATEDIF(Payroll!$I11,I$2,"M")/Payroll!$K11,0))),0)) -> 0 | J110: =IF(J$2=Payroll!$I11,Payroll!$F11,IF(J$2>Payroll!$I11,Payroll!$F11*((1+Payroll!$J11)^(ROUNDDOWN(DATEDIF(Payroll!$I11,J$2,"M")/Payroll!$K11,0))),0)) -> 0 | K110: =IF(K$2=Payroll!$I11,Payroll!$F11,IF(K$2>Payroll!$I11,Payroll!$F11*((1+Payroll!$J11)^(ROUNDDOWN(DATEDIF(Payroll!$I11,K$2,"M")/Payroll!$K11,0))),0)) -> 0 | L110: =IF(L$2=Payroll!$I11,Payroll!$F11,IF(L$2>Payroll!$I11,Payroll!$F11*((1+Payroll!$J11)^(ROUNDDOWN(DATEDIF(Payroll!$I11,L$2,"M")/Payroll!$K11,0))),0)) -> 0 | ... CX110: =IF(CX$2=Payroll!$I11,Payroll!$F11,IF(CX$2>Payroll!$I11,Payroll!$F11*((1+Payroll!$J11)^(ROUNDDOWN(DATEDIF(Payroll!$I11,CX$2,"M")/Payroll!$K11,0))),0)) -> 0
A111: =Payroll!A12 -> Employee 2 | E111: =IF(E$2=Payroll!$I12,Payroll!$F12,IF(E$2>Payroll!$I12,Payroll!$F12*((1+Payroll!$J12)^(ROUNDDOWN(DATEDIF(Payroll!$I12,E$2,"M")/Payroll!$K12,0))),0)) -> 0 | F111: =IF(F$2=Payroll!$I12,Payroll!$F12,IF(F$2>Payroll!$I12,Payroll!$F12*((1+Payroll!$J12)^(ROUNDDOWN(DATEDIF(Payroll!$I12,F$2,"M")/Payroll!$K12,0))),0)) -> 0 | G111: =IF(G$2=Payroll!$I12,Payroll!$F12,IF(G$2>Payroll!$I12,Payroll!$F12*((1+Payroll!$J12)^(ROUNDDOWN(DATEDIF(Payroll!$I12,G$2,"M")/Payroll!$K12,0))),0)) -> 0 | H111: =IF(H$2=Payroll!$I12,Payroll!$F12,IF(H$2>Payroll!$I12,Payroll!$F12*((1+Payroll!$J12)^(ROUNDDOWN(DATEDIF(Payroll!$I12,H$2,"M")/Payroll!$K12,0))),0)) -> 0 | I111: =IF(I$2=Payroll!$I12,Payroll!$F12,IF(I$2>Payroll!$I12,Payroll!$F12*((1+Payroll!$J12)^(ROUNDDOWN(DATEDIF(Payroll!$I12,I$2,"M")/Payroll!$K12,0))),0)) -> 0 | J111: =IF(J$2=Payroll!$I12,Payroll!$F12,IF(J$2>Payroll!$I12,Payroll!$F12*((1+Payroll!$J12)^(ROUNDDOWN(DATEDIF(Payroll!$I12,J$2,"M")/Payroll!$K12,0))),0)) -> 0 | K111: =IF(K$2=Payroll!$I12,Payroll!$F12,IF(K$2>Payroll!$I12,Payroll!$F12*((1+Payroll!$J12)^(ROUNDDOWN(DATEDIF(Payroll!$I12,K$2,"M")/Payroll!$K12,0))),0)) -> 0 | L111: =IF(L$2=Payroll!$I12,Payroll!$F12,IF(L$2>Payroll!$I12,Payroll!$F12*((1+Payroll!$J12)^(ROUNDDOWN(DATEDIF(Payroll!$I12,L$2,"M")/Payroll!$K12,0))),0)) -> 0 | ... CX111: =IF(CX$2=Payroll!$I12,Payroll!$F12,IF(CX$2>Payroll!$I12,Payroll!$F12*((1+Payroll!$J12)^(ROUNDDOWN(DATEDIF(Payroll!$I12,CX$2,"M")/Payroll!$K12,0))),0)) -> 0
A112: =Payroll!A13 -> Employee 3 | E112: =IF(E$2=Payroll!$I13,Payroll!$F13,IF(E$2>Payroll!$I13,Payroll!$F13*((1+Payroll!$J13)^(ROUNDDOWN(DATEDIF(Payroll!$I13,E$2,"M")/Payroll!$K13,0))),0)) -> 0 | F112: =IF(F$2=Payroll!$I13,Payroll!$F13,IF(F$2>Payroll!$I13,Payroll!$F13*((1+Payroll!$J13)^(ROUNDDOWN(DATEDIF(Payroll!$I13,F$2,"M")/Payroll!$K13,0))),0)) -> 0 | G112: =IF(G$2=Payroll!$I13,Payroll!$F13,IF(G$2>Payroll!$I13,Payroll!$F13*((1+Payroll!$J13)^(ROUNDDOWN(DATEDIF(Payroll!$I13,G$2,"M")/Payroll!$K13,0))),0)) -> 0 | H112: =IF(H$2=Payroll!$I13,Payroll!$F13,IF(H$2>Payroll!$I13,Payroll!$F13*((1+Payroll!$J13)^(ROUNDDOWN(DATEDIF(Payroll!$I13,H$2,"M")/Payroll!$K13,0))),0)) -> 0 | I112: =IF(I$2=Payroll!$I13,Payroll!$F13,IF(I$2>Payroll!$I13,Payroll!$F13*((1+Payroll!$J13)^(ROUNDDOWN(DATEDIF(Payroll!$I13,I$2,"M")/Payroll!$K13,0))),0)) -> 0 | J112: =IF(J$2=Payroll!$I13,Payroll!$F13,IF(J$2>Payroll!$I13,Payroll!$F13*((1+Payroll!$J13)^(ROUNDDOWN(DATEDIF(Payroll!$I13,J$2,"M")/Payroll!$K13,0))),0)) -> 0 | K112: =IF(K$2=Payroll!$I13,Payroll!$F13,IF(K$2>Payroll!$I13,Payroll!$F13*((1+Payroll!$J13)^(ROUNDDOWN(DATEDIF(Payroll!$I13,K$2,"M")/Payroll!$K13,0))),0)) -> 0 | L112: =IF(L$2=Payroll!$I13,Payroll!$F13,IF(L$2>Payroll!$I13,Payroll!$F13*((1+Payroll!$J13)^(ROUNDDOWN(DATEDIF(Payroll!$I13,L$2,"M")/Payroll!$K13,0))),0)) -> 0 | ... CX112: =IF(CX$2=Payroll!$I13,Payroll!$F13,IF(CX$2>Payroll!$I13,Payroll!$F13*((1+Payroll!$J13)^(ROUNDDOWN(DATEDIF(Payroll!$I13,CX$2,"M")/Payroll!$K13,0))),0)) -> 0
A113: =Payroll!A14 -> Employee 4 | E113: =IF(E$2=Payroll!$I14,Payroll!$F14,IF(E$2>Payroll!$I14,Payroll!$F14*((1+Payroll!$J14)^(ROUNDDOWN(DATEDIF(Payroll!$I14,E$2,"M")/Payroll!$K14,0))),0)) -> 0 | F113: =IF(F$2=Payroll!$I14,Payroll!$F14,IF(F$2>Payroll!$I14,Payroll!$F14*((1+Payroll!$J14)^(ROUNDDOWN(DATEDIF(Payroll!$I14,F$2,"M")/Payroll!$K14,0))),0)) -> 0 | G113: =IF(G$2=Payroll!$I14,Payroll!$F14,IF(G$2>Payroll!$I14,Payroll!$F14*((1+Payroll!$J14)^(ROUNDDOWN(DATEDIF(Payroll!$I14,G$2,"M")/Payroll!$K14,0))),0)) -> 0 | H113: =IF(H$2=Payroll!$I14,Payroll!$F14,IF(H$2>Payroll!$I14,Payroll!$F14*((1+Payroll!$J14)^(ROUNDDOWN(DATEDIF(Payroll!$I14,H$2,"M")/Payroll!$K14,0))),0)) -> 0 | I113: =IF(I$2=Payroll!$I14,Payroll!$F14,IF(I$2>Payroll!$I14,Payroll!$F14*((1+Payroll!$J14)^(ROUNDDOWN(DATEDIF(Payroll!$I14,I$2,"M")/Payroll!$K14,0))),0)) -> 0 | J113: =IF(J$2=Payroll!$I14,Payroll!$F14,IF(J$2>Payroll!$I14,Payroll!$F14*((1+Payroll!$J14)^(ROUNDDOWN(DATEDIF(Payroll!$I14,J$2,"M")/Payroll!$K14,0))),0)) -> 0 | K113: =IF(K$2=Payroll!$I14,Payroll!$F14,IF(K$2>Payroll!$I14,Payroll!$F14*((1+Payroll!$J14)^(ROUNDDOWN(DATEDIF(Payroll!$I14,K$2,"M")/Payroll!$K14,0))),0)) -> 0 | L113: =IF(L$2=Payroll!$I14,Payroll!$F14,IF(L$2>Payroll!$I14,Payroll!$F14*((1+Payroll!$J14)^(ROUNDDOWN(DATEDIF(Payroll!$I14,L$2,"M")/Payroll!$K14,0))),0)) -> 0 | ... CX113: =IF(CX$2=Payroll!$I14,Payroll!$F14,IF(CX$2>Payroll!$I14,Payroll!$F14*((1+Payroll!$J14)^(ROUNDDOWN(DATEDIF(Payroll!$I14,CX$2,"M")/Payroll!$K14,0))),0)) -> 0
A115: =Payroll!A30 -> Marketing | B115: Marketing | E115: =SUM(E116:E125) -> 0 | F115: =SUM(F116:F125) -> 0 | G115: =SUM(G116:G125) -> 0 | H115: =SUM(H116:H125) -> 0 | I115: =SUM(I116:I125) -> 0 | J115: =SUM(J116:J125) -> 0 | K115: =SUM(K116:K125) -> 0 | L115: =SUM(L116:L125) -> 0 | ... CX115: =SUM(CX116:CX125) -> 5615.3211
A116: =Payroll!A31 -> Head of Marketing | E116: =IF(E$2=Payroll!$I31,Payroll!$F31,IF(E$2>Payroll!$I31,Payroll!$F31*((1+Payroll!$J31)^(ROUNDDOWN(DATEDIF(Payroll!$I31,E$2,"M")/Payroll!$K31,0))),0)) -> 0 | F116: =IF(F$2=Payroll!$I31,Payroll!$F31,IF(F$2>Payroll!$I31,Payroll!$F31*((1+Payroll!$J31)^(ROUNDDOWN(DATEDIF(Payroll!$I31,F$2,"M")/Payroll!$K31,0))),0)) -> 0 | G116: =IF(G$2=Payroll!$I31,Payroll!$F31,IF(G$2>Payroll!$I31,Payroll!$F31*((1+Payroll!$J31)^(ROUNDDOWN(DATEDIF(Payroll!$I31,G$2,"M")/Payroll!$K31,0))),0)) -> 0 | H116: =IF(H$2=Payroll!$I31,Payroll!$F31,IF(H$2>Payroll!$I31,Payroll!$F31*((1+Payroll!$J31)^(ROUNDDOWN(DATEDIF(Payroll!$I31,H$2,"M")/Payroll!$K31,0))),0)) -> 0 | I116: =IF(I$2=Payroll!$I31,Payroll!$F31,IF(I$2>Payroll!$I31,Payroll!$F31*((1+Payroll!$J31)^(ROUNDDOWN(DATEDIF(Payroll!$I31,I$2,"M")/Payroll!$K31,0))),0)) -> 0 | J116: =IF(J$2=Payroll!$I31,Payroll!$F31,IF(J$2>Payroll!$I31,Payroll!$F31*((1+Payroll!$J31)^(ROUNDDOWN(DATEDIF(Payroll!$I31,J$2,"M")/Payroll!$K31,0))),0)) -> 0 | K116: =IF(K$2=Payroll!$I31,Payroll!$F31,IF(K$2>Payroll!$I31,Payroll!$F31*((1+Payroll!$J31)^(ROUNDDOWN(DATEDIF(Payroll!$I31,K$2,"M")/Payroll!$K31,0))),0)) -> 0 | L116: =IF(L$2=Payroll!$I31,Payroll!$F31,IF(L$2>Payroll!$I31,Payroll!$F31*((1+Payroll!$J31)^(ROUNDDOWN(DATEDIF(Payroll!$I31,L$2,"M")/Payroll!$K31,0))),0)) -> 0 | ... CX116: =IF(CX$2=Payroll!$I31,Payroll!$F31,IF(CX$2>Payroll!$I31,Payroll!$F31*((1+Payroll!$J31)^(ROUNDDOWN(DATEDIF(Payroll!$I31,CX$2,"M")/Payroll!$K31,0))),0)) -> 5615.3211
A117: =Payroll!A32 -> Content Marketing Manager | E117: =IF(E$2=Payroll!$I32,Payroll!$F32,IF(E$2>Payroll!$I32,Payroll!$F32*((1+Payroll!$J32)^(ROUNDDOWN(DATEDIF(Payroll!$I32,E$2,"M")/Payroll!$K32,0))),0)) -> 0 | F117: =IF(F$2=Payroll!$I32,Payroll!$F32,IF(F$2>Payroll!$I32,Payroll!$F32*((1+Payroll!$J32)^(ROUNDDOWN(DATEDIF(Payroll!$I32,F$2,"M")/Payroll!$K32,0))),0)) -> 0 | G117: =IF(G$2=Payroll!$I32,Payroll!$F32,IF(G$2>Payroll!$I32,Payroll!$F32*((1+Payroll!$J32)^(ROUNDDOWN(DATEDIF(Payroll!$I32,G$2,"M")/Payroll!$K32,0))),0)) -> 0 | H117: =IF(H$2=Payroll!$I32,Payroll!$F32,IF(H$2>Payroll!$I32,Payroll!$F32*((1+Payroll!$J32)^(ROUNDDOWN(DATEDIF(Payroll!$I32,H$2,"M")/Payroll!$K32,0))),0)) -> 0 | I117: =IF(I$2=Payroll!$I32,Payroll!$F32,IF(I$2>Payroll!$I32,Payroll!$F32*((1+Payroll!$J32)^(ROUNDDOWN(DATEDIF(Payroll!$I32,I$2,"M")/Payroll!$K32,0))),0)) -> 0 | J117: =IF(J$2=Payroll!$I32,Payroll!$F32,IF(J$2>Payroll!$I32,Payroll!$F32*((1+Payroll!$J32)^(ROUNDDOWN(DATEDIF(Payroll!$I32,J$2,"M")/Payroll!$K32,0))),0)) -> 0 | K117: =IF(K$2=Payroll!$I32,Payroll!$F32,IF(K$2>Payroll!$I32,Payroll!$F32*((1+Payroll!$J32)^(ROUNDDOWN(DATEDIF(Payroll!$I32,K$2,"M")/Payroll!$K32,0))),0)) -> 0 | L117: =IF(L$2=Payroll!$I32,Payroll!$F32,IF(L$2>Payroll!$I32,Payroll!$F32*((1+Payroll!$J32)^(ROUNDDOWN(DATEDIF(Payroll!$I32,L$2,"M")/Payroll!$K32,0))),0)) -> 0 | ... CX117: =IF(CX$2=Payroll!$I32,Payroll!$F32,IF(CX$2>Payroll!$I32,Payroll!$F32*((1+Payroll!$J32)^(ROUNDDOWN(DATEDIF(Payroll!$I32,CX$2,"M")/Payroll!$K32,0))),0)) -> 0
A118: =Payroll!A33 -> Performance Marketing Manager | E118: =IF(E$2=Payroll!$I33,Payroll!$F33,IF(E$2>Payroll!$I33,Payroll!$F33*((1+Payroll!$J33)^(ROUNDDOWN(DATEDIF(Payroll!$I33,E$2,"M")/Payroll!$K33,0))),0)) -> 0 | F118: =IF(F$2=Payroll!$I33,Payroll!$F33,IF(F$2>Payroll!$I33,Payroll!$F33*((1+Payroll!$J33)^(ROUNDDOWN(DATEDIF(Payroll!$I33,F$2,"M")/Payroll!$K33,0))),0)) -> 0 | G118: =IF(G$2=Payroll!$I33,Payroll!$F33,IF(G$2>Payroll!$I33,Payroll!$F33*((1+Payroll!$J33)^(ROUNDDOWN(DATEDIF(Payroll!$I33,G$2,"M")/Payroll!$K33,0))),0)) -> 0 | H118: =IF(H$2=Payroll!$I33,Payroll!$F33,IF(H$2>Payroll!$I33,Payroll!$F33*((1+Payroll!$J33)^(ROUNDDOWN(DATEDIF(Payroll!$I33,H$2,"M")/Payroll!$K33,0))),0)) -> 0 | I118: =IF(I$2=Payroll!$I33,Payroll!$F33,IF(I$2>Payroll!$I33,Payroll!$F33*((1+Payroll!$J33)^(ROUNDDOWN(DATEDIF(Payroll!$I33,I$2,"M")/Payroll!$K33,0))),0)) -> 0 | J118: =IF(J$2=Payroll!$I33,Payroll!$F33,IF(J$2>Payroll!$I33,Payroll!$F33*((1+Payroll!$J33)^(ROUNDDOWN(DATEDIF(Payroll!$I33,J$2,"M")/Payroll!$K33,0))),0)) -> 0 | K118: =IF(K$2=Payroll!$I33,Payroll!$F33,IF(K$2>Payroll!$I33,Payroll!$F33*((1+Payroll!$J33)^(ROUNDDOWN(DATEDIF(Payroll!$I33,K$2,"M")/Payroll!$K33,0))),0)) -> 0 | L118: =IF(L$2=Payroll!$I33,Payroll!$F33,IF(L$2>Payroll!$I33,Payroll!$F33*((1+Payroll!$J33)^(ROUNDDOWN(DATEDIF(Payroll!$I33,L$2,"M")/Payroll!$K33,0))),0)) -> 0 | ... CX118: =IF(CX$2=Payroll!$I33,Payroll!$F33,IF(CX$2>Payroll!$I33,Payroll!$F33*((1+Payroll!$J33)^(ROUNDDOWN(DATEDIF(Payroll!$I33,CX$2,"M")/Payroll!$K33,0))),0)) -> 0
A119: =Payroll!A34 -> Community Manager / SMM | E119: =IF(E$2=Payroll!$I34,Payroll!$F34,IF(E$2>Payroll!$I34,Payroll!$F34*((1+Payroll!$J34)^(ROUNDDOWN(DATEDIF(Payroll!$I34,E$2,"M")/Payroll!$K34,0))),0)) -> 0 | F119: =IF(F$2=Payroll!$I34,Payroll!$F34,IF(F$2>Payroll!$I34,Payroll!$F34*((1+Payroll!$J34)^(ROUNDDOWN(DATEDIF(Payroll!$I34,F$2,"M")/Payroll!$K34,0))),0)) -> 0 | G119: =IF(G$2=Payroll!$I34,Payroll!$F34,IF(G$2>Payroll!$I34,Payroll!$F34*((1+Payroll!$J34)^(ROUNDDOWN(DATEDIF(Payroll!$I34,G$2,"M")/Payroll!$K34,0))),0)) -> 0 | H119: =IF(H$2=Payroll!$I34,Payroll!$F34,IF(H$2>Payroll!$I34,Payroll!$F34*((1+Payroll!$J34)^(ROUNDDOWN(DATEDIF(Payroll!$I34,H$2,"M")/Payroll!$K34,0))),0)) -> 0 | I119: =IF(I$2=Payroll!$I34,Payroll!$F34,IF(I$2>Payroll!$I34,Payroll!$F34*((1+Payroll!$J34)^(ROUNDDOWN(DATEDIF(Payroll!$I34,I$2,"M")/Payroll!$K34,0))),0)) -> 0 | J119: =IF(J$2=Payroll!$I34,Payroll!$F34,IF(J$2>Payroll!$I34,Payroll!$F34*((1+Payroll!$J34)^(ROUNDDOWN(DATEDIF(Payroll!$I34,J$2,"M")/Payroll!$K34,0))),0)) -> 0 | K119: =IF(K$2=Payroll!$I34,Payroll!$F34,IF(K$2>Payroll!$I34,Payroll!$F34*((1+Payroll!$J34)^(ROUNDDOWN(DATEDIF(Payroll!$I34,K$2,"M")/Payroll!$K34,0))),0)) -> 0 | L119: =IF(L$2=Payroll!$I34,Payroll!$F34,IF(L$2>Payroll!$I34,Payroll!$F34*((1+Payroll!$J34)^(ROUNDDOWN(DATEDIF(Payroll!$I34,L$2,"M")/Payroll!$K34,0))),0)) -> 0 | ... CX119: =IF(CX$2=Payroll!$I34,Payroll!$F34,IF(CX$2>Payroll!$I34,Payroll!$F34*((1+Payroll!$J34)^(ROUNDDOWN(DATEDIF(Payroll!$I34,CX$2,"M")/Payroll!$K34,0))),0)) -> 0
A120: =Payroll!A35 -> PR / Comms Manager | E120: =IF(E$2=Payroll!$I35,Payroll!$F35,IF(E$2>Payroll!$I35,Payroll!$F35*((1+Payroll!$J35)^(ROUNDDOWN(DATEDIF(Payroll!$I35,E$2,"M")/Payroll!$K35,0))),0)) -> 0 | F120: =IF(F$2=Payroll!$I35,Payroll!$F35,IF(F$2>Payroll!$I35,Payroll!$F35*((1+Payroll!$J35)^(ROUNDDOWN(DATEDIF(Payroll!$I35,F$2,"M")/Payroll!$K35,0))),0)) -> 0 | G120: =IF(G$2=Payroll!$I35,Payroll!$F35,IF(G$2>Payroll!$I35,Payroll!$F35*((1+Payroll!$J35)^(ROUNDDOWN(DATEDIF(Payroll!$I35,G$2,"M")/Payroll!$K35,0))),0)) -> 0 | H120: =IF(H$2=Payroll!$I35,Payroll!$F35,IF(H$2>Payroll!$I35,Payroll!$F35*((1+Payroll!$J35)^(ROUNDDOWN(DATEDIF(Payroll!$I35,H$2,"M")/Payroll!$K35,0))),0)) -> 0 | I120: =IF(I$2=Payroll!$I35,Payroll!$F35,IF(I$2>Payroll!$I35,Payroll!$F35*((1+Payroll!$J35)^(ROUNDDOWN(DATEDIF(Payroll!$I35,I$2,"M")/Payroll!$K35,0))),0)) -> 0 | J120: =IF(J$2=Payroll!$I35,Payroll!$F35,IF(J$2>Payroll!$I35,Payroll!$F35*((1+Payroll!$J35)^(ROUNDDOWN(DATEDIF(Payroll!$I35,J$2,"M")/Payroll!$K35,0))),0)) -> 0 | K120: =IF(K$2=Payroll!$I35,Payroll!$F35,IF(K$2>Payroll!$I35,Payroll!$F35*((1+Payroll!$J35)^(ROUNDDOWN(DATEDIF(Payroll!$I35,K$2,"M")/Payroll!$K35,0))),0)) -> 0 | L120: =IF(L$2=Payroll!$I35,Payroll!$F35,IF(L$2>Payroll!$I35,Payroll!$F35*((1+Payroll!$J35)^(ROUNDDOWN(DATEDIF(Payroll!$I35,L$2,"M")/Payroll!$K35,0))),0)) -> 0 | ... CX120: =IF(CX$2=Payroll!$I35,Payroll!$F35,IF(CX$2>Payroll!$I35,Payroll!$F35*((1+Payroll!$J35)^(ROUNDDOWN(DATEDIF(Payroll!$I35,CX$2,"M")/Payroll!$K35,0))),0)) -> 0
A121: =Payroll!A36 -> Marketing Designer | E121: =IF(E$2=Payroll!$I36,Payroll!$F36,IF(E$2>Payroll!$I36,Payroll!$F36*((1+Payroll!$J36)^(ROUNDDOWN(DATEDIF(Payroll!$I36,E$2,"M")/Payroll!$K36,0))),0)) -> 0 | F121: =IF(F$2=Payroll!$I36,Payroll!$F36,IF(F$2>Payroll!$I36,Payroll!$F36*((1+Payroll!$J36)^(ROUNDDOWN(DATEDIF(Payroll!$I36,F$2,"M")/Payroll!$K36,0))),0)) -> 0 | G121: =IF(G$2=Payroll!$I36,Payroll!$F36,IF(G$2>Payroll!$I36,Payroll!$F36*((1+Payroll!$J36)^(ROUNDDOWN(DATEDIF(Payroll!$I36,G$2,"M")/Payroll!$K36,0))),0)) -> 0 | H121: =IF(H$2=Payroll!$I36,Payroll!$F36,IF(H$2>Payroll!$I36,Payroll!$F36*((1+Payroll!$J36)^(ROUNDDOWN(DATEDIF(Payroll!$I36,H$2,"M")/Payroll!$K36,0))),0)) -> 0 | I121: =IF(I$2=Payroll!$I36,Payroll!$F36,IF(I$2>Payroll!$I36,Payroll!$F36*((1+Payroll!$J36)^(ROUNDDOWN(DATEDIF(Payroll!$I36,I$2,"M")/Payroll!$K36,0))),0)) -> 0 | J121: =IF(J$2=Payroll!$I36,Payroll!$F36,IF(J$2>Payroll!$I36,Payroll!$F36*((1+Payroll!$J36)^(ROUNDDOWN(DATEDIF(Payroll!$I36,J$2,"M")/Payroll!$K36,0))),0)) -> 0 | K121: =IF(K$2=Payroll!$I36,Payroll!$F36,IF(K$2>Payroll!$I36,Payroll!$F36*((1+Payroll!$J36)^(ROUNDDOWN(DATEDIF(Payroll!$I36,K$2,"M")/Payroll!$K36,0))),0)) -> 0 | L121: =IF(L$2=Payroll!$I36,Payroll!$F36,IF(L$2>Payroll!$I36,Payroll!$F36*((1+Payroll!$J36)^(ROUNDDOWN(DATEDIF(Payroll!$I36,L$2,"M")/Payroll!$K36,0))),0)) -> 0 | ... CX121: =IF(CX$2=Payroll!$I36,Payroll!$F36,IF(CX$2>Payroll!$I36,Payroll!$F36*((1+Payroll!$J36)^(ROUNDDOWN(DATEDIF(Payroll!$I36,CX$2,"M")/Payroll!$K36,0))),0)) -> 0
A122: =Payroll!A37 -> Employee 3 | E122: =IF(E$2=Payroll!$I37,Payroll!$F37,IF(E$2>Payroll!$I37,Payroll!$F37*((1+Payroll!$J37)^(ROUNDDOWN(DATEDIF(Payroll!$I37,E$2,"M")/Payroll!$K37,0))),0)) -> 0 | F122: =IF(F$2=Payroll!$I37,Payroll!$F37,IF(F$2>Payroll!$I37,Payroll!$F37*((1+Payroll!$J37)^(ROUNDDOWN(DATEDIF(Payroll!$I37,F$2,"M")/Payroll!$K37,0))),0)) -> 0 | G122: =IF(G$2=Payroll!$I37,Payroll!$F37,IF(G$2>Payroll!$I37,Payroll!$F37*((1+Payroll!$J37)^(ROUNDDOWN(DATEDIF(Payroll!$I37,G$2,"M")/Payroll!$K37,0))),0)) -> 0 | H122: =IF(H$2=Payroll!$I37,Payroll!$F37,IF(H$2>Payroll!$I37,Payroll!$F37*((1+Payroll!$J37)^(ROUNDDOWN(DATEDIF(Payroll!$I37,H$2,"M")/Payroll!$K37,0))),0)) -> 0 | I122: =IF(I$2=Payroll!$I37,Payroll!$F37,IF(I$2>Payroll!$I37,Payroll!$F37*((1+Payroll!$J37)^(ROUNDDOWN(DATEDIF(Payroll!$I37,I$2,"M")/Payroll!$K37,0))),0)) -> 0 | J122: =IF(J$2=Payroll!$I37,Payroll!$F37,IF(J$2>Payroll!$I37,Payroll!$F37*((1+Payroll!$J37)^(ROUNDDOWN(DATEDIF(Payroll!$I37,J$2,"M")/Payroll!$K37,0))),0)) -> 0 | K122: =IF(K$2=Payroll!$I37,Payroll!$F37,IF(K$2>Payroll!$I37,Payroll!$F37*((1+Payroll!$J37)^(ROUNDDOWN(DATEDIF(Payroll!$I37,K$2,"M")/Payroll!$K37,0))),0)) -> 0 | L122: =IF(L$2=Payroll!$I37,Payroll!$F37,IF(L$2>Payroll!$I37,Payroll!$F37*((1+Payroll!$J37)^(ROUNDDOWN(DATEDIF(Payroll!$I37,L$2,"M")/Payroll!$K37,0))),0)) -> 0 | ... CX122: =IF(CX$2=Payroll!$I37,Payroll!$F37,IF(CX$2>Payroll!$I37,Payroll!$F37*((1+Payroll!$J37)^(ROUNDDOWN(DATEDIF(Payroll!$I37,CX$2,"M")/Payroll!$K37,0))),0)) -> 0
A123: =Payroll!A38 -> Employee 4 | E123: =IF(E$2=Payroll!$I38,Payroll!$F38,IF(E$2>Payroll!$I38,Payroll!$F38*((1+Payroll!$J38)^(ROUNDDOWN(DATEDIF(Payroll!$I38,E$2,"M")/Payroll!$K38,0))),0)) -> 0 | F123: =IF(F$2=Payroll!$I38,Payroll!$F38,IF(F$2>Payroll!$I38,Payroll!$F38*((1+Payroll!$J38)^(ROUNDDOWN(DATEDIF(Payroll!$I38,F$2,"M")/Payroll!$K38,0))),0)) -> 0 | G123: =IF(G$2=Payroll!$I38,Payroll!$F38,IF(G$2>Payroll!$I38,Payroll!$F38*((1+Payroll!$J38)^(ROUNDDOWN(DATEDIF(Payroll!$I38,G$2,"M")/Payroll!$K38,0))),0)) -> 0 | H123: =IF(H$2=Payroll!$I38,Payroll!$F38,IF(H$2>Payroll!$I38,Payroll!$F38*((1+Payroll!$J38)^(ROUNDDOWN(DATEDIF(Payroll!$I38,H$2,"M")/Payroll!$K38,0))),0)) -> 0 | I123: =IF(I$2=Payroll!$I38,Payroll!$F38,IF(I$2>Payroll!$I38,Payroll!$F38*((1+Payroll!$J38)^(ROUNDDOWN(DATEDIF(Payroll!$I38,I$2,"M")/Payroll!$K38,0))),0)) -> 0 | J123: =IF(J$2=Payroll!$I38,Payroll!$F38,IF(J$2>Payroll!$I38,Payroll!$F38*((1+Payroll!$J38)^(ROUNDDOWN(DATEDIF(Payroll!$I38,J$2,"M")/Payroll!$K38,0))),0)) -> 0 | K123: =IF(K$2=Payroll!$I38,Payroll!$F38,IF(K$2>Payroll!$I38,Payroll!$F38*((1+Payroll!$J38)^(ROUNDDOWN(DATEDIF(Payroll!$I38,K$2,"M")/Payroll!$K38,0))),0)) -> 0 | L123: =IF(L$2=Payroll!$I38,Payroll!$F38,IF(L$2>Payroll!$I38,Payroll!$F38*((1+Payroll!$J38)^(ROUNDDOWN(DATEDIF(Payroll!$I38,L$2,"M")/Payroll!$K38,0))),0)) -> 0 | ... CX123: =IF(CX$2=Payroll!$I38,Payroll!$F38,IF(CX$2>Payroll!$I38,Payroll!$F38*((1+Payroll!$J38)^(ROUNDDOWN(DATEDIF(Payroll!$I38,CX$2,"M")/Payroll!$K38,0))),0)) -> 0
A127: =Payroll!A48 -> Customer Success & Support | E127: =SUM(E128:E133) -> 0 | F127: =SUM(F128:F133) -> 0 | G127: =SUM(G128:G133) -> 0 | H127: =SUM(H128:H133) -> 0 | I127: =SUM(I128:I133) -> 0 | J127: =SUM(J128:J133) -> 0 | K127: =SUM(K128:K133) -> 0 | L127: =SUM(L128:L133) -> 0 | ... CX127: =SUM(CX128:CX133) -> 13846.154
A128: =Payroll!A49 -> Head of Customer Success | E128: =IF(E$2=Payroll!$I49,Payroll!$F49,IF(E$2>Payroll!$I49,Payroll!$F49*((1+Payroll!$J49)^(ROUNDDOWN(DATEDIF(Payroll!$I49,E$2,"M")/Payroll!$K49,0))),0)) -> 0 | F128: =IF(F$2=Payroll!$I49,Payroll!$F49,IF(F$2>Payroll!$I49,Payroll!$F49*((1+Payroll!$J49)^(ROUNDDOWN(DATEDIF(Payroll!$I49,F$2,"M")/Payroll!$K49,0))),0)) -> 0 | G128: =IF(G$2=Payroll!$I49,Payroll!$F49,IF(G$2>Payroll!$I49,Payroll!$F49*((1+Payroll!$J49)^(ROUNDDOWN(DATEDIF(Payroll!$I49,G$2,"M")/Payroll!$K49,0))),0)) -> 0 | H128: =IF(H$2=Payroll!$I49,Payroll!$F49,IF(H$2>Payroll!$I49,Payroll!$F49*((1+Payroll!$J49)^(ROUNDDOWN(DATEDIF(Payroll!$I49,H$2,"M")/Payroll!$K49,0))),0)) -> 0 | I128: =IF(I$2=Payroll!$I49,Payroll!$F49,IF(I$2>Payroll!$I49,Payroll!$F49*((1+Payroll!$J49)^(ROUNDDOWN(DATEDIF(Payroll!$I49,I$2,"M")/Payroll!$K49,0))),0)) -> 0 | J128: =IF(J$2=Payroll!$I49,Payroll!$F49,IF(J$2>Payroll!$I49,Payroll!$F49*((1+Payroll!$J49)^(ROUNDDOWN(DATEDIF(Payroll!$I49,J$2,"M")/Payroll!$K49,0))),0)) -> 0 | K128: =IF(K$2=Payroll!$I49,Payroll!$F49,IF(K$2>Payroll!$I49,Payroll!$F49*((1+Payroll!$J49)^(ROUNDDOWN(DATEDIF(Payroll!$I49,K$2,"M")/Payroll!$K49,0))),0)) -> 0 | L128: =IF(L$2=Payroll!$I49,Payroll!$F49,IF(L$2>Payroll!$I49,Payroll!$F49*((1+Payroll!$J49)^(ROUNDDOWN(DATEDIF(Payroll!$I49,L$2,"M")/Payroll!$K49,0))),0)) -> 0 | ... CX128: =IF(CX$2=Payroll!$I49,Payroll!$F49,IF(CX$2>Payroll!$I49,Payroll!$F49*((1+Payroll!$J49)^(ROUNDDOWN(DATEDIF(Payroll!$I49,CX$2,"M")/Payroll!$K49,0))),0)) -> 1538.4615
A129: =Payroll!A52 -> Technical Support Specialist 1 | E129: =IF(E$2=Payroll!$I52,Payroll!$F52,IF(E$2>Payroll!$I52,Payroll!$F52*((1+Payroll!$J52)^(ROUNDDOWN(DATEDIF(Payroll!$I52,E$2,"M")/Payroll!$K52,0))),0)) -> 0 | F129: =IF(F$2=Payroll!$I52,Payroll!$F52,IF(F$2>Payroll!$I52,Payroll!$F52*((1+Payroll!$J52)^(ROUNDDOWN(DATEDIF(Payroll!$I52,F$2,"M")/Payroll!$K52,0))),0)) -> 0 | G129: =IF(G$2=Payroll!$I52,Payroll!$F52,IF(G$2>Payroll!$I52,Payroll!$F52*((1+Payroll!$J52)^(ROUNDDOWN(DATEDIF(Payroll!$I52,G$2,"M")/Payroll!$K52,0))),0)) -> 0 | H129: =IF(H$2=Payroll!$I52,Payroll!$F52,IF(H$2>Payroll!$I52,Payroll!$F52*((1+Payroll!$J52)^(ROUNDDOWN(DATEDIF(Payroll!$I52,H$2,"M")/Payroll!$K52,0))),0)) -> 0 | I129: =IF(I$2=Payroll!$I52,Payroll!$F52,IF(I$2>Payroll!$I52,Payroll!$F52*((1+Payroll!$J52)^(ROUNDDOWN(DATEDIF(Payroll!$I52,I$2,"M")/Payroll!$K52,0))),0)) -> 0 | J129: =IF(J$2=Payroll!$I52,Payroll!$F52,IF(J$2>Payroll!$I52,Payroll!$F52*((1+Payroll!$J52)^(ROUNDDOWN(DATEDIF(Payroll!$I52,J$2,"M")/Payroll!$K52,0))),0)) -> 0 | K129: =IF(K$2=Payroll!$I52,Payroll!$F52,IF(K$2>Payroll!$I52,Payroll!$F52*((1+Payroll!$J52)^(ROUNDDOWN(DATEDIF(Payroll!$I52,K$2,"M")/Payroll!$K52,0))),0)) -> 0 | L129: =IF(L$2=Payroll!$I52,Payroll!$F52,IF(L$2>Payroll!$I52,Payroll!$F52*((1+Payroll!$J52)^(ROUNDDOWN(DATEDIF(Payroll!$I52,L$2,"M")/Payroll!$K52,0))),0)) -> 0 | ... CX129: =IF(CX$2=Payroll!$I52,Payroll!$F52,IF(CX$2>Payroll!$I52,Payroll!$F52*((1+Payroll!$J52)^(ROUNDDOWN(DATEDIF(Payroll!$I52,CX$2,"M")/Payroll!$K52,0))),0)) -> 0
A130: =Payroll!A53 -> Technical Support Specialist 2 | E130: =IF(E$2=Payroll!$I53,Payroll!$F53,IF(E$2>Payroll!$I53,Payroll!$F53*((1+Payroll!$J53)^(ROUNDDOWN(DATEDIF(Payroll!$I53,E$2,"M")/Payroll!$K53,0))),0)) -> 0 | F130: =IF(F$2=Payroll!$I53,Payroll!$F53,IF(F$2>Payroll!$I53,Payroll!$F53*((1+Payroll!$J53)^(ROUNDDOWN(DATEDIF(Payroll!$I53,F$2,"M")/Payroll!$K53,0))),0)) -> 0 | G130: =IF(G$2=Payroll!$I53,Payroll!$F53,IF(G$2>Payroll!$I53,Payroll!$F53*((1+Payroll!$J53)^(ROUNDDOWN(DATEDIF(Payroll!$I53,G$2,"M")/Payroll!$K53,0))),0)) -> 0 | H130: =IF(H$2=Payroll!$I53,Payroll!$F53,IF(H$2>Payroll!$I53,Payroll!$F53*((1+Payroll!$J53)^(ROUNDDOWN(DATEDIF(Payroll!$I53,H$2,"M")/Payroll!$K53,0))),0)) -> 0 | I130: =IF(I$2=Payroll!$I53,Payroll!$F53,IF(I$2>Payroll!$I53,Payroll!$F53*((1+Payroll!$J53)^(ROUNDDOWN(DATEDIF(Payroll!$I53,I$2,"M")/Payroll!$K53,0))),0)) -> 0 | J130: =IF(J$2=Payroll!$I53,Payroll!$F53,IF(J$2>Payroll!$I53,Payroll!$F53*((1+Payroll!$J53)^(ROUNDDOWN(DATEDIF(Payroll!$I53,J$2,"M")/Payroll!$K53,0))),0)) -> 0 | K130: =IF(K$2=Payroll!$I53,Payroll!$F53,IF(K$2>Payroll!$I53,Payroll!$F53*((1+Payroll!$J53)^(ROUNDDOWN(DATEDIF(Payroll!$I53,K$2,"M")/Payroll!$K53,0))),0)) -> 0 | L130: =IF(L$2=Payroll!$I53,Payroll!$F53,IF(L$2>Payroll!$I53,Payroll!$F53*((1+Payroll!$J53)^(ROUNDDOWN(DATEDIF(Payroll!$I53,L$2,"M")/Payroll!$K53,0))),0)) -> 0 | ... CX130: =IF(CX$2=Payroll!$I53,Payroll!$F53,IF(CX$2>Payroll!$I53,Payroll!$F53*((1+Payroll!$J53)^(ROUNDDOWN(DATEDIF(Payroll!$I53,CX$2,"M")/Payroll!$K53,0))),0)) -> 0
A131: =Payroll!A54 -> Project manager CS | E131: =IF(E$2=Payroll!$I54,Payroll!$F54,IF(E$2>Payroll!$I54,Payroll!$F54*((1+Payroll!$J54)^(ROUNDDOWN(DATEDIF(Payroll!$I54,E$2,"M")/Payroll!$K54,0))),0)) -> 0 | F131: =IF(F$2=Payroll!$I54,Payroll!$F54,IF(F$2>Payroll!$I54,Payroll!$F54*((1+Payroll!$J54)^(ROUNDDOWN(DATEDIF(Payroll!$I54,F$2,"M")/Payroll!$K54,0))),0)) -> 0 | G131: =IF(G$2=Payroll!$I54,Payroll!$F54,IF(G$2>Payroll!$I54,Payroll!$F54*((1+Payroll!$J54)^(ROUNDDOWN(DATEDIF(Payroll!$I54,G$2,"M")/Payroll!$K54,0))),0)) -> 0 | H131: =IF(H$2=Payroll!$I54,Payroll!$F54,IF(H$2>Payroll!$I54,Payroll!$F54*((1+Payroll!$J54)^(ROUNDDOWN(DATEDIF(Payroll!$I54,H$2,"M")/Payroll!$K54,0))),0)) -> 0 | I131: =IF(I$2=Payroll!$I54,Payroll!$F54,IF(I$2>Payroll!$I54,Payroll!$F54*((1+Payroll!$J54)^(ROUNDDOWN(DATEDIF(Payroll!$I54,I$2,"M")/Payroll!$K54,0))),0)) -> 0 | J131: =IF(J$2=Payroll!$I54,Payroll!$F54,IF(J$2>Payroll!$I54,Payroll!$F54*((1+Payroll!$J54)^(ROUNDDOWN(DATEDIF(Payroll!$I54,J$2,"M")/Payroll!$K54,0))),0)) -> 0 | K131: =IF(K$2=Payroll!$I54,Payroll!$F54,IF(K$2>Payroll!$I54,Payroll!$F54*((1+Payroll!$J54)^(ROUNDDOWN(DATEDIF(Payroll!$I54,K$2,"M")/Payroll!$K54,0))),0)) -> 0 | L131: =IF(L$2=Payroll!$I54,Payroll!$F54,IF(L$2>Payroll!$I54,Payroll!$F54*((1+Payroll!$J54)^(ROUNDDOWN(DATEDIF(Payroll!$I54,L$2,"M")/Payroll!$K54,0))),0)) -> 0 | ... CX131: =IF(CX$2=Payroll!$I54,Payroll!$F54,IF(CX$2>Payroll!$I54,Payroll!$F54*((1+Payroll!$J54)^(ROUNDDOWN(DATEDIF(Payroll!$I54,CX$2,"M")/Payroll!$K54,0))),0)) -> 0
A132: =Payroll!A55 -> Account Manager | E132: =IF(E$2=Payroll!$I55,Payroll!$F55,IF(E$2>Payroll!$I55,Payroll!$F55*((1+Payroll!$J55)^(ROUNDDOWN(DATEDIF(Payroll!$I55,E$2,"M")/Payroll!$K55,0))),0)) -> 0 | F132: =IF(F$2=Payroll!$I55,Payroll!$F55,IF(F$2>Payroll!$I55,Payroll!$F55*((1+Payroll!$J55)^(ROUNDDOWN(DATEDIF(Payroll!$I55,F$2,"M")/Payroll!$K55,0))),0)) -> 0 | G132: =IF(G$2=Payroll!$I55,Payroll!$F55,IF(G$2>Payroll!$I55,Payroll!$F55*((1+Payroll!$J55)^(ROUNDDOWN(DATEDIF(Payroll!$I55,G$2,"M")/Payroll!$K55,0))),0)) -> 0 | H132: =IF(H$2=Payroll!$I55,Payroll!$F55,IF(H$2>Payroll!$I55,Payroll!$F55*((1+Payroll!$J55)^(ROUNDDOWN(DATEDIF(Payroll!$I55,H$2,"M")/Payroll!$K55,0))),0)) -> 0 | I132: =IF(I$2=Payroll!$I55,Payroll!$F55,IF(I$2>Payroll!$I55,Payroll!$F55*((1+Payroll!$J55)^(ROUNDDOWN(DATEDIF(Payroll!$I55,I$2,"M")/Payroll!$K55,0))),0)) -> 0 | J132: =IF(J$2=Payroll!$I55,Payroll!$F55,IF(J$2>Payroll!$I55,Payroll!$F55*((1+Payroll!$J55)^(ROUNDDOWN(DATEDIF(Payroll!$I55,J$2,"M")/Payroll!$K55,0))),0)) -> 0 | K132: =IF(K$2=Payroll!$I55,Payroll!$F55,IF(K$2>Payroll!$I55,Payroll!$F55*((1+Payroll!$J55)^(ROUNDDOWN(DATEDIF(Payroll!$I55,K$2,"M")/Payroll!$K55,0))),0)) -> 0 | L132: =IF(L$2=Payroll!$I55,Payroll!$F55,IF(L$2>Payroll!$I55,Payroll!$F55*((1+Payroll!$J55)^(ROUNDDOWN(DATEDIF(Payroll!$I55,L$2,"M")/Payroll!$K55,0))),0)) -> 0 | ... CX132: =IF(CX$2=Payroll!$I55,Payroll!$F55,IF(CX$2>Payroll!$I55,Payroll!$F55*((1+Payroll!$J55)^(ROUNDDOWN(DATEDIF(Payroll!$I55,CX$2,"M")/Payroll!$K55,0))),0)) -> 12307.692
A133: =Payroll!A56 -> Employee 4 | E133: =IF(E$2=Payroll!$I56,Payroll!$F56,IF(E$2>Payroll!$I56,Payroll!$F56*((1+Payroll!$J56)^(ROUNDDOWN(DATEDIF(Payroll!$I56,E$2,"M")/Payroll!$K56,0))),0)) -> 0 | F133: =IF(F$2=Payroll!$I56,Payroll!$F56,IF(F$2>Payroll!$I56,Payroll!$F56*((1+Payroll!$J56)^(ROUNDDOWN(DATEDIF(Payroll!$I56,F$2,"M")/Payroll!$K56,0))),0)) -> 0 | G133: =IF(G$2=Payroll!$I56,Payroll!$F56,IF(G$2>Payroll!$I56,Payroll!$F56*((1+Payroll!$J56)^(ROUNDDOWN(DATEDIF(Payroll!$I56,G$2,"M")/Payroll!$K56,0))),0)) -> 0 | H133: =IF(H$2=Payroll!$I56,Payroll!$F56,IF(H$2>Payroll!$I56,Payroll!$F56*((1+Payroll!$J56)^(ROUNDDOWN(DATEDIF(Payroll!$I56,H$2,"M")/Payroll!$K56,0))),0)) -> 0 | I133: =IF(I$2=Payroll!$I56,Payroll!$F56,IF(I$2>Payroll!$I56,Payroll!$F56*((1+Payroll!$J56)^(ROUNDDOWN(DATEDIF(Payroll!$I56,I$2,"M")/Payroll!$K56,0))),0)) -> 0 | J133: =IF(J$2=Payroll!$I56,Payroll!$F56,IF(J$2>Payroll!$I56,Payroll!$F56*((1+Payroll!$J56)^(ROUNDDOWN(DATEDIF(Payroll!$I56,J$2,"M")/Payroll!$K56,0))),0)) -> 0 | K133: =IF(K$2=Payroll!$I56,Payroll!$F56,IF(K$2>Payroll!$I56,Payroll!$F56*((1+Payroll!$J56)^(ROUNDDOWN(DATEDIF(Payroll!$I56,K$2,"M")/Payroll!$K56,0))),0)) -> 0 | L133: =IF(L$2=Payroll!$I56,Payroll!$F56,IF(L$2>Payroll!$I56,Payroll!$F56*((1+Payroll!$J56)^(ROUNDDOWN(DATEDIF(Payroll!$I56,L$2,"M")/Payroll!$K56,0))),0)) -> 0 | ... CX133: =IF(CX$2=Payroll!$I56,Payroll!$F56,IF(CX$2>Payroll!$I56,Payroll!$F56*((1+Payroll!$J56)^(ROUNDDOWN(DATEDIF(Payroll!$I56,CX$2,"M")/Payroll!$K56,0))),0)) -> 0
A134: =Payroll!A57
A135: =Payroll!A58
...

Sheet Unit economics
A1: =Settings!B4 -> Healthy4U
A2: Month | C2: ='Monthly forecast'!D2 -> 45108 | D2: ='Monthly forecast'!E2 -> 45139 | E2: =EDATE(D2,1) -> 45170 | F2: =EDATE(E2,1) -> 45200 | G2: =EDATE(F2,1) -> 45231 | H2: =EDATE(G2,1) -> 45261 | I2: =EDATE(H2,1) -> 45292 | J2: =EDATE(I2,1) -> 45323 | K2: =EDATE(J2,1) -> 45352 | L2: =EDATE(K2,1) -> 45383 | ... CW2: =EDATE(CV2,1) -> 48092
A4: ='Monthly forecast'!A15 -> REVENUE STREAM 1: SELF-SERVICE
A6: Subscription price per month | C6: =IF(C2>=Projections!$D$28,Projections!$B$28,0) -> 0 | D6: =IF(D2>=Projections!$D$28,Projections!$B$28,0) -> 100 | E6: =IF(E2>=Projections!$D$28,Projections!$B$28,0) -> 100 | F6: =IF(F2>=Projections!$D$28,Projections!$B$28,0) -> 100 | G6: =IF(G2>=Projections!$D$28,Projections!$B$28,0) -> 100 | H6: =IF(H2>=Projections!$D$28,Projections!$B$28,0) -> 100 | I6: =IF(I2>=Projections!$D$28,Projections!$B$28,0) -> 100 | J6: =IF(J2>=Projections!$D$28,Projections!$B$28,0) -> 100 | ... CW6: =IF(CW2>=Projections!$D$28,Projections!$B$28,0) -> 100
A7: ARPPU | C7: =C6 -> 0 | D7: =D6 -> 100 | E7: =E6 -> 100 | F7: =F6 -> 100 | G7: =G6 -> 100 | H7: =H6 -> 100 | I7: =I6 -> 100 | J7: =J6 -> 100 | ... CW7: =CW6 -> 100
A9: Churn | C9: ='Monthly forecast'!D18 | D9: ='Monthly forecast'!E18 -> 0.15 | E9: ='Monthly forecast'!F18 -> 0.15 | F9: ='Monthly forecast'!G18 -> 0.15 | G9: ='Monthly forecast'!H18 -> 0.15 | H9: ='Monthly forecast'!I18 -> 0.15 | I9: ='Monthly forecast'!J18 -> 0.15 | J9: ='Monthly forecast'!K18 -> 0.15 | ... CW9: ='Monthly forecast'!CX18 -> 0.15
A10: LT (Ilifetime) | C10: =IFERROR(1/C9,0) -> 0 | D10: =IFERROR(1/D9,0) -> 6.6666667 | E10: =IFERROR(1/E9,0) -> 6.6666667 | F10: =IFERROR(1/F9,0) -> 6.6666667 | G10: =IFERROR(1/G9,0) -> 6.6666667 | H10: =IFERROR(1/H9,0) -> 6.6666667 | I10: =IFERROR(1/I9,0) -> 6.6666667 | J10: =IFERROR(1/J9,0) -> 6.6666667 | ... CW10: =IFERROR(1/CW9,0) -> 6.6666667
A12: LTV | C12: =C7*C10 -> 0 | D12: =D7*D10 -> 666.66667 | E12: =E7*E10 -> 666.66667 | F12: =F7*F10 -> 666.66667 | G12: =G7*G10 -> 666.66667 | H12: =H7*H10 -> 666.66667 | I12: =I7*I10 -> 666.66667 | J12: =J7*J10 -> 666.66667 | ... CW12: =CW7*CW10 -> 666.66667
A13: LTV 3 month | C13: =C7*3 -> 0 | D13: =D7*3 -> 300 | E13: =E7*3 -> 300 | F13: =F7*3 -> 300 | G13: =G7*3 -> 300 | H13: =H7*3 -> 300 | I13: =I7*3 -> 300 | J13: =J7*3 -> 300 | ... CW13: =CW7*3 -> 300
A14: LTV 6 month | C14: =C7*6 -> 0 | D14: =D7*6 -> 600 | E14: =E7*6 -> 600 | F14: =F7*6 -> 600 | G14: =G7*6 -> 600 | H14: =H7*6 -> 600 | I14: =I7*6 -> 600 | J14: =J7*6 -> 600 | ... CW14: =CW7*6 -> 600
A15: LTV 12 month | C15: =C7*12 -> 0 | D15: =D7*12 -> 1200 | E15: =E7*12 -> 1200 | F15: =F7*12 -> 1200 | G15: =G7*12 -> 1200 | H15: =H7*12 -> 1200 | I15: =I7*12 -> 1200 | J15: =J7*12 -> 1200 | ... CW15: =CW7*12 -> 1200
A17: pCAC (CAC paid channels) | D17: ='Monthly forecast'!E10/Projections!$B$36 -> 600 | E17: ='Monthly forecast'!F10/Projections!$B$36 -> 570 | F17: ='Monthly forecast'!G10/Projections!$B$36 -> 541.5 | G17: ='Monthly forecast'!H10/Projections!$B$36 -> 514.425 | H17: ='Monthly forecast'!I10/Projections!$B$36 -> 488.70375 | I17: ='Monthly forecast'!J10/Projections!$B$36 -> 464.26856 | J17: ='Monthly forecast'!K10/Projections!$B$36 -> 441.05513 | K17: ='Monthly forecast'!L10/Projections!$B$36 -> 419.00238 | ... CW17: ='Monthly forecast'!CX10/Projections!$B$36 -> 400
A18: LTV/CAC | D18: =D12/D$17 -> 1.1111111 | E18: =E12/E$17 -> 1.1695906 | F18: =F12/F$17 -> 1.231148 | G18: =G12/G$17 -> 1.2959453 | H18: =H12/H$17 -> 1.364153 | I18: =I12/I$17 -> 1.4359505 | J18: =J12/J$17 -> 1.5115268 | K18: =K12/K$17 -> 1.5910809 | ... CW18: =CW12/CW$17 -> 1.6666667
A19: LTV 3 month/CAC | D19: =D13/D$17 -> 0.5 | E19: =E13/E$17 -> 0.52631579 | F19: =F13/F$17 -> 0.55401662 | G19: =G13/G$17 -> 0.58317539 | H19: =H13/H$17 -> 0.61386883 | I19: =I13/I$17 -> 0.64617772 | J19: =J13/J$17 -> 0.68018707 | K19: =K13/K$17 -> 0.71598639 | ... CW19: =CW13/CW$17 -> 0.75
A20: LTV 6 month/CAC | D20: =D14/D$17 -> 1 | E20: =E14/E$17 -> 1.0526316 | F20: =F14/F$17 -> 1.1080332 | G20: =G14/G$17 -> 1.1663508 | H20: =H14/H$17 -> 1.2277377 | I20: =I14/I$17 -> 1.2923554 | J20: =J14/J$17 -> 1.3603741 | K20: =K14/K$17 -> 1.4319728 | ... CW20: =CW14/CW$17 -> 1.5
A21: LTV 12 month/CAC | D21: =D15/D$17 -> 2 | E21: =E15/E$17 -> 2.1052632 | F21: =F15/F$17 -> 2.2160665 | G21: =G15/G$17 -> 2.3327016 | H21: =H15/H$17 -> 2.4554753 | I21: =I15/I$17 -> 2.5847109 | J21: =J15/J$17 -> 2.7207483 | K21: =K15/K$17 -> 2.8639456 | ... CW21: =CW15/CW$17 -> 3
A24: ='Monthly forecast'!A24 -> REVENUE STREAM 2: INBOUND SALES
A26: Subscription price per month | C26: =IF(C2>=Projections!$D$28,Projections!$B$28,0) -> 0 | D26: =IF(D2>=Projections!$D$28,Projections!$B$28,0) -> 100 | E26: =IF(E2>=Projections!$D$28,Projections!$B$28,0) -> 100 | F26: =IF(F2>=Projections!$D$28,Projections!$B$28,0) -> 100 | G26: =IF(G2>=Projections!$D$28,Projections!$B$28,0) -> 100 | H26: =IF(H2>=Projections!$D$28,Projections!$B$28,0) -> 100 | I26: =IF(I2>=Projections!$D$28,Projections!$B$28,0) -> 100 | J26: =IF(J2>=Projections!$D$28,Projections!$B$28,0) -> 100 | ... CW26: =IF(CW2>=Projections!$D$28,Projections!$B$28,0) -> 100
A27: ARPPU | C27: =C26 -> 0 | D27: =D26 -> 100 | E27: =E26 -> 100 | F27: =F26 -> 100 | G27: =G26 -> 100 | H27: =H26 -> 100 | I27: =I26 -> 100 | J27: =J26 -> 100 | ... CW27: =CW26 -> 100
A29: Churn | C29: ='Monthly forecast'!D38 | D29: ='Monthly forecast'!E29 -> 0.15 | E29: ='Monthly forecast'!F29 -> 0.15 | F29: ='Monthly forecast'!G29 -> 0.15 | G29: ='Monthly forecast'!H29 -> 0.15 | H29: ='Monthly forecast'!I29 -> 0.15 | I29: ='Monthly forecast'!J29 -> 0.15 | J29: ='Monthly forecast'!K29 -> 0.15 | K29: ='Monthly forecast'!L29 -> 0.15 | ... CW29: ='Monthly forecast'!CX29 -> 0.15
A30: LT (Ilifetime) | C30: =IFERROR(1/C29,0) -> 0 | D30: =IFERROR(1/D29,0) -> 6.6666667 | E30: =IFERROR(1/E29,0) -> 6.6666667 | F30: =IFERROR(1/F29,0) -> 6.6666667 | G30: =IFERROR(1/G29,0) -> 6.6666667 | H30: =IFERROR(1/H29,0) -> 6.6666667 | I30: =IFERROR(1/I29,0) -> 6.6666667 | J30: =IFERROR(1/J29,0) -> 6.6666667 | ... CW30: =IFERROR(1/CW29,0) -> 6.6666667
A32: LTV | C32: =C27*C30 -> 0 | D32: =D27*D30 -> 666.66667 | E32: =E27*E30 -> 666.66667 | F32: =F27*F30 -> 666.66667 | G32: =G27*G30 -> 666.66667 | H32: =H27*H30 -> 666.66667 | I32: =I27*I30 -> 666.66667 | J32: =J27*J30 -> 666.66667 | ... CW32: =CW27*CW30 -> 666.66667
A33: LTV 3 month | C33: =C27*3 -> 0 | D33: =D27*3 -> 300 | E33: =E27*3 -> 300 | F33: =F27*3 -> 300 | G33: =G27*3 -> 300 | H33: =H27*3 -> 300 | I33: =I27*3 -> 300 | J33: =J27*3 -> 300 | ... CW33: =CW27*3 -> 300
A34: LTV 6 month | C34: =C27*6 -> 0 | D34: =D27*6 -> 600 | E34: =E27*6 -> 600 | F34: =F27*6 -> 600 | G34: =G27*6 -> 600 | H34: =H27*6 -> 600 | I34: =I27*6 -> 600 | J34: =J27*6 -> 600 | ... CW34: =CW27*6 -> 600
A35: LTV 12 month | C35: =C27*12 -> 0 | D35: =D27*12 -> 1200 | E35: =E27*12 -> 1200 | F35: =F27*12 -> 1200 | G35: =G27*12 -> 1200 | H35: =H27*12 -> 1200 | I35: =I27*12 -> 1200 | J35: =J27*12 -> 1200 | ... CW35: =CW27*12 -> 1200
A37: Marketing Costs | D37: ='Monthly forecast'!E10/Projections!$B$45/Projections!$B$50 -> 300 | E37: ='Monthly forecast'!F10/Projections!$B$45/Projections!$B$50 -> 285 | F37: ='Monthly forecast'!G10/Projections!$B$45/Projections!$B$50 -> 270.75 | G37: ='Monthly forecast'!H10/Projections!$B$45/Projections!$B$50 -> 257.2125 | H37: ='Monthly forecast'!I10/Projections!$B$45/Projections!$B$50 -> 244.35188 | I37: ='Monthly forecast'!J10/Projections!$B$45/Projections!$B$50 -> 232.13428 | J37: ='Monthly forecast'!K10/Projections!$B$45/Projections!$B$50 -> 220.52757 | K37: ='Monthly forecast'!L10/Projections!$B$45/Projections!$B$50 -> 209.50119 | ... CW37: ='Monthly forecast'!CX10/Projections!$B$45/Projections!$B$50 -> 200
A38: Cost of Inbound Sales Managers team | D38: ='Monthly forecast'!E83/(Projections!$B$49*Projections!$B$50) -> 153.84615 | E38: ='Monthly forecast'!F83/(Projections!$B$49*Projections!$B$50) -> 153.84615 | F38: ='Monthly forecast'!G83/(Projections!$B$49*Projections!$B$50) -> 153.84615 | G38: ='Monthly forecast'!H83/(Projections!$B$49*Projections!$B$50) -> 153.84615 | H38: ='Monthly forecast'!I83/(Projections!$B$49*Projections!$B$50) -> 153.84615 | I38: ='Monthly forecast'!J83/(Projections!$B$49*Projections!$B$50) -> 153.84615 | J38: ='Monthly forecast'!K83/(Projections!$B$49*Projections!$B$50) -> 153.84615 | K38: ='Monthly forecast'!L83/(Projections!$B$49*Projections!$B$50) -> 153.84615 | ... CW38: ='Monthly forecast'!CX83/(Projections!$B$49*Projections!$B$50) -> 180.25529
A39: CAC | D39: =D37+D38 -> 453.84615 | E39: =E37+E38 -> 438.84615 | F39: =F37+F38 -> 424.59615 | G39: =G37+G38 -> 411.05865 | H39: =H37+H38 -> 398.19803 | I39: =I37+I38 -> 385.98044 | J39: =J37+J38 -> 374.37372 | K39: =K37+K38 -> 363.34734 | ... CW39: =CW37+CW38 -> 380.25529
A41: LTV/CAC | D41: =D32/D39 -> 1.4689266 | E41: =E32/E39 -> 1.5191353 | F41: =F32/F39 -> 1.5701194 | G41: =G32/G39 -> 1.6218286 | H41: =H32/H39 -> 1.6742089 | I41: =I32/I39 -> 1.7272033 | J41: =J32/J39 -> 1.7807518 | K41: =K32/K39 -> 1.8347916 | ... CV41: =CV32/CV39 -> 1.7532081
A42: LTV 3 month/CAC | D42: =D33/D$39 -> 0.66101695 | E42: =E33/E$39 -> 0.68361087 | F42: =F33/F$39 -> 0.70655374 | G42: =G33/G$39 -> 0.72982285 | H42: =H33/H$39 -> 0.75339399 | I42: =I33/I$39 -> 0.77724147 | J42: =J33/J$39 -> 0.8013383 | K42: =K33/K$39 -> 0.82565624 | ... CW42: =CW33/CW$39 -> 0.78894366
A43: LTV 6 month/CAC | D43: =D34/D$39 -> 1.3220339 | E43: =E34/E$39 -> 1.3672217 | F43: =F34/F$39 -> 1.4131075 | G43: =G34/G$39 -> 1.4596457 | H43: =H34/H$39 -> 1.506788 | I43: =I34/I$39 -> 1.5544829 | J43: =J34/J$39 -> 1.6026766 | K43: =K34/K$39 -> 1.6513125 | ... CW43: =CW34/CW$39 -> 1.5778873
A44: LTV 12 month/CAC | D44: =D35/D$39 -> 2.6440678 | E44: =E35/E$39 -> 2.7344435 | F44: =F35/F$39 -> 2.826215 | G44: =G35/G$39 -> 2.9192914 | H44: =H35/H$39 -> 3.0135759 | I44: =I35/I$39 -> 3.1089659 | J44: =J35/J$39 -> 3.2053532 | K44: =K35/K$39 -> 3.302625 | ... CW44: =CW35/CW$39 -> 3.1557746
A46: ='Monthly forecast'!A35 -> REVENUE STREAM 3: OUTBOUND SALES
A48: Subscription price per month | C48: =IF(C2>=Projections!$D$28,Projections!$B$28,0) -> 0 | D48: =IF(D2>=Projections!$D$28,Projections!$B$28,0) -> 100 | E48: =IF(E2>=Projections!$D$28,Projections!$B$28,0) -> 100 | F48: =IF(F2>=Projections!$D$28,Projections!$B$28,0) -> 100 | G48: =IF(G2>=Projections!$D$28,Projections!$B$28,0) -> 100 | H48: =IF(H2>=Projections!$D$28,Projections!$B$28,0) -> 100 | I48: =IF(I2>=Projections!$D$28,Projections!$B$28,0) -> 100 | J48: =IF(J2>=Projections!$D$28,Projections!$B$28,0) -> 100 | ... CW48: =IF(CW2>=Projections!$D$28,Projections!$B$28,0) -> 100
A49: ARPPU | C49: =C48 -> 0 | D49: =D48 -> 100 | E49: =E48 -> 100 | F49: =F48 -> 100 | G49: =G48 -> 100 | H49: =H48 -> 100 | I49: =I48 -> 100 | J49: =J48 -> 100 | ... CW49: =CW48 -> 100
A51: Churn | C51: ='Monthly forecast'!D60 | D51: ='Monthly forecast'!E38 -> 0.15 | E51: ='Monthly forecast'!F38 -> 0.15 | F51: ='Monthly forecast'!G38 -> 0.15 | G51: ='Monthly forecast'!H38 -> 0.15 | H51: ='Monthly forecast'!I38 -> 0.15 | I51: ='Monthly forecast'!J38 -> 0.15 | J51: ='Monthly forecast'!K38 -> 0.15 | K51: ='Monthly forecast'!L38 -> 0.15 | ... CW51: ='Monthly forecast'!CX38 -> 0.15
A52: LT (Ilifetime) | C52: =IFERROR(1/C51,0) -> 0 | D52: =IFERROR(1/D51,0) -> 6.6666667 | E52: =IFERROR(1/E51,0) -> 6.6666667 | F52: =IFERROR(1/F51,0) -> 6.6666667 | G52: =IFERROR(1/G51,0) -> 6.6666667 | H52: =IFERROR(1/H51,0) -> 6.6666667 | I52: =IFERROR(1/I51,0) -> 6.6666667 | J52: =IFERROR(1/J51,0) -> 6.6666667 | ... CW52: =IFERROR(1/CW51,0) -> 6.6666667
A54: LTV | C54: =C49*C52 -> 0 | D54: =D49*D52 -> 666.66667 | E54: =E49*E52 -> 666.66667 | F54: =F49*F52 -> 666.66667 | G54: =G49*G52 -> 666.66667 | H54: =H49*H52 -> 666.66667 | I54: =I49*I52 -> 666.66667 | J54: =J49*J52 -> 666.66667 | ... CW54: =CW49*CW52 -> 666.66667
A55: LTV 3 month | C55: =C49*3 -> 0 | D55: =D49*3 -> 300 | E55: =E49*3 -> 300 | F55: =F49*3 -> 300 | G55: =G49*3 -> 300 | H55: =H49*3 -> 300 | I55: =I49*3 -> 300 | J55: =J49*3 -> 300 | ... CW55: =CW49*3 -> 300
A56: LTV 6 month | C56: =C49*6 -> 0 | D56: =D49*6 -> 600 | E56: =E49*6 -> 600 | F56: =F49*6 -> 600 | G56: =G49*6 -> 600 | H56: =H49*6 -> 600 | I56: =I49*6 -> 600 | J56: =J49*6 -> 600 | ... CW56: =CW49*6 -> 600
A57: LTV 12 month | C57: =C49*12 -> 0 | D57: =D49*12 -> 1200 | E57: =E49*12 -> 1200 | F57: =F49*12 -> 1200 | G57: =G49*12 -> 1200 | H57: =H49*12 -> 1200 | I57: =I49*12 -> 1200 | J57: =J49*12 -> 1200 | ... CW57: =CW49*12 -> 1200
A59: CAC - Cost of Outbound Sales Managers | D59: ='Monthly forecast'!E89/'Monthly forecast'!E37 -> 0 | E59: ='Monthly forecast'!F89/'Monthly forecast'!F37 -> 0 | F59: ='Monthly forecast'!G89/'Monthly forecast'!G37 -> 0 | G59: ='Monthly forecast'!H89/'Monthly forecast'!H37 -> 0 | H59: ='Monthly forecast'!I89/'Monthly forecast'!I37 -> 0 | I59: ='Monthly forecast'!J89/'Monthly forecast'!J37 -> 0 | J59: ='Monthly forecast'!K89/'Monthly forecast'!K37 -> 0 | K59: ='Monthly forecast'!L89/'Monthly forecast'!L37 -> 0 | ... CW59: ='Monthly forecast'!CX89/'Monthly forecast'!CX37 -> 0
A60: LTV/CAC | D60: =D54/D$59 -> #DIV/0! | E60: =E54/E$59 -> #DIV/0! | F60: =F54/F$59 -> #DIV/0! | G60: =G54/G$59 -> #DIV/0! | H60: =H54/H$59 -> #DIV/0! | I60: =I54/I$59 -> #DIV/0! | J60: =J54/J$59 -> #DIV/0! | K60: =K54/K$59 -> #DIV/0! | ... CW60: =CW54/CW$59 -> #DIV/0!
A61: LTV 3 month/CAC | D61: =D55/D$59 -> #DIV/0! | E61: =E55/E$59 -> #DIV/0! | F61: =F55/F$59 -> #DIV/0! | G61: =G55/G$59 -> #DIV/0! | H61: =H55/H$59 -> #DIV/0! | I61: =I55/I$59 -> #DIV/0! | J61: =J55/J$59 -> #DIV/0! | K61: =K55/K$59 -> #DIV/0! | ... CW61: =CW55/CW$59 -> #DIV/0!
A62: LTV 6 month/CAC | D62: =D56/D$59 -> #DIV/0! | E62: =E56/E$59 -> #DIV/0! | F62: =F56/F$59 -> #DIV/0! | G62: =G56/G$59 -> #DIV/0! | H62: =H56/H$59 -> #DIV/0! | I62: =I56/I$59 -> #DIV/0! | J62: =J56/J$59 -> #DIV/0! | K62: =K56/K$59 -> #DIV/0! | ... CW62: =CW56/CW$59 -> #DIV/0!
A63: LTV 12 month/CAC | D63: =D57/D$59 -> #DIV/0! | E63: =E57/E$59 -> #DIV/0! | F63: =F57/F$59 -> #DIV/0! | G63: =G57/G$59 -> #DIV/0! | H63: =H57/H$59 -> #DIV/0! | I63: =I57/I$59 -> #DIV/0! | J63: =J57/J$59 -> #DIV/0! | K63: =K57/K$59 -> #DIV/0! | ... CW63: =CW57/CW$59 -> #DIV/0!

Sheet P&L | Cash Flow | Balance
A1: =Settings!B4 -> Healthy4U
A2: Month | C2: =EDATE(D2,-1) -> 45108 | D2: =Projections!$B$4 -> 45139 | E2: =EDATE(D2,1) -> 45170 | F2: =EDATE(E2,1) -> 45200 | G2: =EDATE(F2,1) -> 45231 | H2: =EDATE(G2,1) -> 45261 | I2: =EDATE(H2,1) -> 45292 | J2: =EDATE(I2,1) -> 45323 | K2: =EDATE(J2,1) -> 45352 | L2: =EDATE(K2,1) -> 45383 | ... CW2: =EDATE(CV2,1) -> 48092
A4: P&L
A6: REVENUE | C6: =C7 | D6: =SUM(D7:D9) -> 2204.5 | E6: =SUM(E7:E9) -> 4179.4158 | F6: =SUM(F7:F9) -> 5964.3313 | G6: =SUM(G7:G9) -> 7793.1527 | H6: =SUM(H7:H9) -> 9464.9733 | I6: =SUM(I7:I9) -> 11009.309 | J6: =SUM(J7:J9) -> 12651.551 | K6: =SUM(K7:K9) -> 14183.598 | ... CW6: =SUM(CW7:CW9) -> 878799.58
A7: ='Monthly forecast'!A15 -> REVENUE STREAM 1: SELF-SERVICE | C7: ='Monthly forecast'!D22 | D7: ='Monthly forecast'!E22 -> 668.16667 | E7: ='Monthly forecast'!F22 -> 1269.8053 | F7: ='Monthly forecast'!G22 -> 1816.6104 | G7: ='Monthly forecast'!H22 -> 2318.6092 | H7: ='Monthly forecast'!I22 -> 2784.4157 | I7: ='Monthly forecast'!J22 -> 3221.4473 | J7: ='Monthly forecast'!K22 -> 3636.1097 | ... CW7: ='Monthly forecast'!CX22 -> 288488.76
A8: ='Monthly forecast'!A24 -> REVENUE STREAM 2: INBOUND SALES | C8: ='Monthly forecast'!D33 | D8: ='Monthly forecast'!E33 -> 1336.3333 | E8: ='Monthly forecast'!F33 -> 2539.6105 | F8: ='Monthly forecast'!G33 -> 3633.2209 | G8: ='Monthly forecast'!H33 -> 4637.2185 | H8: ='Monthly forecast'!I33 -> 5568.8313 | I8: ='Monthly forecast'!J33 -> 6442.8947 | J8: ='Monthly forecast'!K33 -> 7272.2194 | ... CW8: ='Monthly forecast'!CX33 -> 576977.52
A9: ='Monthly forecast'!A35 -> REVENUE STREAM 3: OUTBOUND SALES | C9: ='Monthly forecast'!D42 | D9: ='Monthly forecast'!E42 -> 200 | E9: ='Monthly forecast'!F42 -> 370 | F9: ='Monthly forecast'!G42 -> 514.5 | G9: ='Monthly forecast'!H42 -> 837.325 | H9: ='Monthly forecast'!I42 -> 1111.7262 | I9: ='Monthly forecast'!J42 -> 1344.9673 | J9: ='Monthly forecast'!K42 -> 1743.2222 | ... CW9: ='Monthly forecast'!CX42 -> 13333.3
A11: COGS | C11: ='Monthly forecast'!D47 | D11: ='Monthly forecast'!E47 -> 66.135 | E11: ='Monthly forecast'!F47 -> 125.38247 | F11: ='Monthly forecast'!G47 -> 178.92994 | G11: ='Monthly forecast'!H47 -> 233.79458 | H11: ='Monthly forecast'!I47 -> 283.9492 | I11: ='Monthly forecast'!J47 -> 330.27928 | J11: ='Monthly forecast'!K47 -> 379.54654 | ... CW11: ='Monthly forecast'!CX47 -> 26363.987
A12: Gross profit | C12: =C6-C11 -> 0 | D12: =D6-D11 -> 2138.365 | E12: =E6-E11 -> 4054.0333 | F12: =F6-F11 -> 5785.4014 | G12: =G6-G11 -> 7559.3581 | H12: =H6-H11 -> 9181.0241 | I12: =I6-I11 -> 10679.03 | J12: =J6-J11 -> 12272.005 | ... CW12: =CW6-CW11 -> 852435.59
A13: Gross margin | C13: =iferror(C12/#REF!,0) -> 0 | D13: =iferror(D12/#REF!,0) -> 0 | E13: =iferror(E12/#REF!,0) -> 0 | F13: =iferror(F12/#REF!,0) -> 0 | G13: =iferror(G12/#REF!,0) -> 0 | H13: =iferror(H12/#REF!,0) -> 0 | I13: =iferror(I12/#REF!,0) -> 0 | J13: =iferror(J12/#REF!,0) -> 0 | ... CW13: =iferror(CW12/#REF!,0) -> 0
A15: SG&A | C15: ='Monthly forecast'!D53 | D15: ='Monthly forecast'!E53 -> 7076.9231 | E15: ='Monthly forecast'!F53 -> 7076.9231 | F15: ='Monthly forecast'!G53 -> 7076.9231 | G15: ='Monthly forecast'!H53 -> 7076.9231 | H15: ='Monthly forecast'!I53 -> 7076.9231 | I15: ='Monthly forecast'!J53 -> 7076.9231 | J15: ='Monthly forecast'!K53 -> 7076.9231 | ... CW15: ='Monthly forecast'!CX53 -> 240053.82
A17: EBITDA | C17: =C12-C15 -> 0 | D17: =D12-D15 -> -4938.5581 | E17: =E12-E15 -> -3022.8898 | F17: =F12-F15 -> -1291.5217 | G17: =G12-G15 -> 482.43502 | H17: =H12-H15 -> 2104.101 | I17: =I12-I15 -> 3602.107 | J17: =J12-J15 -> 5195.0818 | ... CW17: =CW12-CW15 -> 612381.78
A18: EBITDA, % | C18: =iferror(C17/#REF!,0) -> 0 | D18: =iferror(D17/#REF!,0) -> 0 | E18: =iferror(E17/#REF!,0) -> 0 | F18: =iferror(F17/#REF!,0) -> 0 | G18: =iferror(G17/#REF!,0) -> 0 | H18: =iferror(H17/#REF!,0) -> 0 | I18: =iferror(I17/#REF!,0) -> 0 | J18: =iferror(J17/#REF!,0) -> 0 | ... CW18: =iferror(CW17/#REF!,0) -> 0
A20: Depreciation | C20: ='Monthly forecast'!D169 | D20: ='Monthly forecast'!E169 -> 500 | E20: ='Monthly forecast'!F169 -> 500 | F20: ='Monthly forecast'!G169 -> 500 | G20: ='Monthly forecast'!H169 -> 500 | H20: ='Monthly forecast'!I169 -> 500 | I20: ='Monthly forecast'!J169 -> 500 | J20: ='Monthly forecast'!K169 -> 500 | ... CW20: ='Monthly forecast'!CX169 -> 0
A21: Interest
A23: Tax base | C23: =C17-C20-C21 -> 0 | D23: =D17-D20-D21 -> -5438.5581 | E23: =E17-E20-E21 -> -3522.8898 | F23: =F17-F20-F21 -> -1791.5217 | G23: =G17-G20-G21 -> -17.564982 | H23: =H17-H20-H21 -> 1604.101 | I23: =I17-I20-I21 -> 3102.107 | J23: =J17-J20-J21 -> 4695.0818 | ... CW23: =CW17-CW20-CW21 -> 612381.78
A25: Tax fee, % | C25: =Settings!$B$7 -> 0.23 | D25: =Settings!$B$7 -> 0.23 | E25: =Settings!$B$7 -> 0.23 | F25: =Settings!$B$7 -> 0.23 | G25: =Settings!$B$7 -> 0.23 | H25: =Settings!$B$7 -> 0.23 | I25: =Settings!$B$7 -> 0.23 | J25: =Settings!$B$7 -> 0.23 | ... CW25: =Settings!$B$7 -> 0.23
A26: Taxes | C26: =IF(C23>0,C23*C25,0) -> 0 | D26: =IF(D23>0,D23*D25,0) -> 0 | E26: =IF(E23>0,E23*E25,0) -> 0 | F26: =IF(F23>0,F23*F25,0) -> 0 | G26: =IF(G23>0,G23*G25,0) -> 0 | H26: =IF(H23>0,H23*H25,0) -> 368.94323 | I26: =IF(I23>0,I23*I25,0) -> 713.48461 | J26: =IF(J23>0,J23*J25,0) -> 1079.8688 | ... CW26: =IF(CW23>0,CW23*CW25,0) -> 140847.81
A28: Net income | C28: =C17-C20-C21-C26 -> 0 | D28: =D17-D20-D21-D26 -> -5438.5581 | E28: =E17-E20-E21-E26 -> -3522.8898 | F28: =F17-F20-F21-F26 -> -1791.5217 | G28: =G17-G20-G21-G26 -> -17.564982 | H28: =H17-H20-H21-H26 -> 1235.1578 | I28: =I17-I20-I21-I26 -> 2388.6224 | J28: =J17-J20-J21-J26 -> 3615.213 | ... CW28: =CW17-CW20-CW21-CW26 -> 471533.97
A29: Net margin | C29: =IFERROR(C28/#REF!,0) -> 0 | D29: =IFERROR(D28/#REF!,0) -> 0 | E29: =IFERROR(E28/#REF!,0) -> 0 | F29: =IFERROR(F28/#REF!,0) -> 0 | G29: =IFERROR(G28/#REF!,0) -> 0 | H29: =IFERROR(H28/#REF!,0) -> 0 | I29: =IFERROR(I28/#REF!,0) -> 0 | J29: =IFERROR(J28/#REF!,0) -> 0 | ... CW29: =IFERROR(CW28/#REF!,0) -> 0
A32: CASH FLOW
A34: Cash at the beginning of month | C34: =Settings!$B$10 -> 0 | D34: =C39 -> 0 | E34: =D39 -> -16938.558 | F34: =E39 -> -19961.448 | G34: =F39 -> -21252.97 | H34: =G39 -> -20770.535 | I34: =H39 -> -19035.377 | J34: =I39 -> -16146.754 | K34: =J39 -> -12031.541 | ... CW34: =CV39 -> 8361641.8
A35: Fundraising
A36: Cash flow from Operations | C36: =C28+C20 -> 0 | D36: =D28+D20 -> -4938.5581 | E36: =E28+E20 -> -3022.8898 | F36: =F28+F20 -> -1291.5217 | G36: =G28+G20 -> 482.43502 | H36: =H28+H20 -> 1735.1578 | I36: =I28+I20 -> 2888.6224 | J36: =J28+J20 -> 4115.213 | ... CW36: =CW28+CW20 -> 471533.97
A37: Cash flow from Investing | C37: =-'Monthly forecast'!D160 -> 0 | D37: =-'Monthly forecast'!E160 -> -12000 | E37: =-'Monthly forecast'!F160 -> 0 | F37: =-'Monthly forecast'!G160 -> 0 | G37: =-'Monthly forecast'!H160 -> 0 | H37: =-'Monthly forecast'!I160 -> 0 | I37: =-'Monthly forecast'!J160 -> 0 | J37: =-'Monthly forecast'!K160 -> 0 | ... CW37: =-'Monthly forecast'!CX160 -> 0
A38: Cash flow from Financing
A39: Cash at the end of month | C39: =C34+C35+C36+C37+C38 -> 0 | D39: =D34+D35+D36+D37+D38 -> -16938.558 | E39: =E34+E35+E36+E37+E38 -> -19961.448 | F39: =F34+F35+F36+F37+F38 -> -21252.97 | G39: =G34+G35+G36+G37+G38 -> -20770.535 | H39: =H34+H35+H36+H37+H38 -> -19035.377 | I39: =I34+I35+I36+I37+I38 -> -16146.754 | J39: =J34+J35+J36+J37+J38 -> -12031.541 | ... CW39: =CW34+CW35+CW36+CW37+CW38 -> 8833175.8
A43: BALANCE SHEET
A45: ASSETS
A46: Cash | C46: =C39 -> 0 | D46: =D39 -> -16938.558 | E46: =E39 -> -19961.448 | F46: =F39 -> -21252.97 | G46: =G39 -> -20770.535 | H46: =H39 -> -19035.377 | I46: =I39 -> -16146.754 | J46: =J39 -> -12031.541 | ... CW46: =CW39 -> 8833175.8
A47: Accounts receivable
A48: Inventory
A49: Property & Equipment | C49: =C37-C20 -> 0 | D49: =C49-D37-D20 -> 11500 | E49: =D49-E37-E20 -> 11000 | F49: =E49-F37-F20 -> 10500 | G49: =F49-G37-G20 -> 10000 | H49: =G49-H37-H20 -> 9500 | I49: =H49-I37-I20 -> 9000 | J49: =I49-J37-J20 -> 8500 | K49: =J49-K37-K20 -> 8000 | ... CW49: =CV49-CW37-CW20 -> -2000
A50: Total assets | C50: =ROUND(SUM(C46:C49),0) -> 0 | D50: =ROUND(SUM(D46:D49),0) -> -5439 | E50: =ROUND(SUM(E46:E49),0) -> -8961 | F50: =ROUND(SUM(F46:F49),0) -> -10753 | G50: =ROUND(SUM(G46:G49),0) -> -10771 | H50: =ROUND(SUM(H46:H49),0) -> -9535 | I50: =ROUND(SUM(I46:I49),0) -> -7147 | J50: =ROUND(SUM(J46:J49),0) -> -3532 | ... CW50: =ROUND(SUM(CW46:CW49),0) -> 8831176
A53: LIABILITIES
A54: Accounts payable
A55: Debt | C55: =C35 | D55: =C55 | E55: =D55 | F55: =E55 | G55: =F55 | H55: =G55 | I55: =H55 | J55: =I55 | K55: =J55 | ... CW55: =CV55
A56: Total liabilities | C56: =SUM(C54:C55) -> 0 | D56: =SUM(D54:D55) -> 0 | E56: =SUM(E54:E55) -> 0 | F56: =SUM(F54:F55) -> 0 | G56: =SUM(G54:G55) -> 0 | H56: =SUM(H54:H55) -> 0 | I56: =SUM(I54:I55) -> 0 | J56: =SUM(J54:J55) -> 0 | ... CW56: =SUM(CW54:CW55) -> 0
A58: SHAREHOLDER'S EQUITY
A59: Equity capital | C59: =Settings!$B$10 -> 0 | D59: =C59 -> 0 | E59: =D59 -> 0 | F59: =E59 -> 0 | G59: =F59 -> 0 | H59: =G59 -> 0 | I59: =H59 -> 0 | J59: =I59 -> 0 | K59: =J59 -> 0 | ... CW59: =CV59 -> 0
A60: Retained earnings | C60: =C28 -> 0 | D60: =C60+D28 -> -5438.5581 | E60: =D60+E28 -> -8961.4478 | F60: =E60+F28 -> -10752.97 | G60: =F60+G28 -> -10770.535 | H60: =G60+H28 -> -9535.3768 | I60: =H60+I28 -> -7146.7544 | J60: =I60+J28 -> -3531.5414 | K60: =J60+K28 -> 1227.9573 | ... CW60: =CV60+CW28 -> 8831175.8
A61: Shareholder's equity | C61: =SUM(C59:C60) -> 0 | D61: =SUM(D59:D60) -> -5438.5581 | E61: =SUM(E59:E60) -> -8961.4478 | F61: =SUM(F59:F60) -> -10752.97 | G61: =SUM(G59:G60) -> -10770.535 | H61: =SUM(H59:H60) -> -9535.3768 | I61: =SUM(I59:I60) -> -7146.7544 | J61: =SUM(J59:J60) -> -3531.5414 | ... CW61: =SUM(CW59:CW60) -> 8831175.8
A62: Total liabilities & Shareholder's equity | C62: =ROUND(C56+C61,0) -> 0 | D62: =ROUND(D56+D61,0) -> -5439 | E62: =ROUND(E56+E61,0) -> -8961 | F62: =ROUND(F56+F61,0) -> -10753 | G62: =ROUND(G56+G61,0) -> -10771 | H62: =ROUND(H56+H61,0) -> -9535 | I62: =ROUND(I56+I61,0) -> -7147 | J62: =ROUND(J56+J61,0) -> -3532 | ... CW62: =ROUND(CW56+CW61,0) -> 8831176
A64: Balance sheet check | C64: =C62-C50 -> 0 | D64: =D62-D50 -> 0 | E64: =E62-E50 -> 0 | F64: =F62-F50 -> 0 | G64: =G62-G50 -> 0 | H64: =H62-H50 -> 0 | I64: =I62-I50 -> 0 | J64: =J62-J50 -> 0 | ... CW64: =CW62-CW50 -> 0

Sheet Cap Table
B1: =Settings!B4 -> Healthy4U
B3: Foundation | G3: Round 1 | L3: Round 2 | Q3: Round 3
B4: Date | C4: =Roadmap!C7 -> 45139 | G4: Date | H4: 45444 | L4: Date | M4: 45809 | Q4: Date | R4: 46174
B6: Company Valuation | G6: Company Valuation | L6: Company Valuation | Q6: Company Valuation
C7: Value | D7: Share Price | E7: Number of Shares | H7: Value | I7: Share Price | J7: Number of Shares | M7: Value | N7: Share Price | O7: Number of Shares | R7: Value | S7: Share Price | T7: Number of Shares
B8: Valuation | C8: 0 | D8: =C8/E8 -> 0 | E8: 1000000 | G8: Valuation | H8: 1000000 | I8: =H8/J8 -> 1 | J8: 1000000 | L8: Valuation | M8: 5000000 | N8: =M8/O8 -> 2.5 | O8: =J11 -> 2000000 | Q8: Valuation | R8: 10000000 | S8: =R8/T8 -> 3.4246575 | T8: =O11 -> 2920000
G9: New Capital Raised | H9: =SUM(H20:H23) -> 1000000 | I9: =I8 -> 1 | J9: =H9/I8 -> 1000000 | L9: New Capital Raised | M9: =SUM(M15:M27) -> 2300000 | N9: =N8 -> 2.5 | O9: =M9/N8 -> 920000 | Q9: New Capital Raised | R9: =SUM(R15:R29) -> 2000000 | S9: =S8 -> 3.4246575 | T9: =R9/S8 -> 584000
G10: Post-money Valuation | H10: =H8+H9 -> 2000000 | L10: Post-money Valuation | M10: =M8+M9 -> 7300000 | Q10: Post-money Valuation | R10: =R8+R9 -> 12000000
B11: Total | E11: =E8+E9 -> 1000000 | G11: Total | J11: =J8+J9 -> 2000000 | L11: Total | O11: =O8+O9 -> 2920000 | Q11: Total | T11: =T8+T9 -> 3504000
B13: Company Ownership Capitalization Table | G13: Company Ownership Capitalization Table | L13: Company Ownership Capitalization Table | Q13: Company Ownership Capitalization Table
C14: Capital | D14: Number of Shares | E14: % of Ownership | H14: Capital Raised in this Round | I14: Number of Shares | J14: % of Ownership | M14: Capital Raised in this Round | N14: Number of Shares | O14: % of Ownership | R14: Capital Raised in this Round | S14: Number of Shares | T14: % of Ownership
B15: Founder 1 | C15: 0 | D15: =$E$8*E15 -> 350000 | E15: 0.35 | G15: Founder 1 | H15: 0 | I15: =D15 -> 350000 | J15: =I15/$J$11 -> 0.175 | L15: Founder 1 | M15: 0 | N15: =IF(M15>0,I15+(M15/$N$9),I15) -> 350000 | O15: =N15/$O$11 -> 0.11986301 | Q15: Founder 1 | R15: 0 | S15: =IF(R15>0,N15+(R15/$S$9),N15) -> 350000 | T15: =S15/$T$11 -> 0.099885845
B16: Founder 2 | C16: 0 | D16: =$E$8*E16 -> 350000 | E16: 0.35 | G16: Founder 2 | H16: 0 | I16: =D16 -> 350000 | J16: =I16/$J$11 -> 0.175 | L16: Founder 2 | M16: 0 | N16: =IF(M16>0,I16+(M16/$N$9),I16) -> 350000 | O16: =N16/$O$11 -> 0.11986301 | Q16: Founder 2 | R16: 0 | S16: =IF(R16>0,N16+(R16/$S$9),N16) -> 350000 | T16: =S16/$T$11 -> 0.099885845
B17: Founder 3 | C17: 0 | D17: =$E$8*E17 -> 240000 | E17: 0.24 | G17: Founder 3 | H17: 0 | I17: =D17 -> 240000 | J17: =I17/$J$11 -> 0.12 | L17: Founder 3 | M17: 0 | N17: =IF(M17>0,I17+(M17/$N$9),I17) -> 240000 | O17: =N17/$O$11 -> 0.082191781 | Q17: Founder 3 | R17: 0 | S17: =IF(R17>0,N17+(R17/$S$9),N17) -> 240000 | T17: =S17/$T$11 -> 0.068493151
B18: Key Employees | C18: 0 | D18: =$E$8*E18 -> 50000 | E18: 0.05 | G18: Key Employees | H18: 0 | I18: =D18 -> 50000 | J18: =I18/$J$11 -> 0.025 | L18: Key Employees | M18: 0 | N18: =IF(M18>0,I18+(M18/$N$9),I18) -> 50000 | O18: =N18/$O$11 -> 0.017123288 | Q18: Key Employees | R18: 0 | S18: =IF(R18>0,N18+(R18/$S$9),N18) -> 50000 | T18: =S18/$T$11 -> 0.014269406
B19: Advisors | C19: 0 | D19: =$E$8*E19 -> 10000 | E19: 0.01 | G19: Advisors | H19: 0 | I19: =D19 -> 10000 | J19: =I19/$J$11 -> 0.005 | L19: Advisors | M19: 0 | N19: =IF(M19>0,I19+(M19/$N$9),I19) -> 10000 | O19: =N19/$O$11 -> 0.0034246575 | Q19: Advisors | R19: 0 | S19: =IF(R19>0,N19+(R19/$S$9),N19) -> 10000 | T19: =S19/$T$11 -> 0.0028538813
G20: Investor 1 | H20: 500000 | I20: =H20/$I$9 -> 500000 | J20: =I20/$J$11 -> 0.25 | L20: Investor 1 | M20: 100000 | N20: =IF(M20>0,I20+(M20/$N$9),I20) -> 540000 | O20: =N20/$O$11 -> 0.18493151 | Q20: Investor 1 | R20: 0 | S20: =IF(R20>0,N20+(R20/$S$9),N20) -> 540000 | T20: =S20/$T$11 -> 0.15410959
G21: Investor 2 | H21: 300000 | I21: =H21/$I$9 -> 300000 | J21: =I21/$J$11 -> 0.15 | L21: Investor 2 | M21: 0 | N21: =IF(M21>0,I21+(M21/$N$9),I21) -> 300000 | O21: =N21/$O$11 -> 0.10273973 | Q21: Investor 2 | R21: 500000 | S21: =IF(R21>0,N21+(R21/$S$9),N21) -> 446000 | T21: =S21/$T$11 -> 0.12728311
G22: Investor 3 | H22: 100000 | I22: =H22/$I$9 -> 100000 | J22: =I22/$J$11 -> 0.05 | L22: Investor 3 | M22: 200000 | N22: =IF(M22>0,I22+(M22/$N$9),I22) -> 180000 | O22: =N22/$O$11 -> 0.061643836 | Q22: Investor 3 | R22: 0 | S22: =IF(R22>0,N22+(R22/$S$9),N22) -> 180000 | T22: =S22/$T$11 -> 0.051369863
G23: Investor 4 | H23: 100000 | I23: =H23/$I$9 -> 100000 | J23: =I23/$J$11 -> 0.05 | L23: Investor 4 | M23: 0 | N23: =IF(M23>0,I23+(M23/$N$9),I23) -> 100000 | O23: =N23/$O$11 -> 0.034246575 | Q23: Investor 4 | R23: 0 | S23: =IF(R23>0,N23+(R23/$S$9),N23) -> 100000 | T23: =S23/$T$11 -> 0.028538813
I24: =SUM(I15:I23) -> 2000000 | L24: Investor 5 | M24: 600000 | N24: =M24/$N$9 -> 240000 | O24: =N24/$O$11 -> 0.082191781 | Q24: Investor 5 | R24: 0 | S24: =IF(R24>0,N24+(R24/$S$9),N24) -> 240000 | T24: =S24/$T$11 -> 0.068493151
L25: Investor 6 | M25: 500000 | N25: =M25/$N$9 -> 200000 | O25: =N25/$O$11 -> 0.068493151 | Q25: Investor 6 | R25: 0 | S25: =IF(R25>0,N25+(R25/$S$9),N25) -> 200000 | T25: =S25/$T$11 -> 0.057077626
L26: Investor 7 | M26: 300000 | N26: =M26/$N$9 -> 120000 | O26: =N26/$O$11 -> 0.04109589 | Q26: Investor 7 | R26: 0 | S26: =IF(R26>0,N26+(R26/$S$9),N26) -> 120000 | T26: =S26/$T$11 -> 0.034246575
L27: Investor 8 | M27: 600000 | N27: =M27/$N$9 -> 240000 | O27: =N27/$O$11 -> 0.082191781 | Q27: Investor 8 | R27: 0 | S27: =IF(R27>0,N27+(R27/$S$9),N27) -> 240000 | T27: =S27/$T$11 -> 0.068493151
N28: =SUM(N15:N27) -> 2920000 | Q28: Investor 9 | R28: 1000000 | S28: =R28/$S$9 -> 292000 | T28: =S28/$T$11 -> 0.083333333
Q29: Investor 10 | R29: 500000 | S29: =R29/$S$9 -> 146000 | T29: =S29/$T$11 -> 0.041666667
S30: =SUM(S15:S29) -> 3504000

Sheet Dividends
B1: =Settings!B4 -> Healthy4U
C3: ='For Pitchdeck'!C2 -> 2023 | E3: ='For Pitchdeck'!D2 -> 2024 | G3: ='For Pitchdeck'!E2 -> 2025 | I3: ='For Pitchdeck'!F2 -> 2026 | K3: ='For Pitchdeck'!G2 -> 2027
A4: 1 | B4: Net Income | C4: ='For Pitchdeck'!C8 -> -9535.3768 | E4: ='For Pitchdeck'!D8 -> 91762.113 | G4: ='For Pitchdeck'!E8 -> 208098.45 | I4: ='For Pitchdeck'!F8 -> 159822.02 | K4: ='For Pitchdeck'!G8 -> 176469.28
C6: =C3 -> 2023 | E6: =E3 -> 2024 | G6: =G3 -> 2025 | I6: =I3 -> 2026 | K6: =K3 -> 2027
C7: Share | D7: Dividends | E7: Share | F7: Dividends | G7: Share | H7: Dividends | I7: Share | J7: Dividends | K7: Share | L7: Dividends
B8: ='Cap Table'!Q15 -> Founder 1 | C8: =IFS($C$6<YEAR('Cap Table'!$C$4),0,and($C$6=YEAR('Cap Table'!$C$4),YEAR('Cap Table'!$H$4)-YEAR('Cap Table'!$C$4)>0),'Cap Table'!$E15,and($C$6=YEAR('Cap Table'!$H$4),YEAR('Cap Table'!$M$4)-YEAR('Cap Table'!$H$4>0)),'Cap Table'!$J15,and($C$6=YEAR('Cap Table'!$M$4),YEAR('Cap Table'!$R$4)-YEAR('Cap Table'!$M$4>0)),'Cap Table'!$O15,$C$6>=YEAR('Cap Table'!$R$4),'Cap Table'!$T15) -> 0.35 | D8: =if(and($C$4>0,$A$4>0),$C$4*C8,if(and($C$4>0,$A$4<0),($C$4+$A$4)*C8,0)) -> 0 | E8: =IFS($E$6<YEAR('Cap Table'!$C$4),0,and($E$6=YEAR('Cap Table'!$C$4),YEAR('Cap Table'!$H$4)-YEAR('Cap Table'!$C$4)>0),'Cap Table'!$E15,and($E$6=YEAR('Cap Table'!$H$4),YEAR('Cap Table'!$M$4)-YEAR('Cap Table'!$H$4>0)),'Cap Table'!$J15,and($E$6=YEAR('Cap Table'!$M$4),YEAR('Cap Table'!$R$4)-YEAR('Cap Table'!$M$4>0)),'Cap Table'!$O15,$E$6>=YEAR('Cap Table'!$R$4),'Cap Table'!$T15) -> 0.175 | F8: =if(and($E$4>0,$C$4>0),$E$4*E8,if(and($E$4>0,$C$4<0),($E$4+$C$4)*E8,0)) -> 14389.679 | G8: =IFS($G$6<YEAR('Cap Table'!$C$4),0,and($G$6=YEAR('Cap Table'!$C$4),YEAR('Cap Table'!$H$4)-YEAR('Cap Table'!$C$4)>0),'Cap Table'!$E15,and($G$6=YEAR('Cap Table'!$H$4),YEAR('Cap Table'!$M$4)-YEAR('Cap Table'!$H$4>0)),'Cap Table'!$J15,and($G$6=YEAR('Cap Table'!$M$4),YEAR('Cap Table'!$R$4)-YEAR('Cap Table'!$M$4>0)),'Cap Table'!$O15,$G$6>=YEAR('Cap Table'!$R$4),'Cap Table'!$T15) -> 0.11986301 | H8: =if(and($G$4>0,$E$4>0),$G$4*G8,if(and($G$4>0,$E$4<0),($G$4+$E$4)*G8,0)) -> 24943.308 | I8: =IFS($I$6<YEAR('Cap Table'!$C$4),0,and($I$6=YEAR('Cap Table'!$C$4),YEAR('Cap Table'!$H$4)-YEAR('Cap Table'!$C$4)>0),'Cap Table'!$E15,and($I$6=YEAR('Cap Table'!$H$4),YEAR('Cap Table'!$M$4)-YEAR('Cap Table'!$H$4>0)),'Cap Table'!$J15,and($I$6=YEAR('Cap Table'!$M$4),YEAR('Cap Table'!$R$4)-YEAR('Cap Table'!$M$4>0)),'Cap Table'!$O15,$I$6>=YEAR('Cap Table'!$R$4),'Cap Table'!$T15) -> 0.099885845 | J8: =if(and($I$4>0,$G$4>0),$I$4*I8,if(and($I$4>0,$G$4<0),($I$4+$G$4)*I8,0)) -> 15963.957 | K8: =IFS($K$6<YEAR('Cap Table'!$C$4),0,and($K$6=YEAR('Cap Table'!$C$4),YEAR('Cap Table'!$H$4)-YEAR('Cap Table'!$C$4)>0),'Cap Table'!$E15,and($K$6=YEAR('Cap Table'!$H$4),YEAR('Cap Table'!$M$4)-YEAR('Cap Table'!$H$4>0)),'Cap Table'!$J15,and($K$6=YEAR('Cap Table'!$M$4),YEAR('Cap Table'!$R$4)-YEAR('Cap Table'!$M$4>0)),'Cap Table'!$O15,$K$6>=YEAR('Cap Table'!$R$4),'Cap Table'!$T15) -> 0.099885845 | L8: =if(and($K$4>0,$I$4>0),$K$4*K8,if(and($K$4>0,$I$4<0),($K$4+$I$4)*K8,0)) -> 17626.783
B9: ='Cap Table'!Q16 -> Founder 2 | C9: =IFS($C$6<YEAR('Cap Table'!$C$4),0,and($C$6=YEAR('Cap Table'!$C$4),YEAR('Cap Table'!$H$4)-YEAR('Cap Table'!$C$4)>0),'Cap Table'!$E16,and($C$6=YEAR('Cap Table'!$H$4),YEAR('Cap Table'!$M$4)-YEAR('Cap Table'!$H$4>0)),'Cap Table'!$J16,and($C$6=YEAR('Cap Table'!$M$4),YEAR('Cap Table'!$R$4)-YEAR('Cap Table'!$M$4>0)),'Cap Table'!$O16,$C$6>=YEAR('Cap Table'!$R$4),'Cap Table'!$T16) -> 0.35 | D9: =if(and($C$4>0,$A$4>0),$C$4*C9,if(and($C$4>0,$A$4<0),($C$4+$A$4)*C9,0)) -> 0 | E9: =IFS($E$6<YEAR('Cap Table'!$C$4),0,and($E$6=YEAR('Cap Table'!$C$4),YEAR('Cap Table'!$H$4)-YEAR('Cap Table'!$C$4)>0),'Cap Table'!$E16,and($E$6=YEAR('Cap Table'!$H$4),YEAR('Cap Table'!$M$4)-YEAR('Cap Table'!$H$4>0)),'Cap Table'!$J16,and($E$6=YEAR('Cap Table'!$M$4),YEAR('Cap Table'!$R$4)-YEAR('Cap Table'!$M$4>0)),'Cap Table'!$O16,$E$6>=YEAR('Cap Table'!$R$4),'Cap Table'!$T16) -> 0.175 | F9: =if(and($E$4>0,$C$4>0),$E$4*E9,if(and($E$4>0,$C$4<0),($E$4+$C$4)*E9,0)) -> 14389.679 | G9: =IFS($G$6<YEAR('Cap Table'!$C$4),0,and($G$6=YEAR('Cap Table'!$C$4),YEAR('Cap Table'!$H$4)-YEAR('Cap Table'!$C$4)>0),'Cap Table'!$E16,and($G$6=YEAR('Cap Table'!$H$4),YEAR('Cap Table'!$M$4)-YEAR('Cap Table'!$H$4>0)),'Cap Table'!$J16,and($G$6=YEAR('Cap Table'!$M$4),YEAR('Cap Table'!$R$4)-YEAR('Cap Table'!$M$4>0)),'Cap Table'!$O16,$G$6>=YEAR('Cap Table'!$R$4),'Cap Table'!$T16) -> 0.11986301 | H9: =if(and($G$4>0,$E$4>0),$G$4*G9,if(and($G$4>0,$E$4<0),($G$4+$E$4)*G9,0)) -> 24943.308 | I9: =IFS($I$6<YEAR('Cap Table'!$C$4),0,and($I$6=YEAR('Cap Table'!$C$4),YEAR('Cap Table'!$H$4)-YEAR('Cap Table'!$C$4)>0),'Cap Table'!$E16,and($I$6=YEAR('Cap Table'!$H$4),YEAR('Cap Table'!$M$4)-YEAR('Cap Table'!$H$4>0)),'Cap Table'!$J16,and($I$6=YEAR('Cap Table'!$M$4),YEAR('Cap Table'!$R$4)-YEAR('Cap Table'!$M$4>0)),'Cap Table'!$O16,$I$6>=YEAR('Cap Table'!$R$4),'Cap Table'!$T16) -> 0.099885845 | J9: =if(and($I$4>0,$G$4>0),$I$4*I9,if(and($I$4>0,$G$4<0),($I$4+$G$4)*I9,0)) -> 15963.957 | K9: =IFS($K$6<YEAR('Cap Table'!$C$4),0,and($K$6=YEAR('Cap Table'!$C$4),YEAR('Cap Table'!$H$4)-YEAR('Cap Table'!$C$4)>0),'Cap Table'!$E16,and($K$6=YEAR('Cap Table'!$H$4),YEAR('Cap Table'!$M$4)-YEAR('Cap Table'!$H$4>0)),'Cap Table'!$J16,and($K$6=YEAR('Cap Table'!$M$4),YEAR('Cap Table'!$R$4)-YEAR('Cap Table'!$M$4>0)),'Cap Table'!$O16,$K$6>=YEAR('Cap Table'!$R$4),'Cap Table'!$T16) -> 0.099885845 | L9: =if(and($K$4>0,$I$4>0),$K$4*K9,if(and($K$4>0,$I$4<0),($K$4+$I$4)*K9,0)) -> 17626.783
B10: ='Cap Table'!Q17 -> Founder 3 | C10: =IFS($C$6<YEAR('Cap Table'!$C$4),0,and($C$6=YEAR('Cap Table'!$C$4),YEAR('Cap Table'!$H$4)-YEAR('Cap Table'!$C$4)>0),'Cap Table'!$E17,and($C$6=YEAR('Cap Table'!$H$4),YEAR('Cap Table'!$M$4)-YEAR('Cap Table'!$H$4>0)),'Cap Table'!$J17,and($C$6=YEAR('Cap Table'!$M$4),YEAR('Cap Table'!$R$4)-YEAR('Cap Table'!$M$4>0)),'Cap Table'!$O17,$C$6>=YEAR('Cap Table'!$R$4),'Cap Table'!$T17) -> 0.24 | D10: =if(and($C$4>0,$A$4>0),$C$4*C10,if(and($C$4>0,$A$4<0),($C$4+$A$4)*C10,0)) -> 0 | E10: =IFS($E$6<YEAR('Cap Table'!$C$4),0,and($E$6=YEAR('Cap Table'!$C$4),YEAR('Cap Table'!$H$4)-YEAR('Cap Table'!$C$4)>0),'Cap Table'!$E17,and($E$6=YEAR('Cap Table'!$H$4),YEAR('Cap Table'!$M$4)-YEAR('Cap Table'!$H$4>0)),'Cap Table'!$J17,and($E$6=YEAR('Cap Table'!$M$4),YEAR('Cap Table'!$R$4)-YEAR('Cap Table'!$M$4>0)),'Cap Table'!$O17,$E$6>=YEAR('Cap Table'!$R$4),'Cap Table'!$T17) -> 0.12 | F10: =if(and($E$4>0,$C$4>0),$E$4*E10,if(and($E$4>0,$C$4<0),($E$4+$C$4)*E10,0)) -> 9867.2084 | G10: =IFS($G$6<YEAR('Cap Table'!$C$4),0,and($G$6=YEAR('Cap Table'!$C$4),YEAR('Cap Table'!$H$4)-YEAR('Cap Table'!$C$4)>0),'Cap Table'!$E17,and($G$6=YEAR('Cap Table'!$H$4),YEAR('Cap Table'!$M$4)-YEAR('Cap Table'!$H$4>0)),'Cap Table'!$J17,and($G$6=YEAR('Cap Table'!$M$4),YEAR('Cap Table'!$R$4)-YEAR('Cap Table'!$M$4>0)),'Cap Table'!$O17,$G$6>=YEAR('Cap Table'!$R$4),'Cap Table'!$T17) -> 0.082191781 | H10: =if(and($G$4>0,$E$4>0),$G$4*G10,if(and($G$4>0,$E$4<0),($G$4+$E$4)*G10,0)) -> 17103.982 | I10: =IFS($I$6<YEAR('Cap Table'!$C$4),0,and($I$6=YEAR('Cap Table'!$C$4),YEAR('Cap Table'!$H$4)-YEAR('Cap Table'!$C$4)>0),'Cap Table'!$E17,and($I$6=YEAR('Cap Table'!$H$4),YEAR('Cap Table'!$M$4)-YEAR('Cap Table'!$H$4>0)),'Cap Table'!$J17,and($I$6=YEAR('Cap Table'!$M$4),YEAR('Cap Table'!$R$4)-YEAR('Cap Table'!$M$4>0)),'Cap Table'!$O17,$I$6>=YEAR('Cap Table'!$R$4),'Cap Table'!$T17) -> 0.068493151 | J10: =if(and($I$4>0,$G$4>0),$I$4*I10,if(and($I$4>0,$G$4<0),($I$4+$G$4)*I10,0)) -> 10946.714 | K10: =IFS($K$6<YEAR('Cap Table'!$C$4),0,and($K$6=YEAR('Cap Table'!$C$4),YEAR('Cap Table'!$H$4)-YEAR('Cap Table'!$C$4)>0),'Cap Table'!$E17,and($K$6=YEAR('Cap Table'!$H$4),YEAR('Cap Table'!$M$4)-YEAR('Cap Table'!$H$4>0)),'Cap Table'!$J17,and($K$6=YEAR('Cap Table'!$M$4),YEAR('Cap Table'!$R$4)-YEAR('Cap Table'!$M$4>0)),'Cap Table'!$O17,$K$6>=YEAR('Cap Table'!$R$4),'Cap Table'!$T17) -> 0.068493151 | L10: =if(and($K$4>0,$I$4>0),$K$4*K10,if(and($K$4>0,$I$4<0),($K$4+$I$4)*K10,0)) -> 12086.937
B11: ='Cap Table'!Q18 -> Key Employees | C11: =IFS($C$6<YEAR('Cap Table'!$C$4),0,and($C$6=YEAR('Cap Table'!$C$4),YEAR('Cap Table'!$H$4)-YEAR('Cap Table'!$C$4)>0),'Cap Table'!$E18,and($C$6=YEAR('Cap Table'!$H$4),YEAR('Cap Table'!$M$4)-YEAR('Cap Table'!$H$4>0)),'Cap Table'!$J18,and($C$6=YEAR('Cap Table'!$M$4),YEAR('Cap Table'!$R$4)-YEAR('Cap Table'!$M$4>0)),'Cap Table'!$O18,$C$6>=YEAR('Cap Table'!$R$4),'Cap Table'!$T18) -> 0.05 | D11: =if(and($C$4>0,$A$4>0),$C$4*C11,if(and($C$4>0,$A$4<0),($C$4+$A$4)*C11,0)) -> 0 | E11: =IFS($E$6<YEAR('Cap Table'!$C$4),0,and($E$6=YEAR('Cap Table'!$C$4),YEAR('Cap Table'!$H$4)-YEAR('Cap Table'!$C$4)>0),'Cap Table'!$E18,and($E$6=YEAR('Cap Table'!$H$4),YEAR('Cap Table'!$M$4)-YEAR('Cap Table'!$H$4>0)),'Cap Table'!$J18,and($E$6=YEAR('Cap Table'!$M$4),YEAR('Cap Table'!$R$4)-YEAR('Cap Table'!$M$4>0)),'Cap Table'!$O18,$E$6>=YEAR('Cap Table'!$R$4),'Cap Table'!$T18) -> 0.025 | F11: =if(and($E$4>0,$C$4>0),$E$4*E11,if(and($E$4>0,$C$4<0),($E$4+$C$4)*E11,0)) -> 2055.6684 | G11: =IFS($G$6<YEAR('Cap Table'!$C$4),0,and($G$6=YEAR('Cap Table'!$C$4),YEAR('Cap Table'!$H$4)-YEAR('Cap Table'!$C$4)>0),'Cap Table'!$E18,and($G$6=YEAR('Cap Table'!$H$4),YEAR('Cap Table'!$M$4)-YEAR('Cap Table'!$H$4>0)),'Cap Table'!$J18,and($G$6=YEAR('Cap Table'!$M$4),YEAR('Cap Table'!$R$4)-YEAR('Cap Table'!$M$4>0)),'Cap Table'!$O18,$G$6>=YEAR('Cap Table'!$R$4),'Cap Table'!$T18) -> 0.017123288 | H11: =if(and($G$4>0,$E$4>0),$G$4*G11,if(and($G$4>0,$E$4<0),($G$4+$E$4)*G11,0)) -> 3563.3297 | I11: =IFS($I$6<YEAR('Cap Table'!$C$4),0,and($I$6=YEAR('Cap Table'!$C$4),YEAR('Cap Table'!$H$4)-YEAR('Cap Table'!$C$4)>0),'Cap Table'!$E18,and($I$6=YEAR('Cap Table'!$H$4),YEAR('Cap Table'!$M$4)-YEAR('Cap Table'!$H$4>0)),'Cap Table'!$J18,and($I$6=YEAR('Cap Table'!$M$4),YEAR('Cap Table'!$R$4)-YEAR('Cap Table'!$M$4>0)),'Cap Table'!$O18,$I$6>=YEAR('Cap Table'!$R$4),'Cap Table'!$T18) -> 0.014269406 | J11: =if(and($I$4>0,$G$4>0),$I$4*I11,if(and($I$4>0,$G$4<0),($I$4+$G$4)*I11,0)) -> 2280.5653 | K11: =IFS($K$6<YEAR('Cap Table'!$C$4),0,and($K$6=YEAR('Cap Table'!$C$4),YEAR('Cap Table'!$H$4)-YEAR('Cap Table'!$C$4)>0),'Cap Table'!$E18,and($K$6=YEAR('Cap Table'!$H$4),YEAR('Cap Table'!$M$4)-YEAR('Cap Table'!$H$4>0)),'Cap Table'!$J18,and($K$6=YEAR('Cap Table'!$M$4),YEAR('Cap Table'!$R$4)-YEAR('Cap Table'!$M$4>0)),'Cap Table'!$O18,$K$6>=YEAR('Cap Table'!$R$4),'Cap Table'!$T18) -> 0.014269406 | L11: =if(and($K$4>0,$I$4>0),$K$4*K11,if(and($K$4>0,$I$4<0),($K$4+$I$4)*K11,0)) -> 2518.1118
B12: ='Cap Table'!Q19 -> Advisors | C12: =IFS($C$6<YEAR('Cap Table'!$C$4),0,and($C$6=YEAR('Cap Table'!$C$4),YEAR('Cap Table'!$H$4)-YEAR('Cap Table'!$C$4)>0),'Cap Table'!$E19,and($C$6=YEAR('Cap Table'!$H$4),YEAR('Cap Table'!$M$4)-YEAR('Cap Table'!$H$4>0)),'Cap Table'!$J19,and($C$6=YEAR('Cap Table'!$M$4),YEAR('Cap Table'!$R$4)-YEAR('Cap Table'!$M$4>0)),'Cap Table'!$O19,$C$6>=YEAR('Cap Table'!$R$4),'Cap Table'!$T19) -> 0.01 | D12: =if(and($C$4>0,$A$4>0),$C$4*C12,if(and($C$4>0,$A$4<0),($C$4+$A$4)*C12,0)) -> 0 | E12: =IFS($E$6<YEAR('Cap Table'!$C$4),0,and($E$6=YEAR('Cap Table'!$C$4),YEAR('Cap Table'!$H$4)-YEAR('Cap Table'!$C$4)>0),'Cap Table'!$E19,and($E$6=YEAR('Cap Table'!$H$4),YEAR('Cap Table'!$M$4)-YEAR('Cap Table'!$H$4>0)),'Cap Table'!$J19,and($E$6=YEAR('Cap Table'!$M$4),YEAR('Cap Table'!$R$4)-YEAR('Cap Table'!$M$4>0)),'Cap Table'!$O19,$E$6>=YEAR('Cap Table'!$R$4),'Cap Table'!$T19) -> 0.005 | F12: =if(and($E$4>0,$C$4>0),$E$4*E12,if(and($E$4>0,$C$4<0),($E$4+$C$4)*E12,0)) -> 411.13368 | G12: =IFS($G$6<YEAR('Cap Table'!$C$4),0,and($G$6=YEAR('Cap Table'!$C$4),YEAR('Cap Table'!$H$4)-YEAR('Cap Table'!$C$4)>0),'Cap Table'!$E19,and($G$6=YEAR('Cap Table'!$H$4),YEAR('Cap Table'!$M$4)-YEAR('Cap Table'!$H$4>0)),'Cap Table'!$J19,and($G$6=YEAR('Cap Table'!$M$4),YEAR('Cap Table'!$R$4)-YEAR('Cap Table'!$M$4>0)),'Cap Table'!$O19,$G$6>=YEAR('Cap Table'!$R$4),'Cap Table'!$T19) -> 0.0034246575 | H12: =if(and($G$4>0,$E$4>0),$G$4*G12,if(and($G$4>0,$E$4<0),($G$4+$E$4)*G12,0)) -> 712.66593 | I12: =IFS($I$6<YEAR('Cap Table'!$C$4),0,and($I$6=YEAR('Cap Table'!$C$4),YEAR('Cap Table'!$H$4)-YEAR('Cap Table'!$C$4)>0),'Cap Table'!$E19,and($I$6=YEAR('Cap Table'!$H$4),YEAR('Cap Table'!$M$4)-YEAR('Cap Table'!$H$4>0)),'Cap Table'!$J19,and($I$6=YEAR('Cap Table'!$M$4),YEAR('Cap Table'!$R$4)-YEAR('Cap Table'!$M$4>0)),'Cap Table'!$O19,$I$6>=YEAR('Cap Table'!$R$4),'Cap Table'!$T19) -> 0.0028538813 | J12: =if(and($I$4>0,$G$4>0),$I$4*I12,if(and($I$4>0,$G$4<0),($I$4+$G$4)*I12,0)) -> 456.11306 | K12: =IFS($K$6<YEAR('Cap Table'!$C$4),0,and($K$6=YEAR('Cap Table'!$C$4),YEAR('Cap Table'!$H$4)-YEAR('Cap Table'!$C$4)>0),'Cap Table'!$E19,and($K$6=YEAR('Cap Table'!$H$4),YEAR('Cap Table'!$M$4)-YEAR('Cap Table'!$H$4>0)),'Cap Table'!$J19,and($K$6=YEAR('Cap Table'!$M$4),YEAR('Cap Table'!$R$4)-YEAR('Cap Table'!$M$4>0)),'Cap Table'!$O19,$K$6>=YEAR('Cap Table'!$R$4),'Cap Table'!$T19) -> 0.0028538813 | L12: =if(and($K$4>0,$I$4>0),$K$4*K12,if(and($K$4>0,$I$4<0),($K$4+$I$4)*K12,0)) -> 503.62237
B13: ='Cap Table'!Q20 -> Investor 1 | C13: =IFS($C$6<YEAR('Cap Table'!$C$4),0,and($C$6=YEAR('Cap Table'!$C$4),YEAR('Cap Table'!$H$4)-YEAR('Cap Table'!$C$4)>0),'Cap Table'!$E20,and($C$6=YEAR('Cap Table'!$H$4),YEAR('Cap Table'!$M$4)-YEAR('Cap Table'!$H$4>0)),'Cap Table'!$J20,and($C$6=YEAR('Cap Table'!$M$4),YEAR('Cap Table'!$R$4)-YEAR('Cap Table'!$M$4>0)),'Cap Table'!$O20,$C$6>=YEAR('Cap Table'!$R$4),'Cap Table'!$T20) | D13: =if(and($C$4>0,$A$4>0),$C$4*C13,if(and($C$4>0,$A$4<0),($C$4+$A$4)*C13,0)) -> 0 | E13: =IFS($E$6<YEAR('Cap Table'!$C$4),0,and($E$6=YEAR('Cap Table'!$C$4),YEAR('Cap Table'!$H$4)-YEAR('Cap Table'!$C$4)>0),'Cap Table'!$E20,and($E$6=YEAR('Cap Table'!$H$4),YEAR('Cap Table'!$M$4)-YEAR('Cap Table'!$H$4>0)),'Cap Table'!$J20,and($E$6=YEAR('Cap Table'!$M$4),YEAR('Cap Table'!$R$4)-YEAR('Cap Table'!$M$4>0)),'Cap Table'!$O20,$E$6>=YEAR('Cap Table'!$R$4),'Cap Table'!$T20) -> 0.25 | F13: =if(and($E$4>0,$C$4>0),$E$4*E13,if(and($E$4>0,$C$4<0),($E$4+$C$4)*E13,0)) -> 20556.684 | G13: =IFS($G$6<YEAR('Cap Table'!$C$4),0,and($G$6=YEAR('Cap Table'!$C$4),YEAR('Cap Table'!$H$4)-YEAR('Cap Table'!$C$4)>0),'Cap Table'!$E20,and($G$6=YEAR('Cap Table'!$H$4),YEAR('Cap Table'!$M$4)-YEAR('Cap Table'!$H$4>0)),'Cap Table'!$J20,and($G$6=YEAR('Cap Table'!$M$4),YEAR('Cap Table'!$R$4)-YEAR('Cap Table'!$M$4>0)),'Cap Table'!$O20,$G$6>=YEAR('Cap Table'!$R$4),'Cap Table'!$T20) -> 0.18493151 | H13: =if(and($G$4>0,$E$4>0),$G$4*G13,if(and($G$4>0,$E$4<0),($G$4+$E$4)*G13,0)) -> 38483.96 | I13: =IFS($I$6<YEAR('Cap Table'!$C$4),0,and($I$6=YEAR('Cap Table'!$C$4),YEAR('Cap Table'!$H$4)-YEAR('Cap Table'!$C$4)>0),'Cap Table'!$E20,and($I$6=YEAR('Cap Table'!$H$4),YEAR('Cap Table'!$M$4)-YEAR('Cap Table'!$H$4>0)),'Cap Table'!$J20,and($I$6=YEAR('Cap Table'!$M$4),YEAR('Cap Table'!$R$4)-YEAR('Cap Table'!$M$4>0)),'Cap Table'!$O20,$I$6>=YEAR('Cap Table'!$R$4),'Cap Table'!$T20) -> 0.15410959 | J13: =if(and($I$4>0,$G$4>0),$I$4*I13,if(and($I$4>0,$G$4<0),($I$4+$G$4)*I13,0)) -> 24630.105 | K13: =IFS($K$6<YEAR('Cap Table'!$C$4),0,and($K$6=YEAR('Cap Table'!$C$4),YEAR('Cap Table'!$H$4)-YEAR('Cap Table'!$C$4)>0),'Cap Table'!$E20,and($K$6=YEAR('Cap Table'!$H$4),YEAR('Cap Table'!$M$4)-YEAR('Cap Table'!$H$4>0)),'Cap Table'!$J20,and($K$6=YEAR('Cap Table'!$M$4),YEAR('Cap Table'!$R$4)-YEAR('Cap Table'!$M$4>0)),'Cap Table'!$O20,$K$6>=YEAR('Cap Table'!$R$4),'Cap Table'!$T20) -> 0.15410959 | L13: =if(and($K$4>0,$I$4>0),$K$4*K13,if(and($K$4>0,$I$4<0),($K$4+$I$4)*K13,0)) -> 27195.608
B14: ='Cap Table'!Q21 -> Investor 2 | C14: =IFS($C$6<YEAR('Cap Table'!$C$4),0,and($C$6=YEAR('Cap Table'!$C$4),YEAR('Cap Table'!$H$4)-YEAR('Cap Table'!$C$4)>0),'Cap Table'!$E21,and($C$6=YEAR('Cap Table'!$H$4),YEAR('Cap Table'!$M$4)-YEAR('Cap Table'!$H$4>0)),'Cap Table'!$J21,and($C$6=YEAR('Cap Table'!$M$4),YEAR('Cap Table'!$R$4)-YEAR('Cap Table'!$M$4>0)),'Cap Table'!$O21,$C$6>=YEAR('Cap Table'!$R$4),'Cap Table'!$T21) | D14: =if(and($C$4>0,$A$4>0),$C$4*C14,if(and($C$4>0,$A$4<0),($C$4+$A$4)*C14,0)) -> 0 | E14: =IFS($E$6<YEAR('Cap Table'!$C$4),0,and($E$6=YEAR('Cap Table'!$C$4),YEAR('Cap Table'!$H$4)-YEAR('Cap Table'!$C$4)>0),'Cap Table'!$E21,and($E$6=YEAR('Cap Table'!$H$4),YEAR('Cap Table'!$M$4)-YEAR('Cap Table'!$H$4>0)),'Cap Table'!$J21,and($E$6=YEAR('Cap Table'!$M$4),YEAR('Cap Table'!$R$4)-YEAR('Cap Table'!$M$4>0)),'Cap Table'!$O21,$E$6>=YEAR('Cap Table'!$R$4),'Cap Table'!$T21) -> 0.15 | F14: =if(and($E$4>0,$C$4>0),$E$4*E14,if(and($E$4>0,$C$4<0),($E$4+$C$4)*E14,0)) -> 12334.01 | G14: =IFS($G$6<YEAR('Cap Table'!$C$4),0,and($G$6=YEAR('Cap Table'!$C$4),YEAR('Cap Table'!$H$4)-YEAR('Cap Table'!$C$4)>0),'Cap Table'!$E21,and($G$6=YEAR('Cap Table'!$H$4),YEAR('Cap Table'!$M$4)-YEAR('Cap Table'!$H$4>0)),'Cap Table'!$J21,and($G$6=YEAR('Cap Table'!$M$4),YEAR('Cap Table'!$R$4)-YEAR('Cap Table'!$M$4>0)),'Cap Table'!$O21,$G$6>=YEAR('Cap Table'!$R$4),'Cap Table'!$T21) -> 0.10273973 | H14: =if(and($G$4>0,$E$4>0),$G$4*G14,if(and($G$4>0,$E$4<0),($G$4+$E$4)*G14,0)) -> 21379.978 | I14: =IFS($I$6<YEAR('Cap Table'!$C$4),0,and($I$6=YEAR('Cap Table'!$C$4),YEAR('Cap Table'!$H$4)-YEAR('Cap Table'!$C$4)>0),'Cap Table'!$E21,and($I$6=YEAR('Cap Table'!$H$4),YEAR('Cap Table'!$M$4)-YEAR('Cap Table'!$H$4>0)),'Cap Table'!$J21,and($I$6=YEAR('Cap Table'!$M$4),YEAR('Cap Table'!$R$4)-YEAR('Cap Table'!$M$4>0)),'Cap Table'!$O21,$I$6>=YEAR('Cap Table'!$R$4),'Cap Table'!$T21) -> 0.12728311 | J14: =if(and($I$4>0,$G$4>0),$I$4*I14,if(and($I$4>0,$G$4<0),($I$4+$G$4)*I14,0)) -> 20342.643 | K14: =IFS($K$6<YEAR('Cap Table'!$C$4),0,and($K$6=YEAR('Cap Table'!$C$4),YEAR('Cap Table'!$H$4)-YEAR('Cap Table'!$C$4)>0),'Cap Table'!$E21,and($K$6=YEAR('Cap Table'!$H$4),YEAR('Cap Table'!$M$4)-YEAR('Cap Table'!$H$4>0)),'Cap Table'!$J21,and($K$6=YEAR('Cap Table'!$M$4),YEAR('Cap Table'!$R$4)-YEAR('Cap Table'!$M$4>0)),'Cap Table'!$O21,$K$6>=YEAR('Cap Table'!$R$4),'Cap Table'!$T21) -> 0.12728311 | L14: =if(and($K$4>0,$I$4>0),$K$4*K14,if(and($K$4>0,$I$4<0),($K$4+$I$4)*K14,0)) -> 22461.558
B15: ='Cap Table'!Q22 -> Investor 3 | C15: =IFS($C$6<YEAR('Cap Table'!$C$4),0,and($C$6=YEAR('Cap Table'!$C$4),YEAR('Cap Table'!$H$4)-YEAR('Cap Table'!$C$4)>0),'Cap Table'!$E22,and($C$6=YEAR('Cap Table'!$H$4),YEAR('Cap Table'!$M$4)-YEAR('Cap Table'!$H$4>0)),'Cap Table'!$J22,and($C$6=YEAR('Cap Table'!$M$4),YEAR('Cap Table'!$R$4)-YEAR('Cap Table'!$M$4>0)),'Cap Table'!$O22,$C$6>=YEAR('Cap Table'!$R$4),'Cap Table'!$T22) | D15: =if(and($C$4>0,$A$4>0),$C$4*C15,if(and($C$4>0,$A$4<0),($C$4+$A$4)*C15,0)) -> 0 | E15: =IFS($E$6<YEAR('Cap Table'!$C$4),0,and($E$6=YEAR('Cap Table'!$C$4),YEAR('Cap Table'!$H$4)-YEAR('Cap Table'!$C$4)>0),'Cap Table'!$E22,and($E$6=YEAR('Cap Table'!$H$4),YEAR('Cap Table'!$M$4)-YEAR('Cap Table'!$H$4>0)),'Cap Table'!$J22,and($E$6=YEAR('Cap Table'!$M$4),YEAR('Cap Table'!$R$4)-YEAR('Cap Table'!$M$4>0)),'Cap Table'!$O22,$E$6>=YEAR('Cap Table'!$R$4),'Cap Table'!$T22) -> 0.05 | F15: =if(and($E$4>0,$C$4>0),$E$4*E15,if(and($E$4>0,$C$4<0),($E$4+$C$4)*E15,0)) -> 4111.3368 | G15: =IFS($G$6<YEAR('Cap Table'!$C$4),0,and($G$6=YEAR('Cap Table'!$C$4),YEAR('Cap Table'!$H$4)-YEAR('Cap Table'!$C$4)>0),'Cap Table'!$E22,and($G$6=YEAR('Cap Table'!$H$4),YEAR('Cap Table'!$M$4)-YEAR('Cap Table'!$H$4>0)),'Cap Table'!$J22,and($G$6=YEAR('Cap Table'!$M$4),YEAR('Cap Table'!$R$4)-YEAR('Cap Table'!$M$4>0)),'Cap Table'!$O22,$G$6>=YEAR('Cap Table'!$R$4),'Cap Table'!$T22) -> 0.061643836 | H15: =if(and($G$4>0,$E$4>0),$G$4*G15,if(and($G$4>0,$E$4<0),($G$4+$E$4)*G15,0)) -> 12827.987 | I15: =IFS($I$6<YEAR('Cap Table'!$C$4),0,and($I$6=YEAR('Cap Table'!$C$4),YEAR('Cap Table'!$H$4)-YEAR('Cap Table'!$C$4)>0),'Cap Table'!$E22,and($I$6=YEAR('Cap Table'!$H$4),YEAR('Cap Table'!$M$4)-YEAR('Cap Table'!$H$4>0)),'Cap Table'!$J22,and($I$6=YEAR('Cap Table'!$M$4),YEAR('Cap Table'!$R$4)-YEAR('Cap Table'!$M$4>0)),'Cap Table'!$O22,$I$6>=YEAR('Cap Table'!$R$4),'Cap Table'!$T22) -> 0.051369863 | J15: =if(and($I$4>0,$G$4>0),$I$4*I15,if(and($I$4>0,$G$4<0),($I$4+$G$4)*I15,0)) -> 8210.0351 | K15: =IFS($K$6<YEAR('Cap Table'!$C$4),0,and($K$6=YEAR('Cap Table'!$C$4),YEAR('Cap Table'!$H$4)-YEAR('Cap Table'!$C$4)>0),'Cap Table'!$E22,and($K$6=YEAR('Cap Table'!$H$4),YEAR('Cap Table'!$M$4)-YEAR('Cap Table'!$H$4>0)),'Cap Table'!$J22,and($K$6=YEAR('Cap Table'!$M$4),YEAR('Cap Table'!$R$4)-YEAR('Cap Table'!$M$4>0)),'Cap Table'!$O22,$K$6>=YEAR('Cap Table'!$R$4),'Cap Table'!$T22) -> 0.051369863 | L15: =if(and($K$4>0,$I$4>0),$K$4*K15,if(and($K$4>0,$I$4<0),($K$4+$I$4)*K15,0)) -> 9065.2026
B16: ='Cap Table'!Q23 -> Investor 4 | C16: =IFS($C$6<YEAR('Cap Table'!$C$4),0,and($C$6=YEAR('Cap Table'!$C$4),YEAR('Cap Table'!$H$4)-YEAR('Cap Table'!$C$4)>0),'Cap Table'!$E23,and($C$6=YEAR('Cap Table'!$H$4),YEAR('Cap Table'!$M$4)-YEAR('Cap Table'!$H$4>0)),'Cap Table'!$J23,and($C$6=YEAR('Cap Table'!$M$4),YEAR('Cap Table'!$R$4)-YEAR('Cap Table'!$M$4>0)),'Cap Table'!$O23,$C$6>=YEAR('Cap Table'!$R$4),'Cap Table'!$T23) | D16: =if(and($C$4>0,$A$4>0),$C$4*C16,if(and($C$4>0,$A$4<0),($C$4+$A$4)*C16,0)) -> 0 | E16: =IFS($E$6<YEAR('Cap Table'!$C$4),0,and($E$6=YEAR('Cap Table'!$C$4),YEAR('Cap Table'!$H$4)-YEAR('Cap Table'!$C$4)>0),'Cap Table'!$E23,and($E$6=YEAR('Cap Table'!$H$4),YEAR('Cap Table'!$M$4)-YEAR('Cap Table'!$H$4>0)),'Cap Table'!$J23,and($E$6=YEAR('Cap Table'!$M$4),YEAR('Cap Table'!$R$4)-YEAR('Cap Table'!$M$4>0)),'Cap Table'!$O23,$E$6>=YEAR('Cap Table'!$R$4),'Cap Table'!$T23) -> 0.05 | F16: =if(and($E$4>0,$C$4>0),$E$4*E16,if(and($E$4>0,$C$4<0),($E$4+$C$4)*E16,0)) -> 4111.3368 | G16: =IFS($G$6<YEAR('Cap Table'!$C$4),0,and($G$6=YEAR('Cap Table'!$C$4),YEAR('Cap Table'!$H$4)-YEAR('Cap Table'!$C$4)>0),'Cap Table'!$E23,and($G$6=YEAR('Cap Table'!$H$4),YEAR('Cap Table'!$M$4)-YEAR('Cap Table'!$H$4>0)),'Cap Table'!$J23,and($G$6=YEAR('Cap Table'!$M$4),YEAR('Cap Table'!$R$4)-YEAR('Cap Table'!$M$4>0)),'Cap Table'!$O23,$G$6>=YEAR('Cap Table'!$R$4),'Cap Table'!$T23) -> 0.034246575 | H16: =if(and($G$4>0,$E$4>0),$G$4*G16,if(and($G$4>0,$E$4<0),($G$4+$E$4)*G16,0)) -> 7126.6593 | I16: =IFS($I$6<YEAR('Cap Table'!$C$4),0,and($I$6=YEAR('Cap Table'!$C$4),YEAR('Cap Table'!$H$4)-YEAR('Cap Table'!$C$4)>0),'Cap Table'!$E23,and($I$6=YEAR('Cap Table'!$H$4),YEAR('Cap Table'!$M$4)-YEAR('Cap Table'!$H$4>0)),'Cap Table'!$J23,and($I$6=YEAR('Cap Table'!$M$4),YEAR('Cap Table'!$R$4)-YEAR('Cap Table'!$M$4>0)),'Cap Table'!$O23,$I$6>=YEAR('Cap Table'!$R$4),'Cap Table'!$T23) -> 0.028538813 | J16: =if(and($I$4>0,$G$4>0),$I$4*I16,if(and($I$4>0,$G$4<0),($I$4+$G$4)*I16,0)) -> 4561.1306 | K16: =IFS($K$6<YEAR('Cap Table'!$C$4),0,and($K$6=YEAR('Cap Table'!$C$4),YEAR('Cap Table'!$H$4)-YEAR('Cap Table'!$C$4)>0),'Cap Table'!$E23,and($K$6=YEAR('Cap Table'!$H$4),YEAR('Cap Table'!$M$4)-YEAR('Cap Table'!$H$4>0)),'Cap Table'!$J23,and($K$6=YEAR('Cap Table'!$M$4),YEAR('Cap Table'!$R$4)-YEAR('Cap Table'!$M$4>0)),'Cap Table'!$O23,$K$6>=YEAR('Cap Table'!$R$4),'Cap Table'!$T23) -> 0.028538813 | L16: =if(and($K$4>0,$I$4>0),$K$4*K16,if(and($K$4>0,$I$4<0),($K$4+$I$4)*K16,0)) -> 5036.2237
B17: ='Cap Table'!Q24 -> Investor 5 | C17: =IFS($C$6<YEAR('Cap Table'!$C$4),0,and($C$6=YEAR('Cap Table'!$C$4),YEAR('Cap Table'!$H$4)-YEAR('Cap Table'!$C$4)>0),'Cap Table'!$E24,and($C$6=YEAR('Cap Table'!$H$4),YEAR('Cap Table'!$M$4)-YEAR('Cap Table'!$H$4>0)),'Cap Table'!$J24,and($C$6=YEAR('Cap Table'!$M$4),YEAR('Cap Table'!$R$4)-YEAR('Cap Table'!$M$4>0)),'Cap Table'!$O24,$C$6>=YEAR('Cap Table'!$R$4),'Cap Table'!$T24) | D17: =if(and($C$4>0,$A$4>0),$C$4*C17,if(and($C$4>0,$A$4<0),($C$4+$A$4)*C17,0)) -> 0 | E17: =IFS($E$6<YEAR('Cap Table'!$C$4),0,and($E$6=YEAR('Cap Table'!$C$4),YEAR('Cap Table'!$H$4)-YEAR('Cap Table'!$C$4)>0),'Cap Table'!$E24,and($E$6=YEAR('Cap Table'!$H$4),YEAR('Cap Table'!$M$4)-YEAR('Cap Table'!$H$4>0)),'Cap Table'!$J24,and($E$6=YEAR('Cap Table'!$M$4),YEAR('Cap Table'!$R$4)-YEAR('Cap Table'!$M$4>0)),'Cap Table'!$O24,$E$6>=YEAR('Cap Table'!$R$4),'Cap Table'!$T24) | F17: =if(and($E$4>0,$C$4>0),$E$4*E17,if(and($E$4>0,$C$4<0),($E$4+$C$4)*E17,0)) -> 0 | G17: =IFS($G$6<YEAR('Cap Table'!$C$4),0,and($G$6=YEAR('Cap Table'!$C$4),YEAR('Cap Table'!$H$4)-YEAR('Cap Table'!$C$4)>0),'Cap Table'!$E24,and($G$6=YEAR('Cap Table'!$H$4),YEAR('Cap Table'!$M$4)-YEAR('Cap Table'!$H$4>0)),'Cap Table'!$J24,and($G$6=YEAR('Cap Table'!$M$4),YEAR('Cap Table'!$R$4)-YEAR('Cap Table'!$M$4>0)),'Cap Table'!$O24,$G$6>=YEAR('Cap Table'!$R$4),'Cap Table'!$T24) -> 0.082191781 | H17: =if(and($G$4>0,$E$4>0),$G$4*G17,if(and($G$4>0,$E$4<0),($G$4+$E$4)*G17,0)) -> 17103.982 | I17: =IFS($I$6<YEAR('Cap Table'!$C$4),0,and($I$6=YEAR('Cap Table'!$C$4),YEAR('Cap Table'!$H$4)-YEAR('Cap Table'!$C$4)>0),'Cap Table'!$E24,and($I$6=YEAR('Cap Table'!$H$4),YEAR('Cap Table'!$M$4)-YEAR('Cap Table'!$H$4>0)),'Cap Table'!$J24,and($I$6=YEAR('Cap Table'!$M$4),YEAR('Cap Table'!$R$4)-YEAR('Cap Table'!$M$4>0)),'Cap Table'!$O24,$I$6>=YEAR('Cap Table'!$R$4),'Cap Table'!$T24) -> 0.068493151 | J17: =if(and($I$4>0,$G$4>0),$I$4*I17,if(and($I$4>0,$G$4<0),($I$4+$G$4)*I17,0)) -> 10946.714 | K17: =IFS($K$6<YEAR('Cap Table'!$C$4),0,and($K$6=YEAR('Cap Table'!$C$4),YEAR('Cap Table'!$H$4)-YEAR('Cap Table'!$C$4)>0),'Cap Table'!$E24,and($K$6=YEAR('Cap Table'!$H$4),YEAR('Cap Table'!$M$4)-YEAR('Cap Table'!$H$4>0)),'Cap Table'!$J24,and($K$6=YEAR('Cap Table'!$M$4),YEAR('Cap Table'!$R$4)-YEAR('Cap Table'!$M$4>0)),'Cap Table'!$O24,$K$6>=YEAR('Cap Table'!$R$4),'Cap Table'!$T24) -> 0.068493151 | L17: =if(and($K$4>0,$I$4>0),$K$4*K17,if(and($K$4>0,$I$4<0),($K$4+$I$4)*K17,0)) -> 12086.937
B18: ='Cap Table'!Q25 -> Investor 6 | C18: =IFS($C$6<YEAR('Cap Table'!$C$4),0,and($C$6=YEAR('Cap Table'!$C$4),YEAR('Cap Table'!$H$4)-YEAR('Cap Table'!$C$4)>0),'Cap Table'!$E25,and($C$6=YEAR('Cap Table'!$H$4),YEAR('Cap Table'!$M$4)-YEAR('Cap Table'!$H$4>0)),'Cap Table'!$J25,and($C$6=YEAR('Cap Table'!$M$4),YEAR('Cap Table'!$R$4)-YEAR('Cap Table'!$M$4>0)),'Cap Table'!$O25,$C$6>=YEAR('Cap Table'!$R$4),'Cap Table'!$T25) | D18: =if(and($C$4>0,$A$4>0),$C$4*C18,if(and($C$4>0,$A$4<0),($C$4+$A$4)*C18,0)) -> 0 | E18: =IFS($E$6<YEAR('Cap Table'!$C$4),0,and($E$6=YEAR('Cap Table'!$C$4),YEAR('Cap Table'!$H$4)-YEAR('Cap Table'!$C$4)>0),'Cap Table'!$E25,and($E$6=YEAR('Cap Table'!$H$4),YEAR('Cap Table'!$M$4)-YEAR('Cap Table'!$H$4>0)),'Cap Table'!$J25,and($E$6=YEAR('Cap Table'!$M$4),YEAR('Cap Table'!$R$4)-YEAR('Cap Table'!$M$4>0)),'Cap Table'!$O25,$E$6>=YEAR('Cap Table'!$R$4),'Cap Table'!$T25) | F18: =if(and($E$4>0,$C$4>0),$E$4*E18,if(and($E$4>0,$C$4<0),($E$4+$C$4)*E18,0)) -> 0 | G18: =IFS($G$6<YEAR('Cap Table'!$C$4),0,and($G$6=YEAR('Cap Table'!$C$4),YEAR('Cap Table'!$H$4)-YEAR('Cap Table'!$C$4)>0),'Cap Table'!$E25,and($G$6=YEAR('Cap Table'!$H$4),YEAR('Cap Table'!$M$4)-YEAR('Cap Table'!$H$4>0)),'Cap Table'!$J25,and($G$6=YEAR('Cap Table'!$M$4),YEAR('Cap Table'!$R$4)-YEAR('Cap Table'!$M$4>0)),'Cap Table'!$O25,$G$6>=YEAR('Cap Table'!$R$4),'Cap Table'!$T25) -> 0.068493151 | H18: =if(and($G$4>0,$E$4>0),$G$4*G18,if(and($G$4>0,$E$4<0),($G$4+$E$4)*G18,0)) -> 14253.319 | I18: =IFS($I$6<YEAR('Cap Table'!$C$4),0,and($I$6=YEAR('Cap Table'!$C$4),YEAR('Cap Table'!$H$4)-YEAR('Cap Table'!$C$4)>0),'Cap Table'!$E25,and($I$6=YEAR('Cap Table'!$H$4),YEAR('Cap Table'!$M$4)-YEAR('Cap Table'!$H$4>0)),'Cap Table'!$J25,and($I$6=YEAR('Cap Table'!$M$4),YEAR('Cap Table'!$R$4)-YEAR('Cap Table'!$M$4>0)),'Cap Table'!$O25,$I$6>=YEAR('Cap Table'!$R$4),'Cap Table'!$T25) -> 0.057077626 | J18: =if(and($I$4>0,$G$4>0),$I$4*I18,if(and($I$4>0,$G$4<0),($I$4+$G$4)*I18,0)) -> 9122.2613 | K18: =IFS($K$6<YEAR('Cap Table'!$C$4),0,and($K$6=YEAR('Cap Table'!$C$4),YEAR('Cap Table'!$H$4)-YEAR('Cap Table'!$C$4)>0),'Cap Table'!$E25,and($K$6=YEAR('Cap Table'!$H$4),YEAR('Cap Table'!$M$4)-YEAR('Cap Table'!$H$4>0)),'Cap Table'!$J25,and($K$6=YEAR('Cap Table'!$M$4),YEAR('Cap Table'!$R$4)-YEAR('Cap Table'!$M$4>0)),'Cap Table'!$O25,$K$6>=YEAR('Cap Table'!$R$4),'Cap Table'!$T25) -> 0.057077626 | L18: =if(and($K$4>0,$I$4>0),$K$4*K18,if(and($K$4>0,$I$4<0),($K$4+$I$4)*K18,0)) -> 10072.447
B19: ='Cap Table'!Q26 -> Investor 7 | C19: =IFS($C$6<YEAR('Cap Table'!$C$4),0,and($C$6=YEAR('Cap Table'!$C$4),YEAR('Cap Table'!$H$4)-YEAR('Cap Table'!$C$4)>0),'Cap Table'!$E26,and($C$6=YEAR('Cap Table'!$H$4),YEAR('Cap Table'!$M$4)-YEAR('Cap Table'!$H$4>0)),'Cap Table'!$J26,and($C$6=YEAR('Cap Table'!$M$4),YEAR('Cap Table'!$R$4)-YEAR('Cap Table'!$M$4>0)),'Cap Table'!$O26,$C$6>=YEAR('Cap Table'!$R$4),'Cap Table'!$T26) | D19: =if(and($C$4>0,$A$4>0),$C$4*C19,if(and($C$4>0,$A$4<0),($C$4+$A$4)*C19,0)) -> 0 | E19: =IFS($E$6<YEAR('Cap Table'!$C$4),0,and($E$6=YEAR('Cap Table'!$C$4),YEAR('Cap Table'!$H$4)-YEAR('Cap Table'!$C$4)>0),'Cap Table'!$E26,and($E$6=YEAR('Cap Table'!$H$4),YEAR('Cap Table'!$M$4)-YEAR('Cap Table'!$H$4>0)),'Cap Table'!$J26,and($E$6=YEAR('Cap Table'!$M$4),YEAR('Cap Table'!$R$4)-YEAR('Cap Table'!$M$4>0)),'Cap Table'!$O26,$E$6>=YEAR('Cap Table'!$R$4),'Cap Table'!$T26) | F19: =if(and($E$4>0,$C$4>0),$E$4*E19,if(and($E$4>0,$C$4<0),($E$4+$C$4)*E19,0)) -> 0 | G19: =IFS($G$6<YEAR('Cap Table'!$C$4),0,and($G$6=YEAR('Cap Table'!$C$4),YEAR('Cap Table'!$H$4)-YEAR('Cap Table'!$C$4)>0),'Cap Table'!$E26,and($G$6=YEAR('Cap Table'!$H$4),YEAR('Cap Table'!$M$4)-YEAR('Cap Table'!$H$4>0)),'Cap Table'!$J26,and($G$6=YEAR('Cap Table'!$M$4),YEAR('Cap Table'!$R$4)-YEAR('Cap Table'!$M$4>0)),'Cap Table'!$O26,$G$6>=YEAR('Cap Table'!$R$4),'Cap Table'!$T26) -> 0.04109589 | H19: =if(and($G$4>0,$E$4>0),$G$4*G19,if(and($G$4>0,$E$4<0),($G$4+$E$4)*G19,0)) -> 8551.9912 | I19: =IFS($I$6<YEAR('Cap Table'!$C$4),0,and($I$6=YEAR('Cap Table'!$C$4),YEAR('Cap Table'!$H$4)-YEAR('Cap Table'!$C$4)>0),'Cap Table'!$E26,and($I$6=YEAR('Cap Table'!$H$4),YEAR('Cap Table'!$M$4)-YEAR('Cap Table'!$H$4>0)),'Cap Table'!$J26,and($I$6=YEAR('Cap Table'!$M$4),YEAR('Cap Table'!$R$4)-YEAR('Cap Table'!$M$4>0)),'Cap Table'!$O26,$I$6>=YEAR('Cap Table'!$R$4),'Cap Table'!$T26) -> 0.034246575 | J19: =if(and($I$4>0,$G$4>0),$I$4*I19,if(and($I$4>0,$G$4<0),($I$4+$G$4)*I19,0)) -> 5473.3568 | K19: =IFS($K$6<YEAR('Cap Table'!$C$4),0,and($K$6=YEAR('Cap Table'!$C$4),YEAR('Cap Table'!$H$4)-YEAR('Cap Table'!$C$4)>0),'Cap Table'!$E26,and($K$6=YEAR('Cap Table'!$H$4),YEAR('Cap Table'!$M$4)-YEAR('Cap Table'!$H$4>0)),'Cap Table'!$J26,and($K$6=YEAR('Cap Table'!$M$4),YEAR('Cap Table'!$R$4)-YEAR('Cap Table'!$M$4>0)),'Cap Table'!$O26,$K$6>=YEAR('Cap Table'!$R$4),'Cap Table'!$T26) -> 0.034246575 | L19: =if(and($K$4>0,$I$4>0),$K$4*K19,if(and($K$4>0,$I$4<0),($K$4+$I$4)*K19,0)) -> 6043.4684
... B22: ='Cap Table'!Q29 -> Investor 10 | C22: =IFS($C$6<YEAR('Cap Table'!$C$4),0,and($C$6=YEAR('Cap Table'!$C$4),YEAR('Cap Table'!$H$4)-YEAR('Cap Table'!$C$4)>0),'Cap Table'!$E29,and($C$6=YEAR('Cap Table'!$H$4),YEAR('Cap Table'!$M$4)-YEAR('Cap Table'!$H$4>0)),'Cap Table'!$J29,and($C$6=YEAR('Cap Table'!$M$4),YEAR('Cap Table'!$R$4)-YEAR('Cap Table'!$M$4>0)),'Cap Table'!$O29,$C$6>=YEAR('Cap Table'!$R$4),'Cap Table'!$T29) | D22: =if(and($C$4>0,$A$4>0),$C$4*C22,if(and($C$4>0,$A$4<0),($C$4+$A$4)*C22,0)) -> 0 | E22: =IFS($E$6<YEAR('Cap Table'!$C$4),0,and($E$6=YEAR('Cap Table'!$C$4),YEAR('Cap Table'!$H$4)-YEAR('Cap Table'!$C$4)>0),'Cap Table'!$E29,and($E$6=YEAR('Cap Table'!$H$4),YEAR('Cap Table'!$M$4)-YEAR('Cap Table'!$H$4>0)),'Cap Table'!$J29,and($E$6=YEAR('Cap Table'!$M$4),YEAR('Cap Table'!$R$4)-YEAR('Cap Table'!$M$4>0)),'Cap Table'!$O29,$E$6>=YEAR('Cap Table'!$R$4),'Cap Table'!$T29) | F22: =if(and($E$4>0,$C$4>0),$E$4*E22,if(and($E$4>0,$C$4<0),($E$4+$C$4)*E22,0)) -> 0 | G22: =IFS($G$6<YEAR('Cap Table'!$C$4),0,and($G$6=YEAR('Cap Table'!$C$4),YEAR('Cap Table'!$H$4)-YEAR('Cap Table'!$C$4)>0),'Cap Table'!$E29,and($G$6=YEAR('Cap Table'!$H$4),YEAR('Cap Table'!$M$4)-YEAR('Cap Table'!$H$4>0)),'Cap Table'!$J29,and($G$6=YEAR('Cap Table'!$M$4),YEAR('Cap Table'!$R$4)-YEAR('Cap Table'!$M$4>0)),'Cap Table'!$O29,$G$6>=YEAR('Cap Table'!$R$4),'Cap Table'!$T29) | H22: =if(and($G$4>0,$E$4>0),$G$4*G22,if(and($G$4>0,$E$4<0),($G$4+$E$4)*G22,0)) -> 0 | I22: =IFS($I$6<YEAR('Cap Table'!$C$4),0,and($I$6=YEAR('Cap Table'!$C$4),YEAR('Cap Table'!$H$4)-YEAR('Cap Table'!$C$4)>0),'Cap Table'!$E29,and($I$6=YEAR('Cap Table'!$H$4),YEAR('Cap Table'!$M$4)-YEAR('Cap Table'!$H$4>0)),'Cap Table'!$J29,and($I$6=YEAR('Cap Table'!$M$4),YEAR('Cap Table'!$R$4)-YEAR('Cap Table'!$M$4>0)),'Cap Table'!$O29,$I$6>=YEAR('Cap Table'!$R$4),'Cap Table'!$T29) -> 0.041666667 | J22: =if(and($I$4>0,$G$4>0),$I$4*I22,if(and($I$4>0,$G$4<0),($I$4+$G$4)*I22,0)) -> 6659.2507 | K22: =IFS($K$6<YEAR('Cap Table'!$C$4),0,and($K$6=YEAR('Cap Table'!$C$4),YEAR('Cap Table'!$H$4)-YEAR('Cap Table'!$C$4)>0),'Cap Table'!$E29,and($K$6=YEAR('Cap Table'!$H$4),YEAR('Cap Table'!$M$4)-YEAR('Cap Table'!$H$4>0)),'Cap Table'!$J29,and($K$6=YEAR('Cap Table'!$M$4),YEAR('Cap Table'!$R$4)-YEAR('Cap Table'!$M$4>0)),'Cap Table'!$O29,$K$6>=YEAR('Cap Table'!$R$4),'Cap Table'!$T29) -> 0.041666667 | L22: =if(and($K$4>0,$I$4>0),$K$4*K22,if(and($K$4>0,$I$4<0),($K$4+$I$4)*K22,0)) -> 7352.8865
B23: ='Cap Table'!Q30 | E23: =IFS($E$6<YEAR('Cap Table'!$C$4),0,and($E$6=YEAR('Cap Table'!$C$4),YEAR('Cap Table'!$H$4)-YEAR('Cap Table'!$C$4)>0),'Cap Table'!$E30,and($E$6=YEAR('Cap Table'!$H$4),YEAR('Cap Table'!$M$4)-YEAR('Cap Table'!$H$4>0)),'Cap Table'!$J30,and($E$6=YEAR('Cap Table'!$M$4),YEAR('Cap Table'!$R$4)-YEAR('Cap Table'!$M$4>0)),'Cap Table'!$O30,$E$6>=YEAR('Cap Table'!$R$4),'Cap Table'!$T30)

Sheet Exit Scenarios
B1: =Settings!B4 -> Healthy4U
B3: Expected Exit Scenario | C3: Strategic acquasition
B5: Target valuation | C5: 40000000
B7: Expected Year of Exit | C7: 2027
B9: Shareholder | C9: Share | D9: Capital Invested | E9: Exit | F9: ROI
B10: =Dividends!B8 -> Founder 1 | C10: ='Cap Table'!T15 -> 0.099885845 | D10: =SUMIF('Cap Table'!$B$15:$B$19,B10,'Cap Table'!$C$15:$C$19)+SUMIF('Cap Table'!$G$15:$G$23,B10,'Cap Table'!$H$15:$H$23)+SUMIF('Cap Table'!$L$15:$L$27,B10,'Cap Table'!$M$15:$M$27)+SUMIF('Cap Table'!$Q$15:$Q$29,B10,'Cap Table'!$R$15:$R$29) -> 0 | E10: =$C$5*C10 -> 3995433.8
B11: =Dividends!B9 -> Founder 2 | C11: ='Cap Table'!T16 -> 0.099885845 | D11: =SUMIF('Cap Table'!$B$15:$B$19,B11,'Cap Table'!$C$15:$C$19)+SUMIF('Cap Table'!$G$15:$G$23,B11,'Cap Table'!$H$15:$H$23)+SUMIF('Cap Table'!$L$15:$L$27,B11,'Cap Table'!$M$15:$M$27)+SUMIF('Cap Table'!$Q$15:$Q$29,B11,'Cap Table'!$R$15:$R$29) -> 0 | E11: =$C$5*C11 -> 3995433.8
B12: =Dividends!B10 -> Founder 3 | C12: ='Cap Table'!T17 -> 0.068493151 | D12: =SUMIF('Cap Table'!$B$15:$B$19,B12,'Cap Table'!$C$15:$C$19)+SUMIF('Cap Table'!$G$15:$G$23,B12,'Cap Table'!$H$15:$H$23)+SUMIF('Cap Table'!$L$15:$L$27,B12,'Cap Table'!$M$15:$M$27)+SUMIF('Cap Table'!$Q$15:$Q$29,B12,'Cap Table'!$R$15:$R$29) -> 0 | E12: =$C$5*C12 -> 2739726
B13: =Dividends!B11 -> Key Employees | C13: ='Cap Table'!T18 -> 0.014269406 | D13: =SUMIF('Cap Table'!$B$15:$B$19,B13,'Cap Table'!$C$15:$C$19)+SUMIF('Cap Table'!$G$15:$G$23,B13,'Cap Table'!$H$15:$H$23)+SUMIF('Cap Table'!$L$15:$L$27,B13,'Cap Table'!$M$15:$M$27)+SUMIF('Cap Table'!$Q$15:$Q$29,B13,'Cap Table'!$R$15:$R$29) -> 0 | E13: =$C$5*C13 -> 570776.26
B14: =Dividends!B12 -> Advisors | C14: ='Cap Table'!T19 -> 0.0028538813 | D14: =SUMIF('Cap Table'!$B$15:$B$19,B14,'Cap Table'!$C$15:$C$19)+SUMIF('Cap Table'!$G$15:$G$23,B14,'Cap Table'!$H$15:$H$23)+SUMIF('Cap Table'!$L$15:$L$27,B14,'Cap Table'!$M$15:$M$27)+SUMIF('Cap Table'!$Q$15:$Q$29,B14,'Cap Table'!$R$15:$R$29) -> 0 | E14: =$C$5*C14 -> 114155.25
B15: =Dividends!B13 -> Investor 1 | C15: ='Cap Table'!T20 -> 0.15410959 | D15: =SUMIF('Cap Table'!$B$15:$B$19,B15,'Cap Table'!$C$15:$C$19)+SUMIF('Cap Table'!$G$15:$G$23,B15,'Cap Table'!$H$15:$H$23)+SUMIF('Cap Table'!$L$15:$L$27,B15,'Cap Table'!$M$15:$M$27)+SUMIF('Cap Table'!$Q$15:$Q$29,B15,'Cap Table'!$R$15:$R$29) -> 600000 | E15: =$C$5*C15 -> 6164383.6 | F15: =(E15-D15)/D15 -> 9.2739726
B16: =Dividends!B14 -> Investor 2 | C16: ='Cap Table'!T21 -> 0.12728311 | D16: =SUMIF('Cap Table'!$B$15:$B$19,B16,'Cap Table'!$C$15:$C$19)+SUMIF('Cap Table'!$G$15:$G$23,B16,'Cap Table'!$H$15:$H$23)+SUMIF('Cap Table'!$L$15:$L$27,B16,'Cap Table'!$M$15:$M$27)+SUMIF('Cap Table'!$Q$15:$Q$29,B16,'Cap Table'!$R$15:$R$29) -> 800000 | E16: =$C$5*C16 -> 5091324.2 | F16: =(E16-D16)/D16 -> 5.3641553
B17: =Dividends!B15 -> Investor 3 | C17: ='Cap Table'!T22 -> 0.051369863 | D17: =SUMIF('Cap Table'!$B$15:$B$19,B17,'Cap Table'!$C$15:$C$19)+SUMIF('Cap Table'!$G$15:$G$23,B17,'Cap Table'!$H$15:$H$23)+SUMIF('Cap Table'!$L$15:$L$27,B17,'Cap Table'!$M$15:$M$27)+SUMIF('Cap Table'!$Q$15:$Q$29,B17,'Cap Table'!$R$15:$R$29) -> 300000 | E17: =$C$5*C17 -> 2054794.5 | F17: =(E17-D17)/D17 -> 5.8493151
B18: =Dividends!B16 -> Investor 4 | C18: ='Cap Table'!T23 -> 0.028538813 | D18: =SUMIF('Cap Table'!$B$15:$B$19,B18,'Cap Table'!$C$15:$C$19)+SUMIF('Cap Table'!$G$15:$G$23,B18,'Cap Table'!$H$15:$H$23)+SUMIF('Cap Table'!$L$15:$L$27,B18,'Cap Table'!$M$15:$M$27)+SUMIF('Cap Table'!$Q$15:$Q$29,B18,'Cap Table'!$R$15:$R$29) -> 100000 | E18: =$C$5*C18 -> 1141552.5 | F18: =(E18-D18)/D18 -> 10.415525
B19: =Dividends!B17 -> Investor 5 | C19: ='Cap Table'!T24 -> 0.068493151 | D19: =SUMIF('Cap Table'!$B$15:$B$19,B19,'Cap Table'!$C$15:$C$19)+SUMIF('Cap Table'!$G$15:$G$23,B19,'Cap Table'!$H$15:$H$23)+SUMIF('Cap Table'!$L$15:$L$27,B19,'Cap Table'!$M$15:$M$27)+SUMIF('Cap Table'!$Q$15:$Q$29,B19,'Cap Table'!$R$15:$R$29) -> 600000 | E19: =$C$5*C19 -> 2739726 | F19: =(E19-D19)/D19 -> 3.56621
B20: =Dividends!B18 -> Investor 6 | C20: ='Cap Table'!T25 -> 0.057077626 | D20: =SUMIF('Cap Table'!$B$15:$B$19,B20,'Cap Table'!$C$15:$C$19)+SUMIF('Cap Table'!$G$15:$G$23,B20,'Cap Table'!$H$15:$H$23)+SUMIF('Cap Table'!$L$15:$L$27,B20,'Cap Table'!$M$15:$M$27)+SUMIF('Cap Table'!$Q$15:$Q$29,B20,'Cap Table'!$R$15:$R$29) -> 500000 | E20: =$C$5*C20 -> 2283105 | F20: =(E20-D20)/D20 -> 3.56621
B21: =Dividends!B19 -> Investor 7 | C21: ='Cap Table'!T26 -> 0.034246575 | D21: =SUMIF('Cap Table'!$B$15:$B$19,B21,'Cap Table'!$C$15:$C$19)+SUMIF('Cap Table'!$G$15:$G$23,B21,'Cap Table'!$H$15:$H$23)+SUMIF('Cap Table'!$L$15:$L$27,B21,'Cap Table'!$M$15:$M$27)+SUMIF('Cap Table'!$Q$15:$Q$29,B21,'Cap Table'!$R$15:$R$29) -> 300000 | E21: =$C$5*C21 -> 1369863 | F21: =(E21-D21)/D21 -> 3.56621
B22: =Dividends!B20 -> Investor 8 | C22: ='Cap Table'!T27 -> 0.068493151 | D22: =SUMIF('Cap Table'!$B$15:$B$19,B22,'Cap Table'!$C$15:$C$19)+SUMIF('Cap Table'!$G$15:$G$23,B22,'Cap Table'!$H$15:$H$23)+SUMIF('Cap Table'!$L$15:$L$27,B22,'Cap Table'!$M$15:$M$27)+SUMIF('Cap Table'!$Q$15:$Q$29,B22,'Cap Table'!$R$15:$R$29) -> 600000 | E22: =$C$5*C22 -> 2739726 | F22: =(E22-D22)/D22 -> 3.56621
B23: =Dividends!B21 -> Investor 9 | C23: ='Cap Table'!T28 -> 0.083333333 | D23: =SUMIF('Cap Table'!$B$15:$B$19,B23,'Cap Table'!$C$15:$C$19)+SUMIF('Cap Table'!$G$15:$G$23,B23,'Cap Table'!$H$15:$H$23)+SUMIF('Cap Table'!$L$15:$L$27,B23,'Cap Table'!$M$15:$M$27)+SUMIF('Cap Table'!$Q$15:$Q$29,B23,'Cap Table'!$R$15:$R$29) -> 1000000 | E23: =$C$5*C23 -> 3333333.3 | F23: =(E23-D23)/D23 -> 2.3333333
B24: =Dividends!B22 -> Investor 10 | C24: ='Cap Table'!T29 -> 0.041666667 | D24: =SUMIF('Cap Table'!$B$15:$B$19,B24,'Cap Table'!$C$15:$C$19)+SUMIF('Cap Table'!$G$15:$G$23,B24,'Cap Table'!$H$15:$H$23)+SUMIF('Cap Table'!$L$15:$L$27,B24,'Cap Table'!$M$15:$M$27)+SUMIF('Cap Table'!$Q$15:$Q$29,B24,'Cap Table'!$R$15:$R$29) -> 500000 | E24: =$C$5*C24 -> 1666666.7 | F24: =(E24-D24)/D24 -> 2.3333333
B25: =Dividends!B23

Sheet Data for charts
A1: =Settings!B4 -> Healthy4U
A2: Month | B2: =EDATE(C2,-1) -> 45108 | C2: =Projections!$B$4 -> 45139 | D2: =EDATE(C2,1) -> 45170 | E2: =EDATE(D2,1) -> 45200 | F2: =EDATE(E2,1) -> 45231 | G2: =EDATE(F2,1) -> 45261 | H2: =EDATE(G2,1) -> 45292 | I2: =EDATE(H2,1) -> 45323 | J2: =EDATE(I2,1) -> 45352 | K2: =EDATE(J2,1) -> 45383 | ... CV2: =EDATE(CU2,1) -> 48092
A4: USE OF FUNDS
